Workbook

Sheet Comportamientos
A1: Fecha | B1: Bugs Totales | C1: Bugs Cancelados | D1: Bugs Solucionados | E1: Bugs Pendientes | F1: Incidentes UAT | G1: %Fuga | I1: Bugs Nuevos | J1: Bugs Solucionados | K1: Bugs Pendientes | L1: BUGS UAT
A2: 45993 | B2: 280 | C2: =B2-D2-E2 -> 36 | D2: 104 | E2: 140 | F2: 23 | G2: =F2/B2 -> 0.082142857
A3: 45999 | B3: 296 | C3: =B3-D3-E3 -> 36 | D3: 114 | E3: 146 | F3: 32 | G3: =F3/B3 -> 0.10810811 | I3: =B3-B2 -> 16 | J3: =D3-D2 -> 10 | K3: =E3-E2 -> 6 | L3: =F3-F2 -> 9
A4: 46006 | B4: 319 | C4: =B4-D4-E4 -> 46 | D4: 129 | E4: 144 | F4: 40 | G4: =F4/B4 -> 0.12539185 | I4: =B4-B3 -> 23 | J4: =D4-D3 -> 15 | K4: =E4-E3 -> -2 | L4: =F4-F3 -> 8
A5: 46013 | B5: 338 | C5: 56 | D5: 140 | E5: 142 | F5: 36 | G5: =F5/B5 -> 0.10650888 | I5: =B5-B4 -> 19 | J5: =D5-D4 -> 11 | K5: =E5-E4 -> -2 | L5: =F5-F4 -> -4
A6: 46020 | B6: 356 | C6: 56 | D6: 158 | E6: 142 | F6: 40 | G6: =F6/B6 -> 0.11235955 | I6: =B6-B5 -> 18 | J6: =D6-D5 -> 18 | K6: =E6-E5 -> 0 | L6: =F6-F5 -> 4
A7: 46027 | B7: 360 | C7: 56 | D7: 158 | E7: 146 | F7: 40 | G7: =F7/B7 -> 0.11111111 | I7: =B7-B6 -> 4 | J7: =D7-D6 -> 0 | K7: =E7-E6 -> 4 | L7: =F7-F6 -> 0
J9: =AVERAGE(J3:J6) -> 13.5
A13: % Fuga por prioridad
A14: Highest | B14: =C14/$F$7 -> 0.2 | C14: 8
A15: High | B15: =C15/$F$7 -> 0.325 | C15: 13
A16: Medium | B16: =C16/$F$7 -> 0.325 | C16: 13
A17: Low | B17: =C17/$F$7 -> 0.15 | C17: 6

Sheet fuga
A1: Fue encontrado durante UAT? | B1: SI
AD2: BUGS TOTALES | AE2: BUGS UAT
A3: Recuento de Fue encontrado durante UAT? | C3: Estado | Y3: VERSIÓN | Z3: %FUGA
A4: En que versión de UAT fue encontrado? | B4: Prioridad | C4: Blocked | D4: Cancelado | E4: READY FOR TESTING | F4: READY FOR UAT | G4: Tareas por hacer | H4: TO BE DEPLOYED-SIT | I4: Total general | Y4: 0.14 S1 | Z4: =AE4/AD4 -> 0.09623431 | AD4: 239 | AE4: 23
A5: UAT_V0.12 | C5: 1 | D5: 6 | F5: 9 | G5: 3 | I5: 19 | Y5: 0.14 S2 | Z5: =AE5/AD5 -> 0.10810811 | AD5: 296 | AE5: 32
A6: UAT_V0.13 | C6: 1 | D6: 1 | E6: 1 | G6: 5 | H6: 1 | I6: 9
A7: UAT_V0.14 | D7: 1 | F7: 6 | G7: 2 | I7: 9
A8: UAT_V0.15 | B8: Alta | G8: 1 | I8: 1
B9: Medio | G9: 2 | I9: 2
A10: UAT_V0.15 Total | G10: 3 | I10: 3
A11: Total general | C11: 2 | D11: 8 | E11: 1 | F11: 15 | G11: 13 | H11: 1 | I11: 40
A45: Fue encontrado durante UAT? | B45: SI
A47: Recuento de Prioridad | B47: Prioridad
A48: Estado | B48: Alta | C48: Baja | D48: Más alta | E48: Medio | F48: Total general
A49: Blocked | B49: 1 | E49: 1 | F49: 2
A50: READY FOR TESTING | B50: 1 | F50: 1
A51: READY FOR UAT | B51: 4 | C51: 3 | D51: 5 | E51: 3 | F51: 15
A52: Tareas por hacer | B52: 4 | D52: 3 | E52: 6 | F52: 13
A53: TO BE DEPLOYED-SIT | E53: 1 | F53: 1
A54: Total general | B54: 10 | C54: 3 | D54: 8 | E54: 11 | F54: 32
A71: % Fuga por prioridad
A72: Highest | B72: =C72/F54 -> 0.25 | C72: =D54 -> 8
A73: High | B73: =C73/F54 -> 0.3125 | C73: =B54 -> 10
A74: Medium | B74: =C74/F54 -> 0.34375 | C74: =E54 -> 11
A75: Low | B75: =C75/F54 -> 0.09375 | C75: =C54 -> 3

Sheet TendenciaXVersión
B3: Versión | C3: Bugs Encontrados | D3: % Casos de Prueba Fallidos | E3: BUGS Cancelados | F3: Bugs Solucionados | G3: BUGS Pendientes por Resolver | H3: % Bugs Pendientes por resolver
B4: 0.4 | C4: ='BUGS X VERSIÓN'!$B10 -> 35 | D4: =+#REF!/#REF! -> #REF! | E4: ='BUGS X VERSIÓN'!$B70 -> 7 | F4: ='BUGS X VERSIÓN'!$B98 -> 22 | G4: ='BUGS X VERSIÓN'!$B120 -> 6 | H4: =G4/C4 -> 0.17142857
B5: 0.5 | C5: ='BUGS X VERSIÓN'!$B11 -> 9 | D5: =+C4/#REF! -> #REF! | E5: ='BUGS X VERSIÓN'!$B71 -> 4 | F5: ='BUGS X VERSIÓN'!$B99 -> 5 | G5: 0 | H5: =G5/C5 -> 0
B6: 0.5.1 | C6: ='BUGS X VERSIÓN'!$B12 -> 10 | E6: ='BUGS X VERSIÓN'!$B72 -> 3 | F6: ='BUGS X VERSIÓN'!$B100 -> 6 | G6: ='BUGS X VERSIÓN'!$B121 -> 1 | H6: =G6/C6 -> 0.1
B7: 0.6 | C7: ='BUGS X VERSIÓN'!$B13 -> 27 | D7: =+C5/#REF! -> #REF! | E7: ='BUGS X VERSIÓN'!$B73 -> 1 | F7: ='BUGS X VERSIÓN'!$B101 -> 22 | G7: ='BUGS X VERSIÓN'!$B122 -> 4 | H7: =G7/C7 -> 0.14814815
B8: 0.6.1 | C8: ='BUGS X VERSIÓN'!$B14 -> 10 | E8: 0 | F8: ='BUGS X VERSIÓN'!$B102 -> 9 | G8: ='BUGS X VERSIÓN'!$B123 -> 1 | H8: =G8/C8 -> 0.1
B9: 0.7 | C9: ='BUGS X VERSIÓN'!$B15 -> 21 | D9: =+C7/#REF! -> #REF! | E9: ='BUGS X VERSIÓN'!$B$74 -> 2 | F9: ='BUGS X VERSIÓN'!$B103 -> 15 | G9: ='BUGS X VERSIÓN'!$B124 -> 4 | H9: =G9/C9 -> 0.19047619
B10: 0.8 | C10: ='BUGS X VERSIÓN'!$B16 -> 15 | D10: =+C9/#REF! -> #REF! | E10: ='BUGS X VERSIÓN'!$B$75 -> 5 | F10: ='BUGS X VERSIÓN'!$B89 -> 5 | G10: ='BUGS X VERSIÓN'!$B111 -> 5 | H10: =G10/C10 -> 0.33333333
B11: 0.9 | C11: ='BUGS X VERSIÓN'!$B17 -> 7 | E11: 0 | F11: ='BUGS X VERSIÓN'!$B90 -> 5 | G11: ='BUGS X VERSIÓN'!$B112 -> 2 | H11: =G11/C11 -> 0.28571429
B12: 0.1 | C12: ='BUGS X VERSIÓN'!$B4 -> 12 | E12: 0 | F12: ='BUGS X VERSIÓN'!$B91 -> 8 | G12: ='BUGS X VERSIÓN'!$B113 -> 4 | H12: =G12/C12 -> 0.33333333
B13: 0.10.1 | C13: ='BUGS X VERSIÓN'!$B5 -> 19 | E13: ='BUGS X VERSIÓN'!$B65 -> 2 | F13: ='BUGS X VERSIÓN'!$B92 -> 7 | G13: ='BUGS X VERSIÓN'!$B114 -> 10 | H13: =G13/C13 -> 0.52631579
B14: 0.11 | C14: ='BUGS X VERSIÓN'!$B6 -> 35 | D14: =+C13/#REF! -> #REF! | E14: ='BUGS X VERSIÓN'!$B66 -> 9 | F14: ='BUGS X VERSIÓN'!$B93 -> 8 | G14: ='BUGS X VERSIÓN'!$B115 -> 18 | H14: =G14/C14 -> 0.51428571
B15: 0.12 | C15: ='BUGS X VERSIÓN'!$B7 -> 51 | E15: ='BUGS X VERSIÓN'!$B67 -> 15 | F15: ='BUGS X VERSIÓN'!$B94 -> 18 | G15: ='BUGS X VERSIÓN'!$B116 -> 18 | H15: =G15/C15 -> 0.35294118
B16: 0.13 | C16: ='BUGS X VERSIÓN'!$B8 -> 24 | E16: ='BUGS X VERSIÓN'!$B$68 -> 1 | F16: ='BUGS X VERSIÓN'!$B95 -> 6 | G16: ='BUGS X VERSIÓN'!$B117 -> 17 | H16: =G16/C16 -> 0.70833333
B17: 0.14 | C17: ='BUGS X VERSIÓN'!$B9 -> 38 | E17: ='BUGS X VERSIÓN'!$B$69 -> 5 | F17: ='BUGS X VERSIÓN'!$B96 -> 15 | G17: ='BUGS X VERSIÓN'!$B118 -> 18 | H17: =G17/C17 -> 0.47368421
A18: En curso | B18: 0.15 | C18: 47 | E18: ='BUGS X VERSIÓN'!$B$76 -> 2 | F18: ='BUGS X VERSIÓN'!$B97 -> 7 | G18: 38 | H18: =G18/C18 -> 0.80851064
C19: =SUM(C4:C18) -> 360 | D19: =C19/#REF! -> #REF! | E19: =SUM(E4:E18) -> 56 | F19: =SUM(F4:F18) -> 158 | G19: =SUM(G4:G18) -> 146 | H19: =G19/C19 -> 0.40555556

Sheet BUGS X VERSIÓN
A1: Estado | B1: (Todas)
A3: ¿En qué versión fue encontrado? | B3: Recuento de Estado
A4: 0.10 | B4: 12
A5: 0.10.1 | B5: 19
A6: 0.11 | B6: 35
A7: 0.12 | B7: 51
A8: 0.13 | B8: 24
A9: 0.14 | B9: 38
A10: 0.4 | B10: 35
A11: 0.5 | B11: 9
A12: 0.5.1 | B12: 10
A13: 0.6 | B13: 27
A14: 0.6.1 | B14: 10
A15: 0.7 | B15: 21
... A19: Total general | B19: 360
A36: ¿En qué versión fue encontrado? | B36: Recuento de ¿En qué versión fue encontrado?
A37: V0.9 | B37: 7
A38: V0.8 | B38: 15
A39: V0.7 | B39: 21
A40: V0.6.1 | B40: 10
A41: V0.6 | B41: 27
A42: V0.5.1 | B42: 10
A43: V0.5 | B43: 9
A44: V0.4 | B44: 35
A45: V0.15 | B45: 47
A46: V0.14 | B46: 38
A47: V0.13 | B47: 24
A48: V0.12 | B48: 51
... A52: Total general | B52: 360
A59: BUGS CANCELADOS
A62: Estado | B62: Cancelado
A64: ¿En qué versión fue encontrado? | B64: Recuento de Estado
A65: 0.10.1 | B65: 2
A66: 0.11 | B66: 9
A67: 0.12 | B67: 15
A68: 0.13 | B68: 1 | H68: Cómo colocar lo que este en la columna B de la hoja Bugs x Versión si E de la hoja tendenciaXVersionen de un archivo coincide con A de la hoja Bugs x Versión
A69: 0.14 | B69: 5
A70: 0.4 | B70: 7
A71: 0.5 | B71: 4
A72: 0.5.1 | B72: 3
A73: 0.6 | B73: 1
A74: 0.7 | B74: 2
A75: 0.8 | B75: 5
A76: V0.15 | B76: 2
A77: Total general | B77: 56
A84: BUGS FINALIZADO
A86: Estado | B86: READY FOR UAT
A88: ¿En qué versión fue encontrado? | B88: Recuento de Estado
A89: 0.8 | B89: 5
A90: 0.9 | B90: 5
A91: V0.10 | B91: 8
A92: V0.10.1 | B92: 7
A93: V0.11 | B93: 8
A94: V0.12 | B94: 18
A95: V0.13 | B95: 6
A96: V0.14 | B96: 15
A97: V0.15 | B97: 7
A98: V0.4 | B98: 22
A99: V0.5 | B99: 5
A100: V0.5.1 | B100: 6
... A104: Total general | B104: 158
A106: Pendientes por resolver
A108: Estado | B108: (Varios elementos)
A110: ¿En qué versión fue encontrado? | B110: Recuento de Estado
A111: 0.8 | B111: 5
A112: 0.9 | B112: 2
A113: V0.10 | B113: 4
A114: V0.10.1 | B114: 10
A115: V0.11 | B115: 18
A116: V0.12 | B116: 18
A117: V0.13 | B117: 17
A118: V0.14 | B118: 18
A119: V0.15 | B119: 38
A120: V0.4 | B120: 6
A121: V0.5.1 | B121: 1
A122: V0.6 | B122: 4
... A125: Total general | B125: 146
A127: Pendientes por resolver X Prioridad
A129: Estado | B129: (Varios elementos)
A131: Recuento de Estado | B131: Prioridad
A132: ¿En qué versión fue encontrado? | B132: Alta | C132: Baja | D132: Más alta | E132: Medio | F132: Total general
A133: 0.8 | B133: 2 | E133: 3 | F133: 5
A134: 0.9 | E134: 2 | F134: 2
A135: V0.10 | B135: 4 | F135: 4
A136: V0.10.1 | B136: 6 | C136: 1 | E136: 3 | F136: 10
A137: V0.11 | B137: 10 | C137: 1 | E137: 7 | F137: 18
A138: V0.12 | B138: 9 | C138: 2 | D138: 1 | E138: 6 | F138: 18
A139: V0.13 | B139: 6 | D139: 2 | E139: 9 | F139: 17
A140: V0.14 | B140: 8 | C140: 1 | D140: 1 | E140: 8 | F140: 18
A141: V0.15 | B141: 9 | C141: 2 | D141: 1 | E141: 26 | F141: 38
A142: V0.4 | B142: 1 | E142: 5 | F142: 6
A143: V0.5.1 | E143: 1 | F143: 1
A144: V0.6 | E144: 4 | F144: 4
A145: V0.6.1 | B145: 1 | F145: 1
A146: V0.7 | C146: 1 | E146: 3 | F146: 4
A147: Total general | B147: 56 | C147: 8 | D147: 5 | E147: 77 | F147: 146

Sheet Reporte_Gral
A1: Tipo de Incidencia | B1: Clave de incidencia | C1: ID de la incidencia | D1: Resumen | E1: Prioridad | F1: Estado | G1: Sprint | H1: Sprint2 | I1: Sprint3 | J1: Sprint4 | K1: Sprint5 | L1: Sprint6 | M1: Sprint7 | N1: Sprint8 | O1: Sprint9 | P1: Sprint10 | Q1: Sprint11 | R1: Etiquetas | S1: Etiquetas10 | T1: Etiquetas11 | U1: Etiquetas12 | V1: Etiquetas13 | W1: Etiquetas14 | X1: Etiquetas15 | Y1: Etiquetas16 | Z1: Etiquetas17 | AA1: Informador | AB1: Creada | AC1: Versiones corregidas | AD1: Versiones corregidas19 | AE1: Versiones corregidas20 | AF1: Versiones corregidas21 | AG1: Módulo | AH1: Desarrollador | AI1: Desarrollador_Bug_Cancelado | AJ1: ¿En que Sprint fue encontrado? | AK1: ¿En qué versión fue encontrado? | AL1: ¿En qué versión fue corregido? | AM1: ¿En que Sprint fue corregido? | AN1: Categoría | AO1: Funcionalidad | AP1: Fue encontrado durante UAT? | AQ1: En que versión de UAT fue encontrado? | AR1: Fue devuelto? | AS1: Cuántas veces fue devuelto?
A2: Error | B2: T20-3755 | C2: 124509 | D2: POS - En menú BBB la opción “Abrir cajón” se muestra sin tilde | E2: Baja | F2: Tareas por hacer | R2: Controlar-Gaveta | S2: Look&Feel | T2: QA-IntegraciónV0.15 | AA2: Yubisleinys Mora Vega | AB2: 46024.531 | AG2: POS | AH2: Andres Vergara | AJ2: {=IFERROR(_xlfn.XLOOKUP(TRUE,COUNTIF(Tabla[[#This Row],[Etiquetas]:[Etiquetas17]],Versiones!$G$2:$G$36)>0,Versiones!$B$2:$B$36), "")} -> 25 | AK2: {=IFERROR(_xlfn.XLOOKUP(TRUE,COUNTIF(Tabla[[#This Row],[Etiquetas]:[Etiquetas17]],Versiones!$G$2:$G$36)>0,Versiones!$A$2:$A$36), "")} -> V0.15 | AL2: ="V"&MAX(IFERROR(VALUE(MID(Tabla[[#This Row],[Versiones corregidas]],2,99)),0), IFERROR(VALUE(MID(Tabla[[#This Row],[Versiones corregidas19]],2,99)),0), IFERROR(VALUE(MID(Tabla[[#This Row],[Versiones corregidas20]],2,99)),0), IFERROR(VALUE(MID(Tabla[[#This Row],[Versiones corregidas21]],2,99)),0),IFERROR(VALUE(MID(#REF!,2,99)),0)) -> V0 | AM2: =IFERROR(_xlfn.XLOOKUP(Tabla[[#This Row],[¿En qué versión fue corregido?]],Versiones!$A$2:$A$34,Versiones!$B$2:$B$34),"No encontrado") -> No encontrado | AN2: {=IFERROR(_xlfn.XLOOKUP(TRUE,COUNTIF(Tabla[[#This Row],[Etiquetas]:[Etiquetas17]],Categorías!$A$2:$A$12)>0,Categorías!$A$2:$A$12),"No encontrado")} -> Look&Feel | AO2: {=IFERROR(INDEX(Funcionalidades!$A$2:$A$80,MATCH(TRUE, COUNTIF(Reporte_Gral!R2:Z2,Funcionalidades!$A$2:$A$80)>0,0)),"No encontrado")} -> Controlar-Gaveta | AP2: =IF(AND(COUNTIF(Tabla[[#This Row],[Etiquetas]:[Etiquetas17]],"*UAT_V*")>0,COUNTIF(Tabla[[#This Row],[Etiquetas]:[Etiquetas17]],"*QA-Integración*")=0),"SI","") | AQ2: {=IF(Tabla[[#This Row],[Fue encontrado durante UAT?]]="SI",IFERROR(_xlfn.XLOOKUP(TRUE,ISNUMBER(SEARCH("UAT_V",Tabla[[#This Row],[Etiquetas]:[Etiquetas17]])),Tabla[[#This Row],[Etiquetas]:[Etiquetas17]]),""),"")} | AR2: =IF(COUNTIF(Tabla[[#This Row],[Etiquetas]:[Etiquetas17]],"*Devuelto*")>0,"SI","") | AS2: =COUNTIF(Tabla[[#This Row],[Etiquetas]:[Etiquetas17]],"*Devuelto*") -> 0
A3: Error | B3: T20-3752 | C3: 124120 | D3: POS – Realizar una venta crea copias del producto en el tablero y provoca cálculo incorrecto en unidades vendidas en el panel Ventas | E3: Alta | F3: Tareas por hacer | R3: Funcional | S3: Iniciar-Venta | T3: QA-IntegraciónV0.15 | AA3: Yubisleinys Mora Vega | AB3: 46021.659 | AG3: BOT | AH3: Ludovic Hern | AJ3: {=IFERROR(_xlfn.XLOOKUP(TRUE,COUNTIF(Tabla[[#This Row],[Etiquetas]:[Etiquetas17]],Versiones!$G$2:$G$36)>0,Versiones!$B$2:$B$36), "")} -> 25 | AK3: {=IFERROR(_xlfn.XLOOKUP(TRUE,COUNTIF(Tabla[[#This Row],[Etiquetas]:[Etiquetas17]],Versiones!$G$2:$G$36)>0,Versiones!$A$2:$A$36), "")} -> V0.15 | AL3: ="V"&MAX(IFERROR(VALUE(MID(Tabla[[#This Row],[Versiones corregidas]],2,99)),0), IFERROR(VALUE(MID(Tabla[[#This Row],[Versiones corregidas19]],2,99)),0), IFERROR(VALUE(MID(Tabla[[#This Row],[Versiones corregidas20]],2,99)),0), IFERROR(VALUE(MID(Tabla[[#This Row],[Versiones corregidas21]],2,99)),0),IFERROR(VALUE(MID(#REF!,2,99)),0)) -> V0 | AM3: =IFERROR(_xlfn.XLOOKUP(Tabla[[#This Row],[¿En qué versión fue corregido?]],Versiones!$A$2:$A$34,Versiones!$B$2:$B$34),"No encontrado") -> No encontrado | AN3: {=IFERROR(_xlfn.XLOOKUP(TRUE,COUNTIF(Tabla[[#This Row],[Etiquetas]:[Etiquetas17]],Categorías!$A$2:$A$12)>0,Categorías!$A$2:$A$12),"No encontrado")} -> Funcional | AO3: {=IFERROR(INDEX(Funcionalidades!$A$2:$A$80,MATCH(TRUE, COUNTIF(Reporte_Gral!R3:Z3,Funcionalidades!$A$2:$A$80)>0,0)),"No encontrado")} -> Iniciar-Venta | AP3: =IF(AND(COUNTIF(Tabla[[#This Row],[Etiquetas]:[Etiquetas17]],"*UAT_V*")>0,COUNTIF(Tabla[[#This Row],[Etiquetas]:[Etiquetas17]],"*QA-Integración*")=0),"SI","") | AQ3: {=IF(Tabla[[#This Row],[Fue encontrado durante UAT?]]="SI",IFERROR(_xlfn.XLOOKUP(TRUE,ISNUMBER(SEARCH("UAT_V",Tabla[[#This Row],[Etiquetas]:[Etiquetas17]])),Tabla[[#This Row],[Etiquetas]:[Etiquetas17]]),""),"")} | AR3: =IF(COUNTIF(Tabla[[#This Row],[Etiquetas]:[Etiquetas17]],"*Devuelto*")>0,"SI","") | AS3: =COUNTIF(Tabla[[#This Row],[Etiquetas]:[Etiquetas17]],"*Devuelto*") -> 0
A4: Error | B4: T20-3751 | C4: 124095 | D4: POS - Se genera mensaje de alivio independiente y el cierre de turno muestra importes incorrectos | E4: Alta | F4: Tareas por hacer | R4: Cierre-De-Turno | S4: Funcional | T4: QA-IntegraciónV0.15 | AA4: Yubisleinys Mora Vega | AB4: 46021.608 | AG4: BOT | AH4: Ludovic Hern | AJ4: {=IFERROR(_xlfn.XLOOKUP(TRUE,COUNTIF(Tabla[[#This Row],[Etiquetas]:[Etiquetas17]],Versiones!$G$2:$G$36)>0,Versiones!$B$2:$B$36), "")} -> 25 | AK4: {=IFERROR(_xlfn.XLOOKUP(TRUE,COUNTIF(Tabla[[#This Row],[Etiquetas]:[Etiquetas17]],Versiones!$G$2:$G$36)>0,Versiones!$A$2:$A$36), "")} -> V0.15 | AL4: ="V"&MAX(IFERROR(VALUE(MID(Tabla[[#This Row],[Versiones corregidas]],2,99)),0), IFERROR(VALUE(MID(Tabla[[#This Row],[Versiones corregidas19]],2,99)),0), IFERROR(VALUE(MID(Tabla[[#This Row],[Versiones corregidas20]],2,99)),0), IFERROR(VALUE(MID(Tabla[[#This Row],[Versiones corregidas21]],2,99)),0),IFERROR(VALUE(MID(#REF!,2,99)),0)) -> V0 | AM4: =IFERROR(_xlfn.XLOOKUP(Tabla[[#This Row],[¿En qué versión fue corregido?]],Versiones!$A$2:$A$34,Versiones!$B$2:$B$34),"No encontrado") -> No encontrado | AN4: {=IFERROR(_xlfn.XLOOKUP(TRUE,COUNTIF(Tabla[[#This Row],[Etiquetas]:[Etiquetas17]],Categorías!$A$2:$A$12)>0,Categorías!$A$2:$A$12),"No encontrado")} -> Funcional | AO4: {=IFERROR(INDEX(Funcionalidades!$A$2:$A$80,MATCH(TRUE, COUNTIF(Reporte_Gral!R4:Z4,Funcionalidades!$A$2:$A$80)>0,0)),"No encontrado")} -> Cierre-De-Turno | AP4: =IF(AND(COUNTIF(Tabla[[#This Row],[Etiquetas]:[Etiquetas17]],"*UAT_V*")>0,COUNTIF(Tabla[[#This Row],[Etiquetas]:[Etiquetas17]],"*QA-Integración*")=0),"SI","") | AQ4: {=IF(Tabla[[#This Row],[Fue encontrado durante UAT?]]="SI",IFERROR(_xlfn.XLOOKUP(TRUE,ISNUMBER(SEARCH("UAT_V",Tabla[[#This Row],[Etiquetas]:[Etiquetas17]])),Tabla[[#This Row],[Etiquetas]:[Etiquetas17]]),""),"")} | AR4: =IF(COUNTIF(Tabla[[#This Row],[Etiquetas]:[Etiquetas17]],"*Devuelto*")>0,"SI","") | AS4: =COUNTIF(Tabla[[#This Row],[Etiquetas]:[Etiquetas17]],"*Devuelto*") -> 0
A5: Error | B5: T20-3749 | C5: 124062 | D5: BOT – Al aceptar mensaje entrante de “Recibir Mercancía” con productos de la misma clave, se cierra el BOT y el mensaje queda en el tablero | E5: Alta | F5: Tareas por hacer | R5: Funcional | S5: QA-IntegraciónV0.15 | T5: Recibir-Mercancía-Almacén-Tienda | AA5: Yubisleinys Mora Vega | AB5: 46021.535 | AG5: BOT | AH5: Ludovic Hern | AJ5: {=IFERROR(_xlfn.XLOOKUP(TRUE,COUNTIF(Tabla[[#This Row],[Etiquetas]:[Etiquetas17]],Versiones!$G$2:$G$36)>0,Versiones!$B$2:$B$36), "")} -> 25 | AK5: {=IFERROR(_xlfn.XLOOKUP(TRUE,COUNTIF(Tabla[[#This Row],[Etiquetas]:[Etiquetas17]],Versiones!$G$2:$G$36)>0,Versiones!$A$2:$A$36), "")} -> V0.15 | AL5: ="V"&MAX(IFERROR(VALUE(MID(Tabla[[#This Row],[Versiones corregidas]],2,99)),0), IFERROR(VALUE(MID(Tabla[[#This Row],[Versiones corregidas19]],2,99)),0), IFERROR(VALUE(MID(Tabla[[#This Row],[Versiones corregidas20]],2,99)),0), IFERROR(VALUE(MID(Tabla[[#This Row],[Versiones corregidas21]],2,99)),0),IFERROR(VALUE(MID(#REF!,2,99)),0)) -> V0 | AM5: =IFERROR(_xlfn.XLOOKUP(Tabla[[#This Row],[¿En qué versión fue corregido?]],Versiones!$A$2:$A$34,Versiones!$B$2:$B$34),"No encontrado") -> No encontrado | AN5: {=IFERROR(_xlfn.XLOOKUP(TRUE,COUNTIF(Tabla[[#This Row],[Etiquetas]:[Etiquetas17]],Categorías!$A$2:$A$12)>0,Categorías!$A$2:$A$12),"No encontrado")} -> Funcional | AO5: {=IFERROR(INDEX(Funcionalidades!$A$2:$A$80,MATCH(TRUE, COUNTIF(Reporte_Gral!R5:Z5,Funcionalidades!$A$2:$A$80)>0,0)),"No encontrado")} -> Recibir-Mercancía-Almacén-Tienda | AP5: =IF(AND(COUNTIF(Tabla[[#This Row],[Etiquetas]:[Etiquetas17]],"*UAT_V*")>0,COUNTIF(Tabla[[#This Row],[Etiquetas]:[Etiquetas17]],"*QA-Integración*")=0),"SI","") | AQ5: {=IF(Tabla[[#This Row],[Fue encontrado durante UAT?]]="SI",IFERROR(_xlfn.XLOOKUP(TRUE,ISNUMBER(SEARCH("UAT_V",Tabla[[#This Row],[Etiquetas]:[Etiquetas17]])),Tabla[[#This Row],[Etiquetas]:[Etiquetas17]]),""),"")} | AR5: =IF(COUNTIF(Tabla[[#This Row],[Etiquetas]:[Etiquetas17]],"*Devuelto*")>0,"SI","") | AS5: =COUNTIF(Tabla[[#This Row],[Etiquetas]:[Etiquetas17]],"*Devuelto*") -> 0
A6: Error | B6: T20-3746 | C6: 123840 | D6: BOT - Impresora de carátula no imprime | E6: Alta | F6: TO BE DEPLOYED-SIT | G6: T20 Sprint 26 2025 | R6: Funcional | S6: QA-IntegraciónV0.15 | T6: Registrar-Merma | U6: T3B20_Kotlin | V6: Tienda2.0 | AA6: Yubisleinys Mora Vega | AB6: 46020.558 | AC6: v0.16 | AG6: BOT | AH6: Ludovic Hern | AJ6: {=IFERROR(_xlfn.XLOOKUP(TRUE,COUNTIF(Tabla[[#This Row],[Etiquetas]:[Etiquetas17]],Versiones!$G$2:$G$36)>0,Versiones!$B$2:$B$36), "")} -> 25 | AK6: {=IFERROR(_xlfn.XLOOKUP(TRUE,COUNTIF(Tabla[[#This Row],[Etiquetas]:[Etiquetas17]],Versiones!$G$2:$G$36)>0,Versiones!$A$2:$A$36), "")} -> V0.15 | AL6: ="V"&MAX(IFERROR(VALUE(MID(Tabla[[#This Row],[Versiones corregidas]],2,99)),0), IFERROR(VALUE(MID(Tabla[[#This Row],[Versiones corregidas19]],2,99)),0), IFERROR(VALUE(MID(Tabla[[#This Row],[Versiones corregidas20]],2,99)),0), IFERROR(VALUE(MID(Tabla[[#This Row],[Versiones corregidas21]],2,99)),0),IFERROR(VALUE(MID(#REF!,2,99)),0)) -> V0.16 | AM6: =IFERROR(_xlfn.XLOOKUP(Tabla[[#This Row],[¿En qué versión fue corregido?]],Versiones!$A$2:$A$34,Versiones!$B$2:$B$34),"No encontrado") -> 0 | AN6: {=IFERROR(_xlfn.XLOOKUP(TRUE,COUNTIF(Tabla[[#This Row],[Etiquetas]:[Etiquetas17]],Categorías!$A$2:$A$12)>0,Categorías!$A$2:$A$12),"No encontrado")} -> Funcional | AO6: {=IFERROR(INDEX(Funcionalidades!$A$2:$A$80,MATCH(TRUE, COUNTIF(Reporte_Gral!R6:Z6,Funcionalidades!$A$2:$A$80)>0,0)),"No encontrado")} -> Registrar-Merma | AP6: =IF(AND(COUNTIF(Tabla[[#This Row],[Etiquetas]:[Etiquetas17]],"*UAT_V*")>0,COUNTIF(Tabla[[#This Row],[Etiquetas]:[Etiquetas17]],"*QA-Integración*")=0),"SI","") | AQ6: {=IF(Tabla[[#This Row],[Fue encontrado durante UAT?]]="SI",IFERROR(_xlfn.XLOOKUP(TRUE,ISNUMBER(SEARCH("UAT_V",Tabla[[#This Row],[Etiquetas]:[Etiquetas17]])),Tabla[[#This Row],[Etiquetas]:[Etiquetas17]]),""),"")} | AR6: =IF(COUNTIF(Tabla[[#This Row],[Etiquetas]:[Etiquetas17]],"*Devuelto*")>0,"SI","") | AS6: =COUNTIF(Tabla[[#This Row],[Etiquetas]:[Etiquetas17]],"*Devuelto*") -> 0
A7: Error | B7: T20-3742 | C7: 123791 | D7: POS - Alivio - Espacio en blanco adicional en tickets de alivio | E7: Baja | F7: Tareas por hacer | R7: Alivios | S7: Funcional | T7: QA-IntegraciónV0.15 | AA7: Yubisleinys Mora Vega | AB7: 46020.446 | AG7: POS | AH7: Juan Munoz | AJ7: {=IFERROR(_xlfn.XLOOKUP(TRUE,COUNTIF(Tabla[[#This Row],[Etiquetas]:[Etiquetas17]],Versiones!$G$2:$G$36)>0,Versiones!$B$2:$B$36), "")} -> 25 | AK7: {=IFERROR(_xlfn.XLOOKUP(TRUE,COUNTIF(Tabla[[#This Row],[Etiquetas]:[Etiquetas17]],Versiones!$G$2:$G$36)>0,Versiones!$A$2:$A$36), "")} -> V0.15 | AL7: ="V"&MAX(IFERROR(VALUE(MID(Tabla[[#This Row],[Versiones corregidas]],2,99)),0), IFERROR(VALUE(MID(Tabla[[#This Row],[Versiones corregidas19]],2,99)),0), IFERROR(VALUE(MID(Tabla[[#This Row],[Versiones corregidas20]],2,99)),0), IFERROR(VALUE(MID(Tabla[[#This Row],[Versiones corregidas21]],2,99)),0),IFERROR(VALUE(MID(#REF!,2,99)),0)) -> V0 | AM7: =IFERROR(_xlfn.XLOOKUP(Tabla[[#This Row],[¿En qué versión fue corregido?]],Versiones!$A$2:$A$34,Versiones!$B$2:$B$34),"No encontrado") -> No encontrado | AN7: {=IFERROR(_xlfn.XLOOKUP(TRUE,COUNTIF(Tabla[[#This Row],[Etiquetas]:[Etiquetas17]],Categorías!$A$2:$A$12)>0,Categorías!$A$2:$A$12),"No encontrado")} -> Funcional | AO7: {=IFERROR(INDEX(Funcionalidades!$A$2:$A$80,MATCH(TRUE, COUNTIF(Reporte_Gral!R7:Z7,Funcionalidades!$A$2:$A$80)>0,0)),"No encontrado")} -> Alivios | AP7: =IF(AND(COUNTIF(Tabla[[#This Row],[Etiquetas]:[Etiquetas17]],"*UAT_V*")>0,COUNTIF(Tabla[[#This Row],[Etiquetas]:[Etiquetas17]],"*QA-Integración*")=0),"SI","") | AQ7: {=IF(Tabla[[#This Row],[Fue encontrado durante UAT?]]="SI",IFERROR(_xlfn.XLOOKUP(TRUE,ISNUMBER(SEARCH("UAT_V",Tabla[[#This Row],[Etiquetas]:[Etiquetas17]])),Tabla[[#This Row],[Etiquetas]:[Etiquetas17]]),""),"")} | AR7: =IF(COUNTIF(Tabla[[#This Row],[Etiquetas]:[Etiquetas17]],"*Devuelto*")>0,"SI","") | AS7: =COUNTIF(Tabla[[#This Row],[Etiquetas]:[Etiquetas17]],"*Devuelto*") -> 0
A8: Error | B8: T20-3741 | C8: 123774 | D8: BOT - Cambio de precio - Error al guardar configuración de producto obliga al cierre del BOT (intermitente) | E8: Alta | F8: Tareas por hacer | R8: Funcional | S8: Imprimir-Cambios-De-Precio | T8: QA-IntegraciónV0.15 | AA8: Yubisleinys Mora Vega | AB8: 46020.408 | AG8: BOT | AH8: PENDIENTES | AJ8: {=IFERROR(_xlfn.XLOOKUP(TRUE,COUNTIF(Tabla[[#This Row],[Etiquetas]:[Etiquetas17]],Versiones!$G$2:$G$36)>0,Versiones!$B$2:$B$36), "")} -> 25 | AK8: {=IFERROR(_xlfn.XLOOKUP(TRUE,COUNTIF(Tabla[[#This Row],[Etiquetas]:[Etiquetas17]],Versiones!$G$2:$G$36)>0,Versiones!$A$2:$A$36), "")} -> V0.15 | AL8: ="V"&MAX(IFERROR(VALUE(MID(Tabla[[#This Row],[Versiones corregidas]],2,99)),0), IFERROR(VALUE(MID(Tabla[[#This Row],[Versiones corregidas19]],2,99)),0), IFERROR(VALUE(MID(Tabla[[#This Row],[Versiones corregidas20]],2,99)),0), IFERROR(VALUE(MID(Tabla[[#This Row],[Versiones corregidas21]],2,99)),0),IFERROR(VALUE(MID(#REF!,2,99)),0)) -> V0 | AM8: =IFERROR(_xlfn.XLOOKUP(Tabla[[#This Row],[¿En qué versión fue corregido?]],Versiones!$A$2:$A$34,Versiones!$B$2:$B$34),"No encontrado") -> No encontrado | AN8: {=IFERROR(_xlfn.XLOOKUP(TRUE,COUNTIF(Tabla[[#This Row],[Etiquetas]:[Etiquetas17]],Categorías!$A$2:$A$12)>0,Categorías!$A$2:$A$12),"No encontrado")} -> Funcional | AO8: {=IFERROR(INDEX(Funcionalidades!$A$2:$A$80,MATCH(TRUE, COUNTIF(Reporte_Gral!R8:Z8,Funcionalidades!$A$2:$A$80)>0,0)),"No encontrado")} -> Imprimir-Cambios-De-Precio | AP8: =IF(AND(COUNTIF(Tabla[[#This Row],[Etiquetas]:[Etiquetas17]],"*UAT_V*")>0,COUNTIF(Tabla[[#This Row],[Etiquetas]:[Etiquetas17]],"*QA-Integración*")=0),"SI","") | AQ8: {=IF(Tabla[[#This Row],[Fue encontrado durante UAT?]]="SI",IFERROR(_xlfn.XLOOKUP(TRUE,ISNUMBER(SEARCH("UAT_V",Tabla[[#This Row],[Etiquetas]:[Etiquetas17]])),Tabla[[#This Row],[Etiquetas]:[Etiquetas17]]),""),"")} | AR8: =IF(COUNTIF(Tabla[[#This Row],[Etiquetas]:[Etiquetas17]],"*Devuelto*")>0,"SI","") | AS8: =COUNTIF(Tabla[[#This Row],[Etiquetas]:[Etiquetas17]],"*Devuelto*") -> 0
A9: Error | B9: T20-3739 | C9: 123727 | D9: POS - Alivio automático para Tómbola imprime solo un ticket | E9: Medio | F9: Tareas por hacer | R9: Alivios | S9: Funcional | T9: QA-IntegraciónV0.15 | AA9: Yubisleinys Mora Vega | AB9: 46020.265 | AG9: POS | AH9: Juan Munoz | AJ9: {=IFERROR(_xlfn.XLOOKUP(TRUE,COUNTIF(Tabla[[#This Row],[Etiquetas]:[Etiquetas17]],Versiones!$G$2:$G$36)>0,Versiones!$B$2:$B$36), "")} -> 25 | AK9: {=IFERROR(_xlfn.XLOOKUP(TRUE,COUNTIF(Tabla[[#This Row],[Etiquetas]:[Etiquetas17]],Versiones!$G$2:$G$36)>0,Versiones!$A$2:$A$36), "")} -> V0.15 | AL9: ="V"&MAX(IFERROR(VALUE(MID(Tabla[[#This Row],[Versiones corregidas]],2,99)),0), IFERROR(VALUE(MID(Tabla[[#This Row],[Versiones corregidas19]],2,99)),0), IFERROR(VALUE(MID(Tabla[[#This Row],[Versiones corregidas20]],2,99)),0), IFERROR(VALUE(MID(Tabla[[#This Row],[Versiones corregidas21]],2,99)),0),IFERROR(VALUE(MID(#REF!,2,99)),0)) -> V0 | AM9: =IFERROR(_xlfn.XLOOKUP(Tabla[[#This Row],[¿En qué versión fue corregido?]],Versiones!$A$2:$A$34,Versiones!$B$2:$B$34),"No encontrado") -> No encontrado | AN9: {=IFERROR(_xlfn.XLOOKUP(TRUE,COUNTIF(Tabla[[#This Row],[Etiquetas]:[Etiquetas17]],Categorías!$A$2:$A$12)>0,Categorías!$A$2:$A$12),"No encontrado")} -> Funcional | AO9: {=IFERROR(INDEX(Funcionalidades!$A$2:$A$80,MATCH(TRUE, COUNTIF(Reporte_Gral!R9:Z9,Funcionalidades!$A$2:$A$80)>0,0)),"No encontrado")} -> Alivios | AP9: =IF(AND(COUNTIF(Tabla[[#This Row],[Etiquetas]:[Etiquetas17]],"*UAT_V*")>0,COUNTIF(Tabla[[#This Row],[Etiquetas]:[Etiquetas17]],"*QA-Integración*")=0),"SI","") | AQ9: {=IF(Tabla[[#This Row],[Fue encontrado durante UAT?]]="SI",IFERROR(_xlfn.XLOOKUP(TRUE,ISNUMBER(SEARCH("UAT_V",Tabla[[#This Row],[Etiquetas]:[Etiquetas17]])),Tabla[[#This Row],[Etiquetas]:[Etiquetas17]]),""),"")} | AR9: =IF(COUNTIF(Tabla[[#This Row],[Etiquetas]:[Etiquetas17]],"*Devuelto*")>0,"SI","") | AS9: =COUNTIF(Tabla[[#This Row],[Etiquetas]:[Etiquetas17]],"*Devuelto*") -> 0
A10: Error | B10: T20-3738 | C10: 123559 | D10: POS - Ticket de Tiempo de Aire no muestra el cambio al cliente | E10: Medio | F10: Tareas por hacer | R10: Funcional | S10: Pago-De-Tiempo-Aire | T10: QA-IntegraciónV0.15 | AA10: Yubisleinys Mora Vega | AB10: 46017.685 | AG10: POS | AH10: PENDIENTES | AJ10: {=IFERROR(_xlfn.XLOOKUP(TRUE,COUNTIF(Tabla[[#This Row],[Etiquetas]:[Etiquetas17]],Versiones!$G$2:$G$36)>0,Versiones!$B$2:$B$36), "")} -> 25 | AK10: {=IFERROR(_xlfn.XLOOKUP(TRUE,COUNTIF(Tabla[[#This Row],[Etiquetas]:[Etiquetas17]],Versiones!$G$2:$G$36)>0,Versiones!$A$2:$A$36), "")} -> V0.15 | AL10: ="V"&MAX(IFERROR(VALUE(MID(Tabla[[#This Row],[Versiones corregidas]],2,99)),0), IFERROR(VALUE(MID(Tabla[[#This Row],[Versiones corregidas19]],2,99)),0), IFERROR(VALUE(MID(Tabla[[#This Row],[Versiones corregidas20]],2,99)),0), IFERROR(VALUE(MID(Tabla[[#This Row],[Versiones corregidas21]],2,99)),0),IFERROR(VALUE(MID(#REF!,2,99)),0)) -> V0 | AM10: =IFERROR(_xlfn.XLOOKUP(Tabla[[#This Row],[¿En qué versión fue corregido?]],Versiones!$A$2:$A$34,Versiones!$B$2:$B$34),"No encontrado") -> No encontrado | AN10: {=IFERROR(_xlfn.XLOOKUP(TRUE,COUNTIF(Tabla[[#This Row],[Etiquetas]:[Etiquetas17]],Categorías!$A$2:$A$12)>0,Categorías!$A$2:$A$12),"No encontrado")} -> Funcional | AO10: {=IFERROR(INDEX(Funcionalidades!$A$2:$A$80,MATCH(TRUE, COUNTIF(Reporte_Gral!R10:Z10,Funcionalidades!$A$2:$A$80)>0,0)),"No encontrado")} -> Pago-De-Tiempo-Aire | AP10: =IF(AND(COUNTIF(Tabla[[#This Row],[Etiquetas]:[Etiquetas17]],"*UAT_V*")>0,COUNTIF(Tabla[[#This Row],[Etiquetas]:[Etiquetas17]],"*QA-Integración*")=0),"SI","") | AQ10: {=IF(Tabla[[#This Row],[Fue encontrado durante UAT?]]="SI",IFERROR(_xlfn.XLOOKUP(TRUE,ISNUMBER(SEARCH("UAT_V",Tabla[[#This Row],[Etiquetas]:[Etiquetas17]])),Tabla[[#This Row],[Etiquetas]:[Etiquetas17]]),""),"")} | AR10: =IF(COUNTIF(Tabla[[#This Row],[Etiquetas]:[Etiquetas17]],"*Devuelto*")>0,"SI","") | AS10: =COUNTIF(Tabla[[#This Row],[Etiquetas]:[Etiquetas17]],"*Devuelto*") -> 0
A11: Error | B11: T20-3737 | C11: 123542 | D11: POS - Ticket de Alivio para Tómbola muestra concepto incorrecto en la impresión | E11: Medio | F11: Tareas por hacer | R11: Alivios | S11: Funcional | T11: QA-IntegraciónV0.15 | AA11: Yubisleinys Mora Vega | AB11: 46017.66 | AG11: POS | AH11: Juan Munoz | AJ11: {=IFERROR(_xlfn.XLOOKUP(TRUE,COUNTIF(Tabla[[#This Row],[Etiquetas]:[Etiquetas17]],Versiones!$G$2:$G$36)>0,Versiones!$B$2:$B$36), "")} -> 25 | AK11: {=IFERROR(_xlfn.XLOOKUP(TRUE,COUNTIF(Tabla[[#This Row],[Etiquetas]:[Etiquetas17]],Versiones!$G$2:$G$36)>0,Versiones!$A$2:$A$36), "")} -> V0.15 | AL11: ="V"&MAX(IFERROR(VALUE(MID(Tabla[[#This Row],[Versiones corregidas]],2,99)),0), IFERROR(VALUE(MID(Tabla[[#This Row],[Versiones corregidas19]],2,99)),0), IFERROR(VALUE(MID(Tabla[[#This Row],[Versiones corregidas20]],2,99)),0), IFERROR(VALUE(MID(Tabla[[#This Row],[Versiones corregidas21]],2,99)),0),IFERROR(VALUE(MID(#REF!,2,99)),0)) -> V0 | AM11: =IFERROR(_xlfn.XLOOKUP(Tabla[[#This Row],[¿En qué versión fue corregido?]],Versiones!$A$2:$A$34,Versiones!$B$2:$B$34),"No encontrado") -> No encontrado | AN11: {=IFERROR(_xlfn.XLOOKUP(TRUE,COUNTIF(Tabla[[#This Row],[Etiquetas]:[Etiquetas17]],Categorías!$A$2:$A$12)>0,Categorías!$A$2:$A$12),"No encontrado")} -> Funcional | AO11: {=IFERROR(INDEX(Funcionalidades!$A$2:$A$80,MATCH(TRUE, COUNTIF(Reporte_Gral!R11:Z11,Funcionalidades!$A$2:$A$80)>0,0)),"No encontrado")} -> Alivios | AP11: =IF(AND(COUNTIF(Tabla[[#This Row],[Etiquetas]:[Etiquetas17]],"*UAT_V*")>0,COUNTIF(Tabla[[#This Row],[Etiquetas]:[Etiquetas17]],"*QA-Integración*")=0),"SI","") | AQ11: {=IF(Tabla[[#This Row],[Fue encontrado durante UAT?]]="SI",IFERROR(_xlfn.XLOOKUP(TRUE,ISNUMBER(SEARCH("UAT_V",Tabla[[#This Row],[Etiquetas]:[Etiquetas17]])),Tabla[[#This Row],[Etiquetas]:[Etiquetas17]]),""),"")} | AR11: =IF(COUNTIF(Tabla[[#This Row],[Etiquetas]:[Etiquetas17]],"*Devuelto*")>0,"SI","") | AS11: =COUNTIF(Tabla[[#This Row],[Etiquetas]:[Etiquetas17]],"*Devuelto*") -> 0
A12: Error | B12: T20-3735 | C12: 123001 | D12: POS - Servicios - Error en modal Cambio al cliente | E12: Medio | F12: Tareas por hacer | R12: Funcional | S12: Pago-De-Servicios-Con-Catálogo | T12: QA-IntegraciónV0.15 | AA12: Yubisleinys Mora Vega | AB12: 46014.735 | AC12: v0.15 | AG12: POS | AH12: Andres Vergara | AJ12: {=IFERROR(_xlfn.XLOOKUP(TRUE,COUNTIF(Tabla[[#This Row],[Etiquetas]:[Etiquetas17]],Versiones!$G$2:$G$36)>0,Versiones!$B$2:$B$36), "")} -> 25 | AK12: {=IFERROR(_xlfn.XLOOKUP(TRUE,COUNTIF(Tabla[[#This Row],[Etiquetas]:[Etiquetas17]],Versiones!$G$2:$G$36)>0,Versiones!$A$2:$A$36), "")} -> V0.15 | AL12: ="V"&MAX(IFERROR(VALUE(MID(Tabla[[#This Row],[Versiones corregidas]],2,99)),0), IFERROR(VALUE(MID(Tabla[[#This Row],[Versiones corregidas19]],2,99)),0), IFERROR(VALUE(MID(Tabla[[#This Row],[Versiones corregidas20]],2,99)),0), IFERROR(VALUE(MID(Tabla[[#This Row],[Versiones corregidas21]],2,99)),0),IFERROR(VALUE(MID(#REF!,2,99)),0)) -> V0.15 | AM12: =IFERROR(_xlfn.XLOOKUP(Tabla[[#This Row],[¿En qué versión fue corregido?]],Versiones!$A$2:$A$34,Versiones!$B$2:$B$34),"No encontrado") -> 25 | AN12: {=IFERROR(_xlfn.XLOOKUP(TRUE,COUNTIF(Tabla[[#This Row],[Etiquetas]:[Etiquetas17]],Categorías!$A$2:$A$12)>0,Categorías!$A$2:$A$12),"No encontrado")} -> Funcional | AO12: {=IFERROR(INDEX(Funcionalidades!$A$2:$A$80,MATCH(TRUE, COUNTIF(Reporte_Gral!R12:Z12,Funcionalidades!$A$2:$A$80)>0,0)),"No encontrado")} -> Pago-De-Servicios-Con-Catálogo | AP12: =IF(AND(COUNTIF(Tabla[[#This Row],[Etiquetas]:[Etiquetas17]],"*UAT_V*")>0,COUNTIF(Tabla[[#This Row],[Etiquetas]:[Etiquetas17]],"*QA-Integración*")=0),"SI","") | AQ12: {=IF(Tabla[[#This Row],[Fue encontrado durante UAT?]]="SI",IFERROR(_xlfn.XLOOKUP(TRUE,ISNUMBER(SEARCH("UAT_V",Tabla[[#This Row],[Etiquetas]:[Etiquetas17]])),Tabla[[#This Row],[Etiquetas]:[Etiquetas17]]),""),"")} | AR12: =IF(COUNTIF(Tabla[[#This Row],[Etiquetas]:[Etiquetas17]],"*Devuelto*")>0,"SI","") | AS12: =COUNTIF(Tabla[[#This Row],[Etiquetas]:[Etiquetas17]],"*Devuelto*") -> 0
A13: Error | B13: T20-3734 | C13: 122963 | D13: POS - El sistema permite realizar un alivio por una cantidad mayor al efectivo disponible | E13: Medio | F13: Tareas por hacer | R13: Alivios | S13: Funcional | T13: UAT_V0.15 | AA13: Yubisleinys Mora Vega | AB13: 46014.659 | AG13: BOT | AH13: Juan Munoz | AJ13: {=IFERROR(_xlfn.XLOOKUP(TRUE,COUNTIF(Tabla[[#This Row],[Etiquetas]:[Etiquetas17]],Versiones!$G$2:$G$36)>0,Versiones!$B$2:$B$36), "")} -> 25 | AK13: {=IFERROR(_xlfn.XLOOKUP(TRUE,COUNTIF(Tabla[[#This Row],[Etiquetas]:[Etiquetas17]],Versiones!$G$2:$G$36)>0,Versiones!$A$2:$A$36), "")} -> V0.15 | AL13: ="V"&MAX(IFERROR(VALUE(MID(Tabla[[#This Row],[Versiones corregidas]],2,99)),0), IFERROR(VALUE(MID(Tabla[[#This Row],[Versiones corregidas19]],2,99)),0), IFERROR(VALUE(MID(Tabla[[#This Row],[Versiones corregidas20]],2,99)),0), IFERROR(VALUE(MID(Tabla[[#This Row],[Versiones corregidas21]],2,99)),0),IFERROR(VALUE(MID(#REF!,2,99)),0)) -> V0 | AM13: =IFERROR(_xlfn.XLOOKUP(Tabla[[#This Row],[¿En qué versión fue corregido?]],Versiones!$A$2:$A$34,Versiones!$B$2:$B$34),"No encontrado") -> No encontrado | AN13: {=IFERROR(_xlfn.XLOOKUP(TRUE,COUNTIF(Tabla[[#This Row],[Etiquetas]:[Etiquetas17]],Categorías!$A$2:$A$12)>0,Categorías!$A$2:$A$12),"No encontrado")} -> Funcional | AO13: {=IFERROR(INDEX(Funcionalidades!$A$2:$A$80,MATCH(TRUE, COUNTIF(Reporte_Gral!R13:Z13,Funcionalidades!$A$2:$A$80)>0,0)),"No encontrado")} -> Alivios | AP13: =IF(AND(COUNTIF(Tabla[[#This Row],[Etiquetas]:[Etiquetas17]],"*UAT_V*")>0,COUNTIF(Tabla[[#This Row],[Etiquetas]:[Etiquetas17]],"*QA-Integración*")=0),"SI","") -> SI | AQ13: {=IF(Tabla[[#This Row],[Fue encontrado durante UAT?]]="SI",IFERROR(_xlfn.XLOOKUP(TRUE,ISNUMBER(SEARCH("UAT_V",Tabla[[#This Row],[Etiquetas]:[Etiquetas17]])),Tabla[[#This Row],[Etiquetas]:[Etiquetas17]]),""),"")} -> UAT_V0.15 | AR13: =IF(COUNTIF(Tabla[[#This Row],[Etiquetas]:[Etiquetas17]],"*Devuelto*")>0,"SI","") | AS13: =COUNTIF(Tabla[[#This Row],[Etiquetas]:[Etiquetas17]],"*Devuelto*") -> 0
A14: Error | B14: T20-3733 | C14: 122956 | D14: BOT - Registro de merma - El sistema permite realizar merma sobre pagos de servicios y recargas | E14: Medio | F14: Tareas por hacer | R14: Funcional | S14: Registrar-Merma | T14: UAT_V0.15 | AA14: Yubisleinys Mora Vega | AB14: 46014.633 | AG14: BOT | AH14: PENDIENTES | AJ14: {=IFERROR(_xlfn.XLOOKUP(TRUE,COUNTIF(Tabla[[#This Row],[Etiquetas]:[Etiquetas17]],Versiones!$G$2:$G$36)>0,Versiones!$B$2:$B$36), "")} -> 25 | AK14: {=IFERROR(_xlfn.XLOOKUP(TRUE,COUNTIF(Tabla[[#This Row],[Etiquetas]:[Etiquetas17]],Versiones!$G$2:$G$36)>0,Versiones!$A$2:$A$36), "")} -> V0.15 | AL14: ="V"&MAX(IFERROR(VALUE(MID(Tabla[[#This Row],[Versiones corregidas]],2,99)),0), IFERROR(VALUE(MID(Tabla[[#This Row],[Versiones corregidas19]],2,99)),0), IFERROR(VALUE(MID(Tabla[[#This Row],[Versiones corregidas20]],2,99)),0), IFERROR(VALUE(MID(Tabla[[#This Row],[Versiones corregidas21]],2,99)),0),IFERROR(VALUE(MID(#REF!,2,99)),0)) -> V0 | AM14: =IFERROR(_xlfn.XLOOKUP(Tabla[[#This Row],[¿En qué versión fue corregido?]],Versiones!$A$2:$A$34,Versiones!$B$2:$B$34),"No encontrado") -> No encontrado | AN14: {=IFERROR(_xlfn.XLOOKUP(TRUE,COUNTIF(Tabla[[#This Row],[Etiquetas]:[Etiquetas17]],Categorías!$A$2:$A$12)>0,Categorías!$A$2:$A$12),"No encontrado")} -> Funcional | AO14: {=IFERROR(INDEX(Funcionalidades!$A$2:$A$80,MATCH(TRUE, COUNTIF(Reporte_Gral!R14:Z14,Funcionalidades!$A$2:$A$80)>0,0)),"No encontrado")} -> Registrar-Merma | AP14: =IF(AND(COUNTIF(Tabla[[#This Row],[Etiquetas]:[Etiquetas17]],"*UAT_V*")>0,COUNTIF(Tabla[[#This Row],[Etiquetas]:[Etiquetas17]],"*QA-Integración*")=0),"SI","") -> SI | AQ14: {=IF(Tabla[[#This Row],[Fue encontrado durante UAT?]]="SI",IFERROR(_xlfn.XLOOKUP(TRUE,ISNUMBER(SEARCH("UAT_V",Tabla[[#This Row],[Etiquetas]:[Etiquetas17]])),Tabla[[#This Row],[Etiquetas]:[Etiquetas17]]),""),"")} -> UAT_V0.15 | AR14: =IF(COUNTIF(Tabla[[#This Row],[Etiquetas]:[Etiquetas17]],"*Devuelto*")>0,"SI","") | AS14: =COUNTIF(Tabla[[#This Row],[Etiquetas]:[Etiquetas17]],"*Devuelto*") -> 0
A15: Error | B15: T20-3702 | C15: 122888 | D15: BOT - Pedido eficiente - El resumen del pedido muestra todos los productos en lugar de solo los solicitados | E15: Alta | F15: Tareas por hacer | R15: Funcional | S15: Realizar-Pedido-Eficiente | T15: UAT_V0.15 | AA15: Yubisleinys Mora Vega | AB15: 46014.594 | AG15: BOT | AH15: Andres Vergara | AJ15: {=IFERROR(_xlfn.XLOOKUP(TRUE,COUNTIF(Tabla[[#This Row],[Etiquetas]:[Etiquetas17]],Versiones!$G$2:$G$36)>0,Versiones!$B$2:$B$36), "")} -> 25 | AK15: {=IFERROR(_xlfn.XLOOKUP(TRUE,COUNTIF(Tabla[[#This Row],[Etiquetas]:[Etiquetas17]],Versiones!$G$2:$G$36)>0,Versiones!$A$2:$A$36), "")} -> V0.15 | AL15: ="V"&MAX(IFERROR(VALUE(MID(Tabla[[#This Row],[Versiones corregidas]],2,99)),0), IFERROR(VALUE(MID(Tabla[[#This Row],[Versiones corregidas19]],2,99)),0), IFERROR(VALUE(MID(Tabla[[#This Row],[Versiones corregidas20]],2,99)),0), IFERROR(VALUE(MID(Tabla[[#This Row],[Versiones corregidas21]],2,99)),0),IFERROR(VALUE(MID(#REF!,2,99)),0)) -> V0 | AM15: =IFERROR(_xlfn.XLOOKUP(Tabla[[#This Row],[¿En qué versión fue corregido?]],Versiones!$A$2:$A$34,Versiones!$B$2:$B$34),"No encontrado") -> No encontrado | AN15: {=IFERROR(_xlfn.XLOOKUP(TRUE,COUNTIF(Tabla[[#This Row],[Etiquetas]:[Etiquetas17]],Categorías!$A$2:$A$12)>0,Categorías!$A$2:$A$12),"No encontrado")} -> Funcional | AO15: {=IFERROR(INDEX(Funcionalidades!$A$2:$A$80,MATCH(TRUE, COUNTIF(Reporte_Gral!R15:Z15,Funcionalidades!$A$2:$A$80)>0,0)),"No encontrado")} -> Realizar-Pedido-Eficiente | AP15: =IF(AND(COUNTIF(Tabla[[#This Row],[Etiquetas]:[Etiquetas17]],"*UAT_V*")>0,COUNTIF(Tabla[[#This Row],[Etiquetas]:[Etiquetas17]],"*QA-Integración*")=0),"SI","") -> SI | AQ15: {=IF(Tabla[[#This Row],[Fue encontrado durante UAT?]]="SI",IFERROR(_xlfn.XLOOKUP(TRUE,ISNUMBER(SEARCH("UAT_V",Tabla[[#This Row],[Etiquetas]:[Etiquetas17]])),Tabla[[#This Row],[Etiquetas]:[Etiquetas17]]),""),"")} -> UAT_V0.15 | AR15: =IF(COUNTIF(Tabla[[#This Row],[Etiquetas]:[Etiquetas17]],"*Devuelto*")>0,"SI","") | AS15: =COUNTIF(Tabla[[#This Row],[Etiquetas]:[Etiquetas17]],"*Devuelto*") -> 0
A16: Error | B16: T20-3701 | C16: 122869 | D16: BOT - Cambio de precio - Es necesario realizar dos clics para que el tipo de señalización “Tachado” funcione correctamente | E16: Medio | F16: Tareas por hacer | R16: Funcional | S16: Imprimir-Cambios-De-Precio | T16: QA-IntegraciónV0.15 | AA16: Yubisleinys Mora Vega | AB16: 46014.553 | AG16: BOT | AH16: CANCELADO | AJ16: {=IFERROR(_xlfn.XLOOKUP(TRUE,COUNTIF(Tabla[[#This Row],[Etiquetas]:[Etiquetas17]],Versiones!$G$2:$G$36)>0,Versiones!$B$2:$B$36), "")} -> 25 | AK16: {=IFERROR(_xlfn.XLOOKUP(TRUE,COUNTIF(Tabla[[#This Row],[Etiquetas]:[Etiquetas17]],Versiones!$G$2:$G$36)>0,Versiones!$A$2:$A$36), "")} -> V0.15 | AL16: ="V"&MAX(IFERROR(VALUE(MID(Tabla[[#This Row],[Versiones corregidas]],2,99)),0), IFERROR(VALUE(MID(Tabla[[#This Row],[Versiones corregidas19]],2,99)),0), IFERROR(VALUE(MID(Tabla[[#This Row],[Versiones corregidas20]],2,99)),0), IFERROR(VALUE(MID(Tabla[[#This Row],[Versiones corregidas21]],2,99)),0),IFERROR(VALUE(MID(#REF!,2,99)),0)) -> V0 | AM16: =IFERROR(_xlfn.XLOOKUP(Tabla[[#This Row],[¿En qué versión fue corregido?]],Versiones!$A$2:$A$34,Versiones!$B$2:$B$34),"No encontrado") -> No encontrado | AN16: {=IFERROR(_xlfn.XLOOKUP(TRUE,COUNTIF(Tabla[[#This Row],[Etiquetas]:[Etiquetas17]],Categorías!$A$2:$A$12)>0,Categorías!$A$2:$A$12),"No encontrado")} -> Funcional | AO16: {=IFERROR(INDEX(Funcionalidades!$A$2:$A$80,MATCH(TRUE, COUNTIF(Reporte_Gral!R16:Z16,Funcionalidades!$A$2:$A$80)>0,0)),"No encontrado")} -> Imprimir-Cambios-De-Precio | AP16: =IF(AND(COUNTIF(Tabla[[#This Row],[Etiquetas]:[Etiquetas17]],"*UAT_V*")>0,COUNTIF(Tabla[[#This Row],[Etiquetas]:[Etiquetas17]],"*QA-Integración*")=0),"SI","") | AQ16: {=IF(Tabla[[#This Row],[Fue encontrado durante UAT?]]="SI",IFERROR(_xlfn.XLOOKUP(TRUE,ISNUMBER(SEARCH("UAT_V",Tabla[[#This Row],[Etiquetas]:[Etiquetas17]])),Tabla[[#This Row],[Etiquetas]:[Etiquetas17]]),""),"")} | AR16: =IF(COUNTIF(Tabla[[#This Row],[Etiquetas]:[Etiquetas17]],"*Devuelto*")>0,"SI","") | AS16: =COUNTIF(Tabla[[#This Row],[Etiquetas]:[Etiquetas17]],"*Devuelto*") -> 0
A17: Error | B17: T20-3692 | C17: 122677 | D17: POS - No existe tope al multiplicar cantidades, generando valores negativos | E17: Medio | F17: Tareas por hacer | R17: Funcional | S17: Multiplicar-Producto | T17: QA-IntegraciónV0.15 | U17: UAT | V17: UAT_V0.15 | AA17: Yubisleinys Mora Vega | AB17: 46013.712 | AG17: POS | AH17: PENDIENTES | AJ17: {=IFERROR(_xlfn.XLOOKUP(TRUE,COUNTIF(Tabla[[#This Row],[Etiquetas]:[Etiquetas17]],Versiones!$G$2:$G$36)>0,Versiones!$B$2:$B$36), "")} -> 25 | AK17: {=IFERROR(_xlfn.XLOOKUP(TRUE,COUNTIF(Tabla[[#This Row],[Etiquetas]:[Etiquetas17]],Versiones!$G$2:$G$36)>0,Versiones!$A$2:$A$36), "")} -> V0.15 | AL17: ="V"&MAX(IFERROR(VALUE(MID(Tabla[[#This Row],[Versiones corregidas]],2,99)),0), IFERROR(VALUE(MID(Tabla[[#This Row],[Versiones corregidas19]],2,99)),0), IFERROR(VALUE(MID(Tabla[[#This Row],[Versiones corregidas20]],2,99)),0), IFERROR(VALUE(MID(Tabla[[#This Row],[Versiones corregidas21]],2,99)),0),IFERROR(VALUE(MID(#REF!,2,99)),0)) -> V0 | AM17: =IFERROR(_xlfn.XLOOKUP(Tabla[[#This Row],[¿En qué versión fue corregido?]],Versiones!$A$2:$A$34,Versiones!$B$2:$B$34),"No encontrado") -> No encontrado | AN17: {=IFERROR(_xlfn.XLOOKUP(TRUE,COUNTIF(Tabla[[#This Row],[Etiquetas]:[Etiquetas17]],Categorías!$A$2:$A$12)>0,Categorías!$A$2:$A$12),"No encontrado")} -> Funcional | AO17: {=IFERROR(INDEX(Funcionalidades!$A$2:$A$80,MATCH(TRUE, COUNTIF(Reporte_Gral!R17:Z17,Funcionalidades!$A$2:$A$80)>0,0)),"No encontrado")} -> Multiplicar-Producto | AP17: =IF(AND(COUNTIF(Tabla[[#This Row],[Etiquetas]:[Etiquetas17]],"*UAT_V*")>0,COUNTIF(Tabla[[#This Row],[Etiquetas]:[Etiquetas17]],"*QA-Integración*")=0),"SI","") | AQ17: {=IF(Tabla[[#This Row],[Fue encontrado durante UAT?]]="SI",IFERROR(_xlfn.XLOOKUP(TRUE,ISNUMBER(SEARCH("UAT_V",Tabla[[#This Row],[Etiquetas]:[Etiquetas17]])),Tabla[[#This Row],[Etiquetas]:[Etiquetas17]]),""),"")} | AR17: =IF(COUNTIF(Tabla[[#This Row],[Etiquetas]:[Etiquetas17]],"*Devuelto*")>0,"SI","") | AS17: =COUNTIF(Tabla[[#This Row],[Etiquetas]:[Etiquetas17]],"*Devuelto*") -> 0
A18: Error | B18: T20-3691 | C18: 122602 | D18: BOT - Desaparición de números en alivios agregados | E18: Medio | F18: Tareas por hacer | R18: Entrega-de-Valores | S18: Funcional | T18: QA-IntegraciónV0.15 | U18: UAT | AA18: Yubisleinys Mora Vega | AB18: 46013.627 | AG18: BOT | AH18: Ludovic Hern | AJ18: {=IFERROR(_xlfn.XLOOKUP(TRUE,COUNTIF(Tabla[[#This Row],[Etiquetas]:[Etiquetas17]],Versiones!$G$2:$G$36)>0,Versiones!$B$2:$B$36), "")} -> 25 | AK18: {=IFERROR(_xlfn.XLOOKUP(TRUE,COUNTIF(Tabla[[#This Row],[Etiquetas]:[Etiquetas17]],Versiones!$G$2:$G$36)>0,Versiones!$A$2:$A$36), "")} -> V0.15 | AL18: ="V"&MAX(IFERROR(VALUE(MID(Tabla[[#This Row],[Versiones corregidas]],2,99)),0), IFERROR(VALUE(MID(Tabla[[#This Row],[Versiones corregidas19]],2,99)),0), IFERROR(VALUE(MID(Tabla[[#This Row],[Versiones corregidas20]],2,99)),0), IFERROR(VALUE(MID(Tabla[[#This Row],[Versiones corregidas21]],2,99)),0),IFERROR(VALUE(MID(#REF!,2,99)),0)) -> V0 | AM18: =IFERROR(_xlfn.XLOOKUP(Tabla[[#This Row],[¿En qué versión fue corregido?]],Versiones!$A$2:$A$34,Versiones!$B$2:$B$34),"No encontrado") -> No encontrado | AN18: {=IFERROR(_xlfn.XLOOKUP(TRUE,COUNTIF(Tabla[[#This Row],[Etiquetas]:[Etiquetas17]],Categorías!$A$2:$A$12)>0,Categorías!$A$2:$A$12),"No encontrado")} -> Funcional | AO18: {=IFERROR(INDEX(Funcionalidades!$A$2:$A$80,MATCH(TRUE, COUNTIF(Reporte_Gral!R18:Z18,Funcionalidades!$A$2:$A$80)>0,0)),"No encontrado")} -> Entrega-De-Valores | AP18: =IF(AND(COUNTIF(Tabla[[#This Row],[Etiquetas]:[Etiquetas17]],"*UAT_V*")>0,COUNTIF(Tabla[[#This Row],[Etiquetas]:[Etiquetas17]],"*QA-Integración*")=0),"SI","") | AQ18: {=IF(Tabla[[#This Row],[Fue encontrado durante UAT?]]="SI",IFERROR(_xlfn.XLOOKUP(TRUE,ISNUMBER(SEARCH("UAT_V",Tabla[[#This Row],[Etiquetas]:[Etiquetas17]])),Tabla[[#This Row],[Etiquetas]:[Etiquetas17]]),""),"")} | AR18: =IF(COUNTIF(Tabla[[#This Row],[Etiquetas]:[Etiquetas17]],"*Devuelto*")>0,"SI","") | AS18: =COUNTIF(Tabla[[#This Row],[Etiquetas]:[Etiquetas17]],"*Devuelto*") -> 0
A19: Error | B19: T20-3690 | C19: 122599 | D19: POS - Pago de Servicio - El último valor agregado no se elimina en el comprobante de servicio | E19: Medio | F19: Tareas por hacer | R19: Funcional | S19: Pago-De-Servicios-Con-Catálogo | T19: QA-IntegraciónV0.15 | U19: Revisado | V19: UAT | AA19: Yubisleinys Mora Vega | AB19: 46013.615 | AG19: POS | AH19: PENDIENTES | AJ19: {=IFERROR(_xlfn.XLOOKUP(TRUE,COUNTIF(Tabla[[#This Row],[Etiquetas]:[Etiquetas17]],Versiones!$G$2:$G$36)>0,Versiones!$B$2:$B$36), "")} -> 25 | AK19: {=IFERROR(_xlfn.XLOOKUP(TRUE,COUNTIF(Tabla[[#This Row],[Etiquetas]:[Etiquetas17]],Versiones!$G$2:$G$36)>0,Versiones!$A$2:$A$36), "")} -> V0.15 | AL19: ="V"&MAX(IFERROR(VALUE(MID(Tabla[[#This Row],[Versiones corregidas]],2,99)),0), IFERROR(VALUE(MID(Tabla[[#This Row],[Versiones corregidas19]],2,99)),0), IFERROR(VALUE(MID(Tabla[[#This Row],[Versiones corregidas20]],2,99)),0), IFERROR(VALUE(MID(Tabla[[#This Row],[Versiones corregidas21]],2,99)),0),IFERROR(VALUE(MID(#REF!,2,99)),0)) -> V0 | AM19: =IFERROR(_xlfn.XLOOKUP(Tabla[[#This Row],[¿En qué versión fue corregido?]],Versiones!$A$2:$A$34,Versiones!$B$2:$B$34),"No encontrado") -> No encontrado | AN19: {=IFERROR(_xlfn.XLOOKUP(TRUE,COUNTIF(Tabla[[#This Row],[Etiquetas]:[Etiquetas17]],Categorías!$A$2:$A$12)>0,Categorías!$A$2:$A$12),"No encontrado")} -> Funcional | AO19: {=IFERROR(INDEX(Funcionalidades!$A$2:$A$80,MATCH(TRUE, COUNTIF(Reporte_Gral!R19:Z19,Funcionalidades!$A$2:$A$80)>0,0)),"No encontrado")} -> Pago-De-Servicios-Con-Catálogo | AP19: =IF(AND(COUNTIF(Tabla[[#This Row],[Etiquetas]:[Etiquetas17]],"*UAT_V*")>0,COUNTIF(Tabla[[#This Row],[Etiquetas]:[Etiquetas17]],"*QA-Integración*")=0),"SI","") | AQ19: {=IF(Tabla[[#This Row],[Fue encontrado durante UAT?]]="SI",IFERROR(_xlfn.XLOOKUP(TRUE,ISNUMBER(SEARCH("UAT_V",Tabla[[#This Row],[Etiquetas]:[Etiquetas17]])),Tabla[[#This Row],[Etiquetas]:[Etiquetas17]]),""),"")} | AR19: =IF(COUNTIF(Tabla[[#This Row],[Etiquetas]:[Etiquetas17]],"*Devuelto*")>0,"SI","") | AS19: =COUNTIF(Tabla[[#This Row],[Etiquetas]:[Etiquetas17]],"*Devuelto*") -> 0
A20: Error | B20: T20-3685 | C20: 122555 | D20: POS - Ticket de cobro con CODI no muestra folio ni número de transacción | E20: Alta | F20: Tareas por hacer | R20: Funcional | S20: Pago-Codi | T20: QA-IntegraciónV0.15 | U20: Revisado | V20: UAT | AA20: Yubisleinys Mora Vega | AB20: 46013.521 | AG20: POS | AH20: PENDIENTES | AJ20: {=IFERROR(_xlfn.XLOOKUP(TRUE,COUNTIF(Tabla[[#This Row],[Etiquetas]:[Etiquetas17]],Versiones!$G$2:$G$36)>0,Versiones!$B$2:$B$36), "")} -> 25 | AK20: {=IFERROR(_xlfn.XLOOKUP(TRUE,COUNTIF(Tabla[[#This Row],[Etiquetas]:[Etiquetas17]],Versiones!$G$2:$G$36)>0,Versiones!$A$2:$A$36), "")} -> V0.15 | AL20: ="V"&MAX(IFERROR(VALUE(MID(Tabla[[#This Row],[Versiones corregidas]],2,99)),0), IFERROR(VALUE(MID(Tabla[[#This Row],[Versiones corregidas19]],2,99)),0), IFERROR(VALUE(MID(Tabla[[#This Row],[Versiones corregidas20]],2,99)),0), IFERROR(VALUE(MID(Tabla[[#This Row],[Versiones corregidas21]],2,99)),0),IFERROR(VALUE(MID(#REF!,2,99)),0)) -> V0 | AM20: =IFERROR(_xlfn.XLOOKUP(Tabla[[#This Row],[¿En qué versión fue corregido?]],Versiones!$A$2:$A$34,Versiones!$B$2:$B$34),"No encontrado") -> No encontrado | AN20: {=IFERROR(_xlfn.XLOOKUP(TRUE,COUNTIF(Tabla[[#This Row],[Etiquetas]:[Etiquetas17]],Categorías!$A$2:$A$12)>0,Categorías!$A$2:$A$12),"No encontrado")} -> Funcional | AO20: {=IFERROR(INDEX(Funcionalidades!$A$2:$A$80,MATCH(TRUE, COUNTIF(Reporte_Gral!R20:Z20,Funcionalidades!$A$2:$A$80)>0,0)),"No encontrado")} -> Pago-CODI | AP20: =IF(AND(COUNTIF(Tabla[[#This Row],[Etiquetas]:[Etiquetas17]],"*UAT_V*")>0,COUNTIF(Tabla[[#This Row],[Etiquetas]:[Etiquetas17]],"*QA-Integración*")=0),"SI","") | AQ20: {=IF(Tabla[[#This Row],[Fue encontrado durante UAT?]]="SI",IFERROR(_xlfn.XLOOKUP(TRUE,ISNUMBER(SEARCH("UAT_V",Tabla[[#This Row],[Etiquetas]:[Etiquetas17]])),Tabla[[#This Row],[Etiquetas]:[Etiquetas17]]),""),"")} | AR20: =IF(COUNTIF(Tabla[[#This Row],[Etiquetas]:[Etiquetas17]],"*Devuelto*")>0,"SI","") | AS20: =COUNTIF(Tabla[[#This Row],[Etiquetas]:[Etiquetas17]],"*Devuelto*") -> 0
A21: Error | B21: T20-3684 | C21: 122543 | D21: POS - Pago de Servicio - No funcionan los atajos de teclado para aceptar Pago de Servicios en el POS | E21: Medio | F21: Tareas por hacer | R21: Funcional | S21: Pago-De-Servicios-Con-Catálogo | T21: QA-IntegraciónV0.15 | U21: UAT | AA21: Yubisleinys Mora Vega | AB21: 46013.497 | AG21: POS | AH21: PENDIENTES | AJ21: {=IFERROR(_xlfn.XLOOKUP(TRUE,COUNTIF(Tabla[[#This Row],[Etiquetas]:[Etiquetas17]],Versiones!$G$2:$G$36)>0,Versiones!$B$2:$B$36), "")} -> 25 | AK21: {=IFERROR(_xlfn.XLOOKUP(TRUE,COUNTIF(Tabla[[#This Row],[Etiquetas]:[Etiquetas17]],Versiones!$G$2:$G$36)>0,Versiones!$A$2:$A$36), "")} -> V0.15 | AL21: ="V"&MAX(IFERROR(VALUE(MID(Tabla[[#This Row],[Versiones corregidas]],2,99)),0), IFERROR(VALUE(MID(Tabla[[#This Row],[Versiones corregidas19]],2,99)),0), IFERROR(VALUE(MID(Tabla[[#This Row],[Versiones corregidas20]],2,99)),0), IFERROR(VALUE(MID(Tabla[[#This Row],[Versiones corregidas21]],2,99)),0),IFERROR(VALUE(MID(#REF!,2,99)),0)) -> V0 | AM21: =IFERROR(_xlfn.XLOOKUP(Tabla[[#This Row],[¿En qué versión fue corregido?]],Versiones!$A$2:$A$34,Versiones!$B$2:$B$34),"No encontrado") -> No encontrado | AN21: {=IFERROR(_xlfn.XLOOKUP(TRUE,COUNTIF(Tabla[[#This Row],[Etiquetas]:[Etiquetas17]],Categorías!$A$2:$A$12)>0,Categorías!$A$2:$A$12),"No encontrado")} -> Funcional | AO21: {=IFERROR(INDEX(Funcionalidades!$A$2:$A$80,MATCH(TRUE, COUNTIF(Reporte_Gral!R21:Z21,Funcionalidades!$A$2:$A$80)>0,0)),"No encontrado")} -> Pago-De-Servicios-Con-Catálogo | AP21: =IF(AND(COUNTIF(Tabla[[#This Row],[Etiquetas]:[Etiquetas17]],"*UAT_V*")>0,COUNTIF(Tabla[[#This Row],[Etiquetas]:[Etiquetas17]],"*QA-Integración*")=0),"SI","") | AQ21: {=IF(Tabla[[#This Row],[Fue encontrado durante UAT?]]="SI",IFERROR(_xlfn.XLOOKUP(TRUE,ISNUMBER(SEARCH("UAT_V",Tabla[[#This Row],[Etiquetas]:[Etiquetas17]])),Tabla[[#This Row],[Etiquetas]:[Etiquetas17]]),""),"")} | AR21: =IF(COUNTIF(Tabla[[#This Row],[Etiquetas]:[Etiquetas17]],"*Devuelto*")>0,"SI","") | AS21: =COUNTIF(Tabla[[#This Row],[Etiquetas]:[Etiquetas17]],"*Devuelto*") -> 0
A22: Error | B22: T20-3683 | C22: 122534 | D22: POS - Pago de Servicio - No se visualiza el monto de la comisión en el ticket | E22: Medio | F22: Tareas por hacer | R22: Funcional | S22: Pago-De-Servicios-Con-Catálogo | T22: QA-IntegraciónV0.15 | U22: Revisado | V22: UAT | AA22: Yubisleinys Mora Vega | AB22: 46013.487 | AG22: POS | AH22: PENDIENTES | AJ22: {=IFERROR(_xlfn.XLOOKUP(TRUE,COUNTIF(Tabla[[#This Row],[Etiquetas]:[Etiquetas17]],Versiones!$G$2:$G$36)>0,Versiones!$B$2:$B$36), "")} -> 25 | AK22: {=IFERROR(_xlfn.XLOOKUP(TRUE,COUNTIF(Tabla[[#This Row],[Etiquetas]:[Etiquetas17]],Versiones!$G$2:$G$36)>0,Versiones!$A$2:$A$36), "")} -> V0.15 | AL22: ="V"&MAX(IFERROR(VALUE(MID(Tabla[[#This Row],[Versiones corregidas]],2,99)),0), IFERROR(VALUE(MID(Tabla[[#This Row],[Versiones corregidas19]],2,99)),0), IFERROR(VALUE(MID(Tabla[[#This Row],[Versiones corregidas20]],2,99)),0), IFERROR(VALUE(MID(Tabla[[#This Row],[Versiones corregidas21]],2,99)),0),IFERROR(VALUE(MID(#REF!,2,99)),0)) -> V0 | AM22: =IFERROR(_xlfn.XLOOKUP(Tabla[[#This Row],[¿En qué versión fue corregido?]],Versiones!$A$2:$A$34,Versiones!$B$2:$B$34),"No encontrado") -> No encontrado | AN22: {=IFERROR(_xlfn.XLOOKUP(TRUE,COUNTIF(Tabla[[#This Row],[Etiquetas]:[Etiquetas17]],Categorías!$A$2:$A$12)>0,Categorías!$A$2:$A$12),"No encontrado")} -> Funcional | AO22: {=IFERROR(INDEX(Funcionalidades!$A$2:$A$80,MATCH(TRUE, COUNTIF(Reporte_Gral!R22:Z22,Funcionalidades!$A$2:$A$80)>0,0)),"No encontrado")} -> Pago-De-Servicios-Con-Catálogo | AP22: =IF(AND(COUNTIF(Tabla[[#This Row],[Etiquetas]:[Etiquetas17]],"*UAT_V*")>0,COUNTIF(Tabla[[#This Row],[Etiquetas]:[Etiquetas17]],"*QA-Integración*")=0),"SI","") | AQ22: {=IF(Tabla[[#This Row],[Fue encontrado durante UAT?]]="SI",IFERROR(_xlfn.XLOOKUP(TRUE,ISNUMBER(SEARCH("UAT_V",Tabla[[#This Row],[Etiquetas]:[Etiquetas17]])),Tabla[[#This Row],[Etiquetas]:[Etiquetas17]]),""),"")} | AR22: =IF(COUNTIF(Tabla[[#This Row],[Etiquetas]:[Etiquetas17]],"*Devuelto*")>0,"SI","") | AS22: =COUNTIF(Tabla[[#This Row],[Etiquetas]:[Etiquetas17]],"*Devuelto*") -> 0
A23: Error | B23: T20-3681 | C23: 122511 | D23: BOT - El sistema permite realizar una entrega de valores aun cuando no hay dinero disponible, generando saldos negativos. | E23: Más alta | F23: Tareas por hacer | G23: T20 Sprint 26 2025 | R23: Entrega-de-Valores | S23: Funcional | T23: QA-IntegraciónV0.15 | U23: T3B20_BOT | V23: Tienda2.0 | W23: UAT | AA23: Yubisleinys Mora Vega | AB23: 46013.455 | AG23: BOT | AH23: PENDIENTES | AJ23: {=IFERROR(_xlfn.XLOOKUP(TRUE,COUNTIF(Tabla[[#This Row],[Etiquetas]:[Etiquetas17]],Versiones!$G$2:$G$36)>0,Versiones!$B$2:$B$36), "")} -> 25 | AK23: {=IFERROR(_xlfn.XLOOKUP(TRUE,COUNTIF(Tabla[[#This Row],[Etiquetas]:[Etiquetas17]],Versiones!$G$2:$G$36)>0,Versiones!$A$2:$A$36), "")} -> V0.15 | AL23: ="V"&MAX(IFERROR(VALUE(MID(Tabla[[#This Row],[Versiones corregidas]],2,99)),0), IFERROR(VALUE(MID(Tabla[[#This Row],[Versiones corregidas19]],2,99)),0), IFERROR(VALUE(MID(Tabla[[#This Row],[Versiones corregidas20]],2,99)),0), IFERROR(VALUE(MID(Tabla[[#This Row],[Versiones corregidas21]],2,99)),0),IFERROR(VALUE(MID(#REF!,2,99)),0)) -> V0 | AM23: =IFERROR(_xlfn.XLOOKUP(Tabla[[#This Row],[¿En qué versión fue corregido?]],Versiones!$A$2:$A$34,Versiones!$B$2:$B$34),"No encontrado") -> No encontrado | AN23: {=IFERROR(_xlfn.XLOOKUP(TRUE,COUNTIF(Tabla[[#This Row],[Etiquetas]:[Etiquetas17]],Categorías!$A$2:$A$12)>0,Categorías!$A$2:$A$12),"No encontrado")} -> Funcional | AO23: {=IFERROR(INDEX(Funcionalidades!$A$2:$A$80,MATCH(TRUE, COUNTIF(Reporte_Gral!R23:Z23,Funcionalidades!$A$2:$A$80)>0,0)),"No encontrado")} -> Entrega-De-Valores | AP23: =IF(AND(COUNTIF(Tabla[[#This Row],[Etiquetas]:[Etiquetas17]],"*UAT_V*")>0,COUNTIF(Tabla[[#This Row],[Etiquetas]:[Etiquetas17]],"*QA-Integración*")=0),"SI","") | AQ23: {=IF(Tabla[[#This Row],[Fue encontrado durante UAT?]]="SI",IFERROR(_xlfn.XLOOKUP(TRUE,ISNUMBER(SEARCH("UAT_V",Tabla[[#This Row],[Etiquetas]:[Etiquetas17]])),Tabla[[#This Row],[Etiquetas]:[Etiquetas17]]),""),"")} | AR23: =IF(COUNTIF(Tabla[[#This Row],[Etiquetas]:[Etiquetas17]],"*Devuelto*")>0,"SI","") | AS23: =COUNTIF(Tabla[[#This Row],[Etiquetas]:[Etiquetas17]],"*Devuelto*") -> 0
A24: Error | B24: T20-3670 | C24: 122248 | D24: BOT/POS - Cancelación de productos genera descuento incorrecto de stock y unidades vendidas erróneas en Dashboard de ventas | E24: Alta | F24: Tareas por hacer | R24: Eliminar-Artículo-De-Venta | S24: Funcional | T24: QA-IntegraciónV0.15 | AA24: Yubisleinys Mora Vega | AB24: 46010.61 | AG24: BOT | AH24: PENDIENTES | AJ24: {=IFERROR(_xlfn.XLOOKUP(TRUE,COUNTIF(Tabla[[#This Row],[Etiquetas]:[Etiquetas17]],Versiones!$G$2:$G$36)>0,Versiones!$B$2:$B$36), "")} -> 25 | AK24: {=IFERROR(_xlfn.XLOOKUP(TRUE,COUNTIF(Tabla[[#This Row],[Etiquetas]:[Etiquetas17]],Versiones!$G$2:$G$36)>0,Versiones!$A$2:$A$36), "")} -> V0.15 | AL24: ="V"&MAX(IFERROR(VALUE(MID(Tabla[[#This Row],[Versiones corregidas]],2,99)),0), IFERROR(VALUE(MID(Tabla[[#This Row],[Versiones corregidas19]],2,99)),0), IFERROR(VALUE(MID(Tabla[[#This Row],[Versiones corregidas20]],2,99)),0), IFERROR(VALUE(MID(Tabla[[#This Row],[Versiones corregidas21]],2,99)),0),IFERROR(VALUE(MID(#REF!,2,99)),0)) -> V0 | AM24: =IFERROR(_xlfn.XLOOKUP(Tabla[[#This Row],[¿En qué versión fue corregido?]],Versiones!$A$2:$A$34,Versiones!$B$2:$B$34),"No encontrado") -> No encontrado | AN24: {=IFERROR(_xlfn.XLOOKUP(TRUE,COUNTIF(Tabla[[#This Row],[Etiquetas]:[Etiquetas17]],Categorías!$A$2:$A$12)>0,Categorías!$A$2:$A$12),"No encontrado")} -> Funcional | AO24: {=IFERROR(INDEX(Funcionalidades!$A$2:$A$80,MATCH(TRUE, COUNTIF(Reporte_Gral!R24:Z24,Funcionalidades!$A$2:$A$80)>0,0)),"No encontrado")} -> Eliminar-Artículo-De-Venta | AP24: =IF(AND(COUNTIF(Tabla[[#This Row],[Etiquetas]:[Etiquetas17]],"*UAT_V*")>0,COUNTIF(Tabla[[#This Row],[Etiquetas]:[Etiquetas17]],"*QA-Integración*")=0),"SI","") | AQ24: {=IF(Tabla[[#This Row],[Fue encontrado durante UAT?]]="SI",IFERROR(_xlfn.XLOOKUP(TRUE,ISNUMBER(SEARCH("UAT_V",Tabla[[#This Row],[Etiquetas]:[Etiquetas17]])),Tabla[[#This Row],[Etiquetas]:[Etiquetas17]]),""),"")} | AR24: =IF(COUNTIF(Tabla[[#This Row],[Etiquetas]:[Etiquetas17]],"*Devuelto*")>0,"SI","") | AS24: =COUNTIF(Tabla[[#This Row],[Etiquetas]:[Etiquetas17]],"*Devuelto*") -> 0
A25: Error | B25: T20-3669 | C25: 122179 | D25: BOT - Modal Transferir mercancía no muestra botón para minimizar | E25: Medio | F25: Tareas por hacer | R25: Funcional | S25: QA-IntegraciónV0.15 | T25: Realizar-Transferencia | U25: Revisar_Diseño | AA25: Yubisleinys Mora Vega | AB25: 46010.48 | AG25: BOT | AH25: PENDIENTES | AJ25: {=IFERROR(_xlfn.XLOOKUP(TRUE,COUNTIF(Tabla[[#This Row],[Etiquetas]:[Etiquetas17]],Versiones!$G$2:$G$36)>0,Versiones!$B$2:$B$36), "")} -> 25 | AK25: {=IFERROR(_xlfn.XLOOKUP(TRUE,COUNTIF(Tabla[[#This Row],[Etiquetas]:[Etiquetas17]],Versiones!$G$2:$G$36)>0,Versiones!$A$2:$A$36), "")} -> V0.15 | AL25: ="V"&MAX(IFERROR(VALUE(MID(Tabla[[#This Row],[Versiones corregidas]],2,99)),0), IFERROR(VALUE(MID(Tabla[[#This Row],[Versiones corregidas19]],2,99)),0), IFERROR(VALUE(MID(Tabla[[#This Row],[Versiones corregidas20]],2,99)),0), IFERROR(VALUE(MID(Tabla[[#This Row],[Versiones corregidas21]],2,99)),0),IFERROR(VALUE(MID(#REF!,2,99)),0)) -> V0 | AM25: =IFERROR(_xlfn.XLOOKUP(Tabla[[#This Row],[¿En qué versión fue corregido?]],Versiones!$A$2:$A$34,Versiones!$B$2:$B$34),"No encontrado") -> No encontrado | AN25: {=IFERROR(_xlfn.XLOOKUP(TRUE,COUNTIF(Tabla[[#This Row],[Etiquetas]:[Etiquetas17]],Categorías!$A$2:$A$12)>0,Categorías!$A$2:$A$12),"No encontrado")} -> Funcional | AO25: {=IFERROR(INDEX(Funcionalidades!$A$2:$A$80,MATCH(TRUE, COUNTIF(Reporte_Gral!R25:Z25,Funcionalidades!$A$2:$A$80)>0,0)),"No encontrado")} -> Realizar-Transferencia | AP25: =IF(AND(COUNTIF(Tabla[[#This Row],[Etiquetas]:[Etiquetas17]],"*UAT_V*")>0,COUNTIF(Tabla[[#This Row],[Etiquetas]:[Etiquetas17]],"*QA-Integración*")=0),"SI","") | AQ25: {=IF(Tabla[[#This Row],[Fue encontrado durante UAT?]]="SI",IFERROR(_xlfn.XLOOKUP(TRUE,ISNUMBER(SEARCH("UAT_V",Tabla[[#This Row],[Etiquetas]:[Etiquetas17]])),Tabla[[#This Row],[Etiquetas]:[Etiquetas17]]),""),"")} | AR25: =IF(COUNTIF(Tabla[[#This Row],[Etiquetas]:[Etiquetas17]],"*Devuelto*")>0,"SI","") | AS25: =COUNTIF(Tabla[[#This Row],[Etiquetas]:[Etiquetas17]],"*Devuelto*") -> 0
A26: Error | B26: T20-3668 | C26: 122115 | D26: BOT - Modal Recibir mercancía no se visualiza botón para minimizar | E26: Alta | F26: Tareas por hacer | R26: Funcional | S26: QA-IntegraciónV0.15 | T26: Recibir-Mercancía-Almacén-Tienda | U26: Revisar_Diseño | AA26: Yubisleinys Mora Vega | AB26: 46010.382 | AG26: BOT | AH26: CANCELADO | AJ26: {=IFERROR(_xlfn.XLOOKUP(TRUE,COUNTIF(Tabla[[#This Row],[Etiquetas]:[Etiquetas17]],Versiones!$G$2:$G$36)>0,Versiones!$B$2:$B$36), "")} -> 25 | AK26: {=IFERROR(_xlfn.XLOOKUP(TRUE,COUNTIF(Tabla[[#This Row],[Etiquetas]:[Etiquetas17]],Versiones!$G$2:$G$36)>0,Versiones!$A$2:$A$36), "")} -> V0.15 | AL26: ="V"&MAX(IFERROR(VALUE(MID(Tabla[[#This Row],[Versiones corregidas]],2,99)),0), IFERROR(VALUE(MID(Tabla[[#This Row],[Versiones corregidas19]],2,99)),0), IFERROR(VALUE(MID(Tabla[[#This Row],[Versiones corregidas20]],2,99)),0), IFERROR(VALUE(MID(Tabla[[#This Row],[Versiones corregidas21]],2,99)),0),IFERROR(VALUE(MID(#REF!,2,99)),0)) -> V0 | AM26: =IFERROR(_xlfn.XLOOKUP(Tabla[[#This Row],[¿En qué versión fue corregido?]],Versiones!$A$2:$A$34,Versiones!$B$2:$B$34),"No encontrado") -> No encontrado | AN26: {=IFERROR(_xlfn.XLOOKUP(TRUE,COUNTIF(Tabla[[#This Row],[Etiquetas]:[Etiquetas17]],Categorías!$A$2:$A$12)>0,Categorías!$A$2:$A$12),"No encontrado")} -> Funcional | AO26: {=IFERROR(INDEX(Funcionalidades!$A$2:$A$80,MATCH(TRUE, COUNTIF(Reporte_Gral!R26:Z26,Funcionalidades!$A$2:$A$80)>0,0)),"No encontrado")} -> Recibir-Mercancía-Almacén-Tienda | AP26: =IF(AND(COUNTIF(Tabla[[#This Row],[Etiquetas]:[Etiquetas17]],"*UAT_V*")>0,COUNTIF(Tabla[[#This Row],[Etiquetas]:[Etiquetas17]],"*QA-Integración*")=0),"SI","") | AQ26: {=IF(Tabla[[#This Row],[Fue encontrado durante UAT?]]="SI",IFERROR(_xlfn.XLOOKUP(TRUE,ISNUMBER(SEARCH("UAT_V",Tabla[[#This Row],[Etiquetas]:[Etiquetas17]])),Tabla[[#This Row],[Etiquetas]:[Etiquetas17]]),""),"")} | AR26: =IF(COUNTIF(Tabla[[#This Row],[Etiquetas]:[Etiquetas17]],"*Devuelto*")>0,"SI","") | AS26: =COUNTIF(Tabla[[#This Row],[Etiquetas]:[Etiquetas17]],"*Devuelto*") -> 0
A27: Error | B27: T20-3667 | C27: 122110 | D27: BOT - No se muestra botón [-] minimizar en panel "Configuración de Etiquetas" | E27: Medio | F27: Tareas por hacer | R27: configuracion-de-etiquetas | S27: Funcional | T27: Imprimir-Cambios-De-Precio | U27: QA-IntegraciónV0.15 | V27: Revisar_Diseño | AA27: Daniela Soto | AB27: 46010.372 | AG27: BOT | AH27: Sergio Ordaz Romero | AJ27: {=IFERROR(_xlfn.XLOOKUP(TRUE,COUNTIF(Tabla[[#This Row],[Etiquetas]:[Etiquetas17]],Versiones!$G$2:$G$36)>0,Versiones!$B$2:$B$36), "")} -> 25 | AK27: {=IFERROR(_xlfn.XLOOKUP(TRUE,COUNTIF(Tabla[[#This Row],[Etiquetas]:[Etiquetas17]],Versiones!$G$2:$G$36)>0,Versiones!$A$2:$A$36), "")} -> V0.15 | AL27: ="V"&MAX(IFERROR(VALUE(MID(Tabla[[#This Row],[Versiones corregidas]],2,99)),0), IFERROR(VALUE(MID(Tabla[[#This Row],[Versiones corregidas19]],2,99)),0), IFERROR(VALUE(MID(Tabla[[#This Row],[Versiones corregidas20]],2,99)),0), IFERROR(VALUE(MID(Tabla[[#This Row],[Versiones corregidas21]],2,99)),0),IFERROR(VALUE(MID(#REF!,2,99)),0)) -> V0 | AM27: =IFERROR(_xlfn.XLOOKUP(Tabla[[#This Row],[¿En qué versión fue corregido?]],Versiones!$A$2:$A$34,Versiones!$B$2:$B$34),"No encontrado") -> No encontrado | AN27: {=IFERROR(_xlfn.XLOOKUP(TRUE,COUNTIF(Tabla[[#This Row],[Etiquetas]:[Etiquetas17]],Categorías!$A$2:$A$12)>0,Categorías!$A$2:$A$12),"No encontrado")} -> Funcional | AO27: {=IFERROR(INDEX(Funcionalidades!$A$2:$A$80,MATCH(TRUE, COUNTIF(Reporte_Gral!R27:Z27,Funcionalidades!$A$2:$A$80)>0,0)),"No encontrado")} -> Imprimir-Cambios-De-Precio | AP27: =IF(AND(COUNTIF(Tabla[[#This Row],[Etiquetas]:[Etiquetas17]],"*UAT_V*")>0,COUNTIF(Tabla[[#This Row],[Etiquetas]:[Etiquetas17]],"*QA-Integración*")=0),"SI","") | AQ27: {=IF(Tabla[[#This Row],[Fue encontrado durante UAT?]]="SI",IFERROR(_xlfn.XLOOKUP(TRUE,ISNUMBER(SEARCH("UAT_V",Tabla[[#This Row],[Etiquetas]:[Etiquetas17]])),Tabla[[#This Row],[Etiquetas]:[Etiquetas17]]),""),"")} | AR27: =IF(COUNTIF(Tabla[[#This Row],[Etiquetas]:[Etiquetas17]],"*Devuelto*")>0,"SI","") | AS27: =COUNTIF(Tabla[[#This Row],[Etiquetas]:[Etiquetas17]],"*Devuelto*") -> 0
A28: Error | B28: T20-3664 | C28: 122099 | D28: BOT - Errores en modal "Recibir mercancía" | E28: Medio | F28: Tareas por hacer | R28: Funcional | S28: QA-IntegraciónV0.15 | T28: Recibir-Mercancía-Almacén-Tienda | AA28: Yubisleinys Mora Vega | AB28: 46010.347 | AG28: BOT | AH28: Juan Camilo Collantes Tovar | AJ28: {=IFERROR(_xlfn.XLOOKUP(TRUE,COUNTIF(Tabla[[#This Row],[Etiquetas]:[Etiquetas17]],Versiones!$G$2:$G$36)>0,Versiones!$B$2:$B$36), "")} -> 25 | AK28: {=IFERROR(_xlfn.XLOOKUP(TRUE,COUNTIF(Tabla[[#This Row],[Etiquetas]:[Etiquetas17]],Versiones!$G$2:$G$36)>0,Versiones!$A$2:$A$36), "")} -> V0.15 | AL28: ="V"&MAX(IFERROR(VALUE(MID(Tabla[[#This Row],[Versiones corregidas]],2,99)),0), IFERROR(VALUE(MID(Tabla[[#This Row],[Versiones corregidas19]],2,99)),0), IFERROR(VALUE(MID(Tabla[[#This Row],[Versiones corregidas20]],2,99)),0), IFERROR(VALUE(MID(Tabla[[#This Row],[Versiones corregidas21]],2,99)),0),IFERROR(VALUE(MID(#REF!,2,99)),0)) -> V0 | AM28: =IFERROR(_xlfn.XLOOKUP(Tabla[[#This Row],[¿En qué versión fue corregido?]],Versiones!$A$2:$A$34,Versiones!$B$2:$B$34),"No encontrado") -> No encontrado | AN28: {=IFERROR(_xlfn.XLOOKUP(TRUE,COUNTIF(Tabla[[#This Row],[Etiquetas]:[Etiquetas17]],Categorías!$A$2:$A$12)>0,Categorías!$A$2:$A$12),"No encontrado")} -> Funcional | AO28: {=IFERROR(INDEX(Funcionalidades!$A$2:$A$80,MATCH(TRUE, COUNTIF(Reporte_Gral!R28:Z28,Funcionalidades!$A$2:$A$80)>0,0)),"No encontrado")} -> Recibir-Mercancía-Almacén-Tienda | AP28: =IF(AND(COUNTIF(Tabla[[#This Row],[Etiquetas]:[Etiquetas17]],"*UAT_V*")>0,COUNTIF(Tabla[[#This Row],[Etiquetas]:[Etiquetas17]],"*QA-Integración*")=0),"SI","") | AQ28: {=IF(Tabla[[#This Row],[Fue encontrado durante UAT?]]="SI",IFERROR(_xlfn.XLOOKUP(TRUE,ISNUMBER(SEARCH("UAT_V",Tabla[[#This Row],[Etiquetas]:[Etiquetas17]])),Tabla[[#This Row],[Etiquetas]:[Etiquetas17]]),""),"")} | AR28: =IF(COUNTIF(Tabla[[#This Row],[Etiquetas]:[Etiquetas17]],"*Devuelto*")>0,"SI","") | AS28: =COUNTIF(Tabla[[#This Row],[Etiquetas]:[Etiquetas17]],"*Devuelto*") -> 0
A29: Error | B29: T20-3663 | C29: 121959 | D29: POS - No se visualizan los atajos de los pagos electrónico (D - C - I) | E29: Medio | F29: TO BE DEPLOYED-SIT | G29: T20 Sprint 25 2025 | H29: T20 Sprint 26 2025 | R29: Look&Feel | S29: Pago-Con-Tarjeta | T29: QA-IntegraciónV0.15 | U29: T3B20_POS | V29: Tienda2.0 | AA29: Daniela Soto | AB29: 46009.61 | AC29: v0.16 | AG29: POS | AH29: Juan Camilo Collantes Tovar | AJ29: {=IFERROR(_xlfn.XLOOKUP(TRUE,COUNTIF(Tabla[[#This Row],[Etiquetas]:[Etiquetas17]],Versiones!$G$2:$G$36)>0,Versiones!$B$2:$B$36), "")} -> 25 | AK29: {=IFERROR(_xlfn.XLOOKUP(TRUE,COUNTIF(Tabla[[#This Row],[Etiquetas]:[Etiquetas17]],Versiones!$G$2:$G$36)>0,Versiones!$A$2:$A$36), "")} -> V0.15 | AL29: ="V"&MAX(IFERROR(VALUE(MID(Tabla[[#This Row],[Versiones corregidas]],2,99)),0), IFERROR(VALUE(MID(Tabla[[#This Row],[Versiones corregidas19]],2,99)),0), IFERROR(VALUE(MID(Tabla[[#This Row],[Versiones corregidas20]],2,99)),0), IFERROR(VALUE(MID(Tabla[[#This Row],[Versiones corregidas21]],2,99)),0),IFERROR(VALUE(MID(#REF!,2,99)),0)) -> V0.16 | AM29: =IFERROR(_xlfn.XLOOKUP(Tabla[[#This Row],[¿En qué versión fue corregido?]],Versiones!$A$2:$A$34,Versiones!$B$2:$B$34),"No encontrado") -> 0 | AN29: {=IFERROR(_xlfn.XLOOKUP(TRUE,COUNTIF(Tabla[[#This Row],[Etiquetas]:[Etiquetas17]],Categorías!$A$2:$A$12)>0,Categorías!$A$2:$A$12),"No encontrado")} -> Look&Feel | AO29: {=IFERROR(INDEX(Funcionalidades!$A$2:$A$80,MATCH(TRUE, COUNTIF(Reporte_Gral!R29:Z29,Funcionalidades!$A$2:$A$80)>0,0)),"No encontrado")} -> Pago-Con-Tarjeta | AP29: =IF(AND(COUNTIF(Tabla[[#This Row],[Etiquetas]:[Etiquetas17]],"*UAT_V*")>0,COUNTIF(Tabla[[#This Row],[Etiquetas]:[Etiquetas17]],"*QA-Integración*")=0),"SI","") | AQ29: {=IF(Tabla[[#This Row],[Fue encontrado durante UAT?]]="SI",IFERROR(_xlfn.XLOOKUP(TRUE,ISNUMBER(SEARCH("UAT_V",Tabla[[#This Row],[Etiquetas]:[Etiquetas17]])),Tabla[[#This Row],[Etiquetas]:[Etiquetas17]]),""),"")} | AR29: =IF(COUNTIF(Tabla[[#This Row],[Etiquetas]:[Etiquetas17]],"*Devuelto*")>0,"SI","") | AS29: =COUNTIF(Tabla[[#This Row],[Etiquetas]:[Etiquetas17]],"*Devuelto*") -> 0
A30: Error | B30: T20-3662 | C30: 121956 | D30: BOT - Cambio de precio - No se visualiza el modal Edición de impresión por producto | E30: Medio | F30: Blocked | R30: Configuración | S30: Imprimir-Cambios-De-Precio | T30: QA-IntegraciónV0.15 | AA30: Yubisleinys Mora Vega | AB30: 46009.602 | AG30: BOT | AJ30: {=IFERROR(_xlfn.XLOOKUP(TRUE,COUNTIF(Tabla[[#This Row],[Etiquetas]:[Etiquetas17]],Versiones!$G$2:$G$36)>0,Versiones!$B$2:$B$36), "")} -> 25 | AK30: {=IFERROR(_xlfn.XLOOKUP(TRUE,COUNTIF(Tabla[[#This Row],[Etiquetas]:[Etiquetas17]],Versiones!$G$2:$G$36)>0,Versiones!$A$2:$A$36), "")} -> V0.15 | AL30: ="V"&MAX(IFERROR(VALUE(MID(Tabla[[#This Row],[Versiones corregidas]],2,99)),0), IFERROR(VALUE(MID(Tabla[[#This Row],[Versiones corregidas19]],2,99)),0), IFERROR(VALUE(MID(Tabla[[#This Row],[Versiones corregidas20]],2,99)),0), IFERROR(VALUE(MID(Tabla[[#This Row],[Versiones corregidas21]],2,99)),0),IFERROR(VALUE(MID(#REF!,2,99)),0)) -> V0 | AM30: =IFERROR(_xlfn.XLOOKUP(Tabla[[#This Row],[¿En qué versión fue corregido?]],Versiones!$A$2:$A$34,Versiones!$B$2:$B$34),"No encontrado") -> No encontrado | AN30: {=IFERROR(_xlfn.XLOOKUP(TRUE,COUNTIF(Tabla[[#This Row],[Etiquetas]:[Etiquetas17]],Categorías!$A$2:$A$12)>0,Categorías!$A$2:$A$12),"No encontrado")} -> Configuración | AO30: {=IFERROR(INDEX(Funcionalidades!$A$2:$A$80,MATCH(TRUE, COUNTIF(Reporte_Gral!R30:Z30,Funcionalidades!$A$2:$A$80)>0,0)),"No encontrado")} -> Imprimir-Cambios-De-Precio | AP30: =IF(AND(COUNTIF(Tabla[[#This Row],[Etiquetas]:[Etiquetas17]],"*UAT_V*")>0,COUNTIF(Tabla[[#This Row],[Etiquetas]:[Etiquetas17]],"*QA-Integración*")=0),"SI","") | AQ30: {=IF(Tabla[[#This Row],[Fue encontrado durante UAT?]]="SI",IFERROR(_xlfn.XLOOKUP(TRUE,ISNUMBER(SEARCH("UAT_V",Tabla[[#This Row],[Etiquetas]:[Etiquetas17]])),Tabla[[#This Row],[Etiquetas]:[Etiquetas17]]),""),"")} | AR30: =IF(COUNTIF(Tabla[[#This Row],[Etiquetas]:[Etiquetas17]],"*Devuelto*")>0,"SI","") | AS30: =COUNTIF(Tabla[[#This Row],[Etiquetas]:[Etiquetas17]],"*Devuelto*") -> 0
A31: Error | B31: T20-3661 | C31: 121955 | D31: BOT - Error en flechas de cenefas - Impresión por productos | E31: Alta | F31: READY FOR UAT | G31: T20 Sprint 25 2025 | H31: T20 Sprint 26 2025 | R31: Imprimir-Cambios-De-Precio | S31: Look&Feel | T31: QA-IntegraciónV0.15 | U31: T3B20_BOT | V31: Tienda2.0 | AA31: Daniela Soto | AB31: 46009.602 | AC31: v0.15 | AG31: BOT | AJ31: {=IFERROR(_xlfn.XLOOKUP(TRUE,COUNTIF(Tabla[[#This Row],[Etiquetas]:[Etiquetas17]],Versiones!$G$2:$G$36)>0,Versiones!$B$2:$B$36), "")} -> 25 | AK31: {=IFERROR(_xlfn.XLOOKUP(TRUE,COUNTIF(Tabla[[#This Row],[Etiquetas]:[Etiquetas17]],Versiones!$G$2:$G$36)>0,Versiones!$A$2:$A$36), "")} -> V0.15 | AL31: ="V"&MAX(IFERROR(VALUE(MID(Tabla[[#This Row],[Versiones corregidas]],2,99)),0), IFERROR(VALUE(MID(Tabla[[#This Row],[Versiones corregidas19]],2,99)),0), IFERROR(VALUE(MID(Tabla[[#This Row],[Versiones corregidas20]],2,99)),0), IFERROR(VALUE(MID(Tabla[[#This Row],[Versiones corregidas21]],2,99)),0),IFERROR(VALUE(MID(#REF!,2,99)),0)) -> V0.15 | AM31: =IFERROR(_xlfn.XLOOKUP(Tabla[[#This Row],[¿En qué versión fue corregido?]],Versiones!$A$2:$A$34,Versiones!$B$2:$B$34),"No encontrado") -> 25 | AN31: {=IFERROR(_xlfn.XLOOKUP(TRUE,COUNTIF(Tabla[[#This Row],[Etiquetas]:[Etiquetas17]],Categorías!$A$2:$A$12)>0,Categorías!$A$2:$A$12),"No encontrado")} -> Look&Feel | AO31: {=IFERROR(INDEX(Funcionalidades!$A$2:$A$80,MATCH(TRUE, COUNTIF(Reporte_Gral!R31:Z31,Funcionalidades!$A$2:$A$80)>0,0)),"No encontrado")} -> Imprimir-Cambios-De-Precio | AP31: =IF(AND(COUNTIF(Tabla[[#This Row],[Etiquetas]:[Etiquetas17]],"*UAT_V*")>0,COUNTIF(Tabla[[#This Row],[Etiquetas]:[Etiquetas17]],"*QA-Integración*")=0),"SI","") | AQ31: {=IF(Tabla[[#This Row],[Fue encontrado durante UAT?]]="SI",IFERROR(_xlfn.XLOOKUP(TRUE,ISNUMBER(SEARCH("UAT_V",Tabla[[#This Row],[Etiquetas]:[Etiquetas17]])),Tabla[[#This Row],[Etiquetas]:[Etiquetas17]]),""),"")} | AR31: =IF(COUNTIF(Tabla[[#This Row],[Etiquetas]:[Etiquetas17]],"*Devuelto*")>0,"SI","") | AS31: =COUNTIF(Tabla[[#This Row],[Etiquetas]:[Etiquetas17]],"*Devuelto*") -> 0
A32: Error | B32: T20-3636 | C32: 121365 | D32: POS – Permite finalizar la venta de productos con stock cero y deja la existencia en negativa | E32: Medio | F32: Cancelado | R32: Dashboard-Productos | S32: Funcional | T32: QA-IntegraciónV0.15 | AA32: Yubisleinys Mora Vega | AB32: 46007.656 | AG32: BOT | AJ32: {=IFERROR(_xlfn.XLOOKUP(TRUE,COUNTIF(Tabla[[#This Row],[Etiquetas]:[Etiquetas17]],Versiones!$G$2:$G$36)>0,Versiones!$B$2:$B$36), "")} -> 25 | AK32: {=IFERROR(_xlfn.XLOOKUP(TRUE,COUNTIF(Tabla[[#This Row],[Etiquetas]:[Etiquetas17]],Versiones!$G$2:$G$36)>0,Versiones!$A$2:$A$36), "")} -> V0.15 | AL32: ="V"&MAX(IFERROR(VALUE(MID(Tabla[[#This Row],[Versiones corregidas]],2,99)),0), IFERROR(VALUE(MID(Tabla[[#This Row],[Versiones corregidas19]],2,99)),0), IFERROR(VALUE(MID(Tabla[[#This Row],[Versiones corregidas20]],2,99)),0), IFERROR(VALUE(MID(Tabla[[#This Row],[Versiones corregidas21]],2,99)),0),IFERROR(VALUE(MID(#REF!,2,99)),0)) -> V0 | AM32: =IFERROR(_xlfn.XLOOKUP(Tabla[[#This Row],[¿En qué versión fue corregido?]],Versiones!$A$2:$A$34,Versiones!$B$2:$B$34),"No encontrado") -> No encontrado | AN32: {=IFERROR(_xlfn.XLOOKUP(TRUE,COUNTIF(Tabla[[#This Row],[Etiquetas]:[Etiquetas17]],Categorías!$A$2:$A$12)>0,Categorías!$A$2:$A$12),"No encontrado")} -> Funcional | AO32: {=IFERROR(INDEX(Funcionalidades!$A$2:$A$80,MATCH(TRUE, COUNTIF(Reporte_Gral!R32:Z32,Funcionalidades!$A$2:$A$80)>0,0)),"No encontrado")} -> Dashboard-Productos | AP32: =IF(AND(COUNTIF(Tabla[[#This Row],[Etiquetas]:[Etiquetas17]],"*UAT_V*")>0,COUNTIF(Tabla[[#This Row],[Etiquetas]:[Etiquetas17]],"*QA-Integración*")=0),"SI","") | AQ32: {=IF(Tabla[[#This Row],[Fue encontrado durante UAT?]]="SI",IFERROR(_xlfn.XLOOKUP(TRUE,ISNUMBER(SEARCH("UAT_V",Tabla[[#This Row],[Etiquetas]:[Etiquetas17]])),Tabla[[#This Row],[Etiquetas]:[Etiquetas17]]),""),"")} | AR32: =IF(COUNTIF(Tabla[[#This Row],[Etiquetas]:[Etiquetas17]],"*Devuelto*")>0,"SI","") | AS32: =COUNTIF(Tabla[[#This Row],[Etiquetas]:[Etiquetas17]],"*Devuelto*") -> 0
A33: Error | B33: T20-3632 | C33: 121349 | D33: BOT - Cierre de turno con diferencia faltante mantiene saldo en Total efectivo y lo suma al turno siguiente | E33: Medio | F33: TO BE DEPLOYED-SIT | G33: T20 Sprint 26 2025 | R33: Funcional | S33: Main-Dashboard | T33: QA-IntegraciónV0.15 | U33: T3B20_BOT | V33: Tienda2.0 | AA33: Yubisleinys Mora Vega | AB33: 46007.622 | AC33: v0.16 | AG33: BOT | AJ33: {=IFERROR(_xlfn.XLOOKUP(TRUE,COUNTIF(Tabla[[#This Row],[Etiquetas]:[Etiquetas17]],Versiones!$G$2:$G$36)>0,Versiones!$B$2:$B$36), "")} -> 25 | AK33: {=IFERROR(_xlfn.XLOOKUP(TRUE,COUNTIF(Tabla[[#This Row],[Etiquetas]:[Etiquetas17]],Versiones!$G$2:$G$36)>0,Versiones!$A$2:$A$36), "")} -> V0.15 | AL33: ="V"&MAX(IFERROR(VALUE(MID(Tabla[[#This Row],[Versiones corregidas]],2,99)),0), IFERROR(VALUE(MID(Tabla[[#This Row],[Versiones corregidas19]],2,99)),0), IFERROR(VALUE(MID(Tabla[[#This Row],[Versiones corregidas20]],2,99)),0), IFERROR(VALUE(MID(Tabla[[#This Row],[Versiones corregidas21]],2,99)),0),IFERROR(VALUE(MID(#REF!,2,99)),0)) -> V0.16 | AM33: =IFERROR(_xlfn.XLOOKUP(Tabla[[#This Row],[¿En qué versión fue corregido?]],Versiones!$A$2:$A$34,Versiones!$B$2:$B$34),"No encontrado") -> 0 | AN33: {=IFERROR(_xlfn.XLOOKUP(TRUE,COUNTIF(Tabla[[#This Row],[Etiquetas]:[Etiquetas17]],Categorías!$A$2:$A$12)>0,Categorías!$A$2:$A$12),"No encontrado")} -> Funcional | AO33: {=IFERROR(INDEX(Funcionalidades!$A$2:$A$80,MATCH(TRUE, COUNTIF(Reporte_Gral!R33:Z33,Funcionalidades!$A$2:$A$80)>0,0)),"No encontrado")} -> Main-Dashboard | AP33: =IF(AND(COUNTIF(Tabla[[#This Row],[Etiquetas]:[Etiquetas17]],"*UAT_V*")>0,COUNTIF(Tabla[[#This Row],[Etiquetas]:[Etiquetas17]],"*QA-Integración*")=0),"SI","") | AQ33: {=IF(Tabla[[#This Row],[Fue encontrado durante UAT?]]="SI",IFERROR(_xlfn.XLOOKUP(TRUE,ISNUMBER(SEARCH("UAT_V",Tabla[[#This Row],[Etiquetas]:[Etiquetas17]])),Tabla[[#This Row],[Etiquetas]:[Etiquetas17]]),""),"")} | AR33: =IF(COUNTIF(Tabla[[#This Row],[Etiquetas]:[Etiquetas17]],"*Devuelto*")>0,"SI","") | AS33: =COUNTIF(Tabla[[#This Row],[Etiquetas]:[Etiquetas17]],"*Devuelto*") -> 0
A34: Error | B34: T20-3631 | C34: 121346 | D34: BOT - Al cerrar el turno con diferencia sobrante, el POS mantiene este valor en negativo en “Total efectivo” | E34: Medio | F34: TO BE DEPLOYED-SIT | G34: T20 Sprint 26 2025 | R34: Funcional | S34: Main-Dashboard | T34: QA-IntegraciónV0.15 | U34: T3B20_BOT | V34: Tienda2.0 | AA34: Yubisleinys Mora Vega | AB34: 46007.609 | AC34: v0.16 | AG34: BOT | AJ34: {=IFERROR(_xlfn.XLOOKUP(TRUE,COUNTIF(Tabla[[#This Row],[Etiquetas]:[Etiquetas17]],Versiones!$G$2:$G$36)>0,Versiones!$B$2:$B$36), "")} -> 25 | AK34: {=IFERROR(_xlfn.XLOOKUP(TRUE,COUNTIF(Tabla[[#This Row],[Etiquetas]:[Etiquetas17]],Versiones!$G$2:$G$36)>0,Versiones!$A$2:$A$36), "")} -> V0.15 | AL34: ="V"&MAX(IFERROR(VALUE(MID(Tabla[[#This Row],[Versiones corregidas]],2,99)),0), IFERROR(VALUE(MID(Tabla[[#This Row],[Versiones corregidas19]],2,99)),0), IFERROR(VALUE(MID(Tabla[[#This Row],[Versiones corregidas20]],2,99)),0), IFERROR(VALUE(MID(Tabla[[#This Row],[Versiones corregidas21]],2,99)),0),IFERROR(VALUE(MID(#REF!,2,99)),0)) -> V0.16 | AM34: =IFERROR(_xlfn.XLOOKUP(Tabla[[#This Row],[¿En qué versión fue corregido?]],Versiones!$A$2:$A$34,Versiones!$B$2:$B$34),"No encontrado") -> 0 | AN34: {=IFERROR(_xlfn.XLOOKUP(TRUE,COUNTIF(Tabla[[#This Row],[Etiquetas]:[Etiquetas17]],Categorías!$A$2:$A$12)>0,Categorías!$A$2:$A$12),"No encontrado")} -> Funcional | AO34: {=IFERROR(INDEX(Funcionalidades!$A$2:$A$80,MATCH(TRUE, COUNTIF(Reporte_Gral!R34:Z34,Funcionalidades!$A$2:$A$80)>0,0)),"No encontrado")} -> Main-Dashboard | AP34: =IF(AND(COUNTIF(Tabla[[#This Row],[Etiquetas]:[Etiquetas17]],"*UAT_V*")>0,COUNTIF(Tabla[[#This Row],[Etiquetas]:[Etiquetas17]],"*QA-Integración*")=0),"SI","") | AQ34: {=IF(Tabla[[#This Row],[Fue encontrado durante UAT?]]="SI",IFERROR(_xlfn.XLOOKUP(TRUE,ISNUMBER(SEARCH("UAT_V",Tabla[[#This Row],[Etiquetas]:[Etiquetas17]])),Tabla[[#This Row],[Etiquetas]:[Etiquetas17]]),""),"")} | AR34: =IF(COUNTIF(Tabla[[#This Row],[Etiquetas]:[Etiquetas17]],"*Devuelto*")>0,"SI","") | AS34: =COUNTIF(Tabla[[#This Row],[Etiquetas]:[Etiquetas17]],"*Devuelto*") -> 0
A35: Error | B35: T20-3630 | C35: 121342 | D35: POS - Al seleccionar un botón del menú lateral del POS, este queda "griseado" al terminar o cerrar el modal | E35: Medio | F35: IN SIT | G35: T20 Sprint 26 2025 | R35: Bugs-En-Inputs | S35: Look&Feel | T35: QA-IntegraciónV0.15 | U35: T3B20_POS | V35: Tienda2.0 | AA35: Daniela Soto | AB35: 46007.599 | AC35: v0.16 | AG35: POS | AJ35: {=IFERROR(_xlfn.XLOOKUP(TRUE,COUNTIF(Tabla[[#This Row],[Etiquetas]:[Etiquetas17]],Versiones!$G$2:$G$36)>0,Versiones!$B$2:$B$36), "")} -> 25 | AK35: {=IFERROR(_xlfn.XLOOKUP(TRUE,COUNTIF(Tabla[[#This Row],[Etiquetas]:[Etiquetas17]],Versiones!$G$2:$G$36)>0,Versiones!$A$2:$A$36), "")} -> V0.15 | AL35: ="V"&MAX(IFERROR(VALUE(MID(Tabla[[#This Row],[Versiones corregidas]],2,99)),0), IFERROR(VALUE(MID(Tabla[[#This Row],[Versiones corregidas19]],2,99)),0), IFERROR(VALUE(MID(Tabla[[#This Row],[Versiones corregidas20]],2,99)),0), IFERROR(VALUE(MID(Tabla[[#This Row],[Versiones corregidas21]],2,99)),0),IFERROR(VALUE(MID(#REF!,2,99)),0)) -> V0.16 | AM35: =IFERROR(_xlfn.XLOOKUP(Tabla[[#This Row],[¿En qué versión fue corregido?]],Versiones!$A$2:$A$34,Versiones!$B$2:$B$34),"No encontrado") -> 0 | AN35: {=IFERROR(_xlfn.XLOOKUP(TRUE,COUNTIF(Tabla[[#This Row],[Etiquetas]:[Etiquetas17]],Categorías!$A$2:$A$12)>0,Categorías!$A$2:$A$12),"No encontrado")} -> Look&Feel | AO35: {=IFERROR(INDEX(Funcionalidades!$A$2:$A$80,MATCH(TRUE, COUNTIF(Reporte_Gral!R35:Z35,Funcionalidades!$A$2:$A$80)>0,0)),"No encontrado")} -> Bugs-En-Inputs | AP35: =IF(AND(COUNTIF(Tabla[[#This Row],[Etiquetas]:[Etiquetas17]],"*UAT_V*")>0,COUNTIF(Tabla[[#This Row],[Etiquetas]:[Etiquetas17]],"*QA-Integración*")=0),"SI","") | AQ35: {=IF(Tabla[[#This Row],[Fue encontrado durante UAT?]]="SI",IFERROR(_xlfn.XLOOKUP(TRUE,ISNUMBER(SEARCH("UAT_V",Tabla[[#This Row],[Etiquetas]:[Etiquetas17]])),Tabla[[#This Row],[Etiquetas]:[Etiquetas17]]),""),"")} | AR35: =IF(COUNTIF(Tabla[[#This Row],[Etiquetas]:[Etiquetas17]],"*Devuelto*")>0,"SI","") | AS35: =COUNTIF(Tabla[[#This Row],[Etiquetas]:[Etiquetas17]],"*Devuelto*") -> 0
A36: Error | B36: T20-3629 | C36: 121336 | D36: POS - Campo de búsqueda en Pago de "Servicios" no trae resultados | E36: Medio | F36: Code Review | G36: T20 Sprint 26 2025 | R36: Funcional | S36: Pago-De-Servicios-Con-Catálogo | T36: QA-IntegraciónV0.15 | U36: Revisado | V36: T3B20_POS | W36: Tienda2.0 | AA36: Daniela Soto | AB36: 46007.584 | AC36: v0.16 | AG36: POS | AJ36: {=IFERROR(_xlfn.XLOOKUP(TRUE,COUNTIF(Tabla[[#This Row],[Etiquetas]:[Etiquetas17]],Versiones!$G$2:$G$36)>0,Versiones!$B$2:$B$36), "")} -> 25 | AK36: {=IFERROR(_xlfn.XLOOKUP(TRUE,COUNTIF(Tabla[[#This Row],[Etiquetas]:[Etiquetas17]],Versiones!$G$2:$G$36)>0,Versiones!$A$2:$A$36), "")} -> V0.15 | AL36: ="V"&MAX(IFERROR(VALUE(MID(Tabla[[#This Row],[Versiones corregidas]],2,99)),0), IFERROR(VALUE(MID(Tabla[[#This Row],[Versiones corregidas19]],2,99)),0), IFERROR(VALUE(MID(Tabla[[#This Row],[Versiones corregidas20]],2,99)),0), IFERROR(VALUE(MID(Tabla[[#This Row],[Versiones corregidas21]],2,99)),0),IFERROR(VALUE(MID(#REF!,2,99)),0)) -> V0.16 | AM36: =IFERROR(_xlfn.XLOOKUP(Tabla[[#This Row],[¿En qué versión fue corregido?]],Versiones!$A$2:$A$34,Versiones!$B$2:$B$34),"No encontrado") -> 0 | AN36: {=IFERROR(_xlfn.XLOOKUP(TRUE,COUNTIF(Tabla[[#This Row],[Etiquetas]:[Etiquetas17]],Categorías!$A$2:$A$12)>0,Categorías!$A$2:$A$12),"No encontrado")} -> Funcional | AO36: {=IFERROR(INDEX(Funcionalidades!$A$2:$A$80,MATCH(TRUE, COUNTIF(Reporte_Gral!R36:Z36,Funcionalidades!$A$2:$A$80)>0,0)),"No encontrado")} -> Pago-De-Servicios-Con-Catálogo | AP36: =IF(AND(COUNTIF(Tabla[[#This Row],[Etiquetas]:[Etiquetas17]],"*UAT_V*")>0,COUNTIF(Tabla[[#This Row],[Etiquetas]:[Etiquetas17]],"*QA-Integración*")=0),"SI","") | AQ36: {=IF(Tabla[[#This Row],[Fue encontrado durante UAT?]]="SI",IFERROR(_xlfn.XLOOKUP(TRUE,ISNUMBER(SEARCH("UAT_V",Tabla[[#This Row],[Etiquetas]:[Etiquetas17]])),Tabla[[#This Row],[Etiquetas]:[Etiquetas17]]),""),"")} | AR36: =IF(COUNTIF(Tabla[[#This Row],[Etiquetas]:[Etiquetas17]],"*Devuelto*")>0,"SI","") | AS36: =COUNTIF(Tabla[[#This Row],[Etiquetas]:[Etiquetas17]],"*Devuelto*") -> 0
A37: Error | B37: T20-3628 | C37: 121334 | D37: POS - Filtro de búsqueda en "Tiempo Aire"no trae resultados correctamente | E37: Medio | F37: Code Review | G37: T20 Sprint 26 2025 | R37: Funcional | S37: Pago-De-Tiempo-Aire | T37: QA-IntegraciónV0.15 | U37: T3B20_POS | V37: Tienda2.0 | AA37: Daniela Soto | AB37: 46007.579 | AC37: v0.16 | AG37: POS | AJ37: {=IFERROR(_xlfn.XLOOKUP(TRUE,COUNTIF(Tabla[[#This Row],[Etiquetas]:[Etiquetas17]],Versiones!$G$2:$G$36)>0,Versiones!$B$2:$B$36), "")} -> 25 | AK37: {=IFERROR(_xlfn.XLOOKUP(TRUE,COUNTIF(Tabla[[#This Row],[Etiquetas]:[Etiquetas17]],Versiones!$G$2:$G$36)>0,Versiones!$A$2:$A$36), "")} -> V0.15 | AL37: ="V"&MAX(IFERROR(VALUE(MID(Tabla[[#This Row],[Versiones corregidas]],2,99)),0), IFERROR(VALUE(MID(Tabla[[#This Row],[Versiones corregidas19]],2,99)),0), IFERROR(VALUE(MID(Tabla[[#This Row],[Versiones corregidas20]],2,99)),0), IFERROR(VALUE(MID(Tabla[[#This Row],[Versiones corregidas21]],2,99)),0),IFERROR(VALUE(MID(#REF!,2,99)),0)) -> V0.16 | AM37: =IFERROR(_xlfn.XLOOKUP(Tabla[[#This Row],[¿En qué versión fue corregido?]],Versiones!$A$2:$A$34,Versiones!$B$2:$B$34),"No encontrado") -> 0 | AN37: {=IFERROR(_xlfn.XLOOKUP(TRUE,COUNTIF(Tabla[[#This Row],[Etiquetas]:[Etiquetas17]],Categorías!$A$2:$A$12)>0,Categorías!$A$2:$A$12),"No encontrado")} -> Funcional | AO37: {=IFERROR(INDEX(Funcionalidades!$A$2:$A$80,MATCH(TRUE, COUNTIF(Reporte_Gral!R37:Z37,Funcionalidades!$A$2:$A$80)>0,0)),"No encontrado")} -> Pago-De-Tiempo-Aire | AP37: =IF(AND(COUNTIF(Tabla[[#This Row],[Etiquetas]:[Etiquetas17]],"*UAT_V*")>0,COUNTIF(Tabla[[#This Row],[Etiquetas]:[Etiquetas17]],"*QA-Integración*")=0),"SI","") | AQ37: {=IF(Tabla[[#This Row],[Fue encontrado durante UAT?]]="SI",IFERROR(_xlfn.XLOOKUP(TRUE,ISNUMBER(SEARCH("UAT_V",Tabla[[#This Row],[Etiquetas]:[Etiquetas17]])),Tabla[[#This Row],[Etiquetas]:[Etiquetas17]]),""),"")} | AR37: =IF(COUNTIF(Tabla[[#This Row],[Etiquetas]:[Etiquetas17]],"*Devuelto*")>0,"SI","") | AS37: =COUNTIF(Tabla[[#This Row],[Etiquetas]:[Etiquetas17]],"*Devuelto*") -> 0
A38: Error | B38: T20-3581 | C38: 120956 | D38: POS - Pago de Servicio está imprimiendo dos Ticket | E38: Medio | F38: TO BE DEPLOYED-SIT | G38: T20 Sprint 26 2025 | R38: Funcional | S38: Pago-De-Servicios-Con-Catálogo | T38: QA-IntegraciónV0.15 | U38: T3B20_POS | V38: Tienda2.0 | AA38: Yubisleinys Mora Vega | AB38: 46006.688 | AC38: v0.16 | AG38: POS | AJ38: {=IFERROR(_xlfn.XLOOKUP(TRUE,COUNTIF(Tabla[[#This Row],[Etiquetas]:[Etiquetas17]],Versiones!$G$2:$G$36)>0,Versiones!$B$2:$B$36), "")} -> 25 | AK38: {=IFERROR(_xlfn.XLOOKUP(TRUE,COUNTIF(Tabla[[#This Row],[Etiquetas]:[Etiquetas17]],Versiones!$G$2:$G$36)>0,Versiones!$A$2:$A$36), "")} -> V0.15 | AL38: ="V"&MAX(IFERROR(VALUE(MID(Tabla[[#This Row],[Versiones corregidas]],2,99)),0), IFERROR(VALUE(MID(Tabla[[#This Row],[Versiones corregidas19]],2,99)),0), IFERROR(VALUE(MID(Tabla[[#This Row],[Versiones corregidas20]],2,99)),0), IFERROR(VALUE(MID(Tabla[[#This Row],[Versiones corregidas21]],2,99)),0),IFERROR(VALUE(MID(#REF!,2,99)),0)) -> V0.16 | AM38: =IFERROR(_xlfn.XLOOKUP(Tabla[[#This Row],[¿En qué versión fue corregido?]],Versiones!$A$2:$A$34,Versiones!$B$2:$B$34),"No encontrado") -> 0 | AN38: {=IFERROR(_xlfn.XLOOKUP(TRUE,COUNTIF(Tabla[[#This Row],[Etiquetas]:[Etiquetas17]],Categorías!$A$2:$A$12)>0,Categorías!$A$2:$A$12),"No encontrado")} -> Funcional | AO38: {=IFERROR(INDEX(Funcionalidades!$A$2:$A$80,MATCH(TRUE, COUNTIF(Reporte_Gral!R38:Z38,Funcionalidades!$A$2:$A$80)>0,0)),"No encontrado")} -> Pago-De-Servicios-Con-Catálogo | AP38: =IF(AND(COUNTIF(Tabla[[#This Row],[Etiquetas]:[Etiquetas17]],"*UAT_V*")>0,COUNTIF(Tabla[[#This Row],[Etiquetas]:[Etiquetas17]],"*QA-Integración*")=0),"SI","") | AQ38: {=IF(Tabla[[#This Row],[Fue encontrado durante UAT?]]="SI",IFERROR(_xlfn.XLOOKUP(TRUE,ISNUMBER(SEARCH("UAT_V",Tabla[[#This Row],[Etiquetas]:[Etiquetas17]])),Tabla[[#This Row],[Etiquetas]:[Etiquetas17]]),""),"")} | AR38: =IF(COUNTIF(Tabla[[#This Row],[Etiquetas]:[Etiquetas17]],"*Devuelto*")>0,"SI","") | AS38: =COUNTIF(Tabla[[#This Row],[Etiquetas]:[Etiquetas17]],"*Devuelto*") -> 0
A39: Error | B39: T20-3579 | C39: 120889 | D39: POS - Modal “Cerrar venta” muestra nombre incorrecto “Pago mix” | E39: Baja | F39: Cancelado | R39: Iniciar-Venta | S39: Look&Feel | T39: POS | U39: QA-IntegraciónV0.15 | AA39: Yubisleinys Mora Vega | AB39: 46006.557 | AG39: POS | AJ39: {=IFERROR(_xlfn.XLOOKUP(TRUE,COUNTIF(Tabla[[#This Row],[Etiquetas]:[Etiquetas17]],Versiones!$G$2:$G$36)>0,Versiones!$B$2:$B$36), "")} -> 25 | AK39: {=IFERROR(_xlfn.XLOOKUP(TRUE,COUNTIF(Tabla[[#This Row],[Etiquetas]:[Etiquetas17]],Versiones!$G$2:$G$36)>0,Versiones!$A$2:$A$36), "")} -> V0.15 | AL39: ="V"&MAX(IFERROR(VALUE(MID(Tabla[[#This Row],[Versiones corregidas]],2,99)),0), IFERROR(VALUE(MID(Tabla[[#This Row],[Versiones corregidas19]],2,99)),0), IFERROR(VALUE(MID(Tabla[[#This Row],[Versiones corregidas20]],2,99)),0), IFERROR(VALUE(MID(Tabla[[#This Row],[Versiones corregidas21]],2,99)),0),IFERROR(VALUE(MID(#REF!,2,99)),0)) -> V0 | AM39: =IFERROR(_xlfn.XLOOKUP(Tabla[[#This Row],[¿En qué versión fue corregido?]],Versiones!$A$2:$A$34,Versiones!$B$2:$B$34),"No encontrado") -> No encontrado | AN39: {=IFERROR(_xlfn.XLOOKUP(TRUE,COUNTIF(Tabla[[#This Row],[Etiquetas]:[Etiquetas17]],Categorías!$A$2:$A$12)>0,Categorías!$A$2:$A$12),"No encontrado")} -> Look&Feel | AO39: {=IFERROR(INDEX(Funcionalidades!$A$2:$A$80,MATCH(TRUE, COUNTIF(Reporte_Gral!R39:Z39,Funcionalidades!$A$2:$A$80)>0,0)),"No encontrado")} -> Iniciar-Venta | AP39: =IF(AND(COUNTIF(Tabla[[#This Row],[Etiquetas]:[Etiquetas17]],"*UAT_V*")>0,COUNTIF(Tabla[[#This Row],[Etiquetas]:[Etiquetas17]],"*QA-Integración*")=0),"SI","") | AQ39: {=IF(Tabla[[#This Row],[Fue encontrado durante UAT?]]="SI",IFERROR(_xlfn.XLOOKUP(TRUE,ISNUMBER(SEARCH("UAT_V",Tabla[[#This Row],[Etiquetas]:[Etiquetas17]])),Tabla[[#This Row],[Etiquetas]:[Etiquetas17]]),""),"")} | AR39: =IF(COUNTIF(Tabla[[#This Row],[Etiquetas]:[Etiquetas17]],"*Devuelto*")>0,"SI","") | AS39: =COUNTIF(Tabla[[#This Row],[Etiquetas]:[Etiquetas17]],"*Devuelto*") -> 0
A40: Error | B40: T20-3578 | C40: 120874 | D40: POS - Servicios - Pago de servicio permite completar el flujo sin número de referencia | E40: Alta | F40: READY FOR UAT | G40: T20 Sprint 25 2025 | H40: T20 Sprint 26 2025 | R40: Funcional | S40: Pago-De-Servicios-Con-Catálogo | T40: QA-IntegraciónV0.15 | U40: T3B20_POS | V40: Tienda2.0 | AA40: Yubisleinys Mora Vega | AB40: 46006.544 | AC40: v0.15 | AG40: POS | AJ40: {=IFERROR(_xlfn.XLOOKUP(TRUE,COUNTIF(Tabla[[#This Row],[Etiquetas]:[Etiquetas17]],Versiones!$G$2:$G$36)>0,Versiones!$B$2:$B$36), "")} -> 25 | AK40: {=IFERROR(_xlfn.XLOOKUP(TRUE,COUNTIF(Tabla[[#This Row],[Etiquetas]:[Etiquetas17]],Versiones!$G$2:$G$36)>0,Versiones!$A$2:$A$36), "")} -> V0.15 | AL40: ="V"&MAX(IFERROR(VALUE(MID(Tabla[[#This Row],[Versiones corregidas]],2,99)),0), IFERROR(VALUE(MID(Tabla[[#This Row],[Versiones corregidas19]],2,99)),0), IFERROR(VALUE(MID(Tabla[[#This Row],[Versiones corregidas20]],2,99)),0), IFERROR(VALUE(MID(Tabla[[#This Row],[Versiones corregidas21]],2,99)),0),IFERROR(VALUE(MID(#REF!,2,99)),0)) -> V0.15 | AM40: =IFERROR(_xlfn.XLOOKUP(Tabla[[#This Row],[¿En qué versión fue corregido?]],Versiones!$A$2:$A$34,Versiones!$B$2:$B$34),"No encontrado") -> 25 | AN40: {=IFERROR(_xlfn.XLOOKUP(TRUE,COUNTIF(Tabla[[#This Row],[Etiquetas]:[Etiquetas17]],Categorías!$A$2:$A$12)>0,Categorías!$A$2:$A$12),"No encontrado")} -> Funcional | AO40: {=IFERROR(INDEX(Funcionalidades!$A$2:$A$80,MATCH(TRUE, COUNTIF(Reporte_Gral!R40:Z40,Funcionalidades!$A$2:$A$80)>0,0)),"No encontrado")} -> Pago-De-Servicios-Con-Catálogo | AP40: =IF(AND(COUNTIF(Tabla[[#This Row],[Etiquetas]:[Etiquetas17]],"*UAT_V*")>0,COUNTIF(Tabla[[#This Row],[Etiquetas]:[Etiquetas17]],"*QA-Integración*")=0),"SI","") | AQ40: {=IF(Tabla[[#This Row],[Fue encontrado durante UAT?]]="SI",IFERROR(_xlfn.XLOOKUP(TRUE,ISNUMBER(SEARCH("UAT_V",Tabla[[#This Row],[Etiquetas]:[Etiquetas17]])),Tabla[[#This Row],[Etiquetas]:[Etiquetas17]]),""),"")} | AR40: =IF(COUNTIF(Tabla[[#This Row],[Etiquetas]:[Etiquetas17]],"*Devuelto*")>0,"SI","") | AS40: =COUNTIF(Tabla[[#This Row],[Etiquetas]:[Etiquetas17]],"*Devuelto*") -> 0
A41: Error | B41: T20-3577 | C41: 120867 | D41: POS - Servicios - Campo “Total a pagar” en blanco muestra monto entregado como cambio | E41: Alta | F41: READY FOR UAT | G41: T20 Sprint 25 2025 | H41: T20 Sprint 26 2025 | R41: Funcional | S41: Pago-De-Servicios-Con-Catálogo | T41: QA-IntegraciónV0.15 | U41: T3B20_POS | V41: Tienda2.0 | AA41: Yubisleinys Mora Vega | AB41: 46006.532 | AC41: v0.15 | AG41: POS | AJ41: {=IFERROR(_xlfn.XLOOKUP(TRUE,COUNTIF(Tabla[[#This Row],[Etiquetas]:[Etiquetas17]],Versiones!$G$2:$G$36)>0,Versiones!$B$2:$B$36), "")} -> 25 | AK41: {=IFERROR(_xlfn.XLOOKUP(TRUE,COUNTIF(Tabla[[#This Row],[Etiquetas]:[Etiquetas17]],Versiones!$G$2:$G$36)>0,Versiones!$A$2:$A$36), "")} -> V0.15 | AL41: ="V"&MAX(IFERROR(VALUE(MID(Tabla[[#This Row],[Versiones corregidas]],2,99)),0), IFERROR(VALUE(MID(Tabla[[#This Row],[Versiones corregidas19]],2,99)),0), IFERROR(VALUE(MID(Tabla[[#This Row],[Versiones corregidas20]],2,99)),0), IFERROR(VALUE(MID(Tabla[[#This Row],[Versiones corregidas21]],2,99)),0),IFERROR(VALUE(MID(#REF!,2,99)),0)) -> V0.15 | AM41: =IFERROR(_xlfn.XLOOKUP(Tabla[[#This Row],[¿En qué versión fue corregido?]],Versiones!$A$2:$A$34,Versiones!$B$2:$B$34),"No encontrado") -> 25 | AN41: {=IFERROR(_xlfn.XLOOKUP(TRUE,COUNTIF(Tabla[[#This Row],[Etiquetas]:[Etiquetas17]],Categorías!$A$2:$A$12)>0,Categorías!$A$2:$A$12),"No encontrado")} -> Funcional | AO41: {=IFERROR(INDEX(Funcionalidades!$A$2:$A$80,MATCH(TRUE, COUNTIF(Reporte_Gral!R41:Z41,Funcionalidades!$A$2:$A$80)>0,0)),"No encontrado")} -> Pago-De-Servicios-Con-Catálogo | AP41: =IF(AND(COUNTIF(Tabla[[#This Row],[Etiquetas]:[Etiquetas17]],"*UAT_V*")>0,COUNTIF(Tabla[[#This Row],[Etiquetas]:[Etiquetas17]],"*QA-Integración*")=0),"SI","") | AQ41: {=IF(Tabla[[#This Row],[Fue encontrado durante UAT?]]="SI",IFERROR(_xlfn.XLOOKUP(TRUE,ISNUMBER(SEARCH("UAT_V",Tabla[[#This Row],[Etiquetas]:[Etiquetas17]])),Tabla[[#This Row],[Etiquetas]:[Etiquetas17]]),""),"")} | AR41: =IF(COUNTIF(Tabla[[#This Row],[Etiquetas]:[Etiquetas17]],"*Devuelto*")>0,"SI","") | AS41: =COUNTIF(Tabla[[#This Row],[Etiquetas]:[Etiquetas17]],"*Devuelto*") -> 0
A42: Error | B42: T20-3576 | C42: 120862 | D42: POS - Servicios - Error en modal Cambio al cliente | E42: Medio | F42: READY FOR UAT | G42: T20 Sprint 25 2025 | H42: T20 Sprint 26 2025 | R42: Look&Feel | S42: Pago-De-Servicios-Con-Catálogo | T42: QA-IntegraciónV0.15 | U42: T3B20_POS | V42: Tienda2.0 | AA42: Yubisleinys Mora Vega | AB42: 46006.523 | AC42: v0.15 | AG42: POS | AJ42: {=IFERROR(_xlfn.XLOOKUP(TRUE,COUNTIF(Tabla[[#This Row],[Etiquetas]:[Etiquetas17]],Versiones!$G$2:$G$36)>0,Versiones!$B$2:$B$36), "")} -> 25 | AK42: {=IFERROR(_xlfn.XLOOKUP(TRUE,COUNTIF(Tabla[[#This Row],[Etiquetas]:[Etiquetas17]],Versiones!$G$2:$G$36)>0,Versiones!$A$2:$A$36), "")} -> V0.15 | AL42: ="V"&MAX(IFERROR(VALUE(MID(Tabla[[#This Row],[Versiones corregidas]],2,99)),0), IFERROR(VALUE(MID(Tabla[[#This Row],[Versiones corregidas19]],2,99)),0), IFERROR(VALUE(MID(Tabla[[#This Row],[Versiones corregidas20]],2,99)),0), IFERROR(VALUE(MID(Tabla[[#This Row],[Versiones corregidas21]],2,99)),0),IFERROR(VALUE(MID(#REF!,2,99)),0)) -> V0.15 | AM42: =IFERROR(_xlfn.XLOOKUP(Tabla[[#This Row],[¿En qué versión fue corregido?]],Versiones!$A$2:$A$34,Versiones!$B$2:$B$34),"No encontrado") -> 25 | AN42: {=IFERROR(_xlfn.XLOOKUP(TRUE,COUNTIF(Tabla[[#This Row],[Etiquetas]:[Etiquetas17]],Categorías!$A$2:$A$12)>0,Categorías!$A$2:$A$12),"No encontrado")} -> Look&Feel | AO42: {=IFERROR(INDEX(Funcionalidades!$A$2:$A$80,MATCH(TRUE, COUNTIF(Reporte_Gral!R42:Z42,Funcionalidades!$A$2:$A$80)>0,0)),"No encontrado")} -> Pago-De-Servicios-Con-Catálogo | AP42: =IF(AND(COUNTIF(Tabla[[#This Row],[Etiquetas]:[Etiquetas17]],"*UAT_V*")>0,COUNTIF(Tabla[[#This Row],[Etiquetas]:[Etiquetas17]],"*QA-Integración*")=0),"SI","") | AQ42: {=IF(Tabla[[#This Row],[Fue encontrado durante UAT?]]="SI",IFERROR(_xlfn.XLOOKUP(TRUE,ISNUMBER(SEARCH("UAT_V",Tabla[[#This Row],[Etiquetas]:[Etiquetas17]])),Tabla[[#This Row],[Etiquetas]:[Etiquetas17]]),""),"")} | AR42: =IF(COUNTIF(Tabla[[#This Row],[Etiquetas]:[Etiquetas17]],"*Devuelto*")>0,"SI","") | AS42: =COUNTIF(Tabla[[#This Row],[Etiquetas]:[Etiquetas17]],"*Devuelto*") -> 0
A43: Error | B43: T20-3574 | C43: 120650 | D43: BOT no debe de ejecutar Shortcuts desde la ventana de "Shortcuts" | E43: Medio | F43: READY FOR UAT | G43: T20 Sprint 25 2025 | H43: T20 Sprint 26 2025 | R43: Atajos-Teclado-BOT | S43: Funcional | T43: QA-IntegraciónV0.15 | U43: T3B20_BOT | V43: Tienda2.0 | AA43: Carolina Rodríguez Soriano | AB43: 46006.464 | AC43: v0.15 | AG43: BOT | AJ43: {=IFERROR(_xlfn.XLOOKUP(TRUE,COUNTIF(Tabla[[#This Row],[Etiquetas]:[Etiquetas17]],Versiones!$G$2:$G$36)>0,Versiones!$B$2:$B$36), "")} -> 25 | AK43: {=IFERROR(_xlfn.XLOOKUP(TRUE,COUNTIF(Tabla[[#This Row],[Etiquetas]:[Etiquetas17]],Versiones!$G$2:$G$36)>0,Versiones!$A$2:$A$36), "")} -> V0.15 | AL43: ="V"&MAX(IFERROR(VALUE(MID(Tabla[[#This Row],[Versiones corregidas]],2,99)),0), IFERROR(VALUE(MID(Tabla[[#This Row],[Versiones corregidas19]],2,99)),0), IFERROR(VALUE(MID(Tabla[[#This Row],[Versiones corregidas20]],2,99)),0), IFERROR(VALUE(MID(Tabla[[#This Row],[Versiones corregidas21]],2,99)),0),IFERROR(VALUE(MID(#REF!,2,99)),0)) -> V0.15 | AM43: =IFERROR(_xlfn.XLOOKUP(Tabla[[#This Row],[¿En qué versión fue corregido?]],Versiones!$A$2:$A$34,Versiones!$B$2:$B$34),"No encontrado") -> 25 | AN43: {=IFERROR(_xlfn.XLOOKUP(TRUE,COUNTIF(Tabla[[#This Row],[Etiquetas]:[Etiquetas17]],Categorías!$A$2:$A$12)>0,Categorías!$A$2:$A$12),"No encontrado")} -> Funcional | AO43: {=IFERROR(INDEX(Funcionalidades!$A$2:$A$80,MATCH(TRUE, COUNTIF(Reporte_Gral!R43:Z43,Funcionalidades!$A$2:$A$80)>0,0)),"No encontrado")} -> Atajos-Teclado-BOT | AP43: =IF(AND(COUNTIF(Tabla[[#This Row],[Etiquetas]:[Etiquetas17]],"*UAT_V*")>0,COUNTIF(Tabla[[#This Row],[Etiquetas]:[Etiquetas17]],"*QA-Integración*")=0),"SI","") | AQ43: {=IF(Tabla[[#This Row],[Fue encontrado durante UAT?]]="SI",IFERROR(_xlfn.XLOOKUP(TRUE,ISNUMBER(SEARCH("UAT_V",Tabla[[#This Row],[Etiquetas]:[Etiquetas17]])),Tabla[[#This Row],[Etiquetas]:[Etiquetas17]]),""),"")} | AR43: =IF(COUNTIF(Tabla[[#This Row],[Etiquetas]:[Etiquetas17]],"*Devuelto*")>0,"SI","") | AS43: =COUNTIF(Tabla[[#This Row],[Etiquetas]:[Etiquetas17]],"*Devuelto*") -> 0
A44: Error | B44: T20-3566 | C44: 120243 | D44: BOT - Entrega de valores emite folio XXX | E44: Medio | F44: Tareas por hacer | R44: Entrega-De-Valores | S44: Look&Feel | T44: QA-IntegraciónV0.15 | AA44: Yubisleinys Mora Vega | AB44: 46003.695 | AG44: BOT | AJ44: {=IFERROR(_xlfn.XLOOKUP(TRUE,COUNTIF(Tabla[[#This Row],[Etiquetas]:[Etiquetas17]],Versiones!$G$2:$G$36)>0,Versiones!$B$2:$B$36), "")} -> 25 | AK44: {=IFERROR(_xlfn.XLOOKUP(TRUE,COUNTIF(Tabla[[#This Row],[Etiquetas]:[Etiquetas17]],Versiones!$G$2:$G$36)>0,Versiones!$A$2:$A$36), "")} -> V0.15 | AL44: ="V"&MAX(IFERROR(VALUE(MID(Tabla[[#This Row],[Versiones corregidas]],2,99)),0), IFERROR(VALUE(MID(Tabla[[#This Row],[Versiones corregidas19]],2,99)),0), IFERROR(VALUE(MID(Tabla[[#This Row],[Versiones corregidas20]],2,99)),0), IFERROR(VALUE(MID(Tabla[[#This Row],[Versiones corregidas21]],2,99)),0),IFERROR(VALUE(MID(#REF!,2,99)),0)) -> V0 | AM44: =IFERROR(_xlfn.XLOOKUP(Tabla[[#This Row],[¿En qué versión fue corregido?]],Versiones!$A$2:$A$34,Versiones!$B$2:$B$34),"No encontrado") -> No encontrado | AN44: {=IFERROR(_xlfn.XLOOKUP(TRUE,COUNTIF(Tabla[[#This Row],[Etiquetas]:[Etiquetas17]],Categorías!$A$2:$A$12)>0,Categorías!$A$2:$A$12),"No encontrado")} -> Look&Feel | AO44: {=IFERROR(INDEX(Funcionalidades!$A$2:$A$80,MATCH(TRUE, COUNTIF(Reporte_Gral!R44:Z44,Funcionalidades!$A$2:$A$80)>0,0)),"No encontrado")} -> Entrega-De-Valores | AP44: =IF(AND(COUNTIF(Tabla[[#This Row],[Etiquetas]:[Etiquetas17]],"*UAT_V*")>0,COUNTIF(Tabla[[#This Row],[Etiquetas]:[Etiquetas17]],"*QA-Integración*")=0),"SI","") | AQ44: {=IF(Tabla[[#This Row],[Fue encontrado durante UAT?]]="SI",IFERROR(_xlfn.XLOOKUP(TRUE,ISNUMBER(SEARCH("UAT_V",Tabla[[#This Row],[Etiquetas]:[Etiquetas17]])),Tabla[[#This Row],[Etiquetas]:[Etiquetas17]]),""),"")} | AR44: =IF(COUNTIF(Tabla[[#This Row],[Etiquetas]:[Etiquetas17]],"*Devuelto*")>0,"SI","") | AS44: =COUNTIF(Tabla[[#This Row],[Etiquetas]:[Etiquetas17]],"*Devuelto*") -> 0
A45: Error | B45: T20-3565 | C45: 120242 | D45: BOT - Múltiples errores en la cuarta pantalla "Resumen" de "Entrega de valores" | E45: Medio | F45: Tareas por hacer | G45: T20 Sprint 25 2025 | H45: T20 Sprint 26 2025 | R45: Entrega-de-Valores | S45: Look&Feel | T45: QA-IntegraciónV0.15 | U45: T3B20_BOT | V45: Tienda2.0 | AA45: Daniela Soto | AB45: 46003.694 | AC45: v0.15 | AG45: BOT | AJ45: {=IFERROR(_xlfn.XLOOKUP(TRUE,COUNTIF(Tabla[[#This Row],[Etiquetas]:[Etiquetas17]],Versiones!$G$2:$G$36)>0,Versiones!$B$2:$B$36), "")} -> 25 | AK45: {=IFERROR(_xlfn.XLOOKUP(TRUE,COUNTIF(Tabla[[#This Row],[Etiquetas]:[Etiquetas17]],Versiones!$G$2:$G$36)>0,Versiones!$A$2:$A$36), "")} -> V0.15 | AL45: ="V"&MAX(IFERROR(VALUE(MID(Tabla[[#This Row],[Versiones corregidas]],2,99)),0), IFERROR(VALUE(MID(Tabla[[#This Row],[Versiones corregidas19]],2,99)),0), IFERROR(VALUE(MID(Tabla[[#This Row],[Versiones corregidas20]],2,99)),0), IFERROR(VALUE(MID(Tabla[[#This Row],[Versiones corregidas21]],2,99)),0),IFERROR(VALUE(MID(#REF!,2,99)),0)) -> V0.15 | AM45: =IFERROR(_xlfn.XLOOKUP(Tabla[[#This Row],[¿En qué versión fue corregido?]],Versiones!$A$2:$A$34,Versiones!$B$2:$B$34),"No encontrado") -> 25 | AN45: {=IFERROR(_xlfn.XLOOKUP(TRUE,COUNTIF(Tabla[[#This Row],[Etiquetas]:[Etiquetas17]],Categorías!$A$2:$A$12)>0,Categorías!$A$2:$A$12),"No encontrado")} -> Look&Feel | AO45: {=IFERROR(INDEX(Funcionalidades!$A$2:$A$80,MATCH(TRUE, COUNTIF(Reporte_Gral!R45:Z45,Funcionalidades!$A$2:$A$80)>0,0)),"No encontrado")} -> Entrega-De-Valores | AP45: =IF(AND(COUNTIF(Tabla[[#This Row],[Etiquetas]:[Etiquetas17]],"*UAT_V*")>0,COUNTIF(Tabla[[#This Row],[Etiquetas]:[Etiquetas17]],"*QA-Integración*")=0),"SI","") | AQ45: {=IF(Tabla[[#This Row],[Fue encontrado durante UAT?]]="SI",IFERROR(_xlfn.XLOOKUP(TRUE,ISNUMBER(SEARCH("UAT_V",Tabla[[#This Row],[Etiquetas]:[Etiquetas17]])),Tabla[[#This Row],[Etiquetas]:[Etiquetas17]]),""),"")} | AR45: =IF(COUNTIF(Tabla[[#This Row],[Etiquetas]:[Etiquetas17]],"*Devuelto*")>0,"SI","") | AS45: =COUNTIF(Tabla[[#This Row],[Etiquetas]:[Etiquetas17]],"*Devuelto*") -> 0
A46: Error | B46: T20-3564 | C46: 120240 | D46: BOT - Múltiples errores en la tercera pantalla "Envases y sellos" de "Entrega de valores" | E46: Medio | F46: READY FOR UAT | G46: T20 Sprint 25 2025 | H46: T20 Sprint 26 2025 | R46: Entrega-de-Valores | S46: Look&Feel | T46: QA-IntegraciónV0.15 | U46: T3B20_BOT | V46: Tienda2.0 | AA46: Daniela Soto | AB46: 46003.69 | AC46: v0.15 | AG46: BOT | AJ46: {=IFERROR(_xlfn.XLOOKUP(TRUE,COUNTIF(Tabla[[#This Row],[Etiquetas]:[Etiquetas17]],Versiones!$G$2:$G$36)>0,Versiones!$B$2:$B$36), "")} -> 25 | AK46: {=IFERROR(_xlfn.XLOOKUP(TRUE,COUNTIF(Tabla[[#This Row],[Etiquetas]:[Etiquetas17]],Versiones!$G$2:$G$36)>0,Versiones!$A$2:$A$36), "")} -> V0.15 | AL46: ="V"&MAX(IFERROR(VALUE(MID(Tabla[[#This Row],[Versiones corregidas]],2,99)),0), IFERROR(VALUE(MID(Tabla[[#This Row],[Versiones corregidas19]],2,99)),0), IFERROR(VALUE(MID(Tabla[[#This Row],[Versiones corregidas20]],2,99)),0), IFERROR(VALUE(MID(Tabla[[#This Row],[Versiones corregidas21]],2,99)),0),IFERROR(VALUE(MID(#REF!,2,99)),0)) -> V0.15 | AM46: =IFERROR(_xlfn.XLOOKUP(Tabla[[#This Row],[¿En qué versión fue corregido?]],Versiones!$A$2:$A$34,Versiones!$B$2:$B$34),"No encontrado") -> 25 | AN46: {=IFERROR(_xlfn.XLOOKUP(TRUE,COUNTIF(Tabla[[#This Row],[Etiquetas]:[Etiquetas17]],Categorías!$A$2:$A$12)>0,Categorías!$A$2:$A$12),"No encontrado")} -> Look&Feel | AO46: {=IFERROR(INDEX(Funcionalidades!$A$2:$A$80,MATCH(TRUE, COUNTIF(Reporte_Gral!R46:Z46,Funcionalidades!$A$2:$A$80)>0,0)),"No encontrado")} -> Entrega-De-Valores | AP46: =IF(AND(COUNTIF(Tabla[[#This Row],[Etiquetas]:[Etiquetas17]],"*UAT_V*")>0,COUNTIF(Tabla[[#This Row],[Etiquetas]:[Etiquetas17]],"*QA-Integración*")=0),"SI","") | AQ46: {=IF(Tabla[[#This Row],[Fue encontrado durante UAT?]]="SI",IFERROR(_xlfn.XLOOKUP(TRUE,ISNUMBER(SEARCH("UAT_V",Tabla[[#This Row],[Etiquetas]:[Etiquetas17]])),Tabla[[#This Row],[Etiquetas]:[Etiquetas17]]),""),"")} | AR46: =IF(COUNTIF(Tabla[[#This Row],[Etiquetas]:[Etiquetas17]],"*Devuelto*")>0,"SI","") | AS46: =COUNTIF(Tabla[[#This Row],[Etiquetas]:[Etiquetas17]],"*Devuelto*") -> 0
A47: Error | B47: T20-3563 | C47: 120227 | D47: BOT - Múltiples errores en la segunda pantalla "Llenado de campo" de Entrega de valores | E47: Medio | F47: READY FOR UAT | G47: T20 Sprint 25 2025 | H47: T20 Sprint 26 2025 | R47: Entrega-de-Valores | S47: Look&Feel | T47: QA-IntegraciónV0.15 | U47: T3B20_BOT | V47: Tienda2.0 | AA47: Daniela Soto | AB47: 46003.683 | AC47: v0.15 | AG47: BOT | AJ47: {=IFERROR(_xlfn.XLOOKUP(TRUE,COUNTIF(Tabla[[#This Row],[Etiquetas]:[Etiquetas17]],Versiones!$G$2:$G$36)>0,Versiones!$B$2:$B$36), "")} -> 25 | AK47: {=IFERROR(_xlfn.XLOOKUP(TRUE,COUNTIF(Tabla[[#This Row],[Etiquetas]:[Etiquetas17]],Versiones!$G$2:$G$36)>0,Versiones!$A$2:$A$36), "")} -> V0.15 | AL47: ="V"&MAX(IFERROR(VALUE(MID(Tabla[[#This Row],[Versiones corregidas]],2,99)),0), IFERROR(VALUE(MID(Tabla[[#This Row],[Versiones corregidas19]],2,99)),0), IFERROR(VALUE(MID(Tabla[[#This Row],[Versiones corregidas20]],2,99)),0), IFERROR(VALUE(MID(Tabla[[#This Row],[Versiones corregidas21]],2,99)),0),IFERROR(VALUE(MID(#REF!,2,99)),0)) -> V0.15 | AM47: =IFERROR(_xlfn.XLOOKUP(Tabla[[#This Row],[¿En qué versión fue corregido?]],Versiones!$A$2:$A$34,Versiones!$B$2:$B$34),"No encontrado") -> 25 | AN47: {=IFERROR(_xlfn.XLOOKUP(TRUE,COUNTIF(Tabla[[#This Row],[Etiquetas]:[Etiquetas17]],Categorías!$A$2:$A$12)>0,Categorías!$A$2:$A$12),"No encontrado")} -> Look&Feel | AO47: {=IFERROR(INDEX(Funcionalidades!$A$2:$A$80,MATCH(TRUE, COUNTIF(Reporte_Gral!R47:Z47,Funcionalidades!$A$2:$A$80)>0,0)),"No encontrado")} -> Entrega-De-Valores | AP47: =IF(AND(COUNTIF(Tabla[[#This Row],[Etiquetas]:[Etiquetas17]],"*UAT_V*")>0,COUNTIF(Tabla[[#This Row],[Etiquetas]:[Etiquetas17]],"*QA-Integración*")=0),"SI","") | AQ47: {=IF(Tabla[[#This Row],[Fue encontrado durante UAT?]]="SI",IFERROR(_xlfn.XLOOKUP(TRUE,ISNUMBER(SEARCH("UAT_V",Tabla[[#This Row],[Etiquetas]:[Etiquetas17]])),Tabla[[#This Row],[Etiquetas]:[Etiquetas17]]),""),"")} | AR47: =IF(COUNTIF(Tabla[[#This Row],[Etiquetas]:[Etiquetas17]],"*Devuelto*")>0,"SI","") | AS47: =COUNTIF(Tabla[[#This Row],[Etiquetas]:[Etiquetas17]],"*Devuelto*") -> 0
A48: Error | B48: T20-3562 | C48: 120226 | D48: BOT - Múltiples errores en la primera pantalla de Resumen "Entrega de valores" | E48: Medio | F48: Tareas por hacer | G48: T20 Sprint 25 2025 | H48: T20 Sprint 26 2025 | R48: Bug_Devuelto_v0.15 | S48: Entrega-de-Valores | T48: Look&Feel | U48: QA-IntegraciónV0.15 | V48: T3B20_BOT | W48: Tienda2.0 | AA48: Daniela Soto | AB48: 46003.683 | AC48: v0.15 | AG48: BOT | AJ48: {=IFERROR(_xlfn.XLOOKUP(TRUE,COUNTIF(Tabla[[#This Row],[Etiquetas]:[Etiquetas17]],Versiones!$G$2:$G$36)>0,Versiones!$B$2:$B$36), "")} -> 25 | AK48: {=IFERROR(_xlfn.XLOOKUP(TRUE,COUNTIF(Tabla[[#This Row],[Etiquetas]:[Etiquetas17]],Versiones!$G$2:$G$36)>0,Versiones!$A$2:$A$36), "")} -> V0.15 | AL48: ="V"&MAX(IFERROR(VALUE(MID(Tabla[[#This Row],[Versiones corregidas]],2,99)),0), IFERROR(VALUE(MID(Tabla[[#This Row],[Versiones corregidas19]],2,99)),0), IFERROR(VALUE(MID(Tabla[[#This Row],[Versiones corregidas20]],2,99)),0), IFERROR(VALUE(MID(Tabla[[#This Row],[Versiones corregidas21]],2,99)),0),IFERROR(VALUE(MID(#REF!,2,99)),0)) -> V0.15 | AM48: =IFERROR(_xlfn.XLOOKUP(Tabla[[#This Row],[¿En qué versión fue corregido?]],Versiones!$A$2:$A$34,Versiones!$B$2:$B$34),"No encontrado") -> 25 | AN48: {=IFERROR(_xlfn.XLOOKUP(TRUE,COUNTIF(Tabla[[#This Row],[Etiquetas]:[Etiquetas17]],Categorías!$A$2:$A$12)>0,Categorías!$A$2:$A$12),"No encontrado")} -> Look&Feel | AO48: {=IFERROR(INDEX(Funcionalidades!$A$2:$A$80,MATCH(TRUE, COUNTIF(Reporte_Gral!R48:Z48,Funcionalidades!$A$2:$A$80)>0,0)),"No encontrado")} -> Entrega-De-Valores | AP48: =IF(AND(COUNTIF(Tabla[[#This Row],[Etiquetas]:[Etiquetas17]],"*UAT_V*")>0,COUNTIF(Tabla[[#This Row],[Etiquetas]:[Etiquetas17]],"*QA-Integración*")=0),"SI","") | AQ48: {=IF(Tabla[[#This Row],[Fue encontrado durante UAT?]]="SI",IFERROR(_xlfn.XLOOKUP(TRUE,ISNUMBER(SEARCH("UAT_V",Tabla[[#This Row],[Etiquetas]:[Etiquetas17]])),Tabla[[#This Row],[Etiquetas]:[Etiquetas17]]),""),"")} | AR48: =IF(COUNTIF(Tabla[[#This Row],[Etiquetas]:[Etiquetas17]],"*Devuelto*")>0,"SI","") -> SI | AS48: =COUNTIF(Tabla[[#This Row],[Etiquetas]:[Etiquetas17]],"*Devuelto*") -> 1
A49: Error | B49: T20-3528 | C49: 119805 | D49: BOT - Al finalizar el inventario la pantalla se queda en blanco y no retorna a la pantalla principal del BOT | E49: Medio | F49: Tareas por hacer | G49: T20 Sprint 26 2025 | R49: Funcional | S49: Reporte-De-Inventario | T49: T3B20_BOT | U49: Tienda2.0 | V49: UAT_V0.13 | AA49: Yubisleinys Mora Vega | AB49: 46002.702 | AC49: v0.16 | AG49: BOT | AJ49: {=IFERROR(_xlfn.XLOOKUP(TRUE,COUNTIF(Tabla[[#This Row],[Etiquetas]:[Etiquetas17]],Versiones!$G$2:$G$36)>0,Versiones!$B$2:$B$36), "")} -> 23 | AK49: {=IFERROR(_xlfn.XLOOKUP(TRUE,COUNTIF(Tabla[[#This Row],[Etiquetas]:[Etiquetas17]],Versiones!$G$2:$G$36)>0,Versiones!$A$2:$A$36), "")} -> V0.13 | AL49: ="V"&MAX(IFERROR(VALUE(MID(Tabla[[#This Row],[Versiones corregidas]],2,99)),0), IFERROR(VALUE(MID(Tabla[[#This Row],[Versiones corregidas19]],2,99)),0), IFERROR(VALUE(MID(Tabla[[#This Row],[Versiones corregidas20]],2,99)),0), IFERROR(VALUE(MID(Tabla[[#This Row],[Versiones corregidas21]],2,99)),0),IFERROR(VALUE(MID(#REF!,2,99)),0)) -> V0.16 | AM49: =IFERROR(_xlfn.XLOOKUP(Tabla[[#This Row],[¿En qué versión fue corregido?]],Versiones!$A$2:$A$34,Versiones!$B$2:$B$34),"No encontrado") -> 0 | AN49: {=IFERROR(_xlfn.XLOOKUP(TRUE,COUNTIF(Tabla[[#This Row],[Etiquetas]:[Etiquetas17]],Categorías!$A$2:$A$12)>0,Categorías!$A$2:$A$12),"No encontrado")} -> Funcional | AO49: {=IFERROR(INDEX(Funcionalidades!$A$2:$A$80,MATCH(TRUE, COUNTIF(Reporte_Gral!R49:Z49,Funcionalidades!$A$2:$A$80)>0,0)),"No encontrado")} -> Reporte-De-Inventario | AP49: =IF(AND(COUNTIF(Tabla[[#This Row],[Etiquetas]:[Etiquetas17]],"*UAT_V*")>0,COUNTIF(Tabla[[#This Row],[Etiquetas]:[Etiquetas17]],"*QA-Integración*")=0),"SI","") -> SI | AQ49: {=IF(Tabla[[#This Row],[Fue encontrado durante UAT?]]="SI",IFERROR(_xlfn.XLOOKUP(TRUE,ISNUMBER(SEARCH("UAT_V",Tabla[[#This Row],[Etiquetas]:[Etiquetas17]])),Tabla[[#This Row],[Etiquetas]:[Etiquetas17]]),""),"")} -> UAT_V0.13 | AR49: =IF(COUNTIF(Tabla[[#This Row],[Etiquetas]:[Etiquetas17]],"*Devuelto*")>0,"SI","") | AS49: =COUNTIF(Tabla[[#This Row],[Etiquetas]:[Etiquetas17]],"*Devuelto*") -> 0
A50: Error | B50: T20-3527 | C50: 119803 | D50: BOT - Inventario - El botón “Descargar para reconteo” no se visualiza al finalizar el inventario | E50: Alta | F50: Cancelado | R50: Funcional | S50: Reporte-De-Inventario | T50: UAT_V0.13 | AA50: Yubisleinys Mora Vega | AB50: 46002.695 | AG50: BOT | AJ50: {=IFERROR(_xlfn.XLOOKUP(TRUE,COUNTIF(Tabla[[#This Row],[Etiquetas]:[Etiquetas17]],Versiones!$G$2:$G$36)>0,Versiones!$B$2:$B$36), "")} -> 23 | AK50: {=IFERROR(_xlfn.XLOOKUP(TRUE,COUNTIF(Tabla[[#This Row],[Etiquetas]:[Etiquetas17]],Versiones!$G$2:$G$36)>0,Versiones!$A$2:$A$36), "")} -> V0.13 | AL50: ="V"&MAX(IFERROR(VALUE(MID(Tabla[[#This Row],[Versiones corregidas]],2,99)),0), IFERROR(VALUE(MID(Tabla[[#This Row],[Versiones corregidas19]],2,99)),0), IFERROR(VALUE(MID(Tabla[[#This Row],[Versiones corregidas20]],2,99)),0), IFERROR(VALUE(MID(Tabla[[#This Row],[Versiones corregidas21]],2,99)),0),IFERROR(VALUE(MID(#REF!,2,99)),0)) -> V0 | AM50: =IFERROR(_xlfn.XLOOKUP(Tabla[[#This Row],[¿En qué versión fue corregido?]],Versiones!$A$2:$A$34,Versiones!$B$2:$B$34),"No encontrado") -> No encontrado | AN50: {=IFERROR(_xlfn.XLOOKUP(TRUE,COUNTIF(Tabla[[#This Row],[Etiquetas]:[Etiquetas17]],Categorías!$A$2:$A$12)>0,Categorías!$A$2:$A$12),"No encontrado")} -> Funcional | AO50: {=IFERROR(INDEX(Funcionalidades!$A$2:$A$80,MATCH(TRUE, COUNTIF(Reporte_Gral!R50:Z50,Funcionalidades!$A$2:$A$80)>0,0)),"No encontrado")} -> Reporte-De-Inventario | AP50: =IF(AND(COUNTIF(Tabla[[#This Row],[Etiquetas]:[Etiquetas17]],"*UAT_V*")>0,COUNTIF(Tabla[[#This Row],[Etiquetas]:[Etiquetas17]],"*QA-Integración*")=0),"SI","") -> SI | AQ50: {=IF(Tabla[[#This Row],[Fue encontrado durante UAT?]]="SI",IFERROR(_xlfn.XLOOKUP(TRUE,ISNUMBER(SEARCH("UAT_V",Tabla[[#This Row],[Etiquetas]:[Etiquetas17]])),Tabla[[#This Row],[Etiquetas]:[Etiquetas17]]),""),"")} -> UAT_V0.13 | AR50: =IF(COUNTIF(Tabla[[#This Row],[Etiquetas]:[Etiquetas17]],"*Devuelto*")>0,"SI","") | AS50: =COUNTIF(Tabla[[#This Row],[Etiquetas]:[Etiquetas17]],"*Devuelto*") -> 0
A51: Error | B51: T20-3526 | C51: 119795 | D51: BOT - Dashboard Productos - Header Stockout y Sobrestock no se actualizan | E51: Medio | F51: Tareas por hacer | R51: Dashboard-Productos | S51: Funcional | T51: QA-IntegraciónV0.14 | AA51: Yubisleinys Mora Vega | AB51: 46002.677 | AG51: BOT | AJ51: {=IFERROR(_xlfn.XLOOKUP(TRUE,COUNTIF(Tabla[[#This Row],[Etiquetas]:[Etiquetas17]],Versiones!$G$2:$G$36)>0,Versiones!$B$2:$B$36), "")} -> 24 | AK51: {=IFERROR(_xlfn.XLOOKUP(TRUE,COUNTIF(Tabla[[#This Row],[Etiquetas]:[Etiquetas17]],Versiones!$G$2:$G$36)>0,Versiones!$A$2:$A$36), "")} -> V0.14 | AL51: ="V"&MAX(IFERROR(VALUE(MID(Tabla[[#This Row],[Versiones corregidas]],2,99)),0), IFERROR(VALUE(MID(Tabla[[#This Row],[Versiones corregidas19]],2,99)),0), IFERROR(VALUE(MID(Tabla[[#This Row],[Versiones corregidas20]],2,99)),0), IFERROR(VALUE(MID(Tabla[[#This Row],[Versiones corregidas21]],2,99)),0),IFERROR(VALUE(MID(#REF!,2,99)),0)) -> V0 | AM51: =IFERROR(_xlfn.XLOOKUP(Tabla[[#This Row],[¿En qué versión fue corregido?]],Versiones!$A$2:$A$34,Versiones!$B$2:$B$34),"No encontrado") -> No encontrado | AN51: {=IFERROR(_xlfn.XLOOKUP(TRUE,COUNTIF(Tabla[[#This Row],[Etiquetas]:[Etiquetas17]],Categorías!$A$2:$A$12)>0,Categorías!$A$2:$A$12),"No encontrado")} -> Funcional | AO51: {=IFERROR(INDEX(Funcionalidades!$A$2:$A$80,MATCH(TRUE, COUNTIF(Reporte_Gral!R51:Z51,Funcionalidades!$A$2:$A$80)>0,0)),"No encontrado")} -> Dashboard-Productos | AP51: =IF(AND(COUNTIF(Tabla[[#This Row],[Etiquetas]:[Etiquetas17]],"*UAT_V*")>0,COUNTIF(Tabla[[#This Row],[Etiquetas]:[Etiquetas17]],"*QA-Integración*")=0),"SI","") | AQ51: {=IF(Tabla[[#This Row],[Fue encontrado durante UAT?]]="SI",IFERROR(_xlfn.XLOOKUP(TRUE,ISNUMBER(SEARCH("UAT_V",Tabla[[#This Row],[Etiquetas]:[Etiquetas17]])),Tabla[[#This Row],[Etiquetas]:[Etiquetas17]]),""),"")} | AR51: =IF(COUNTIF(Tabla[[#This Row],[Etiquetas]:[Etiquetas17]],"*Devuelto*")>0,"SI","") | AS51: =COUNTIF(Tabla[[#This Row],[Etiquetas]:[Etiquetas17]],"*Devuelto*") -> 0
A52: Error | B52: T20-3523 | C52: 119765 | D52: Corrección de gama de colores y visualización de tablas dentro del POS y BOT | E52: Medio | F52: READY FOR UAT | G52: T20 Sprint 25 2025 | H52: T20 Sprint 26 2025 | R52: Dashboard-Ventas | S52: Look&Feel | T52: QA-IntegraciónV0.14 | U52: T3B20_Kotlin | V52: Tienda2.0 | AA52: Carolina Rodríguez Soriano | AB52: 46002.638 | AC52: v0.15 | AG52: BOT | AJ52: {=IFERROR(_xlfn.XLOOKUP(TRUE,COUNTIF(Tabla[[#This Row],[Etiquetas]:[Etiquetas17]],Versiones!$G$2:$G$36)>0,Versiones!$B$2:$B$36), "")} -> 24 | AK52: {=IFERROR(_xlfn.XLOOKUP(TRUE,COUNTIF(Tabla[[#This Row],[Etiquetas]:[Etiquetas17]],Versiones!$G$2:$G$36)>0,Versiones!$A$2:$A$36), "")} -> V0.14 | AL52: ="V"&MAX(IFERROR(VALUE(MID(Tabla[[#This Row],[Versiones corregidas]],2,99)),0), IFERROR(VALUE(MID(Tabla[[#This Row],[Versiones corregidas19]],2,99)),0), IFERROR(VALUE(MID(Tabla[[#This Row],[Versiones corregidas20]],2,99)),0), IFERROR(VALUE(MID(Tabla[[#This Row],[Versiones corregidas21]],2,99)),0),IFERROR(VALUE(MID(#REF!,2,99)),0)) -> V0.15 | AM52: =IFERROR(_xlfn.XLOOKUP(Tabla[[#This Row],[¿En qué versión fue corregido?]],Versiones!$A$2:$A$34,Versiones!$B$2:$B$34),"No encontrado") -> 25 | AN52: {=IFERROR(_xlfn.XLOOKUP(TRUE,COUNTIF(Tabla[[#This Row],[Etiquetas]:[Etiquetas17]],Categorías!$A$2:$A$12)>0,Categorías!$A$2:$A$12),"No encontrado")} -> Look&Feel | AO52: {=IFERROR(INDEX(Funcionalidades!$A$2:$A$80,MATCH(TRUE, COUNTIF(Reporte_Gral!R52:Z52,Funcionalidades!$A$2:$A$80)>0,0)),"No encontrado")} -> Dashboard-Ventas | AP52: =IF(AND(COUNTIF(Tabla[[#This Row],[Etiquetas]:[Etiquetas17]],"*UAT_V*")>0,COUNTIF(Tabla[[#This Row],[Etiquetas]:[Etiquetas17]],"*QA-Integración*")=0),"SI","") | AQ52: {=IF(Tabla[[#This Row],[Fue encontrado durante UAT?]]="SI",IFERROR(_xlfn.XLOOKUP(TRUE,ISNUMBER(SEARCH("UAT_V",Tabla[[#This Row],[Etiquetas]:[Etiquetas17]])),Tabla[[#This Row],[Etiquetas]:[Etiquetas17]]),""),"")} | AR52: =IF(COUNTIF(Tabla[[#This Row],[Etiquetas]:[Etiquetas17]],"*Devuelto*")>0,"SI","") | AS52: =COUNTIF(Tabla[[#This Row],[Etiquetas]:[Etiquetas17]],"*Devuelto*") -> 0
A53: Error | B53: T20-3522 | C53: 119724 | D53: BOT - El evento BOT_TRANSFER_ITEMS_OUT no cumple con la estructura definida en la documentación (diferencias en user y product_key) | E53: Alta | F53: Tareas por hacer | R53: Eventos_iOT | S53: QA-IntegraciónV0.14 | T53: Realizar-Transferencia | U53: Revisado | AA53: Yubisleinys Mora Vega | AB53: 46002.528 | AG53: BOT | AJ53: {=IFERROR(_xlfn.XLOOKUP(TRUE,COUNTIF(Tabla[[#This Row],[Etiquetas]:[Etiquetas17]],Versiones!$G$2:$G$36)>0,Versiones!$B$2:$B$36), "")} -> 24 | AK53: {=IFERROR(_xlfn.XLOOKUP(TRUE,COUNTIF(Tabla[[#This Row],[Etiquetas]:[Etiquetas17]],Versiones!$G$2:$G$36)>0,Versiones!$A$2:$A$36), "")} -> V0.14 | AL53: ="V"&MAX(IFERROR(VALUE(MID(Tabla[[#This Row],[Versiones corregidas]],2,99)),0), IFERROR(VALUE(MID(Tabla[[#This Row],[Versiones corregidas19]],2,99)),0), IFERROR(VALUE(MID(Tabla[[#This Row],[Versiones corregidas20]],2,99)),0), IFERROR(VALUE(MID(Tabla[[#This Row],[Versiones corregidas21]],2,99)),0),IFERROR(VALUE(MID(#REF!,2,99)),0)) -> V0 | AM53: =IFERROR(_xlfn.XLOOKUP(Tabla[[#This Row],[¿En qué versión fue corregido?]],Versiones!$A$2:$A$34,Versiones!$B$2:$B$34),"No encontrado") -> No encontrado | AN53: {=IFERROR(_xlfn.XLOOKUP(TRUE,COUNTIF(Tabla[[#This Row],[Etiquetas]:[Etiquetas17]],Categorías!$A$2:$A$12)>0,Categorías!$A$2:$A$12),"No encontrado")} -> Eventos_iOT | AO53: {=IFERROR(INDEX(Funcionalidades!$A$2:$A$80,MATCH(TRUE, COUNTIF(Reporte_Gral!R53:Z53,Funcionalidades!$A$2:$A$80)>0,0)),"No encontrado")} -> Realizar-Transferencia | AP53: =IF(AND(COUNTIF(Tabla[[#This Row],[Etiquetas]:[Etiquetas17]],"*UAT_V*")>0,COUNTIF(Tabla[[#This Row],[Etiquetas]:[Etiquetas17]],"*QA-Integración*")=0),"SI","") | AQ53: {=IF(Tabla[[#This Row],[Fue encontrado durante UAT?]]="SI",IFERROR(_xlfn.XLOOKUP(TRUE,ISNUMBER(SEARCH("UAT_V",Tabla[[#This Row],[Etiquetas]:[Etiquetas17]])),Tabla[[#This Row],[Etiquetas]:[Etiquetas17]]),""),"")} | AR53: =IF(COUNTIF(Tabla[[#This Row],[Etiquetas]:[Etiquetas17]],"*Devuelto*")>0,"SI","") | AS53: =COUNTIF(Tabla[[#This Row],[Etiquetas]:[Etiquetas17]],"*Devuelto*") -> 0
A54: Error | B54: T20-3521 | C54: 119673 | D54: Se bloquea el POS al cerrar modal o cancelar operación de autenticación. | E54: Más alta | F54: READY FOR UAT | G54: T20 Sprint 25 2025 | H54: T20 Sprint 26 2025 | R54: Alivios | S54: Funcional | T54: UAT_V0.14 | AA54: Carolina Rodríguez Soriano | AB54: 46002.452 | AG54: POS | AJ54: {=IFERROR(_xlfn.XLOOKUP(TRUE,COUNTIF(Tabla[[#This Row],[Etiquetas]:[Etiquetas17]],Versiones!$G$2:$G$36)>0,Versiones!$B$2:$B$36), "")} -> 24 | AK54: {=IFERROR(_xlfn.XLOOKUP(TRUE,COUNTIF(Tabla[[#This Row],[Etiquetas]:[Etiquetas17]],Versiones!$G$2:$G$36)>0,Versiones!$A$2:$A$36), "")} -> V0.14 | AL54: ="V"&MAX(IFERROR(VALUE(MID(Tabla[[#This Row],[Versiones corregidas]],2,99)),0), IFERROR(VALUE(MID(Tabla[[#This Row],[Versiones corregidas19]],2,99)),0), IFERROR(VALUE(MID(Tabla[[#This Row],[Versiones corregidas20]],2,99)),0), IFERROR(VALUE(MID(Tabla[[#This Row],[Versiones corregidas21]],2,99)),0),IFERROR(VALUE(MID(#REF!,2,99)),0)) -> V0 | AM54: =IFERROR(_xlfn.XLOOKUP(Tabla[[#This Row],[¿En qué versión fue corregido?]],Versiones!$A$2:$A$34,Versiones!$B$2:$B$34),"No encontrado") -> No encontrado | AN54: {=IFERROR(_xlfn.XLOOKUP(TRUE,COUNTIF(Tabla[[#This Row],[Etiquetas]:[Etiquetas17]],Categorías!$A$2:$A$12)>0,Categorías!$A$2:$A$12),"No encontrado")} -> Funcional | AO54: {=IFERROR(INDEX(Funcionalidades!$A$2:$A$80,MATCH(TRUE, COUNTIF(Reporte_Gral!R54:Z54,Funcionalidades!$A$2:$A$80)>0,0)),"No encontrado")} -> Alivios | AP54: =IF(AND(COUNTIF(Tabla[[#This Row],[Etiquetas]:[Etiquetas17]],"*UAT_V*")>0,COUNTIF(Tabla[[#This Row],[Etiquetas]:[Etiquetas17]],"*QA-Integración*")=0),"SI","") -> SI | AQ54: {=IF(Tabla[[#This Row],[Fue encontrado durante UAT?]]="SI",IFERROR(_xlfn.XLOOKUP(TRUE,ISNUMBER(SEARCH("UAT_V",Tabla[[#This Row],[Etiquetas]:[Etiquetas17]])),Tabla[[#This Row],[Etiquetas]:[Etiquetas17]]),""),"")} -> UAT_V0.14 | AR54: =IF(COUNTIF(Tabla[[#This Row],[Etiquetas]:[Etiquetas17]],"*Devuelto*")>0,"SI","") | AS54: =COUNTIF(Tabla[[#This Row],[Etiquetas]:[Etiquetas17]],"*Devuelto*") -> 0
A55: Error | B55: T20-3516 | C55: 119399 | D55: POS - lista de "Atajos del teclado" dice mal escrito "Cerrat venta" | E55: Medio | F55: Cancelado | R55: Atajos-Teclado | S55: Look&Feel | T55: UAT_V0.14 | AA55: Daniela Soto | AB55: 46001.656 | AG55: POS | AJ55: {=IFERROR(_xlfn.XLOOKUP(TRUE,COUNTIF(Tabla[[#This Row],[Etiquetas]:[Etiquetas17]],Versiones!$G$2:$G$36)>0,Versiones!$B$2:$B$36), "")} -> 24 | AK55: {=IFERROR(_xlfn.XLOOKUP(TRUE,COUNTIF(Tabla[[#This Row],[Etiquetas]:[Etiquetas17]],Versiones!$G$2:$G$36)>0,Versiones!$A$2:$A$36), "")} -> V0.14 | AL55: ="V"&MAX(IFERROR(VALUE(MID(Tabla[[#This Row],[Versiones corregidas]],2,99)),0), IFERROR(VALUE(MID(Tabla[[#This Row],[Versiones corregidas19]],2,99)),0), IFERROR(VALUE(MID(Tabla[[#This Row],[Versiones corregidas20]],2,99)),0), IFERROR(VALUE(MID(Tabla[[#This Row],[Versiones corregidas21]],2,99)),0),IFERROR(VALUE(MID(#REF!,2,99)),0)) -> V0 | AM55: =IFERROR(_xlfn.XLOOKUP(Tabla[[#This Row],[¿En qué versión fue corregido?]],Versiones!$A$2:$A$34,Versiones!$B$2:$B$34),"No encontrado") -> No encontrado | AN55: {=IFERROR(_xlfn.XLOOKUP(TRUE,COUNTIF(Tabla[[#This Row],[Etiquetas]:[Etiquetas17]],Categorías!$A$2:$A$12)>0,Categorías!$A$2:$A$12),"No encontrado")} -> Look&Feel | AO55: {=IFERROR(INDEX(Funcionalidades!$A$2:$A$80,MATCH(TRUE, COUNTIF(Reporte_Gral!R55:Z55,Funcionalidades!$A$2:$A$80)>0,0)),"No encontrado")} -> Atajos-Teclado | AP55: =IF(AND(COUNTIF(Tabla[[#This Row],[Etiquetas]:[Etiquetas17]],"*UAT_V*")>0,COUNTIF(Tabla[[#This Row],[Etiquetas]:[Etiquetas17]],"*QA-Integración*")=0),"SI","") -> SI | AQ55: {=IF(Tabla[[#This Row],[Fue encontrado durante UAT?]]="SI",IFERROR(_xlfn.XLOOKUP(TRUE,ISNUMBER(SEARCH("UAT_V",Tabla[[#This Row],[Etiquetas]:[Etiquetas17]])),Tabla[[#This Row],[Etiquetas]:[Etiquetas17]]),""),"")} -> UAT_V0.14 | AR55: =IF(COUNTIF(Tabla[[#This Row],[Etiquetas]:[Etiquetas17]],"*Devuelto*")>0,"SI","") | AS55: =COUNTIF(Tabla[[#This Row],[Etiquetas]:[Etiquetas17]],"*Devuelto*") -> 0
A56: Error | B56: T20-3513 | C56: 119389 | D56: BOT - Previsualización de Precios – No permite cambiar de página | E56: Medio | F56: READY FOR UAT | G56: T20 Sprint 25 2025 | H56: T20 Sprint 26 2025 | R56: Funcional | S56: Imprimir-Cambios-De-Precio | T56: T3B20_BOT | U56: Tienda2.0 | V56: UAT_V0.14 | AA56: Yubisleinys Mora Vega | AB56: 46001.64 | AC56: v0.15 | AG56: BOT | AJ56: {=IFERROR(_xlfn.XLOOKUP(TRUE,COUNTIF(Tabla[[#This Row],[Etiquetas]:[Etiquetas17]],Versiones!$G$2:$G$36)>0,Versiones!$B$2:$B$36), "")} -> 24 | AK56: {=IFERROR(_xlfn.XLOOKUP(TRUE,COUNTIF(Tabla[[#This Row],[Etiquetas]:[Etiquetas17]],Versiones!$G$2:$G$36)>0,Versiones!$A$2:$A$36), "")} -> V0.14 | AL56: ="V"&MAX(IFERROR(VALUE(MID(Tabla[[#This Row],[Versiones corregidas]],2,99)),0), IFERROR(VALUE(MID(Tabla[[#This Row],[Versiones corregidas19]],2,99)),0), IFERROR(VALUE(MID(Tabla[[#This Row],[Versiones corregidas20]],2,99)),0), IFERROR(VALUE(MID(Tabla[[#This Row],[Versiones corregidas21]],2,99)),0),IFERROR(VALUE(MID(#REF!,2,99)),0)) -> V0.15 | AM56: =IFERROR(_xlfn.XLOOKUP(Tabla[[#This Row],[¿En qué versión fue corregido?]],Versiones!$A$2:$A$34,Versiones!$B$2:$B$34),"No encontrado") -> 25 | AN56: {=IFERROR(_xlfn.XLOOKUP(TRUE,COUNTIF(Tabla[[#This Row],[Etiquetas]:[Etiquetas17]],Categorías!$A$2:$A$12)>0,Categorías!$A$2:$A$12),"No encontrado")} -> Funcional | AO56: {=IFERROR(INDEX(Funcionalidades!$A$2:$A$80,MATCH(TRUE, COUNTIF(Reporte_Gral!R56:Z56,Funcionalidades!$A$2:$A$80)>0,0)),"No encontrado")} -> Imprimir-Cambios-De-Precio | AP56: =IF(AND(COUNTIF(Tabla[[#This Row],[Etiquetas]:[Etiquetas17]],"*UAT_V*")>0,COUNTIF(Tabla[[#This Row],[Etiquetas]:[Etiquetas17]],"*QA-Integración*")=0),"SI","") -> SI | AQ56: {=IF(Tabla[[#This Row],[Fue encontrado durante UAT?]]="SI",IFERROR(_xlfn.XLOOKUP(TRUE,ISNUMBER(SEARCH("UAT_V",Tabla[[#This Row],[Etiquetas]:[Etiquetas17]])),Tabla[[#This Row],[Etiquetas]:[Etiquetas17]]),""),"")} -> UAT_V0.14 | AR56: =IF(COUNTIF(Tabla[[#This Row],[Etiquetas]:[Etiquetas17]],"*Devuelto*")>0,"SI","") | AS56: =COUNTIF(Tabla[[#This Row],[Etiquetas]:[Etiquetas17]],"*Devuelto*") -> 0
A57: Error | B57: T20-3512 | C57: 119388 | D57: POS - Arqueo no está abriendo el cajón del POS | E57: Medio | F57: READY FOR UAT | G57: T20 Sprint 25 2025 | H57: T20 Sprint 26 2025 | R57: Arqueo | S57: Funcional | T57: T3B20_POS | U57: Tienda2.0 | V57: UAT_V0.14 | AA57: Daniela Soto | AB57: 46001.636 | AC57: v0.15 | AG57: POS | AJ57: {=IFERROR(_xlfn.XLOOKUP(TRUE,COUNTIF(Tabla[[#This Row],[Etiquetas]:[Etiquetas17]],Versiones!$G$2:$G$36)>0,Versiones!$B$2:$B$36), "")} -> 24 | AK57: {=IFERROR(_xlfn.XLOOKUP(TRUE,COUNTIF(Tabla[[#This Row],[Etiquetas]:[Etiquetas17]],Versiones!$G$2:$G$36)>0,Versiones!$A$2:$A$36), "")} -> V0.14 | AL57: ="V"&MAX(IFERROR(VALUE(MID(Tabla[[#This Row],[Versiones corregidas]],2,99)),0), IFERROR(VALUE(MID(Tabla[[#This Row],[Versiones corregidas19]],2,99)),0), IFERROR(VALUE(MID(Tabla[[#This Row],[Versiones corregidas20]],2,99)),0), IFERROR(VALUE(MID(Tabla[[#This Row],[Versiones corregidas21]],2,99)),0),IFERROR(VALUE(MID(#REF!,2,99)),0)) -> V0.15 | AM57: =IFERROR(_xlfn.XLOOKUP(Tabla[[#This Row],[¿En qué versión fue corregido?]],Versiones!$A$2:$A$34,Versiones!$B$2:$B$34),"No encontrado") -> 25 | AN57: {=IFERROR(_xlfn.XLOOKUP(TRUE,COUNTIF(Tabla[[#This Row],[Etiquetas]:[Etiquetas17]],Categorías!$A$2:$A$12)>0,Categorías!$A$2:$A$12),"No encontrado")} -> Funcional | AO57: {=IFERROR(INDEX(Funcionalidades!$A$2:$A$80,MATCH(TRUE, COUNTIF(Reporte_Gral!R57:Z57,Funcionalidades!$A$2:$A$80)>0,0)),"No encontrado")} -> Arqueo | AP57: =IF(AND(COUNTIF(Tabla[[#This Row],[Etiquetas]:[Etiquetas17]],"*UAT_V*")>0,COUNTIF(Tabla[[#This Row],[Etiquetas]:[Etiquetas17]],"*QA-Integración*")=0),"SI","") -> SI | AQ57: {=IF(Tabla[[#This Row],[Fue encontrado durante UAT?]]="SI",IFERROR(_xlfn.XLOOKUP(TRUE,ISNUMBER(SEARCH("UAT_V",Tabla[[#This Row],[Etiquetas]:[Etiquetas17]])),Tabla[[#This Row],[Etiquetas]:[Etiquetas17]]),""),"")} -> UAT_V0.14 | AR57: =IF(COUNTIF(Tabla[[#This Row],[Etiquetas]:[Etiquetas17]],"*Devuelto*")>0,"SI","") | AS57: =COUNTIF(Tabla[[#This Row],[Etiquetas]:[Etiquetas17]],"*Devuelto*") -> 0
A58: Error | B58: T20-3510 | C58: 119372 | D58: BOT - Pantalla en blanco después de aplicar Regla 13 | E58: Medio | F58: Tareas por hacer | G58: T20 Sprint 26 2025 | R58: Funcional | S58: Reporte-De-Inventario | T58: T3B20_BOT | U58: Tienda2.0 | V58: UAT_V0.13 | AA58: Yubisleinys Mora Vega | AB58: 46001.611 | AC58: v0.16 | AG58: BOT | AH58: CANCELADO | AJ58: {=IFERROR(_xlfn.XLOOKUP(TRUE,COUNTIF(Tabla[[#This Row],[Etiquetas]:[Etiquetas17]],Versiones!$G$2:$G$36)>0,Versiones!$B$2:$B$36), "")} -> 23 | AK58: {=IFERROR(_xlfn.XLOOKUP(TRUE,COUNTIF(Tabla[[#This Row],[Etiquetas]:[Etiquetas17]],Versiones!$G$2:$G$36)>0,Versiones!$A$2:$A$36), "")} -> V0.13 | AL58: ="V"&MAX(IFERROR(VALUE(MID(Tabla[[#This Row],[Versiones corregidas]],2,99)),0), IFERROR(VALUE(MID(Tabla[[#This Row],[Versiones corregidas19]],2,99)),0), IFERROR(VALUE(MID(Tabla[[#This Row],[Versiones corregidas20]],2,99)),0), IFERROR(VALUE(MID(Tabla[[#This Row],[Versiones corregidas21]],2,99)),0),IFERROR(VALUE(MID(#REF!,2,99)),0)) -> V0.16 | AM58: =IFERROR(_xlfn.XLOOKUP(Tabla[[#This Row],[¿En qué versión fue corregido?]],Versiones!$A$2:$A$34,Versiones!$B$2:$B$34),"No encontrado") -> 0 | AN58: {=IFERROR(_xlfn.XLOOKUP(TRUE,COUNTIF(Tabla[[#This Row],[Etiquetas]:[Etiquetas17]],Categorías!$A$2:$A$12)>0,Categorías!$A$2:$A$12),"No encontrado")} -> Funcional | AO58: {=IFERROR(INDEX(Funcionalidades!$A$2:$A$80,MATCH(TRUE, COUNTIF(Reporte_Gral!R58:Z58,Funcionalidades!$A$2:$A$80)>0,0)),"No encontrado")} -> Reporte-De-Inventario | AP58: =IF(AND(COUNTIF(Tabla[[#This Row],[Etiquetas]:[Etiquetas17]],"*UAT_V*")>0,COUNTIF(Tabla[[#This Row],[Etiquetas]:[Etiquetas17]],"*QA-Integración*")=0),"SI","") -> SI | AQ58: {=IF(Tabla[[#This Row],[Fue encontrado durante UAT?]]="SI",IFERROR(_xlfn.XLOOKUP(TRUE,ISNUMBER(SEARCH("UAT_V",Tabla[[#This Row],[Etiquetas]:[Etiquetas17]])),Tabla[[#This Row],[Etiquetas]:[Etiquetas17]]),""),"")} -> UAT_V0.13 | AR58: =IF(COUNTIF(Tabla[[#This Row],[Etiquetas]:[Etiquetas17]],"*Devuelto*")>0,"SI","") | AS58: =COUNTIF(Tabla[[#This Row],[Etiquetas]:[Etiquetas17]],"*Devuelto*") -> 0
A59: Error | B59: T20-3507 | C59: 119364 | D59: POS - Faltan símbolos en la pantalla modal devolución | E59: Medio | F59: TO BE DEPLOYED-SIT | G59: T20 Sprint 25 2025 | H59: T20 Sprint 26 2025 | R59: Devoluciones | S59: Look&Feel | T59: T3B20_POS | U59: Tienda2.0 | V59: UAT_V0.13 | AA59: Yubisleinys Mora Vega | AB59: 46001.594 | AC59: v0.16 | AG59: POS | AJ59: {=IFERROR(_xlfn.XLOOKUP(TRUE,COUNTIF(Tabla[[#This Row],[Etiquetas]:[Etiquetas17]],Versiones!$G$2:$G$36)>0,Versiones!$B$2:$B$36), "")} -> 23 | AK59: {=IFERROR(_xlfn.XLOOKUP(TRUE,COUNTIF(Tabla[[#This Row],[Etiquetas]:[Etiquetas17]],Versiones!$G$2:$G$36)>0,Versiones!$A$2:$A$36), "")} -> V0.13 | AL59: ="V"&MAX(IFERROR(VALUE(MID(Tabla[[#This Row],[Versiones corregidas]],2,99)),0), IFERROR(VALUE(MID(Tabla[[#This Row],[Versiones corregidas19]],2,99)),0), IFERROR(VALUE(MID(Tabla[[#This Row],[Versiones corregidas20]],2,99)),0), IFERROR(VALUE(MID(Tabla[[#This Row],[Versiones corregidas21]],2,99)),0),IFERROR(VALUE(MID(#REF!,2,99)),0)) -> V0.16 | AM59: =IFERROR(_xlfn.XLOOKUP(Tabla[[#This Row],[¿En qué versión fue corregido?]],Versiones!$A$2:$A$34,Versiones!$B$2:$B$34),"No encontrado") -> 0 | AN59: {=IFERROR(_xlfn.XLOOKUP(TRUE,COUNTIF(Tabla[[#This Row],[Etiquetas]:[Etiquetas17]],Categorías!$A$2:$A$12)>0,Categorías!$A$2:$A$12),"No encontrado")} -> Look&Feel | AO59: {=IFERROR(INDEX(Funcionalidades!$A$2:$A$80,MATCH(TRUE, COUNTIF(Reporte_Gral!R59:Z59,Funcionalidades!$A$2:$A$80)>0,0)),"No encontrado")} -> Devoluciones | AP59: =IF(AND(COUNTIF(Tabla[[#This Row],[Etiquetas]:[Etiquetas17]],"*UAT_V*")>0,COUNTIF(Tabla[[#This Row],[Etiquetas]:[Etiquetas17]],"*QA-Integración*")=0),"SI","") -> SI | AQ59: {=IF(Tabla[[#This Row],[Fue encontrado durante UAT?]]="SI",IFERROR(_xlfn.XLOOKUP(TRUE,ISNUMBER(SEARCH("UAT_V",Tabla[[#This Row],[Etiquetas]:[Etiquetas17]])),Tabla[[#This Row],[Etiquetas]:[Etiquetas17]]),""),"")} -> UAT_V0.13 | AR59: =IF(COUNTIF(Tabla[[#This Row],[Etiquetas]:[Etiquetas17]],"*Devuelto*")>0,"SI","") | AS59: =COUNTIF(Tabla[[#This Row],[Etiquetas]:[Etiquetas17]],"*Devuelto*") -> 0
A60: Error | B60: T20-3506 | C60: 119316 | D60: Se borra toda la información del panel de Ventas (BOT) después de realizar una devolución | E60: Más alta | F60: READY FOR UAT | G60: T20 Sprint 25 2025 | H60: T20 Sprint 26 2025 | R60: Dashboard-Ventas | S60: Funcional | T60: UAT_V0.14 | AA60: Carolina Rodríguez Soriano | AB60: 46001.498 | AG60: BOT | AH60: CANCELADO | AJ60: {=IFERROR(_xlfn.XLOOKUP(TRUE,COUNTIF(Tabla[[#This Row],[Etiquetas]:[Etiquetas17]],Versiones!$G$2:$G$36)>0,Versiones!$B$2:$B$36), "")} -> 24 | AK60: {=IFERROR(_xlfn.XLOOKUP(TRUE,COUNTIF(Tabla[[#This Row],[Etiquetas]:[Etiquetas17]],Versiones!$G$2:$G$36)>0,Versiones!$A$2:$A$36), "")} -> V0.14 | AL60: ="V"&MAX(IFERROR(VALUE(MID(Tabla[[#This Row],[Versiones corregidas]],2,99)),0), IFERROR(VALUE(MID(Tabla[[#This Row],[Versiones corregidas19]],2,99)),0), IFERROR(VALUE(MID(Tabla[[#This Row],[Versiones corregidas20]],2,99)),0), IFERROR(VALUE(MID(Tabla[[#This Row],[Versiones corregidas21]],2,99)),0),IFERROR(VALUE(MID(#REF!,2,99)),0)) -> V0 | AM60: =IFERROR(_xlfn.XLOOKUP(Tabla[[#This Row],[¿En qué versión fue corregido?]],Versiones!$A$2:$A$34,Versiones!$B$2:$B$34),"No encontrado") -> No encontrado | AN60: {=IFERROR(_xlfn.XLOOKUP(TRUE,COUNTIF(Tabla[[#This Row],[Etiquetas]:[Etiquetas17]],Categorías!$A$2:$A$12)>0,Categorías!$A$2:$A$12),"No encontrado")} -> Funcional | AO60: {=IFERROR(INDEX(Funcionalidades!$A$2:$A$80,MATCH(TRUE, COUNTIF(Reporte_Gral!R60:Z60,Funcionalidades!$A$2:$A$80)>0,0)),"No encontrado")} -> Dashboard-Ventas | AP60: =IF(AND(COUNTIF(Tabla[[#This Row],[Etiquetas]:[Etiquetas17]],"*UAT_V*")>0,COUNTIF(Tabla[[#This Row],[Etiquetas]:[Etiquetas17]],"*QA-Integración*")=0),"SI","") -> SI | AQ60: {=IF(Tabla[[#This Row],[Fue encontrado durante UAT?]]="SI",IFERROR(_xlfn.XLOOKUP(TRUE,ISNUMBER(SEARCH("UAT_V",Tabla[[#This Row],[Etiquetas]:[Etiquetas17]])),Tabla[[#This Row],[Etiquetas]:[Etiquetas17]]),""),"")} -> UAT_V0.14 | AR60: =IF(COUNTIF(Tabla[[#This Row],[Etiquetas]:[Etiquetas17]],"*Devuelto*")>0,"SI","") | AS60: =COUNTIF(Tabla[[#This Row],[Etiquetas]:[Etiquetas17]],"*Devuelto*") -> 0
A61: Error | B61: T20-3294 | C61: 118885 | D61: POS - Al ingresar caracteres en un campo de texto, el curso hace un "salto atrás" y dificulta escribir. | E61: Alta | F61: Tareas por hacer | G61: T20 Sprint 24 2025 | H61: T20 Sprint 25 2025 | I61: T20 Sprint 26 2025 | R61: Bugs-En-Inputs | S61: Funcional | T61: QA-IntegraciónV0.14 | U61: Revisado | AA61: Daniela Soto | AB61: 46000.656 | AG61: POS | AJ61: {=IFERROR(_xlfn.XLOOKUP(TRUE,COUNTIF(Tabla[[#This Row],[Etiquetas]:[Etiquetas17]],Versiones!$G$2:$G$36)>0,Versiones!$B$2:$B$36), "")} -> 24 | AK61: {=IFERROR(_xlfn.XLOOKUP(TRUE,COUNTIF(Tabla[[#This Row],[Etiquetas]:[Etiquetas17]],Versiones!$G$2:$G$36)>0,Versiones!$A$2:$A$36), "")} -> V0.14 | AL61: ="V"&MAX(IFERROR(VALUE(MID(Tabla[[#This Row],[Versiones corregidas]],2,99)),0), IFERROR(VALUE(MID(Tabla[[#This Row],[Versiones corregidas19]],2,99)),0), IFERROR(VALUE(MID(Tabla[[#This Row],[Versiones corregidas20]],2,99)),0), IFERROR(VALUE(MID(Tabla[[#This Row],[Versiones corregidas21]],2,99)),0),IFERROR(VALUE(MID(#REF!,2,99)),0)) -> V0 | AM61: =IFERROR(_xlfn.XLOOKUP(Tabla[[#This Row],[¿En qué versión fue corregido?]],Versiones!$A$2:$A$34,Versiones!$B$2:$B$34),"No encontrado") -> No encontrado | AN61: {=IFERROR(_xlfn.XLOOKUP(TRUE,COUNTIF(Tabla[[#This Row],[Etiquetas]:[Etiquetas17]],Categorías!$A$2:$A$12)>0,Categorías!$A$2:$A$12),"No encontrado")} -> Funcional | AO61: {=IFERROR(INDEX(Funcionalidades!$A$2:$A$80,MATCH(TRUE, COUNTIF(Reporte_Gral!R61:Z61,Funcionalidades!$A$2:$A$80)>0,0)),"No encontrado")} -> Bugs-En-Inputs | AP61: =IF(AND(COUNTIF(Tabla[[#This Row],[Etiquetas]:[Etiquetas17]],"*UAT_V*")>0,COUNTIF(Tabla[[#This Row],[Etiquetas]:[Etiquetas17]],"*QA-Integración*")=0),"SI","") | AQ61: {=IF(Tabla[[#This Row],[Fue encontrado durante UAT?]]="SI",IFERROR(_xlfn.XLOOKUP(TRUE,ISNUMBER(SEARCH("UAT_V",Tabla[[#This Row],[Etiquetas]:[Etiquetas17]])),Tabla[[#This Row],[Etiquetas]:[Etiquetas17]]),""),"")} | AR61: =IF(COUNTIF(Tabla[[#This Row],[Etiquetas]:[Etiquetas17]],"*Devuelto*")>0,"SI","") | AS61: =COUNTIF(Tabla[[#This Row],[Etiquetas]:[Etiquetas17]],"*Devuelto*") -> 0
A62: Error | B62: T20-3293 | C62: 118788 | D62: BOT - El botón Cancelar del modal de autenticación no cierra la ventana en flujo de Pedido Eficiente | E62: Alta | F62: Tareas por hacer | R62: Funcional | S62: QA-IntegraciónV0.14 | T62: Realizar-Pedido-Eficiente | U62: Revisado | AA62: Yubisleinys Mora Vega | AB62: 46000.466 | AG62: BOT | AJ62: {=IFERROR(_xlfn.XLOOKUP(TRUE,COUNTIF(Tabla[[#This Row],[Etiquetas]:[Etiquetas17]],Versiones!$G$2:$G$36)>0,Versiones!$B$2:$B$36), "")} -> 24 | AK62: {=IFERROR(_xlfn.XLOOKUP(TRUE,COUNTIF(Tabla[[#This Row],[Etiquetas]:[Etiquetas17]],Versiones!$G$2:$G$36)>0,Versiones!$A$2:$A$36), "")} -> V0.14 | AL62: ="V"&MAX(IFERROR(VALUE(MID(Tabla[[#This Row],[Versiones corregidas]],2,99)),0), IFERROR(VALUE(MID(Tabla[[#This Row],[Versiones corregidas19]],2,99)),0), IFERROR(VALUE(MID(Tabla[[#This Row],[Versiones corregidas20]],2,99)),0), IFERROR(VALUE(MID(Tabla[[#This Row],[Versiones corregidas21]],2,99)),0),IFERROR(VALUE(MID(#REF!,2,99)),0)) -> V0 | AM62: =IFERROR(_xlfn.XLOOKUP(Tabla[[#This Row],[¿En qué versión fue corregido?]],Versiones!$A$2:$A$34,Versiones!$B$2:$B$34),"No encontrado") -> No encontrado | AN62: {=IFERROR(_xlfn.XLOOKUP(TRUE,COUNTIF(Tabla[[#This Row],[Etiquetas]:[Etiquetas17]],Categorías!$A$2:$A$12)>0,Categorías!$A$2:$A$12),"No encontrado")} -> Funcional | AO62: {=IFERROR(INDEX(Funcionalidades!$A$2:$A$80,MATCH(TRUE, COUNTIF(Reporte_Gral!R62:Z62,Funcionalidades!$A$2:$A$80)>0,0)),"No encontrado")} -> Realizar-Pedido-Eficiente | AP62: =IF(AND(COUNTIF(Tabla[[#This Row],[Etiquetas]:[Etiquetas17]],"*UAT_V*")>0,COUNTIF(Tabla[[#This Row],[Etiquetas]:[Etiquetas17]],"*QA-Integración*")=0),"SI","") | AQ62: {=IF(Tabla[[#This Row],[Fue encontrado durante UAT?]]="SI",IFERROR(_xlfn.XLOOKUP(TRUE,ISNUMBER(SEARCH("UAT_V",Tabla[[#This Row],[Etiquetas]:[Etiquetas17]])),Tabla[[#This Row],[Etiquetas]:[Etiquetas17]]),""),"")} | AR62: =IF(COUNTIF(Tabla[[#This Row],[Etiquetas]:[Etiquetas17]],"*Devuelto*")>0,"SI","") | AS62: =COUNTIF(Tabla[[#This Row],[Etiquetas]:[Etiquetas17]],"*Devuelto*") -> 0
A63: Error | B63: T20-3286 | C63: 118755 | D63: POS - Ctrl U no funciona correctamente, se cierra la pantalla | E63: Alta | F63: Cancelado | G63: T20 Sprint 25 2025 | H63: T20 Sprint 26 2025 | R63: Consulta-Última-Transacción-Santander | S63: Funcional | T63: QA-IntegraciónV0.14 | U63: T3B20_POS | V63: Tienda2.0 | AA63: Daniela Soto | AB63: 46000.414 | AG63: POS | AJ63: {=IFERROR(_xlfn.XLOOKUP(TRUE,COUNTIF(Tabla[[#This Row],[Etiquetas]:[Etiquetas17]],Versiones!$G$2:$G$36)>0,Versiones!$B$2:$B$36), "")} -> 24 | AK63: {=IFERROR(_xlfn.XLOOKUP(TRUE,COUNTIF(Tabla[[#This Row],[Etiquetas]:[Etiquetas17]],Versiones!$G$2:$G$36)>0,Versiones!$A$2:$A$36), "")} -> V0.14 | AL63: ="V"&MAX(IFERROR(VALUE(MID(Tabla[[#This Row],[Versiones corregidas]],2,99)),0), IFERROR(VALUE(MID(Tabla[[#This Row],[Versiones corregidas19]],2,99)),0), IFERROR(VALUE(MID(Tabla[[#This Row],[Versiones corregidas20]],2,99)),0), IFERROR(VALUE(MID(Tabla[[#This Row],[Versiones corregidas21]],2,99)),0),IFERROR(VALUE(MID(#REF!,2,99)),0)) -> V0 | AM63: =IFERROR(_xlfn.XLOOKUP(Tabla[[#This Row],[¿En qué versión fue corregido?]],Versiones!$A$2:$A$34,Versiones!$B$2:$B$34),"No encontrado") -> No encontrado | AN63: {=IFERROR(_xlfn.XLOOKUP(TRUE,COUNTIF(Tabla[[#This Row],[Etiquetas]:[Etiquetas17]],Categorías!$A$2:$A$12)>0,Categorías!$A$2:$A$12),"No encontrado")} -> Funcional | AO63: {=IFERROR(INDEX(Funcionalidades!$A$2:$A$80,MATCH(TRUE, COUNTIF(Reporte_Gral!R63:Z63,Funcionalidades!$A$2:$A$80)>0,0)),"No encontrado")} -> Consulta-Última-Transacción-SANTANDER | AP63: =IF(AND(COUNTIF(Tabla[[#This Row],[Etiquetas]:[Etiquetas17]],"*UAT_V*")>0,COUNTIF(Tabla[[#This Row],[Etiquetas]:[Etiquetas17]],"*QA-Integración*")=0),"SI","") | AQ63: {=IF(Tabla[[#This Row],[Fue encontrado durante UAT?]]="SI",IFERROR(_xlfn.XLOOKUP(TRUE,ISNUMBER(SEARCH("UAT_V",Tabla[[#This Row],[Etiquetas]:[Etiquetas17]])),Tabla[[#This Row],[Etiquetas]:[Etiquetas17]]),""),"")} | AR63: =IF(COUNTIF(Tabla[[#This Row],[Etiquetas]:[Etiquetas17]],"*Devuelto*")>0,"SI","") | AS63: =COUNTIF(Tabla[[#This Row],[Etiquetas]:[Etiquetas17]],"*Devuelto*") -> 0
A64: Error | B64: T20-3284 | C64: 118516 | D64: BOT - Pedido eficiente - La pantalla queda en gris al confirmar Pedido Eficiente | E64: Alta | F64: En curso | G64: T20 Sprint 26 2025 | R64: Funcional | S64: QA-IntegraciónV0.14 | T64: Realizar-Pedido-Eficiente | U64: Revisado | V64: T3B20_BOT | W64: Tienda2.0 | AA64: Yubisleinys Mora Vega | AB64: 45999.693 | AC64: v0.16 | AG64: BOT | AJ64: {=IFERROR(_xlfn.XLOOKUP(TRUE,COUNTIF(Tabla[[#This Row],[Etiquetas]:[Etiquetas17]],Versiones!$G$2:$G$36)>0,Versiones!$B$2:$B$36), "")} -> 24 | AK64: {=IFERROR(_xlfn.XLOOKUP(TRUE,COUNTIF(Tabla[[#This Row],[Etiquetas]:[Etiquetas17]],Versiones!$G$2:$G$36)>0,Versiones!$A$2:$A$36), "")} -> V0.14 | AL64: ="V"&MAX(IFERROR(VALUE(MID(Tabla[[#This Row],[Versiones corregidas]],2,99)),0), IFERROR(VALUE(MID(Tabla[[#This Row],[Versiones corregidas19]],2,99)),0), IFERROR(VALUE(MID(Tabla[[#This Row],[Versiones corregidas20]],2,99)),0), IFERROR(VALUE(MID(Tabla[[#This Row],[Versiones corregidas21]],2,99)),0),IFERROR(VALUE(MID(#REF!,2,99)),0)) -> V0.16 | AM64: =IFERROR(_xlfn.XLOOKUP(Tabla[[#This Row],[¿En qué versión fue corregido?]],Versiones!$A$2:$A$34,Versiones!$B$2:$B$34),"No encontrado") -> 0 | AN64: {=IFERROR(_xlfn.XLOOKUP(TRUE,COUNTIF(Tabla[[#This Row],[Etiquetas]:[Etiquetas17]],Categorías!$A$2:$A$12)>0,Categorías!$A$2:$A$12),"No encontrado")} -> Funcional | AO64: {=IFERROR(INDEX(Funcionalidades!$A$2:$A$80,MATCH(TRUE, COUNTIF(Reporte_Gral!R64:Z64,Funcionalidades!$A$2:$A$80)>0,0)),"No encontrado")} -> Realizar-Pedido-Eficiente | AP64: =IF(AND(COUNTIF(Tabla[[#This Row],[Etiquetas]:[Etiquetas17]],"*UAT_V*")>0,COUNTIF(Tabla[[#This Row],[Etiquetas]:[Etiquetas17]],"*QA-Integración*")=0),"SI","") | AQ64: {=IF(Tabla[[#This Row],[Fue encontrado durante UAT?]]="SI",IFERROR(_xlfn.XLOOKUP(TRUE,ISNUMBER(SEARCH("UAT_V",Tabla[[#This Row],[Etiquetas]:[Etiquetas17]])),Tabla[[#This Row],[Etiquetas]:[Etiquetas17]]),""),"")} | AR64: =IF(COUNTIF(Tabla[[#This Row],[Etiquetas]:[Etiquetas17]],"*Devuelto*")>0,"SI","") | AS64: =COUNTIF(Tabla[[#This Row],[Etiquetas]:[Etiquetas17]],"*Devuelto*") -> 0
A65: Error | B65: T20-3283 | C65: 118492 | D65: BOT - No se visualiza la sección “Movimientos” con las operaciones diarias en el panel de Efectivo | E65: Alta | F65: READY FOR UAT | G65: T20 Sprint 25 2025 | H65: T20 Sprint 26 2025 | R65: Dashboard-Efectivo | S65: Funcional | T65: QA-IntegraciónV0.14 | U65: T3B20_BOT | V65: Tienda2.0 | AA65: Yubisleinys Mora Vega | AB65: 45999.665 | AC65: v0.15 | AG65: BOT | AJ65: {=IFERROR(_xlfn.XLOOKUP(TRUE,COUNTIF(Tabla[[#This Row],[Etiquetas]:[Etiquetas17]],Versiones!$G$2:$G$36)>0,Versiones!$B$2:$B$36), "")} -> 24 | AK65: {=IFERROR(_xlfn.XLOOKUP(TRUE,COUNTIF(Tabla[[#This Row],[Etiquetas]:[Etiquetas17]],Versiones!$G$2:$G$36)>0,Versiones!$A$2:$A$36), "")} -> V0.14 | AL65: ="V"&MAX(IFERROR(VALUE(MID(Tabla[[#This Row],[Versiones corregidas]],2,99)),0), IFERROR(VALUE(MID(Tabla[[#This Row],[Versiones corregidas19]],2,99)),0), IFERROR(VALUE(MID(Tabla[[#This Row],[Versiones corregidas20]],2,99)),0), IFERROR(VALUE(MID(Tabla[[#This Row],[Versiones corregidas21]],2,99)),0),IFERROR(VALUE(MID(#REF!,2,99)),0)) -> V0.15 | AM65: =IFERROR(_xlfn.XLOOKUP(Tabla[[#This Row],[¿En qué versión fue corregido?]],Versiones!$A$2:$A$34,Versiones!$B$2:$B$34),"No encontrado") -> 25 | AN65: {=IFERROR(_xlfn.XLOOKUP(TRUE,COUNTIF(Tabla[[#This Row],[Etiquetas]:[Etiquetas17]],Categorías!$A$2:$A$12)>0,Categorías!$A$2:$A$12),"No encontrado")} -> Funcional | AO65: {=IFERROR(INDEX(Funcionalidades!$A$2:$A$80,MATCH(TRUE, COUNTIF(Reporte_Gral!R65:Z65,Funcionalidades!$A$2:$A$80)>0,0)),"No encontrado")} -> Dashboard-Efectivo | AP65: =IF(AND(COUNTIF(Tabla[[#This Row],[Etiquetas]:[Etiquetas17]],"*UAT_V*")>0,COUNTIF(Tabla[[#This Row],[Etiquetas]:[Etiquetas17]],"*QA-Integración*")=0),"SI","") | AQ65: {=IF(Tabla[[#This Row],[Fue encontrado durante UAT?]]="SI",IFERROR(_xlfn.XLOOKUP(TRUE,ISNUMBER(SEARCH("UAT_V",Tabla[[#This Row],[Etiquetas]:[Etiquetas17]])),Tabla[[#This Row],[Etiquetas]:[Etiquetas17]]),""),"")} | AR65: =IF(COUNTIF(Tabla[[#This Row],[Etiquetas]:[Etiquetas17]],"*Devuelto*")>0,"SI","") | AS65: =COUNTIF(Tabla[[#This Row],[Etiquetas]:[Etiquetas17]],"*Devuelto*") -> 0
A66: Error | B66: T20-3282 | C66: 118485 | D66: BOT - No se visualizan los botones en algunos modales | E66: Más alta | F66: READY FOR UAT | G66: T20 Sprint 25 2025 | H66: T20 Sprint 26 2025 | R66: Funcional | S66: QA-IntegraciónV0.14 | T66: Registrar-Merma | U66: T3B20_BOT | V66: Tienda2.0 | AA66: Yubisleinys Mora Vega | AB66: 45999.652 | AC66: v0.15 | AG66: BOT | AH66: CANCELADO | AI66: Emiliano Fraile | AJ66: {=IFERROR(_xlfn.XLOOKUP(TRUE,COUNTIF(Tabla[[#This Row],[Etiquetas]:[Etiquetas17]],Versiones!$G$2:$G$36)>0,Versiones!$B$2:$B$36), "")} -> 24 | AK66: {=IFERROR(_xlfn.XLOOKUP(TRUE,COUNTIF(Tabla[[#This Row],[Etiquetas]:[Etiquetas17]],Versiones!$G$2:$G$36)>0,Versiones!$A$2:$A$36), "")} -> V0.14 | AL66: ="V"&MAX(IFERROR(VALUE(MID(Tabla[[#This Row],[Versiones corregidas]],2,99)),0), IFERROR(VALUE(MID(Tabla[[#This Row],[Versiones corregidas19]],2,99)),0), IFERROR(VALUE(MID(Tabla[[#This Row],[Versiones corregidas20]],2,99)),0), IFERROR(VALUE(MID(Tabla[[#This Row],[Versiones corregidas21]],2,99)),0),IFERROR(VALUE(MID(#REF!,2,99)),0)) -> V0.15 | AM66: =IFERROR(_xlfn.XLOOKUP(Tabla[[#This Row],[¿En qué versión fue corregido?]],Versiones!$A$2:$A$34,Versiones!$B$2:$B$34),"No encontrado") -> 25 | AN66: {=IFERROR(_xlfn.XLOOKUP(TRUE,COUNTIF(Tabla[[#This Row],[Etiquetas]:[Etiquetas17]],Categorías!$A$2:$A$12)>0,Categorías!$A$2:$A$12),"No encontrado")} -> Funcional | AO66: {=IFERROR(INDEX(Funcionalidades!$A$2:$A$80,MATCH(TRUE, COUNTIF(Reporte_Gral!R66:Z66,Funcionalidades!$A$2:$A$80)>0,0)),"No encontrado")} -> Registrar-Merma | AP66: =IF(AND(COUNTIF(Tabla[[#This Row],[Etiquetas]:[Etiquetas17]],"*UAT_V*")>0,COUNTIF(Tabla[[#This Row],[Etiquetas]:[Etiquetas17]],"*QA-Integración*")=0),"SI","") | AQ66: {=IF(Tabla[[#This Row],[Fue encontrado durante UAT?]]="SI",IFERROR(_xlfn.XLOOKUP(TRUE,ISNUMBER(SEARCH("UAT_V",Tabla[[#This Row],[Etiquetas]:[Etiquetas17]])),Tabla[[#This Row],[Etiquetas]:[Etiquetas17]]),""),"")} | AR66: =IF(COUNTIF(Tabla[[#This Row],[Etiquetas]:[Etiquetas17]],"*Devuelto*")>0,"SI","") | AS66: =COUNTIF(Tabla[[#This Row],[Etiquetas]:[Etiquetas17]],"*Devuelto*") -> 0
A67: Error | B67: T20-3278 | C67: 118419 | D67: En pantalla de registro de gastos aunque no se ponga el comentario obligatorio se registra el gasto infinidad de veces y no aparece una notificacion de que ya se realizo el registro del mismo | E67: Más alta | F67: Tareas por hacer | G67: T20 Sprint 26 2025 | R67: Funcional | S67: Registro-de-Gastos | T67: Revisado | U67: T3B20_BOT | V67: Tienda2.0 | W67: UAT | X67: UAT_V0.14 | AA67: Maria Pilar Albacete Occhi | AB67: 45999.519 | AC67: v0.16 | AG67: BOT | AH67: CANCELADO | AJ67: {=IFERROR(_xlfn.XLOOKUP(TRUE,COUNTIF(Tabla[[#This Row],[Etiquetas]:[Etiquetas17]],Versiones!$G$2:$G$36)>0,Versiones!$B$2:$B$36), "")} -> 24 | AK67: {=IFERROR(_xlfn.XLOOKUP(TRUE,COUNTIF(Tabla[[#This Row],[Etiquetas]:[Etiquetas17]],Versiones!$G$2:$G$36)>0,Versiones!$A$2:$A$36), "")} -> V0.14 | AL67: ="V"&MAX(IFERROR(VALUE(MID(Tabla[[#This Row],[Versiones corregidas]],2,99)),0), IFERROR(VALUE(MID(Tabla[[#This Row],[Versiones corregidas19]],2,99)),0), IFERROR(VALUE(MID(Tabla[[#This Row],[Versiones corregidas20]],2,99)),0), IFERROR(VALUE(MID(Tabla[[#This Row],[Versiones corregidas21]],2,99)),0),IFERROR(VALUE(MID(#REF!,2,99)),0)) -> V0.16 | AM67: =IFERROR(_xlfn.XLOOKUP(Tabla[[#This Row],[¿En qué versión fue corregido?]],Versiones!$A$2:$A$34,Versiones!$B$2:$B$34),"No encontrado") -> 0 | AN67: {=IFERROR(_xlfn.XLOOKUP(TRUE,COUNTIF(Tabla[[#This Row],[Etiquetas]:[Etiquetas17]],Categorías!$A$2:$A$12)>0,Categorías!$A$2:$A$12),"No encontrado")} -> Funcional | AO67: {=IFERROR(INDEX(Funcionalidades!$A$2:$A$80,MATCH(TRUE, COUNTIF(Reporte_Gral!R67:Z67,Funcionalidades!$A$2:$A$80)>0,0)),"No encontrado")} -> Registro-De-Gastos | AP67: =IF(AND(COUNTIF(Tabla[[#This Row],[Etiquetas]:[Etiquetas17]],"*UAT_V*")>0,COUNTIF(Tabla[[#This Row],[Etiquetas]:[Etiquetas17]],"*QA-Integración*")=0),"SI","") -> SI | AQ67: {=IF(Tabla[[#This Row],[Fue encontrado durante UAT?]]="SI",IFERROR(_xlfn.XLOOKUP(TRUE,ISNUMBER(SEARCH("UAT_V",Tabla[[#This Row],[Etiquetas]:[Etiquetas17]])),Tabla[[#This Row],[Etiquetas]:[Etiquetas17]]),""),"")} -> UAT_V0.14 | AR67: =IF(COUNTIF(Tabla[[#This Row],[Etiquetas]:[Etiquetas17]],"*Devuelto*")>0,"SI","") | AS67: =COUNTIF(Tabla[[#This Row],[Etiquetas]:[Etiquetas17]],"*Devuelto*") -> 0
A68: Error | B68: T20-3277 | C68: 118418 | D68: Algunos shortcuts no funcionan al instante, se necesita cambiar de Tablero para que ejecuten la actividad. | E68: Alta | F68: Tareas por hacer | R68: Atajos-Teclado-BOT | S68: Funcional | T68: Revisar_Diseño | U68: UAT | V68: UAT_V0.14 | AA68: Maria Pilar Albacete Occhi | AB68: 45999.519 | AG68: BOT | AJ68: {=IFERROR(_xlfn.XLOOKUP(TRUE,COUNTIF(Tabla[[#This Row],[Etiquetas]:[Etiquetas17]],Versiones!$G$2:$G$36)>0,Versiones!$B$2:$B$36), "")} -> 24 | AK68: {=IFERROR(_xlfn.XLOOKUP(TRUE,COUNTIF(Tabla[[#This Row],[Etiquetas]:[Etiquetas17]],Versiones!$G$2:$G$36)>0,Versiones!$A$2:$A$36), "")} -> V0.14 | AL68: ="V"&MAX(IFERROR(VALUE(MID(Tabla[[#This Row],[Versiones corregidas]],2,99)),0), IFERROR(VALUE(MID(Tabla[[#This Row],[Versiones corregidas19]],2,99)),0), IFERROR(VALUE(MID(Tabla[[#This Row],[Versiones corregidas20]],2,99)),0), IFERROR(VALUE(MID(Tabla[[#This Row],[Versiones corregidas21]],2,99)),0),IFERROR(VALUE(MID(#REF!,2,99)),0)) -> V0 | AM68: =IFERROR(_xlfn.XLOOKUP(Tabla[[#This Row],[¿En qué versión fue corregido?]],Versiones!$A$2:$A$34,Versiones!$B$2:$B$34),"No encontrado") -> No encontrado | AN68: {=IFERROR(_xlfn.XLOOKUP(TRUE,COUNTIF(Tabla[[#This Row],[Etiquetas]:[Etiquetas17]],Categorías!$A$2:$A$12)>0,Categorías!$A$2:$A$12),"No encontrado")} -> Funcional | AO68: {=IFERROR(INDEX(Funcionalidades!$A$2:$A$80,MATCH(TRUE, COUNTIF(Reporte_Gral!R68:Z68,Funcionalidades!$A$2:$A$80)>0,0)),"No encontrado")} -> Atajos-Teclado-BOT | AP68: =IF(AND(COUNTIF(Tabla[[#This Row],[Etiquetas]:[Etiquetas17]],"*UAT_V*")>0,COUNTIF(Tabla[[#This Row],[Etiquetas]:[Etiquetas17]],"*QA-Integración*")=0),"SI","") -> SI | AQ68: {=IF(Tabla[[#This Row],[Fue encontrado durante UAT?]]="SI",IFERROR(_xlfn.XLOOKUP(TRUE,ISNUMBER(SEARCH("UAT_V",Tabla[[#This Row],[Etiquetas]:[Etiquetas17]])),Tabla[[#This Row],[Etiquetas]:[Etiquetas17]]),""),"")} -> UAT_V0.14 | AR68: =IF(COUNTIF(Tabla[[#This Row],[Etiquetas]:[Etiquetas17]],"*Devuelto*")>0,"SI","") | AS68: =COUNTIF(Tabla[[#This Row],[Etiquetas]:[Etiquetas17]],"*Devuelto*") -> 0
A69: Error | B69: T20-3276 | C69: 118417 | D69: En pedido eficiente al seleccionar 20 o 50 articulos a mostrar por pagina se desctiva la opcion, ya no permite regresar. | E69: Alta | F69: READY FOR UAT | G69: T20 Sprint 25 2025 | H69: T20 Sprint 26 2025 | R69: Funcional | S69: Realizar-Pedido-Eficiente | T69: UAT | U69: UAT_V0.14 | AA69: Maria Pilar Albacete Occhi | AB69: 45999.518 | AC69: v0.14 | AG69: BOT | AJ69: {=IFERROR(_xlfn.XLOOKUP(TRUE,COUNTIF(Tabla[[#This Row],[Etiquetas]:[Etiquetas17]],Versiones!$G$2:$G$36)>0,Versiones!$B$2:$B$36), "")} -> 24 | AK69: {=IFERROR(_xlfn.XLOOKUP(TRUE,COUNTIF(Tabla[[#This Row],[Etiquetas]:[Etiquetas17]],Versiones!$G$2:$G$36)>0,Versiones!$A$2:$A$36), "")} -> V0.14 | AL69: ="V"&MAX(IFERROR(VALUE(MID(Tabla[[#This Row],[Versiones corregidas]],2,99)),0), IFERROR(VALUE(MID(Tabla[[#This Row],[Versiones corregidas19]],2,99)),0), IFERROR(VALUE(MID(Tabla[[#This Row],[Versiones corregidas20]],2,99)),0), IFERROR(VALUE(MID(Tabla[[#This Row],[Versiones corregidas21]],2,99)),0),IFERROR(VALUE(MID(#REF!,2,99)),0)) -> V0.14 | AM69: =IFERROR(_xlfn.XLOOKUP(Tabla[[#This Row],[¿En qué versión fue corregido?]],Versiones!$A$2:$A$34,Versiones!$B$2:$B$34),"No encontrado") -> 24 | AN69: {=IFERROR(_xlfn.XLOOKUP(TRUE,COUNTIF(Tabla[[#This Row],[Etiquetas]:[Etiquetas17]],Categorías!$A$2:$A$12)>0,Categorías!$A$2:$A$12),"No encontrado")} -> Funcional | AO69: {=IFERROR(INDEX(Funcionalidades!$A$2:$A$80,MATCH(TRUE, COUNTIF(Reporte_Gral!R69:Z69,Funcionalidades!$A$2:$A$80)>0,0)),"No encontrado")} -> Realizar-Pedido-Eficiente | AP69: =IF(AND(COUNTIF(Tabla[[#This Row],[Etiquetas]:[Etiquetas17]],"*UAT_V*")>0,COUNTIF(Tabla[[#This Row],[Etiquetas]:[Etiquetas17]],"*QA-Integración*")=0),"SI","") -> SI | AQ69: {=IF(Tabla[[#This Row],[Fue encontrado durante UAT?]]="SI",IFERROR(_xlfn.XLOOKUP(TRUE,ISNUMBER(SEARCH("UAT_V",Tabla[[#This Row],[Etiquetas]:[Etiquetas17]])),Tabla[[#This Row],[Etiquetas]:[Etiquetas17]]),""),"")} -> UAT_V0.14 | AR69: =IF(COUNTIF(Tabla[[#This Row],[Etiquetas]:[Etiquetas17]],"*Devuelto*")>0,"SI","") | AS69: =COUNTIF(Tabla[[#This Row],[Etiquetas]:[Etiquetas17]],"*Devuelto*") -> 0
A70: Error | B70: T20-3275 | C70: 118414 | D70: En una cancelación de producto de peso variable los gramos los cuentan como cantidad de productos y este se ve reflejado en el tablero de ventas. | E70: Alta | F70: Blocked | G70: T20 Sprint 25 2025 | H70: T20 Sprint 26 2025 | R70: Cobro-De-Productos-Peso-Variable | S70: Funcional | T70: Revisado | U70: T3B20_POS | V70: Tienda2.0 | W70: UAT | X70: UAT_V0.13 | AA70: Maria Pilar Albacete Occhi | AB70: 45999.517 | AC70: v0.16 | AG70: POS | AJ70: {=IFERROR(_xlfn.XLOOKUP(TRUE,COUNTIF(Tabla[[#This Row],[Etiquetas]:[Etiquetas17]],Versiones!$G$2:$G$36)>0,Versiones!$B$2:$B$36), "")} -> 23 | AK70: {=IFERROR(_xlfn.XLOOKUP(TRUE,COUNTIF(Tabla[[#This Row],[Etiquetas]:[Etiquetas17]],Versiones!$G$2:$G$36)>0,Versiones!$A$2:$A$36), "")} -> V0.13 | AL70: ="V"&MAX(IFERROR(VALUE(MID(Tabla[[#This Row],[Versiones corregidas]],2,99)),0), IFERROR(VALUE(MID(Tabla[[#This Row],[Versiones corregidas19]],2,99)),0), IFERROR(VALUE(MID(Tabla[[#This Row],[Versiones corregidas20]],2,99)),0), IFERROR(VALUE(MID(Tabla[[#This Row],[Versiones corregidas21]],2,99)),0),IFERROR(VALUE(MID(#REF!,2,99)),0)) -> V0.16 | AM70: =IFERROR(_xlfn.XLOOKUP(Tabla[[#This Row],[¿En qué versión fue corregido?]],Versiones!$A$2:$A$34,Versiones!$B$2:$B$34),"No encontrado") -> 0 | AN70: {=IFERROR(_xlfn.XLOOKUP(TRUE,COUNTIF(Tabla[[#This Row],[Etiquetas]:[Etiquetas17]],Categorías!$A$2:$A$12)>0,Categorías!$A$2:$A$12),"No encontrado")} -> Funcional | AO70: {=IFERROR(INDEX(Funcionalidades!$A$2:$A$80,MATCH(TRUE, COUNTIF(Reporte_Gral!R70:Z70,Funcionalidades!$A$2:$A$80)>0,0)),"No encontrado")} -> Cobro-De-Productos-Peso-Variable | AP70: =IF(AND(COUNTIF(Tabla[[#This Row],[Etiquetas]:[Etiquetas17]],"*UAT_V*")>0,COUNTIF(Tabla[[#This Row],[Etiquetas]:[Etiquetas17]],"*QA-Integración*")=0),"SI","") -> SI | AQ70: {=IF(Tabla[[#This Row],[Fue encontrado durante UAT?]]="SI",IFERROR(_xlfn.XLOOKUP(TRUE,ISNUMBER(SEARCH("UAT_V",Tabla[[#This Row],[Etiquetas]:[Etiquetas17]])),Tabla[[#This Row],[Etiquetas]:[Etiquetas17]]),""),"")} -> UAT_V0.13 | AR70: =IF(COUNTIF(Tabla[[#This Row],[Etiquetas]:[Etiquetas17]],"*Devuelto*")>0,"SI","") | AS70: =COUNTIF(Tabla[[#This Row],[Etiquetas]:[Etiquetas17]],"*Devuelto*") -> 0
A71: Error | B71: T20-3274 | C71: 118413 | D71: EL PANEL DE AJUSTE DE INVENTARIO NO SE ACTUALIZA DESPUES DE REALIZAR EL AJUSTE | E71: Más alta | F71: Tareas por hacer | G71: T20 Sprint 26 2025 | R71: Funcional | S71: Realizar-Inventario | T71: Revisado | U71: T3B20_BOT | V71: Tienda2.0 | W71: UAT | X71: UAT_V0.13 | AA71: Maria Pilar Albacete Occhi | AB71: 45999.516 | AC71: v0.16 | AG71: BOT | AJ71: {=IFERROR(_xlfn.XLOOKUP(TRUE,COUNTIF(Tabla[[#This Row],[Etiquetas]:[Etiquetas17]],Versiones!$G$2:$G$36)>0,Versiones!$B$2:$B$36), "")} -> 23 | AK71: {=IFERROR(_xlfn.XLOOKUP(TRUE,COUNTIF(Tabla[[#This Row],[Etiquetas]:[Etiquetas17]],Versiones!$G$2:$G$36)>0,Versiones!$A$2:$A$36), "")} -> V0.13 | AL71: ="V"&MAX(IFERROR(VALUE(MID(Tabla[[#This Row],[Versiones corregidas]],2,99)),0), IFERROR(VALUE(MID(Tabla[[#This Row],[Versiones corregidas19]],2,99)),0), IFERROR(VALUE(MID(Tabla[[#This Row],[Versiones corregidas20]],2,99)),0), IFERROR(VALUE(MID(Tabla[[#This Row],[Versiones corregidas21]],2,99)),0),IFERROR(VALUE(MID(#REF!,2,99)),0)) -> V0.16 | AM71: =IFERROR(_xlfn.XLOOKUP(Tabla[[#This Row],[¿En qué versión fue corregido?]],Versiones!$A$2:$A$34,Versiones!$B$2:$B$34),"No encontrado") -> 0 | AN71: {=IFERROR(_xlfn.XLOOKUP(TRUE,COUNTIF(Tabla[[#This Row],[Etiquetas]:[Etiquetas17]],Categorías!$A$2:$A$12)>0,Categorías!$A$2:$A$12),"No encontrado")} -> Funcional | AO71: {=IFERROR(INDEX(Funcionalidades!$A$2:$A$80,MATCH(TRUE, COUNTIF(Reporte_Gral!R71:Z71,Funcionalidades!$A$2:$A$80)>0,0)),"No encontrado")} -> Realizar-Inventario | AP71: =IF(AND(COUNTIF(Tabla[[#This Row],[Etiquetas]:[Etiquetas17]],"*UAT_V*")>0,COUNTIF(Tabla[[#This Row],[Etiquetas]:[Etiquetas17]],"*QA-Integración*")=0),"SI","") -> SI | AQ71: {=IF(Tabla[[#This Row],[Fue encontrado durante UAT?]]="SI",IFERROR(_xlfn.XLOOKUP(TRUE,ISNUMBER(SEARCH("UAT_V",Tabla[[#This Row],[Etiquetas]:[Etiquetas17]])),Tabla[[#This Row],[Etiquetas]:[Etiquetas17]]),""),"")} -> UAT_V0.13 | AR71: =IF(COUNTIF(Tabla[[#This Row],[Etiquetas]:[Etiquetas17]],"*Devuelto*")>0,"SI","") | AS71: =COUNTIF(Tabla[[#This Row],[Etiquetas]:[Etiquetas17]],"*Devuelto*") -> 0
A72: Error | B72: T20-3273 | C72: 118412 | D72: NO SE ACTUALIZAN LOS PRODUCTOS (Panel de productos) QUE SE ESTAN VENDIDO DURANTE EL PROCESO DE INVENTARIO. | E72: Más alta | F72: Tareas por hacer | G72: T20 Sprint 26 2025 | R72: Funcional | S72: Realizar-Inventario | T72: Revisado | U72: T3B20_BOT | V72: Tienda2.0 | W72: UAT | X72: UAT_V0.13 | AA72: Maria Pilar Albacete Occhi | AB72: 45999.515 | AC72: v0.16 | AG72: BOT | AJ72: {=IFERROR(_xlfn.XLOOKUP(TRUE,COUNTIF(Tabla[[#This Row],[Etiquetas]:[Etiquetas17]],Versiones!$G$2:$G$36)>0,Versiones!$B$2:$B$36), "")} -> 23 | AK72: {=IFERROR(_xlfn.XLOOKUP(TRUE,COUNTIF(Tabla[[#This Row],[Etiquetas]:[Etiquetas17]],Versiones!$G$2:$G$36)>0,Versiones!$A$2:$A$36), "")} -> V0.13 | AL72: ="V"&MAX(IFERROR(VALUE(MID(Tabla[[#This Row],[Versiones corregidas]],2,99)),0), IFERROR(VALUE(MID(Tabla[[#This Row],[Versiones corregidas19]],2,99)),0), IFERROR(VALUE(MID(Tabla[[#This Row],[Versiones corregidas20]],2,99)),0), IFERROR(VALUE(MID(Tabla[[#This Row],[Versiones corregidas21]],2,99)),0),IFERROR(VALUE(MID(#REF!,2,99)),0)) -> V0.16 | AM72: =IFERROR(_xlfn.XLOOKUP(Tabla[[#This Row],[¿En qué versión fue corregido?]],Versiones!$A$2:$A$34,Versiones!$B$2:$B$34),"No encontrado") -> 0 | AN72: {=IFERROR(_xlfn.XLOOKUP(TRUE,COUNTIF(Tabla[[#This Row],[Etiquetas]:[Etiquetas17]],Categorías!$A$2:$A$12)>0,Categorías!$A$2:$A$12),"No encontrado")} -> Funcional | AO72: {=IFERROR(INDEX(Funcionalidades!$A$2:$A$80,MATCH(TRUE, COUNTIF(Reporte_Gral!R72:Z72,Funcionalidades!$A$2:$A$80)>0,0)),"No encontrado")} -> Realizar-Inventario | AP72: =IF(AND(COUNTIF(Tabla[[#This Row],[Etiquetas]:[Etiquetas17]],"*UAT_V*")>0,COUNTIF(Tabla[[#This Row],[Etiquetas]:[Etiquetas17]],"*QA-Integración*")=0),"SI","") -> SI | AQ72: {=IF(Tabla[[#This Row],[Fue encontrado durante UAT?]]="SI",IFERROR(_xlfn.XLOOKUP(TRUE,ISNUMBER(SEARCH("UAT_V",Tabla[[#This Row],[Etiquetas]:[Etiquetas17]])),Tabla[[#This Row],[Etiquetas]:[Etiquetas17]]),""),"")} -> UAT_V0.13 | AR72: =IF(COUNTIF(Tabla[[#This Row],[Etiquetas]:[Etiquetas17]],"*Devuelto*")>0,"SI","") | AS72: =COUNTIF(Tabla[[#This Row],[Etiquetas]:[Etiquetas17]],"*Devuelto*") -> 0
A73: Error | B73: T20-3272 | C73: 118406 | D73: No se visualiza la opcion "adicionar ó reemplazar" despues de generar el primer conteo de inventario. | E73: Alta | F73: Tareas por hacer | R73: Funcional | S73: Pendiente_Desarrollo | T73: Realizar-Inventario | U73: Revisado | V73: T3B20_BOT | W73: Tienda2.0 | X73: UAT | Y73: UAT_V0.13 | AA73: Maria Pilar Albacete Occhi | AB73: 45999.515 | AG73: BOT | AJ73: {=IFERROR(_xlfn.XLOOKUP(TRUE,COUNTIF(Tabla[[#This Row],[Etiquetas]:[Etiquetas17]],Versiones!$G$2:$G$36)>0,Versiones!$B$2:$B$36), "")} -> 23 | AK73: {=IFERROR(_xlfn.XLOOKUP(TRUE,COUNTIF(Tabla[[#This Row],[Etiquetas]:[Etiquetas17]],Versiones!$G$2:$G$36)>0,Versiones!$A$2:$A$36), "")} -> V0.13 | AL73: ="V"&MAX(IFERROR(VALUE(MID(Tabla[[#This Row],[Versiones corregidas]],2,99)),0), IFERROR(VALUE(MID(Tabla[[#This Row],[Versiones corregidas19]],2,99)),0), IFERROR(VALUE(MID(Tabla[[#This Row],[Versiones corregidas20]],2,99)),0), IFERROR(VALUE(MID(Tabla[[#This Row],[Versiones corregidas21]],2,99)),0),IFERROR(VALUE(MID(#REF!,2,99)),0)) -> V0 | AM73: =IFERROR(_xlfn.XLOOKUP(Tabla[[#This Row],[¿En qué versión fue corregido?]],Versiones!$A$2:$A$34,Versiones!$B$2:$B$34),"No encontrado") -> No encontrado | AN73: {=IFERROR(_xlfn.XLOOKUP(TRUE,COUNTIF(Tabla[[#This Row],[Etiquetas]:[Etiquetas17]],Categorías!$A$2:$A$12)>0,Categorías!$A$2:$A$12),"No encontrado")} -> Funcional | AO73: {=IFERROR(INDEX(Funcionalidades!$A$2:$A$80,MATCH(TRUE, COUNTIF(Reporte_Gral!R73:Z73,Funcionalidades!$A$2:$A$80)>0,0)),"No encontrado")} -> Realizar-Inventario | AP73: =IF(AND(COUNTIF(Tabla[[#This Row],[Etiquetas]:[Etiquetas17]],"*UAT_V*")>0,COUNTIF(Tabla[[#This Row],[Etiquetas]:[Etiquetas17]],"*QA-Integración*")=0),"SI","") -> SI | AQ73: {=IF(Tabla[[#This Row],[Fue encontrado durante UAT?]]="SI",IFERROR(_xlfn.XLOOKUP(TRUE,ISNUMBER(SEARCH("UAT_V",Tabla[[#This Row],[Etiquetas]:[Etiquetas17]])),Tabla[[#This Row],[Etiquetas]:[Etiquetas17]]),""),"")} -> UAT_V0.13 | AR73: =IF(COUNTIF(Tabla[[#This Row],[Etiquetas]:[Etiquetas17]],"*Devuelto*")>0,"SI","") | AS73: =COUNTIF(Tabla[[#This Row],[Etiquetas]:[Etiquetas17]],"*Devuelto*") -> 0
A74: Error | B74: T20-3271 | C74: 118404 | D74: POS - La cantidad se visualiza doble al realizar cobro con CODI | E74: Alta | F74: READY FOR TESTING | G74: T20 Sprint 26 2025 | R74: Funcional | S74: T3B20_POS | T74: Tienda2.0 | U74: UAT | V74: UAT_V0.13 | AA74: Maria Pilar Albacete Occhi | AB74: 45999.513 | AC74: v0.16 | AG74: POS | AJ74: {=IFERROR(_xlfn.XLOOKUP(TRUE,COUNTIF(Tabla[[#This Row],[Etiquetas]:[Etiquetas17]],Versiones!$G$2:$G$36)>0,Versiones!$B$2:$B$36), "")} -> 23 | AK74: {=IFERROR(_xlfn.XLOOKUP(TRUE,COUNTIF(Tabla[[#This Row],[Etiquetas]:[Etiquetas17]],Versiones!$G$2:$G$36)>0,Versiones!$A$2:$A$36), "")} -> V0.13 | AL74: ="V"&MAX(IFERROR(VALUE(MID(Tabla[[#This Row],[Versiones corregidas]],2,99)),0), IFERROR(VALUE(MID(Tabla[[#This Row],[Versiones corregidas19]],2,99)),0), IFERROR(VALUE(MID(Tabla[[#This Row],[Versiones corregidas20]],2,99)),0), IFERROR(VALUE(MID(Tabla[[#This Row],[Versiones corregidas21]],2,99)),0),IFERROR(VALUE(MID(#REF!,2,99)),0)) -> V0.16 | AM74: =IFERROR(_xlfn.XLOOKUP(Tabla[[#This Row],[¿En qué versión fue corregido?]],Versiones!$A$2:$A$34,Versiones!$B$2:$B$34),"No encontrado") -> 0 | AN74: {=IFERROR(_xlfn.XLOOKUP(TRUE,COUNTIF(Tabla[[#This Row],[Etiquetas]:[Etiquetas17]],Categorías!$A$2:$A$12)>0,Categorías!$A$2:$A$12),"No encontrado")} -> Funcional | AO74: {=IFERROR(INDEX(Funcionalidades!$A$2:$A$80,MATCH(TRUE, COUNTIF(Reporte_Gral!R74:Z74,Funcionalidades!$A$2:$A$80)>0,0)),"No encontrado")} -> No encontrado | AP74: =IF(AND(COUNTIF(Tabla[[#This Row],[Etiquetas]:[Etiquetas17]],"*UAT_V*")>0,COUNTIF(Tabla[[#This Row],[Etiquetas]:[Etiquetas17]],"*QA-Integración*")=0),"SI","") -> SI | AQ74: {=IF(Tabla[[#This Row],[Fue encontrado durante UAT?]]="SI",IFERROR(_xlfn.XLOOKUP(TRUE,ISNUMBER(SEARCH("UAT_V",Tabla[[#This Row],[Etiquetas]:[Etiquetas17]])),Tabla[[#This Row],[Etiquetas]:[Etiquetas17]]),""),"")} -> UAT_V0.13 | AR74: =IF(COUNTIF(Tabla[[#This Row],[Etiquetas]:[Etiquetas17]],"*Devuelto*")>0,"SI","") | AS74: =COUNTIF(Tabla[[#This Row],[Etiquetas]:[Etiquetas17]],"*Devuelto*") -> 0
A75: Error | B75: T20-3270 | C75: 118392 | D75: POS - No se visualiza el usuario correcto en la pantalla de POS al iniciar y cerrar turno | E75: Alta | F75: READY FOR UAT | G75: T20 Sprint 25 2025 | H75: T20 Sprint 26 2025 | R75: Cierre-De-Turno | S75: Inicio-De-Turno | T75: Look&Feel | U75: QA-IntegraciónV0.14 | V75: T3B20_POS | W75: Tienda2.0 | AA75: Yubisleinys Mora Vega | AB75: 45999.5 | AC75: v0.15 | AG75: POS | AJ75: {=IFERROR(_xlfn.XLOOKUP(TRUE,COUNTIF(Tabla[[#This Row],[Etiquetas]:[Etiquetas17]],Versiones!$G$2:$G$36)>0,Versiones!$B$2:$B$36), "")} -> 24 | AK75: {=IFERROR(_xlfn.XLOOKUP(TRUE,COUNTIF(Tabla[[#This Row],[Etiquetas]:[Etiquetas17]],Versiones!$G$2:$G$36)>0,Versiones!$A$2:$A$36), "")} -> V0.14 | AL75: ="V"&MAX(IFERROR(VALUE(MID(Tabla[[#This Row],[Versiones corregidas]],2,99)),0), IFERROR(VALUE(MID(Tabla[[#This Row],[Versiones corregidas19]],2,99)),0), IFERROR(VALUE(MID(Tabla[[#This Row],[Versiones corregidas20]],2,99)),0), IFERROR(VALUE(MID(Tabla[[#This Row],[Versiones corregidas21]],2,99)),0),IFERROR(VALUE(MID(#REF!,2,99)),0)) -> V0.15 | AM75: =IFERROR(_xlfn.XLOOKUP(Tabla[[#This Row],[¿En qué versión fue corregido?]],Versiones!$A$2:$A$34,Versiones!$B$2:$B$34),"No encontrado") -> 25 | AN75: {=IFERROR(_xlfn.XLOOKUP(TRUE,COUNTIF(Tabla[[#This Row],[Etiquetas]:[Etiquetas17]],Categorías!$A$2:$A$12)>0,Categorías!$A$2:$A$12),"No encontrado")} -> Look&Feel | AO75: {=IFERROR(INDEX(Funcionalidades!$A$2:$A$80,MATCH(TRUE, COUNTIF(Reporte_Gral!R75:Z75,Funcionalidades!$A$2:$A$80)>0,0)),"No encontrado")} -> Inicio-De-Turno | AP75: =IF(AND(COUNTIF(Tabla[[#This Row],[Etiquetas]:[Etiquetas17]],"*UAT_V*")>0,COUNTIF(Tabla[[#This Row],[Etiquetas]:[Etiquetas17]],"*QA-Integración*")=0),"SI","") | AQ75: {=IF(Tabla[[#This Row],[Fue encontrado durante UAT?]]="SI",IFERROR(_xlfn.XLOOKUP(TRUE,ISNUMBER(SEARCH("UAT_V",Tabla[[#This Row],[Etiquetas]:[Etiquetas17]])),Tabla[[#This Row],[Etiquetas]:[Etiquetas17]]),""),"")} | AR75: =IF(COUNTIF(Tabla[[#This Row],[Etiquetas]:[Etiquetas17]],"*Devuelto*")>0,"SI","") | AS75: =COUNTIF(Tabla[[#This Row],[Etiquetas]:[Etiquetas17]],"*Devuelto*") -> 0
A76: Error | B76: T20-3269 | C76: 118377 | D76: POS: Corrección de filtro para generar el arqueo | E76: Alta | F76: READY FOR UAT | G76: T20 Sprint 25 2025 | H76: T20 Sprint 26 2025 | R76: Arqueo | S76: Bug_Devuelto_v0.15 | T76: Funcional | U76: T3B20_POS | V76: Tienda2.0 | W76: UAT_V0.14 | AA76: Ludo | AB76: 45999.481 | AC76: v0.15 | AG76: POS | AJ76: {=IFERROR(_xlfn.XLOOKUP(TRUE,COUNTIF(Tabla[[#This Row],[Etiquetas]:[Etiquetas17]],Versiones!$G$2:$G$36)>0,Versiones!$B$2:$B$36), "")} -> 24 | AK76: {=IFERROR(_xlfn.XLOOKUP(TRUE,COUNTIF(Tabla[[#This Row],[Etiquetas]:[Etiquetas17]],Versiones!$G$2:$G$36)>0,Versiones!$A$2:$A$36), "")} -> V0.14 | AL76: ="V"&MAX(IFERROR(VALUE(MID(Tabla[[#This Row],[Versiones corregidas]],2,99)),0), IFERROR(VALUE(MID(Tabla[[#This Row],[Versiones corregidas19]],2,99)),0), IFERROR(VALUE(MID(Tabla[[#This Row],[Versiones corregidas20]],2,99)),0), IFERROR(VALUE(MID(Tabla[[#This Row],[Versiones corregidas21]],2,99)),0),IFERROR(VALUE(MID(#REF!,2,99)),0)) -> V0.15 | AM76: =IFERROR(_xlfn.XLOOKUP(Tabla[[#This Row],[¿En qué versión fue corregido?]],Versiones!$A$2:$A$34,Versiones!$B$2:$B$34),"No encontrado") -> 25 | AN76: {=IFERROR(_xlfn.XLOOKUP(TRUE,COUNTIF(Tabla[[#This Row],[Etiquetas]:[Etiquetas17]],Categorías!$A$2:$A$12)>0,Categorías!$A$2:$A$12),"No encontrado")} -> Funcional | AO76: {=IFERROR(INDEX(Funcionalidades!$A$2:$A$80,MATCH(TRUE, COUNTIF(Reporte_Gral!R76:Z76,Funcionalidades!$A$2:$A$80)>0,0)),"No encontrado")} -> Arqueo | AP76: =IF(AND(COUNTIF(Tabla[[#This Row],[Etiquetas]:[Etiquetas17]],"*UAT_V*")>0,COUNTIF(Tabla[[#This Row],[Etiquetas]:[Etiquetas17]],"*QA-Integración*")=0),"SI","") -> SI | AQ76: {=IF(Tabla[[#This Row],[Fue encontrado durante UAT?]]="SI",IFERROR(_xlfn.XLOOKUP(TRUE,ISNUMBER(SEARCH("UAT_V",Tabla[[#This Row],[Etiquetas]:[Etiquetas17]])),Tabla[[#This Row],[Etiquetas]:[Etiquetas17]]),""),"")} -> UAT_V0.14 | AR76: =IF(COUNTIF(Tabla[[#This Row],[Etiquetas]:[Etiquetas17]],"*Devuelto*")>0,"SI","") -> SI | AS76: =COUNTIF(Tabla[[#This Row],[Etiquetas]:[Etiquetas17]],"*Devuelto*") -> 1
A77: Error | B77: T20-3268 | C77: 118373 | D77: BOT - En el evento BOT_START_STORY_DAY viene siempre como user: Maria Elena Vargas Lozano | E77: Alta | F77: READY FOR UAT | G77: T20 Sprint 25 2025 | H77: T20 Sprint 26 2025 | R77: Eventos_iOT | S77: Inicio-De-Día | T77: QA-IntegraciónV0.14 | U77: T3B20_BOT | V77: Tienda2.0 | AA77: Yubisleinys Mora Vega | AB77: 45999.473 | AC77: v0.15 | AG77: BOT | AJ77: {=IFERROR(_xlfn.XLOOKUP(TRUE,COUNTIF(Tabla[[#This Row],[Etiquetas]:[Etiquetas17]],Versiones!$G$2:$G$36)>0,Versiones!$B$2:$B$36), "")} -> 24 | AK77: {=IFERROR(_xlfn.XLOOKUP(TRUE,COUNTIF(Tabla[[#This Row],[Etiquetas]:[Etiquetas17]],Versiones!$G$2:$G$36)>0,Versiones!$A$2:$A$36), "")} -> V0.14 | AL77: ="V"&MAX(IFERROR(VALUE(MID(Tabla[[#This Row],[Versiones corregidas]],2,99)),0), IFERROR(VALUE(MID(Tabla[[#This Row],[Versiones corregidas19]],2,99)),0), IFERROR(VALUE(MID(Tabla[[#This Row],[Versiones corregidas20]],2,99)),0), IFERROR(VALUE(MID(Tabla[[#This Row],[Versiones corregidas21]],2,99)),0),IFERROR(VALUE(MID(#REF!,2,99)),0)) -> V0.15 | AM77: =IFERROR(_xlfn.XLOOKUP(Tabla[[#This Row],[¿En qué versión fue corregido?]],Versiones!$A$2:$A$34,Versiones!$B$2:$B$34),"No encontrado") -> 25 | AN77: {=IFERROR(_xlfn.XLOOKUP(TRUE,COUNTIF(Tabla[[#This Row],[Etiquetas]:[Etiquetas17]],Categorías!$A$2:$A$12)>0,Categorías!$A$2:$A$12),"No encontrado")} -> Eventos_iOT | AO77: {=IFERROR(INDEX(Funcionalidades!$A$2:$A$80,MATCH(TRUE, COUNTIF(Reporte_Gral!R77:Z77,Funcionalidades!$A$2:$A$80)>0,0)),"No encontrado")} -> Inicio-De-Día | AP77: =IF(AND(COUNTIF(Tabla[[#This Row],[Etiquetas]:[Etiquetas17]],"*UAT_V*")>0,COUNTIF(Tabla[[#This Row],[Etiquetas]:[Etiquetas17]],"*QA-Integración*")=0),"SI","") | AQ77: {=IF(Tabla[[#This Row],[Fue encontrado durante UAT?]]="SI",IFERROR(_xlfn.XLOOKUP(TRUE,ISNUMBER(SEARCH("UAT_V",Tabla[[#This Row],[Etiquetas]:[Etiquetas17]])),Tabla[[#This Row],[Etiquetas]:[Etiquetas17]]),""),"")} | AR77: =IF(COUNTIF(Tabla[[#This Row],[Etiquetas]:[Etiquetas17]],"*Devuelto*")>0,"SI","") | AS77: =COUNTIF(Tabla[[#This Row],[Etiquetas]:[Etiquetas17]],"*Devuelto*") -> 0
A78: Error | B78: T20-3254 | C78: 118259 | D78: BOT - Cambio de precio - No imprime correctamente | E78: Medio | F78: Tareas por hacer | G78: T20 Sprint 25 2025 | H78: T20 Sprint 26 2025 | R78: Imprimir-Cambios-De-Precio | S78: Look&Feel | T78: QA-IntegraciónV0.14 | U78: T3B20_BOT | V78: Tienda2.0 | AA78: Yubisleinys Mora Vega | AB78: 45999.354 | AC78: v0.15 | AG78: BOT | AJ78: {=IFERROR(_xlfn.XLOOKUP(TRUE,COUNTIF(Tabla[[#This Row],[Etiquetas]:[Etiquetas17]],Versiones!$G$2:$G$36)>0,Versiones!$B$2:$B$36), "")} -> 24 | AK78: {=IFERROR(_xlfn.XLOOKUP(TRUE,COUNTIF(Tabla[[#This Row],[Etiquetas]:[Etiquetas17]],Versiones!$G$2:$G$36)>0,Versiones!$A$2:$A$36), "")} -> V0.14 | AL78: ="V"&MAX(IFERROR(VALUE(MID(Tabla[[#This Row],[Versiones corregidas]],2,99)),0), IFERROR(VALUE(MID(Tabla[[#This Row],[Versiones corregidas19]],2,99)),0), IFERROR(VALUE(MID(Tabla[[#This Row],[Versiones corregidas20]],2,99)),0), IFERROR(VALUE(MID(Tabla[[#This Row],[Versiones corregidas21]],2,99)),0),IFERROR(VALUE(MID(#REF!,2,99)),0)) -> V0.15 | AM78: =IFERROR(_xlfn.XLOOKUP(Tabla[[#This Row],[¿En qué versión fue corregido?]],Versiones!$A$2:$A$34,Versiones!$B$2:$B$34),"No encontrado") -> 25 | AN78: {=IFERROR(_xlfn.XLOOKUP(TRUE,COUNTIF(Tabla[[#This Row],[Etiquetas]:[Etiquetas17]],Categorías!$A$2:$A$12)>0,Categorías!$A$2:$A$12),"No encontrado")} -> Look&Feel | AO78: {=IFERROR(INDEX(Funcionalidades!$A$2:$A$80,MATCH(TRUE, COUNTIF(Reporte_Gral!R78:Z78,Funcionalidades!$A$2:$A$80)>0,0)),"No encontrado")} -> Imprimir-Cambios-De-Precio | AP78: =IF(AND(COUNTIF(Tabla[[#This Row],[Etiquetas]:[Etiquetas17]],"*UAT_V*")>0,COUNTIF(Tabla[[#This Row],[Etiquetas]:[Etiquetas17]],"*QA-Integración*")=0),"SI","") | AQ78: {=IF(Tabla[[#This Row],[Fue encontrado durante UAT?]]="SI",IFERROR(_xlfn.XLOOKUP(TRUE,ISNUMBER(SEARCH("UAT_V",Tabla[[#This Row],[Etiquetas]:[Etiquetas17]])),Tabla[[#This Row],[Etiquetas]:[Etiquetas17]]),""),"")} | AR78: =IF(COUNTIF(Tabla[[#This Row],[Etiquetas]:[Etiquetas17]],"*Devuelto*")>0,"SI","") | AS78: =COUNTIF(Tabla[[#This Row],[Etiquetas]:[Etiquetas17]],"*Devuelto*") -> 0
A79: Error | B79: T20-3213 | C79: 118023 | D79: BOT - Cambio de precio - Modal de configuración de impresión: botón “Guardar” activo y diseño inconsistente | E79: Alta | F79: READY FOR UAT | G79: T20 Sprint 25 2025 | H79: T20 Sprint 26 2025 | R79: Funcional | S79: Imprimir-Cambios-De-Precio | T79: Look&Feel | U79: QA-IntegraciónV0.13 | V79: T3B20_BOT | W79: Tienda2.0 | AA79: Yubisleinys Mora Vega | AB79: 45996.678 | AC79: v0.15 | AG79: BOT | AH79: CANCELADO | AJ79: {=IFERROR(_xlfn.XLOOKUP(TRUE,COUNTIF(Tabla[[#This Row],[Etiquetas]:[Etiquetas17]],Versiones!$G$2:$G$36)>0,Versiones!$B$2:$B$36), "")} -> 23 | AK79: {=IFERROR(_xlfn.XLOOKUP(TRUE,COUNTIF(Tabla[[#This Row],[Etiquetas]:[Etiquetas17]],Versiones!$G$2:$G$36)>0,Versiones!$A$2:$A$36), "")} -> V0.13 | AL79: ="V"&MAX(IFERROR(VALUE(MID(Tabla[[#This Row],[Versiones corregidas]],2,99)),0), IFERROR(VALUE(MID(Tabla[[#This Row],[Versiones corregidas19]],2,99)),0), IFERROR(VALUE(MID(Tabla[[#This Row],[Versiones corregidas20]],2,99)),0), IFERROR(VALUE(MID(Tabla[[#This Row],[Versiones corregidas21]],2,99)),0),IFERROR(VALUE(MID(#REF!,2,99)),0)) -> V0.15 | AM79: =IFERROR(_xlfn.XLOOKUP(Tabla[[#This Row],[¿En qué versión fue corregido?]],Versiones!$A$2:$A$34,Versiones!$B$2:$B$34),"No encontrado") -> 25 | AN79: {=IFERROR(_xlfn.XLOOKUP(TRUE,COUNTIF(Tabla[[#This Row],[Etiquetas]:[Etiquetas17]],Categorías!$A$2:$A$12)>0,Categorías!$A$2:$A$12),"No encontrado")} -> Funcional | AO79: {=IFERROR(INDEX(Funcionalidades!$A$2:$A$80,MATCH(TRUE, COUNTIF(Reporte_Gral!R79:Z79,Funcionalidades!$A$2:$A$80)>0,0)),"No encontrado")} -> Imprimir-Cambios-De-Precio | AP79: =IF(AND(COUNTIF(Tabla[[#This Row],[Etiquetas]:[Etiquetas17]],"*UAT_V*")>0,COUNTIF(Tabla[[#This Row],[Etiquetas]:[Etiquetas17]],"*QA-Integración*")=0),"SI","") | AQ79: {=IF(Tabla[[#This Row],[Fue encontrado durante UAT?]]="SI",IFERROR(_xlfn.XLOOKUP(TRUE,ISNUMBER(SEARCH("UAT_V",Tabla[[#This Row],[Etiquetas]:[Etiquetas17]])),Tabla[[#This Row],[Etiquetas]:[Etiquetas17]]),""),"")} | AR79: =IF(COUNTIF(Tabla[[#This Row],[Etiquetas]:[Etiquetas17]],"*Devuelto*")>0,"SI","") | AS79: =COUNTIF(Tabla[[#This Row],[Etiquetas]:[Etiquetas17]],"*Devuelto*") -> 0
A80: Error | B80: T20-3212 | C80: 118013 | D80: BOT - Cambio de precio - Errores en impresión | E80: Medio | F80: Tareas por hacer | R80: Funcional | S80: Imprimir-Cambios-De-Precio | T80: Look&Feel | U80: QA-IntegraciónV0.13 | AA80: Yubisleinys Mora Vega | AB80: 45996.665 | AG80: BOT | AH80: CANCELADO | AJ80: {=IFERROR(_xlfn.XLOOKUP(TRUE,COUNTIF(Tabla[[#This Row],[Etiquetas]:[Etiquetas17]],Versiones!$G$2:$G$36)>0,Versiones!$B$2:$B$36), "")} -> 23 | AK80: {=IFERROR(_xlfn.XLOOKUP(TRUE,COUNTIF(Tabla[[#This Row],[Etiquetas]:[Etiquetas17]],Versiones!$G$2:$G$36)>0,Versiones!$A$2:$A$36), "")} -> V0.13 | AL80: ="V"&MAX(IFERROR(VALUE(MID(Tabla[[#This Row],[Versiones corregidas]],2,99)),0), IFERROR(VALUE(MID(Tabla[[#This Row],[Versiones corregidas19]],2,99)),0), IFERROR(VALUE(MID(Tabla[[#This Row],[Versiones corregidas20]],2,99)),0), IFERROR(VALUE(MID(Tabla[[#This Row],[Versiones corregidas21]],2,99)),0),IFERROR(VALUE(MID(#REF!,2,99)),0)) -> V0 | AM80: =IFERROR(_xlfn.XLOOKUP(Tabla[[#This Row],[¿En qué versión fue corregido?]],Versiones!$A$2:$A$34,Versiones!$B$2:$B$34),"No encontrado") -> No encontrado | AN80: {=IFERROR(_xlfn.XLOOKUP(TRUE,COUNTIF(Tabla[[#This Row],[Etiquetas]:[Etiquetas17]],Categorías!$A$2:$A$12)>0,Categorías!$A$2:$A$12),"No encontrado")} -> Funcional | AO80: {=IFERROR(INDEX(Funcionalidades!$A$2:$A$80,MATCH(TRUE, COUNTIF(Reporte_Gral!R80:Z80,Funcionalidades!$A$2:$A$80)>0,0)),"No encontrado")} -> Imprimir-Cambios-De-Precio | AP80: =IF(AND(COUNTIF(Tabla[[#This Row],[Etiquetas]:[Etiquetas17]],"*UAT_V*")>0,COUNTIF(Tabla[[#This Row],[Etiquetas]:[Etiquetas17]],"*QA-Integración*")=0),"SI","") | AQ80: {=IF(Tabla[[#This Row],[Fue encontrado durante UAT?]]="SI",IFERROR(_xlfn.XLOOKUP(TRUE,ISNUMBER(SEARCH("UAT_V",Tabla[[#This Row],[Etiquetas]:[Etiquetas17]])),Tabla[[#This Row],[Etiquetas]:[Etiquetas17]]),""),"")} | AR80: =IF(COUNTIF(Tabla[[#This Row],[Etiquetas]:[Etiquetas17]],"*Devuelto*")>0,"SI","") | AS80: =COUNTIF(Tabla[[#This Row],[Etiquetas]:[Etiquetas17]],"*Devuelto*") -> 0
A81: Error | B81: T20-3210 | C81: 118000 | D81: POS - Realizar arqueo - Inconsistencia en dato de vendedor en ticket impreso | E81: Baja | F81: Tareas por hacer | R81: Arqueo | S81: Look&Feel | T81: QA-IntegraciónV0.14 | AA81: Yubisleinys Mora Vega | AB81: 45996.631 | AG81: POS | AH81: CANCELADO | AJ81: {=IFERROR(_xlfn.XLOOKUP(TRUE,COUNTIF(Tabla[[#This Row],[Etiquetas]:[Etiquetas17]],Versiones!$G$2:$G$36)>0,Versiones!$B$2:$B$36), "")} -> 24 | AK81: {=IFERROR(_xlfn.XLOOKUP(TRUE,COUNTIF(Tabla[[#This Row],[Etiquetas]:[Etiquetas17]],Versiones!$G$2:$G$36)>0,Versiones!$A$2:$A$36), "")} -> V0.14 | AL81: ="V"&MAX(IFERROR(VALUE(MID(Tabla[[#This Row],[Versiones corregidas]],2,99)),0), IFERROR(VALUE(MID(Tabla[[#This Row],[Versiones corregidas19]],2,99)),0), IFERROR(VALUE(MID(Tabla[[#This Row],[Versiones corregidas20]],2,99)),0), IFERROR(VALUE(MID(Tabla[[#This Row],[Versiones corregidas21]],2,99)),0),IFERROR(VALUE(MID(#REF!,2,99)),0)) -> V0 | AM81: =IFERROR(_xlfn.XLOOKUP(Tabla[[#This Row],[¿En qué versión fue corregido?]],Versiones!$A$2:$A$34,Versiones!$B$2:$B$34),"No encontrado") -> No encontrado | AN81: {=IFERROR(_xlfn.XLOOKUP(TRUE,COUNTIF(Tabla[[#This Row],[Etiquetas]:[Etiquetas17]],Categorías!$A$2:$A$12)>0,Categorías!$A$2:$A$12),"No encontrado")} -> Look&Feel | AO81: {=IFERROR(INDEX(Funcionalidades!$A$2:$A$80,MATCH(TRUE, COUNTIF(Reporte_Gral!R81:Z81,Funcionalidades!$A$2:$A$80)>0,0)),"No encontrado")} -> Arqueo | AP81: =IF(AND(COUNTIF(Tabla[[#This Row],[Etiquetas]:[Etiquetas17]],"*UAT_V*")>0,COUNTIF(Tabla[[#This Row],[Etiquetas]:[Etiquetas17]],"*QA-Integración*")=0),"SI","") | AQ81: {=IF(Tabla[[#This Row],[Fue encontrado durante UAT?]]="SI",IFERROR(_xlfn.XLOOKUP(TRUE,ISNUMBER(SEARCH("UAT_V",Tabla[[#This Row],[Etiquetas]:[Etiquetas17]])),Tabla[[#This Row],[Etiquetas]:[Etiquetas17]]),""),"")} | AR81: =IF(COUNTIF(Tabla[[#This Row],[Etiquetas]:[Etiquetas17]],"*Devuelto*")>0,"SI","") | AS81: =COUNTIF(Tabla[[#This Row],[Etiquetas]:[Etiquetas17]],"*Devuelto*") -> 0
A82: Error | B82: T20-3179 | C82: 117507 | D82: BOT - Pie de camión - Botones incorrectos en modales | E82: Medio | F82: Tareas por hacer | R82: Funcional | S82: QA-IntegraciónV0.14 | T82: Recibir-Mercancía-Pie-de-Camión | U82: T3B20_BOT | V82: Tienda2.0 | AA82: Yubisleinys Mora Vega | AB82: 45995.509 | AG82: BOT | AH82: CANCELADO | AJ82: {=IFERROR(_xlfn.XLOOKUP(TRUE,COUNTIF(Tabla[[#This Row],[Etiquetas]:[Etiquetas17]],Versiones!$G$2:$G$36)>0,Versiones!$B$2:$B$36), "")} -> 24 | AK82: {=IFERROR(_xlfn.XLOOKUP(TRUE,COUNTIF(Tabla[[#This Row],[Etiquetas]:[Etiquetas17]],Versiones!$G$2:$G$36)>0,Versiones!$A$2:$A$36), "")} -> V0.14 | AL82: ="V"&MAX(IFERROR(VALUE(MID(Tabla[[#This Row],[Versiones corregidas]],2,99)),0), IFERROR(VALUE(MID(Tabla[[#This Row],[Versiones corregidas19]],2,99)),0), IFERROR(VALUE(MID(Tabla[[#This Row],[Versiones corregidas20]],2,99)),0), IFERROR(VALUE(MID(Tabla[[#This Row],[Versiones corregidas21]],2,99)),0),IFERROR(VALUE(MID(#REF!,2,99)),0)) -> V0 | AM82: =IFERROR(_xlfn.XLOOKUP(Tabla[[#This Row],[¿En qué versión fue corregido?]],Versiones!$A$2:$A$34,Versiones!$B$2:$B$34),"No encontrado") -> No encontrado | AN82: {=IFERROR(_xlfn.XLOOKUP(TRUE,COUNTIF(Tabla[[#This Row],[Etiquetas]:[Etiquetas17]],Categorías!$A$2:$A$12)>0,Categorías!$A$2:$A$12),"No encontrado")} -> Funcional | AO82: {=IFERROR(INDEX(Funcionalidades!$A$2:$A$80,MATCH(TRUE, COUNTIF(Reporte_Gral!R82:Z82,Funcionalidades!$A$2:$A$80)>0,0)),"No encontrado")} -> Recibir-Mercancía-Pie-De-Camión | AP82: =IF(AND(COUNTIF(Tabla[[#This Row],[Etiquetas]:[Etiquetas17]],"*UAT_V*")>0,COUNTIF(Tabla[[#This Row],[Etiquetas]:[Etiquetas17]],"*QA-Integración*")=0),"SI","") | AQ82: {=IF(Tabla[[#This Row],[Fue encontrado durante UAT?]]="SI",IFERROR(_xlfn.XLOOKUP(TRUE,ISNUMBER(SEARCH("UAT_V",Tabla[[#This Row],[Etiquetas]:[Etiquetas17]])),Tabla[[#This Row],[Etiquetas]:[Etiquetas17]]),""),"")} | AR82: =IF(COUNTIF(Tabla[[#This Row],[Etiquetas]:[Etiquetas17]],"*Devuelto*")>0,"SI","") | AS82: =COUNTIF(Tabla[[#This Row],[Etiquetas]:[Etiquetas17]],"*Devuelto*") -> 0
A83: Error | B83: T20-3177 | C83: 117430 | D83: BOT - Pie de camión - No muestra productos después de ingresar número de factura | E83: Alta | F83: Tareas por hacer | G83: T20 Sprint 25 2025 | H83: T20 Sprint 26 2025 | R83: Funcional | S83: QA-IntegraciónV0.14 | T83: Recibir-Mercancía-Pie-De-Camión | AA83: Yubisleinys Mora Vega | AB83: 45995.417 | AG83: BOT | AJ83: {=IFERROR(_xlfn.XLOOKUP(TRUE,COUNTIF(Tabla[[#This Row],[Etiquetas]:[Etiquetas17]],Versiones!$G$2:$G$36)>0,Versiones!$B$2:$B$36), "")} -> 24 | AK83: {=IFERROR(_xlfn.XLOOKUP(TRUE,COUNTIF(Tabla[[#This Row],[Etiquetas]:[Etiquetas17]],Versiones!$G$2:$G$36)>0,Versiones!$A$2:$A$36), "")} -> V0.14 | AL83: ="V"&MAX(IFERROR(VALUE(MID(Tabla[[#This Row],[Versiones corregidas]],2,99)),0), IFERROR(VALUE(MID(Tabla[[#This Row],[Versiones corregidas19]],2,99)),0), IFERROR(VALUE(MID(Tabla[[#This Row],[Versiones corregidas20]],2,99)),0), IFERROR(VALUE(MID(Tabla[[#This Row],[Versiones corregidas21]],2,99)),0),IFERROR(VALUE(MID(#REF!,2,99)),0)) -> V0 | AM83: =IFERROR(_xlfn.XLOOKUP(Tabla[[#This Row],[¿En qué versión fue corregido?]],Versiones!$A$2:$A$34,Versiones!$B$2:$B$34),"No encontrado") -> No encontrado | AN83: {=IFERROR(_xlfn.XLOOKUP(TRUE,COUNTIF(Tabla[[#This Row],[Etiquetas]:[Etiquetas17]],Categorías!$A$2:$A$12)>0,Categorías!$A$2:$A$12),"No encontrado")} -> Funcional | AO83: {=IFERROR(INDEX(Funcionalidades!$A$2:$A$80,MATCH(TRUE, COUNTIF(Reporte_Gral!R83:Z83,Funcionalidades!$A$2:$A$80)>0,0)),"No encontrado")} -> Recibir-Mercancía-Pie-De-Camión | AP83: =IF(AND(COUNTIF(Tabla[[#This Row],[Etiquetas]:[Etiquetas17]],"*UAT_V*")>0,COUNTIF(Tabla[[#This Row],[Etiquetas]:[Etiquetas17]],"*QA-Integración*")=0),"SI","") | AQ83: {=IF(Tabla[[#This Row],[Fue encontrado durante UAT?]]="SI",IFERROR(_xlfn.XLOOKUP(TRUE,ISNUMBER(SEARCH("UAT_V",Tabla[[#This Row],[Etiquetas]:[Etiquetas17]])),Tabla[[#This Row],[Etiquetas]:[Etiquetas17]]),""),"")} | AR83: =IF(COUNTIF(Tabla[[#This Row],[Etiquetas]:[Etiquetas17]],"*Devuelto*")>0,"SI","") | AS83: =COUNTIF(Tabla[[#This Row],[Etiquetas]:[Etiquetas17]],"*Devuelto*") -> 0
A84: Error | B84: T20-3173 | C84: 117165 | D84: BOT - Recibir mercancía - Alineación incorrecta de botones en el modal de selección de folio | E84: Medio | F84: Code Review | G84: T20 Sprint 26 2025 | R84: Look&Feel | S84: QA-IntegraciónV0.14 | T84: Recibir-Mercancía-Almacén-Tienda | U84: T3B20_BOT | V84: Tienda2.0 | AA84: Yubisleinys Mora Vega | AB84: 45994.69 | AC84: v0.16 | AG84: BOT | AJ84: {=IFERROR(_xlfn.XLOOKUP(TRUE,COUNTIF(Tabla[[#This Row],[Etiquetas]:[Etiquetas17]],Versiones!$G$2:$G$36)>0,Versiones!$B$2:$B$36), "")} -> 24 | AK84: {=IFERROR(_xlfn.XLOOKUP(TRUE,COUNTIF(Tabla[[#This Row],[Etiquetas]:[Etiquetas17]],Versiones!$G$2:$G$36)>0,Versiones!$A$2:$A$36), "")} -> V0.14 | AL84: ="V"&MAX(IFERROR(VALUE(MID(Tabla[[#This Row],[Versiones corregidas]],2,99)),0), IFERROR(VALUE(MID(Tabla[[#This Row],[Versiones corregidas19]],2,99)),0), IFERROR(VALUE(MID(Tabla[[#This Row],[Versiones corregidas20]],2,99)),0), IFERROR(VALUE(MID(Tabla[[#This Row],[Versiones corregidas21]],2,99)),0),IFERROR(VALUE(MID(#REF!,2,99)),0)) -> V0.16 | AM84: =IFERROR(_xlfn.XLOOKUP(Tabla[[#This Row],[¿En qué versión fue corregido?]],Versiones!$A$2:$A$34,Versiones!$B$2:$B$34),"No encontrado") -> 0 | AN84: {=IFERROR(_xlfn.XLOOKUP(TRUE,COUNTIF(Tabla[[#This Row],[Etiquetas]:[Etiquetas17]],Categorías!$A$2:$A$12)>0,Categorías!$A$2:$A$12),"No encontrado")} -> Look&Feel | AO84: {=IFERROR(INDEX(Funcionalidades!$A$2:$A$80,MATCH(TRUE, COUNTIF(Reporte_Gral!R84:Z84,Funcionalidades!$A$2:$A$80)>0,0)),"No encontrado")} -> Recibir-Mercancía-Almacén-Tienda | AP84: =IF(AND(COUNTIF(Tabla[[#This Row],[Etiquetas]:[Etiquetas17]],"*UAT_V*")>0,COUNTIF(Tabla[[#This Row],[Etiquetas]:[Etiquetas17]],"*QA-Integración*")=0),"SI","") | AQ84: {=IF(Tabla[[#This Row],[Fue encontrado durante UAT?]]="SI",IFERROR(_xlfn.XLOOKUP(TRUE,ISNUMBER(SEARCH("UAT_V",Tabla[[#This Row],[Etiquetas]:[Etiquetas17]])),Tabla[[#This Row],[Etiquetas]:[Etiquetas17]]),""),"")} | AR84: =IF(COUNTIF(Tabla[[#This Row],[Etiquetas]:[Etiquetas17]],"*Devuelto*")>0,"SI","") | AS84: =COUNTIF(Tabla[[#This Row],[Etiquetas]:[Etiquetas17]],"*Devuelto*") -> 0
A85: Error | B85: T20-3172 | C85: 117145 | D85: POS - Con turno cerrado - No se muestra F11 ni la opción "Salir/Cerrar sesión" | E85: Alta | F85: READY FOR UAT | G85: T20 Sprint 25 2025 | H85: T20 Sprint 26 2025 | R85: Cierre-De-Turno | S85: Grooming_S25 | T85: Look&Feel | U85: QA-IntegraciónV0.14 | V85: T3B20_POS | W85: Tienda2.0 | AA85: Daniela Soto | AB85: 45994.659 | AC85: v0.15 | AG85: POS | AJ85: {=IFERROR(_xlfn.XLOOKUP(TRUE,COUNTIF(Tabla[[#This Row],[Etiquetas]:[Etiquetas17]],Versiones!$G$2:$G$36)>0,Versiones!$B$2:$B$36), "")} -> 24 | AK85: {=IFERROR(_xlfn.XLOOKUP(TRUE,COUNTIF(Tabla[[#This Row],[Etiquetas]:[Etiquetas17]],Versiones!$G$2:$G$36)>0,Versiones!$A$2:$A$36), "")} -> V0.14 | AL85: ="V"&MAX(IFERROR(VALUE(MID(Tabla[[#This Row],[Versiones corregidas]],2,99)),0), IFERROR(VALUE(MID(Tabla[[#This Row],[Versiones corregidas19]],2,99)),0), IFERROR(VALUE(MID(Tabla[[#This Row],[Versiones corregidas20]],2,99)),0), IFERROR(VALUE(MID(Tabla[[#This Row],[Versiones corregidas21]],2,99)),0),IFERROR(VALUE(MID(#REF!,2,99)),0)) -> V0.15 | AM85: =IFERROR(_xlfn.XLOOKUP(Tabla[[#This Row],[¿En qué versión fue corregido?]],Versiones!$A$2:$A$34,Versiones!$B$2:$B$34),"No encontrado") -> 25 | AN85: {=IFERROR(_xlfn.XLOOKUP(TRUE,COUNTIF(Tabla[[#This Row],[Etiquetas]:[Etiquetas17]],Categorías!$A$2:$A$12)>0,Categorías!$A$2:$A$12),"No encontrado")} -> Look&Feel | AO85: {=IFERROR(INDEX(Funcionalidades!$A$2:$A$80,MATCH(TRUE, COUNTIF(Reporte_Gral!R85:Z85,Funcionalidades!$A$2:$A$80)>0,0)),"No encontrado")} -> Cierre-De-Turno | AP85: =IF(AND(COUNTIF(Tabla[[#This Row],[Etiquetas]:[Etiquetas17]],"*UAT_V*")>0,COUNTIF(Tabla[[#This Row],[Etiquetas]:[Etiquetas17]],"*QA-Integración*")=0),"SI","") | AQ85: {=IF(Tabla[[#This Row],[Fue encontrado durante UAT?]]="SI",IFERROR(_xlfn.XLOOKUP(TRUE,ISNUMBER(SEARCH("UAT_V",Tabla[[#This Row],[Etiquetas]:[Etiquetas17]])),Tabla[[#This Row],[Etiquetas]:[Etiquetas17]]),""),"")} | AR85: =IF(COUNTIF(Tabla[[#This Row],[Etiquetas]:[Etiquetas17]],"*Devuelto*")>0,"SI","") | AS85: =COUNTIF(Tabla[[#This Row],[Etiquetas]:[Etiquetas17]],"*Devuelto*") -> 0
A86: Error | B86: T20-3169 | C86: 117005 | D86: BOT - Registro de merma - No se muestra al intentar realizar un registro de merma el modal de Autenticación. | E86: Alta | F86: READY FOR UAT | G86: T20 Sprint 25 2025 | H86: T20 Sprint 26 2025 | R86: Funcional | S86: Grooming_S25 | T86: QA-IntegraciónV0.14 | U86: Registrar-Merma | V86: T3B20_BOT | W86: Tienda2.0 | AA86: Yubisleinys Mora Vega | AB86: 45994.39 | AC86: v0.15 | AG86: BOT | AH86: CANCELADO | AJ86: {=IFERROR(_xlfn.XLOOKUP(TRUE,COUNTIF(Tabla[[#This Row],[Etiquetas]:[Etiquetas17]],Versiones!$G$2:$G$36)>0,Versiones!$B$2:$B$36), "")} -> 24 | AK86: {=IFERROR(_xlfn.XLOOKUP(TRUE,COUNTIF(Tabla[[#This Row],[Etiquetas]:[Etiquetas17]],Versiones!$G$2:$G$36)>0,Versiones!$A$2:$A$36), "")} -> V0.14 | AL86: ="V"&MAX(IFERROR(VALUE(MID(Tabla[[#This Row],[Versiones corregidas]],2,99)),0), IFERROR(VALUE(MID(Tabla[[#This Row],[Versiones corregidas19]],2,99)),0), IFERROR(VALUE(MID(Tabla[[#This Row],[Versiones corregidas20]],2,99)),0), IFERROR(VALUE(MID(Tabla[[#This Row],[Versiones corregidas21]],2,99)),0),IFERROR(VALUE(MID(#REF!,2,99)),0)) -> V0.15 | AM86: =IFERROR(_xlfn.XLOOKUP(Tabla[[#This Row],[¿En qué versión fue corregido?]],Versiones!$A$2:$A$34,Versiones!$B$2:$B$34),"No encontrado") -> 25 | AN86: {=IFERROR(_xlfn.XLOOKUP(TRUE,COUNTIF(Tabla[[#This Row],[Etiquetas]:[Etiquetas17]],Categorías!$A$2:$A$12)>0,Categorías!$A$2:$A$12),"No encontrado")} -> Funcional | AO86: {=IFERROR(INDEX(Funcionalidades!$A$2:$A$80,MATCH(TRUE, COUNTIF(Reporte_Gral!R86:Z86,Funcionalidades!$A$2:$A$80)>0,0)),"No encontrado")} -> Registrar-Merma | AP86: =IF(AND(COUNTIF(Tabla[[#This Row],[Etiquetas]:[Etiquetas17]],"*UAT_V*")>0,COUNTIF(Tabla[[#This Row],[Etiquetas]:[Etiquetas17]],"*QA-Integración*")=0),"SI","") | AQ86: {=IF(Tabla[[#This Row],[Fue encontrado durante UAT?]]="SI",IFERROR(_xlfn.XLOOKUP(TRUE,ISNUMBER(SEARCH("UAT_V",Tabla[[#This Row],[Etiquetas]:[Etiquetas17]])),Tabla[[#This Row],[Etiquetas]:[Etiquetas17]]),""),"")} | AR86: =IF(COUNTIF(Tabla[[#This Row],[Etiquetas]:[Etiquetas17]],"*Devuelto*")>0,"SI","") | AS86: =COUNTIF(Tabla[[#This Row],[Etiquetas]:[Etiquetas17]],"*Devuelto*") -> 0
A87: Error | B87: T20-3165 | C87: 116774 | D87: BOT - Distribución incorrecta mostrada en Desglose al confirmar cierre de turno en BOT | E87: Alta | F87: Tareas por hacer | R87: Confirmar-Cierre-De-Turno | S87: Funcional | T87: Pendiente_Desarrollo | U87: QA-IntegraciónV0.14 | V87: Revisado | W87: T3B20_BOT | X87: Tienda2.0 | AA87: Yubisleinys Mora Vega | AB87: 45993.58 | AG87: BOT | AJ87: {=IFERROR(_xlfn.XLOOKUP(TRUE,COUNTIF(Tabla[[#This Row],[Etiquetas]:[Etiquetas17]],Versiones!$G$2:$G$36)>0,Versiones!$B$2:$B$36), "")} -> 24 | AK87: {=IFERROR(_xlfn.XLOOKUP(TRUE,COUNTIF(Tabla[[#This Row],[Etiquetas]:[Etiquetas17]],Versiones!$G$2:$G$36)>0,Versiones!$A$2:$A$36), "")} -> V0.14 | AL87: ="V"&MAX(IFERROR(VALUE(MID(Tabla[[#This Row],[Versiones corregidas]],2,99)),0), IFERROR(VALUE(MID(Tabla[[#This Row],[Versiones corregidas19]],2,99)),0), IFERROR(VALUE(MID(Tabla[[#This Row],[Versiones corregidas20]],2,99)),0), IFERROR(VALUE(MID(Tabla[[#This Row],[Versiones corregidas21]],2,99)),0),IFERROR(VALUE(MID(#REF!,2,99)),0)) -> V0 | AM87: =IFERROR(_xlfn.XLOOKUP(Tabla[[#This Row],[¿En qué versión fue corregido?]],Versiones!$A$2:$A$34,Versiones!$B$2:$B$34),"No encontrado") -> No encontrado | AN87: {=IFERROR(_xlfn.XLOOKUP(TRUE,COUNTIF(Tabla[[#This Row],[Etiquetas]:[Etiquetas17]],Categorías!$A$2:$A$12)>0,Categorías!$A$2:$A$12),"No encontrado")} -> Funcional | AO87: {=IFERROR(INDEX(Funcionalidades!$A$2:$A$80,MATCH(TRUE, COUNTIF(Reporte_Gral!R87:Z87,Funcionalidades!$A$2:$A$80)>0,0)),"No encontrado")} -> Confirmar-Cierre-De-Turno | AP87: =IF(AND(COUNTIF(Tabla[[#This Row],[Etiquetas]:[Etiquetas17]],"*UAT_V*")>0,COUNTIF(Tabla[[#This Row],[Etiquetas]:[Etiquetas17]],"*QA-Integración*")=0),"SI","") | AQ87: {=IF(Tabla[[#This Row],[Fue encontrado durante UAT?]]="SI",IFERROR(_xlfn.XLOOKUP(TRUE,ISNUMBER(SEARCH("UAT_V",Tabla[[#This Row],[Etiquetas]:[Etiquetas17]])),Tabla[[#This Row],[Etiquetas]:[Etiquetas17]]),""),"")} | AR87: =IF(COUNTIF(Tabla[[#This Row],[Etiquetas]:[Etiquetas17]],"*Devuelto*")>0,"SI","") | AS87: =COUNTIF(Tabla[[#This Row],[Etiquetas]:[Etiquetas17]],"*Devuelto*") -> 0
A88: Error | B88: T20-3163 | C88: 116587 | D88: BOT - Atajo teclado F9 - no abre modal Ubicación de familias | E88: Medio | F88: Cancelado | R88: Atajos-Teclado-BOT | S88: Funcional | T88: QA-IntegraciónV0.14 | AA88: Daniela Soto | AB88: 45993.365 | AG88: BOT | AH88: CANCELADO | AJ88: {=IFERROR(_xlfn.XLOOKUP(TRUE,COUNTIF(Tabla[[#This Row],[Etiquetas]:[Etiquetas17]],Versiones!$G$2:$G$36)>0,Versiones!$B$2:$B$36), "")} -> 24 | AK88: {=IFERROR(_xlfn.XLOOKUP(TRUE,COUNTIF(Tabla[[#This Row],[Etiquetas]:[Etiquetas17]],Versiones!$G$2:$G$36)>0,Versiones!$A$2:$A$36), "")} -> V0.14 | AL88: ="V"&MAX(IFERROR(VALUE(MID(Tabla[[#This Row],[Versiones corregidas]],2,99)),0), IFERROR(VALUE(MID(Tabla[[#This Row],[Versiones corregidas19]],2,99)),0), IFERROR(VALUE(MID(Tabla[[#This Row],[Versiones corregidas20]],2,99)),0), IFERROR(VALUE(MID(Tabla[[#This Row],[Versiones corregidas21]],2,99)),0),IFERROR(VALUE(MID(#REF!,2,99)),0)) -> V0 | AM88: =IFERROR(_xlfn.XLOOKUP(Tabla[[#This Row],[¿En qué versión fue corregido?]],Versiones!$A$2:$A$34,Versiones!$B$2:$B$34),"No encontrado") -> No encontrado | AN88: {=IFERROR(_xlfn.XLOOKUP(TRUE,COUNTIF(Tabla[[#This Row],[Etiquetas]:[Etiquetas17]],Categorías!$A$2:$A$12)>0,Categorías!$A$2:$A$12),"No encontrado")} -> Funcional | AO88: {=IFERROR(INDEX(Funcionalidades!$A$2:$A$80,MATCH(TRUE, COUNTIF(Reporte_Gral!R88:Z88,Funcionalidades!$A$2:$A$80)>0,0)),"No encontrado")} -> Atajos-Teclado-BOT | AP88: =IF(AND(COUNTIF(Tabla[[#This Row],[Etiquetas]:[Etiquetas17]],"*UAT_V*")>0,COUNTIF(Tabla[[#This Row],[Etiquetas]:[Etiquetas17]],"*QA-Integración*")=0),"SI","") | AQ88: {=IF(Tabla[[#This Row],[Fue encontrado durante UAT?]]="SI",IFERROR(_xlfn.XLOOKUP(TRUE,ISNUMBER(SEARCH("UAT_V",Tabla[[#This Row],[Etiquetas]:[Etiquetas17]])),Tabla[[#This Row],[Etiquetas]:[Etiquetas17]]),""),"")} | AR88: =IF(COUNTIF(Tabla[[#This Row],[Etiquetas]:[Etiquetas17]],"*Devuelto*")>0,"SI","") | AS88: =COUNTIF(Tabla[[#This Row],[Etiquetas]:[Etiquetas17]],"*Devuelto*") -> 0
A89: Error | B89: T20-3162 | C89: 116585 | D89: BOT - Atajo teclado F8 - no abre modal Consulta de folios | E89: Medio | F89: Cancelado | R89: Atajos-Teclado-BOT | S89: Funcional | T89: QA-IntegraciónV0.14 | AA89: Daniela Soto | AB89: 45993.365 | AG89: BOT | AJ89: {=IFERROR(_xlfn.XLOOKUP(TRUE,COUNTIF(Tabla[[#This Row],[Etiquetas]:[Etiquetas17]],Versiones!$G$2:$G$36)>0,Versiones!$B$2:$B$36), "")} -> 24 | AK89: {=IFERROR(_xlfn.XLOOKUP(TRUE,COUNTIF(Tabla[[#This Row],[Etiquetas]:[Etiquetas17]],Versiones!$G$2:$G$36)>0,Versiones!$A$2:$A$36), "")} -> V0.14 | AL89: ="V"&MAX(IFERROR(VALUE(MID(Tabla[[#This Row],[Versiones corregidas]],2,99)),0), IFERROR(VALUE(MID(Tabla[[#This Row],[Versiones corregidas19]],2,99)),0), IFERROR(VALUE(MID(Tabla[[#This Row],[Versiones corregidas20]],2,99)),0), IFERROR(VALUE(MID(Tabla[[#This Row],[Versiones corregidas21]],2,99)),0),IFERROR(VALUE(MID(#REF!,2,99)),0)) -> V0 | AM89: =IFERROR(_xlfn.XLOOKUP(Tabla[[#This Row],[¿En qué versión fue corregido?]],Versiones!$A$2:$A$34,Versiones!$B$2:$B$34),"No encontrado") -> No encontrado | AN89: {=IFERROR(_xlfn.XLOOKUP(TRUE,COUNTIF(Tabla[[#This Row],[Etiquetas]:[Etiquetas17]],Categorías!$A$2:$A$12)>0,Categorías!$A$2:$A$12),"No encontrado")} -> Funcional | AO89: {=IFERROR(INDEX(Funcionalidades!$A$2:$A$80,MATCH(TRUE, COUNTIF(Reporte_Gral!R89:Z89,Funcionalidades!$A$2:$A$80)>0,0)),"No encontrado")} -> Atajos-Teclado-BOT | AP89: =IF(AND(COUNTIF(Tabla[[#This Row],[Etiquetas]:[Etiquetas17]],"*UAT_V*")>0,COUNTIF(Tabla[[#This Row],[Etiquetas]:[Etiquetas17]],"*QA-Integración*")=0),"SI","") | AQ89: {=IF(Tabla[[#This Row],[Fue encontrado durante UAT?]]="SI",IFERROR(_xlfn.XLOOKUP(TRUE,ISNUMBER(SEARCH("UAT_V",Tabla[[#This Row],[Etiquetas]:[Etiquetas17]])),Tabla[[#This Row],[Etiquetas]:[Etiquetas17]]),""),"")} | AR89: =IF(COUNTIF(Tabla[[#This Row],[Etiquetas]:[Etiquetas17]],"*Devuelto*")>0,"SI","") | AS89: =COUNTIF(Tabla[[#This Row],[Etiquetas]:[Etiquetas17]],"*Devuelto*") -> 0
A90: Error | B90: T20-3161 | C90: 116584 | D90: BOT - Atajo teclado F7 - no abre modal Entrega de valores | E90: Medio | F90: Blocked | G90: T20 Sprint 26 2025 | R90: Atajos-Teclado-BOT | S90: Funcional | T90: QA-IntegraciónV0.14 | U90: Revisar_Diseño | V90: T3B20_BOT | W90: Tienda2.0 | AA90: Daniela Soto | AB90: 45993.364 | AC90: v0.16 | AG90: BOT | AJ90: {=IFERROR(_xlfn.XLOOKUP(TRUE,COUNTIF(Tabla[[#This Row],[Etiquetas]:[Etiquetas17]],Versiones!$G$2:$G$36)>0,Versiones!$B$2:$B$36), "")} -> 24 | AK90: {=IFERROR(_xlfn.XLOOKUP(TRUE,COUNTIF(Tabla[[#This Row],[Etiquetas]:[Etiquetas17]],Versiones!$G$2:$G$36)>0,Versiones!$A$2:$A$36), "")} -> V0.14 | AL90: ="V"&MAX(IFERROR(VALUE(MID(Tabla[[#This Row],[Versiones corregidas]],2,99)),0), IFERROR(VALUE(MID(Tabla[[#This Row],[Versiones corregidas19]],2,99)),0), IFERROR(VALUE(MID(Tabla[[#This Row],[Versiones corregidas20]],2,99)),0), IFERROR(VALUE(MID(Tabla[[#This Row],[Versiones corregidas21]],2,99)),0),IFERROR(VALUE(MID(#REF!,2,99)),0)) -> V0.16 | AM90: =IFERROR(_xlfn.XLOOKUP(Tabla[[#This Row],[¿En qué versión fue corregido?]],Versiones!$A$2:$A$34,Versiones!$B$2:$B$34),"No encontrado") -> 0 | AN90: {=IFERROR(_xlfn.XLOOKUP(TRUE,COUNTIF(Tabla[[#This Row],[Etiquetas]:[Etiquetas17]],Categorías!$A$2:$A$12)>0,Categorías!$A$2:$A$12),"No encontrado")} -> Funcional | AO90: {=IFERROR(INDEX(Funcionalidades!$A$2:$A$80,MATCH(TRUE, COUNTIF(Reporte_Gral!R90:Z90,Funcionalidades!$A$2:$A$80)>0,0)),"No encontrado")} -> Atajos-Teclado-BOT | AP90: =IF(AND(COUNTIF(Tabla[[#This Row],[Etiquetas]:[Etiquetas17]],"*UAT_V*")>0,COUNTIF(Tabla[[#This Row],[Etiquetas]:[Etiquetas17]],"*QA-Integración*")=0),"SI","") | AQ90: {=IF(Tabla[[#This Row],[Fue encontrado durante UAT?]]="SI",IFERROR(_xlfn.XLOOKUP(TRUE,ISNUMBER(SEARCH("UAT_V",Tabla[[#This Row],[Etiquetas]:[Etiquetas17]])),Tabla[[#This Row],[Etiquetas]:[Etiquetas17]]),""),"")} | AR90: =IF(COUNTIF(Tabla[[#This Row],[Etiquetas]:[Etiquetas17]],"*Devuelto*")>0,"SI","") | AS90: =COUNTIF(Tabla[[#This Row],[Etiquetas]:[Etiquetas17]],"*Devuelto*") -> 0
A91: Error | B91: T20-3160 | C91: 116583 | D91: BOT - Atajo teclado F6 - no abre modal Registrar gastos | E91: Medio | F91: READY FOR UAT | G91: T20 Sprint 25 2025 | H91: T20 Sprint 26 2025 | R91: Atajos-Teclado-BOT | S91: Funcional | T91: QA-IntegraciónV0.14 | U91: T3B20_BOT | V91: Tienda2.0 | AA91: Daniela Soto | AB91: 45993.363 | AC91: v0.15 | AG91: BOT | AJ91: {=IFERROR(_xlfn.XLOOKUP(TRUE,COUNTIF(Tabla[[#This Row],[Etiquetas]:[Etiquetas17]],Versiones!$G$2:$G$36)>0,Versiones!$B$2:$B$36), "")} -> 24 | AK91: {=IFERROR(_xlfn.XLOOKUP(TRUE,COUNTIF(Tabla[[#This Row],[Etiquetas]:[Etiquetas17]],Versiones!$G$2:$G$36)>0,Versiones!$A$2:$A$36), "")} -> V0.14 | AL91: ="V"&MAX(IFERROR(VALUE(MID(Tabla[[#This Row],[Versiones corregidas]],2,99)),0), IFERROR(VALUE(MID(Tabla[[#This Row],[Versiones corregidas19]],2,99)),0), IFERROR(VALUE(MID(Tabla[[#This Row],[Versiones corregidas20]],2,99)),0), IFERROR(VALUE(MID(Tabla[[#This Row],[Versiones corregidas21]],2,99)),0),IFERROR(VALUE(MID(#REF!,2,99)),0)) -> V0.15 | AM91: =IFERROR(_xlfn.XLOOKUP(Tabla[[#This Row],[¿En qué versión fue corregido?]],Versiones!$A$2:$A$34,Versiones!$B$2:$B$34),"No encontrado") -> 25 | AN91: {=IFERROR(_xlfn.XLOOKUP(TRUE,COUNTIF(Tabla[[#This Row],[Etiquetas]:[Etiquetas17]],Categorías!$A$2:$A$12)>0,Categorías!$A$2:$A$12),"No encontrado")} -> Funcional | AO91: {=IFERROR(INDEX(Funcionalidades!$A$2:$A$80,MATCH(TRUE, COUNTIF(Reporte_Gral!R91:Z91,Funcionalidades!$A$2:$A$80)>0,0)),"No encontrado")} -> Atajos-Teclado-BOT | AP91: =IF(AND(COUNTIF(Tabla[[#This Row],[Etiquetas]:[Etiquetas17]],"*UAT_V*")>0,COUNTIF(Tabla[[#This Row],[Etiquetas]:[Etiquetas17]],"*QA-Integración*")=0),"SI","") | AQ91: {=IF(Tabla[[#This Row],[Fue encontrado durante UAT?]]="SI",IFERROR(_xlfn.XLOOKUP(TRUE,ISNUMBER(SEARCH("UAT_V",Tabla[[#This Row],[Etiquetas]:[Etiquetas17]])),Tabla[[#This Row],[Etiquetas]:[Etiquetas17]]),""),"")} | AR91: =IF(COUNTIF(Tabla[[#This Row],[Etiquetas]:[Etiquetas17]],"*Devuelto*")>0,"SI","") | AS91: =COUNTIF(Tabla[[#This Row],[Etiquetas]:[Etiquetas17]],"*Devuelto*") -> 0
A92: Error | B92: T20-3159 | C92: 116567 | D92: BOT - Atajo teclado Ctrl + Alt + M no abre el Reproductor de música | E92: Medio | F92: Cancelado | R92: Atajos-Teclado-BOT | S92: Funcional | T92: QA-IntegraciónV0.14 | U92: T3B20_BOT | V92: Tienda2.0 | AA92: Yubisleinys Mora Vega | AB92: 45993.351 | AG92: BOT | AJ92: {=IFERROR(_xlfn.XLOOKUP(TRUE,COUNTIF(Tabla[[#This Row],[Etiquetas]:[Etiquetas17]],Versiones!$G$2:$G$36)>0,Versiones!$B$2:$B$36), "")} -> 24 | AK92: {=IFERROR(_xlfn.XLOOKUP(TRUE,COUNTIF(Tabla[[#This Row],[Etiquetas]:[Etiquetas17]],Versiones!$G$2:$G$36)>0,Versiones!$A$2:$A$36), "")} -> V0.14 | AL92: ="V"&MAX(IFERROR(VALUE(MID(Tabla[[#This Row],[Versiones corregidas]],2,99)),0), IFERROR(VALUE(MID(Tabla[[#This Row],[Versiones corregidas19]],2,99)),0), IFERROR(VALUE(MID(Tabla[[#This Row],[Versiones corregidas20]],2,99)),0), IFERROR(VALUE(MID(Tabla[[#This Row],[Versiones corregidas21]],2,99)),0),IFERROR(VALUE(MID(#REF!,2,99)),0)) -> V0 | AM92: =IFERROR(_xlfn.XLOOKUP(Tabla[[#This Row],[¿En qué versión fue corregido?]],Versiones!$A$2:$A$34,Versiones!$B$2:$B$34),"No encontrado") -> No encontrado | AN92: {=IFERROR(_xlfn.XLOOKUP(TRUE,COUNTIF(Tabla[[#This Row],[Etiquetas]:[Etiquetas17]],Categorías!$A$2:$A$12)>0,Categorías!$A$2:$A$12),"No encontrado")} -> Funcional | AO92: {=IFERROR(INDEX(Funcionalidades!$A$2:$A$80,MATCH(TRUE, COUNTIF(Reporte_Gral!R92:Z92,Funcionalidades!$A$2:$A$80)>0,0)),"No encontrado")} -> Atajos-Teclado-BOT | AP92: =IF(AND(COUNTIF(Tabla[[#This Row],[Etiquetas]:[Etiquetas17]],"*UAT_V*")>0,COUNTIF(Tabla[[#This Row],[Etiquetas]:[Etiquetas17]],"*QA-Integración*")=0),"SI","") | AQ92: {=IF(Tabla[[#This Row],[Fue encontrado durante UAT?]]="SI",IFERROR(_xlfn.XLOOKUP(TRUE,ISNUMBER(SEARCH("UAT_V",Tabla[[#This Row],[Etiquetas]:[Etiquetas17]])),Tabla[[#This Row],[Etiquetas]:[Etiquetas17]]),""),"")} | AR92: =IF(COUNTIF(Tabla[[#This Row],[Etiquetas]:[Etiquetas17]],"*Devuelto*")>0,"SI","") | AS92: =COUNTIF(Tabla[[#This Row],[Etiquetas]:[Etiquetas17]],"*Devuelto*") -> 0
A93: Error | B93: T20-3158 | C93: 116565 | D93: BOT - Atajo teclado Ctrl + M no abre el modal de Merma | E93: Medio | F93: TO BE DEPLOYED-SIT | G93: T20 Sprint 25 2025 | H93: T20 Sprint 26 2025 | R93: Atajos-Teclado-BOT | S93: Funcional | T93: QA-IntegraciónV0.14 | U93: T3B20_BOT | V93: Tienda2.0 | AA93: Yubisleinys Mora Vega | AB93: 45993.347 | AC93: v0.16 | AG93: BOT | AJ93: {=IFERROR(_xlfn.XLOOKUP(TRUE,COUNTIF(Tabla[[#This Row],[Etiquetas]:[Etiquetas17]],Versiones!$G$2:$G$36)>0,Versiones!$B$2:$B$36), "")} -> 24 | AK93: {=IFERROR(_xlfn.XLOOKUP(TRUE,COUNTIF(Tabla[[#This Row],[Etiquetas]:[Etiquetas17]],Versiones!$G$2:$G$36)>0,Versiones!$A$2:$A$36), "")} -> V0.14 | AL93: ="V"&MAX(IFERROR(VALUE(MID(Tabla[[#This Row],[Versiones corregidas]],2,99)),0), IFERROR(VALUE(MID(Tabla[[#This Row],[Versiones corregidas19]],2,99)),0), IFERROR(VALUE(MID(Tabla[[#This Row],[Versiones corregidas20]],2,99)),0), IFERROR(VALUE(MID(Tabla[[#This Row],[Versiones corregidas21]],2,99)),0),IFERROR(VALUE(MID(#REF!,2,99)),0)) -> V0.16 | AM93: =IFERROR(_xlfn.XLOOKUP(Tabla[[#This Row],[¿En qué versión fue corregido?]],Versiones!$A$2:$A$34,Versiones!$B$2:$B$34),"No encontrado") -> 0 | AN93: {=IFERROR(_xlfn.XLOOKUP(TRUE,COUNTIF(Tabla[[#This Row],[Etiquetas]:[Etiquetas17]],Categorías!$A$2:$A$12)>0,Categorías!$A$2:$A$12),"No encontrado")} -> Funcional | AO93: {=IFERROR(INDEX(Funcionalidades!$A$2:$A$80,MATCH(TRUE, COUNTIF(Reporte_Gral!R93:Z93,Funcionalidades!$A$2:$A$80)>0,0)),"No encontrado")} -> Atajos-Teclado-BOT | AP93: =IF(AND(COUNTIF(Tabla[[#This Row],[Etiquetas]:[Etiquetas17]],"*UAT_V*")>0,COUNTIF(Tabla[[#This Row],[Etiquetas]:[Etiquetas17]],"*QA-Integración*")=0),"SI","") | AQ93: {=IF(Tabla[[#This Row],[Fue encontrado durante UAT?]]="SI",IFERROR(_xlfn.XLOOKUP(TRUE,ISNUMBER(SEARCH("UAT_V",Tabla[[#This Row],[Etiquetas]:[Etiquetas17]])),Tabla[[#This Row],[Etiquetas]:[Etiquetas17]]),""),"")} | AR93: =IF(COUNTIF(Tabla[[#This Row],[Etiquetas]:[Etiquetas17]],"*Devuelto*")>0,"SI","") | AS93: =COUNTIF(Tabla[[#This Row],[Etiquetas]:[Etiquetas17]],"*Devuelto*") -> 0
