Workbook

Sheet Detalle1
A1: Detalles de BUGS X - Prioridad: Alta, ¿En que Sprint fue encontrado?: Sprint 21, Estado: Tareas por hacer
A3: Tipo de Incidencia | B3: Clave de incidencia | C3: ID de la incidencia | D3: Resumen | E3: Principal | F3: Clave principal | G3: Parent summary | H3: Prioridad | I3: Estado | J3: Sprint | K3: Sprint_1 | L3: Sprint_2 | M3: Sprint_3 | N3: Sprint_4 | O3: Sprint_5 | P3: Etiquetas | Q3: Etiquetas_5 | R3: Etiquetas_6 | S3: Etiquetas_7 | T3: Etiquetas_8 | U3: Etiquetas_9 | V3: Etiquetas_10 | W3: Informador | X3: Creada | Y3: Versiones corregidas | Z3: Versiones corregidas_13 | AA3: Versiones corregidas_14 | AB3: Módulo | AC3: Desarrollador | AD3: Desarrollador_Bug_Cancelado | AE3: ¿En que Sprint fue encontrado? | AF3: ¿En qué versión fue corregido? | AG3: ¿En que Sprint fue corregido? | AH3: Categoría
A4: Error | B4: T20-2093 | C4: 102674 | D4: BOT - Panel Productos no se actualiza | E4: 87100 | F4: T20-1091 | G4: 4.- QA | H4: Alta | I4: Tareas por hacer | J4: T20 Sprint 21 2025 | P4: Funcional | Q4: QA-IntegraciónV0.9 | W4: Daniela Soto | X4: 45947.628 | AB4: BOT | AC4: Juan Munoz | AE4: Sprint 21 | AF4: v0 | AG4: N/A | AH4: Funcional

Sheet Detalle2
A1: Detalles de BUGS X - ¿En que Sprint fue encontrado?: Sprint 21
A3: Tipo de Incidencia | B3: Clave de incidencia | C3: ID de la incidencia | D3: Resumen | E3: Principal | F3: Clave principal | G3: Parent summary | H3: Prioridad | I3: Estado | J3: Sprint | K3: Sprint_1 | L3: Sprint_2 | M3: Sprint_3 | N3: Sprint_4 | O3: Sprint_5 | P3: Etiquetas | Q3: Etiquetas_5 | R3: Etiquetas_6 | S3: Etiquetas_7 | T3: Etiquetas_8 | U3: Etiquetas_9 | V3: Etiquetas_10 | W3: Informador | X3: Creada | Y3: Versiones corregidas | Z3: Versiones corregidas_13 | AA3: Versiones corregidas_14 | AB3: Módulo | AC3: Desarrollador | AD3: Desarrollador_Bug_Cancelado | AE3: ¿En que Sprint fue encontrado? | AF3: ¿En qué versión fue corregido? | AG3: ¿En que Sprint fue corregido? | AH3: Categoría
A4: Error | B4: T20-2093 | C4: 102674 | D4: BOT - Panel Productos no se actualiza | E4: 87100 | F4: T20-1091 | G4: 4.- QA | H4: Alta | I4: Tareas por hacer | J4: T20 Sprint 21 2025 | P4: Funcional | Q4: QA-IntegraciónV0.9 | W4: Daniela Soto | X4: 45947.628 | AB4: BOT | AC4: Juan Munoz | AE4: Sprint 21 | AF4: v0 | AG4: N/A | AH4: Funcional
A5: Error | B5: T20-2066 | C5: 102295 | D5: BOT - Modal pie de camión en inglés | E5: 87100 | F5: T20-1091 | G5: 4.- QA | H5: Medio | I5: Tareas por hacer | P5: Look&Feel | Q5: QA-IntegraciónV0.9 | W5: Daniela Soto | X5: 45946.557 | AB5: BOT | AC5: Juan Munoz | AE5: Sprint 21 | AF5: v0 | AG5: N/A | AH5: Look&Feel
A6: Error | B6: T20-2088 | C6: 102584 | D6: POS - Checar precio - Info en Inglés | E6: 87100 | F6: T20-1091 | G6: 4.- QA | H6: Medio | I6: Tareas por hacer | P6: Look&Feel | Q6: QA-IntegraciónV0.9 | W6: Daniela Soto | X6: 45947.383 | AB6: POS | AC6: Andres Vergara | AE6: Sprint 21 | AF6: v0 | AG6: N/A | AH6: Look&Feel
A7: Error | B7: T20-2089 | C7: 102586 | D7: POS - Pantalla principal - Info en inglés | E7: 87100 | F7: T20-1091 | G7: 4.- QA | H7: Medio | I7: Tareas por hacer | P7: Look&Feel | Q7: QA-IntegraciónV0.9 | W7: Daniela Soto | X7: 45947.399 | AB7: POS | AC7: Juan Munoz | AE7: Sprint 21 | AF7: v0 | AG7: N/A | AH7: Look&Feel
A8: Error | B8: T20-2094 | C8: 102710 | D8: Diferencias en tickets de venta - TC/Efectivo y Pago Mix | E8: 87100 | F8: T20-1091 | G8: 4.- QA | H8: Medio | I8: Tareas por hacer | J8: T20 Sprint 21 2025 | P8: Contenido/Datos | Q8: QA-IntegraciónV0.9 | W8: Carolina Rodríguez Soriano | X8: 45947.709 | AC8: Juan Munoz | AE8: Sprint 21 | AF8: v0 | AG8: N/A | AH8: Contenido/Datos

Sheet Tendencia
M1: Incidentes Totales X Estatus X Sprint
B3: Sprint | C3: Casos de Prueba Ejecutados | D3: Casos de prueba Pendientes | E3: Bugs Encontrados | F3: % Casos de Prueba Fallidos | G3: BUGS Cancelados | H3: Bugs Solucionados | I3: BUGS Pendientes por Resolver | J3: % Bugs Pendientes por resolver | M3: BUGS X | N3: ESTADO
B4: Sprint 16 | C4: 135 | E4: ='BUGS X SPRINT'!K7 -> 46 | F4: =+E4/C4 -> 0.34074074 | G4: =GETPIVOTDATA("Estado",$M$3,"Estado","Cancelado","¿En que Sprint fue encontrado?","Sprint 16") -> 7 | H4: 25 | I4: 14 | J4: =I4/E4 -> 0.30434783 | M4: SPRINT | N4: Cancelado | O4: Tareas por hacer | P4: Code Review | Q4: IN SIT | R4: READY FOR TESTING | S4: READY FOR UAT | T4: Blocked | U4: En curso | V4: TO BE DEPLOYED-SIT | W4: Total
B5: Sprint 17 | C5: 139 | E5: ='BUGS X SPRINT'!K8 -> 19 | F5: =+E5/C5 -> 0.13669065 | G5: =GETPIVOTDATA("Estado",$M$3,"Estado","Cancelado","¿En que Sprint fue encontrado?","Sprint 17") -> 2 | H5: 13 | I5: 4 | J5: =I5/E5 -> 0.21052632 | M5: Sprint 16 | N5: 7 | O5: 9 | P5: 3 | Q5: 1 | S5: 25 | T5: 1 | W5: 46
B6: Sprint 18 | C6: 105 | E6: ='BUGS X SPRINT'!K9 -> 28 | F6: =+E6/C6 -> 0.26666667 | G6: =GETPIVOTDATA("Estado",$M$3,"Estado","Cancelado","¿En que Sprint fue encontrado?","Sprint 18") -> 1 | H6: 12 | I6: 15 | J6: =I6/E6 -> 0.53571429 | M6: Sprint 17 | N6: 2 | O6: 4 | S6: 13 | W6: 19
B7: Sprint 19 | C7: 142 | E7: ='BUGS X SPRINT'!K10 -> 21 | F7: =+E7/C7 -> 0.14788732 | G7: =GETPIVOTDATA("Estado",$M$3,"Estado","Cancelado","¿En que Sprint fue encontrado?","Sprint 19") -> 2 | H7: 2 | I7: 17 | J7: =I7/E7 -> 0.80952381 | M7: Sprint 18 | N7: 1 | O7: 13 | P7: 1 | S7: 12 | T7: 1 | W7: 28
B8: Sprint 20 | C8: 136 | D8: * | E8: ='BUGS X SPRINT'!K11 -> 19 | F8: =+E8/C8 -> 0.13970588 | G8: =GETPIVOTDATA("Estado",$M$3,"Estado","Cancelado","¿En que Sprint fue encontrado?","Sprint 20") -> 4 | H8: 0 | I8: 15 | J8: =I8/E8 -> 0.78947368 | M8: Sprint 19 | N8: 2 | O8: 12 | R8: 1 | S8: 2 | V8: 4 | W8: 21
A9: En curso | B9: Sprint 21 | C9: 35 | E9: ='BUGS X SPRINT'!K12 -> 5 | F9: =+E9/C9 -> 0.14285714 | G9: 0 | H9: 0 | I9: 5 | J9: =I9/E9 -> 1 | M9: Sprint 20 | N9: 4 | O9: 11 | P9: 1 | T9: 1 | U9: 1 | V9: 1 | W9: 19
B10: Total | C10: =SUM(C4:C9) -> 692 | E10: =SUM(E4:E9) -> 138 | F10: =E10/C10 -> 0.19942197 | G10: =SUM(G4:G9) -> 16 | H10: =SUM(H4:H9) -> 52 | I10: =SUM(I4:I9) -> 70 | J10: =I10/E10 -> 0.50724638 | M10: Sprint 21 | O10: 5 | W10: 5
M11: Total | N11: 16 | O11: 54 | P11: 5 | Q11: 1 | R11: 1 | S11: 52 | T11: 3 | U11: 1 | V11: 5 | W11: 138

Sheet Reporte_Gral
A1: Tipo de Incidencia | B1: Clave de incidencia | C1: ID de la incidencia | D1: Resumen | E1: Principal | F1: Clave principal | G1: Parent summary | H1: Prioridad | I1: Estado | J1: Sprint | K1: Sprint_1 | L1: Sprint_2 | M1: Sprint_3 | N1: Sprint_4 | O1: Sprint_5 | P1: Etiquetas | Q1: Etiquetas_5 | R1: Etiquetas_6 | S1: Etiquetas_7 | T1: Etiquetas_8 | U1: Etiquetas_9 | V1: Etiquetas_10 | W1: Informador | X1: Creada | Y1: Versiones corregidas | Z1: Versiones corregidas_13 | AA1: Versiones corregidas_14 | AB1: Módulo | AC1: Desarrollador | AD1: Desarrollador_Bug_Cancelado | AE1: ¿En que Sprint fue encontrado? | AF1: ¿En qué versión fue corregido? | AG1: ¿En que Sprint fue corregido? | AH1: Categoría
A2: Error | B2: T20-958 | C2: 83062 | D2: BOT - Se valida el usuario con Entra ID | E2: 87100 | F2: T20-1091 | G2: 4.- QA | H2: Medio | I2: READY FOR UAT | J2: Backlog BUGS | P2: doc_ludo | Q2: Funcional | R2: QA-SmokeV0.4 | S2: T3B20_BOT | T2: T3B20_POS | U2: Tested_In_DEV | V2: Tienda2.0 | W2: Ludo | X2: 45873.228 | Y2: v0.5 | AB2: =IF(LEFT(Jira__32[[#This Row],[Resumen]],3)="POS","POS",IF(LEFT(Jira__32[[#This Row],[Resumen]],3)="BOT","BOT","")) -> BOT | AC2: Andres Vergara | AE2: {=_xlfn.IFS(OR(COUNTIF(P2:V2,Versiones!$G$9)>0, COUNTIF(P2:V2,Versiones!$H$8)>0), "Sprint 21",OR(COUNTIF(P2:V2,Versiones!$G$8)>0, COUNTIF(P2:V2,Versiones!$H$8)>0, COUNTIF(P2:V2,Versiones!$I$8)>0), "Sprint 20",OR(COUNTIF(P2:V2,Versiones!$G$7)>0, COUNTIF(P2:V2,Versiones!$H$7)>0, COUNTIF(P2:V2,Versiones!$I$7)>0), "Sprint 19",OR(COUNTIF(P2:V2,Versiones!$G$6)>0, COUNTIF(P2:V2,Versiones!$H$6)>0, COUNTIF(P2:V2,Versiones!$I$6)>0), "Sprint 18",OR(COUNTIF(P2:V2,Versiones!$G$4)>0, COUNTIF(P2:V2,Versiones!$H$4)>0, COUNTIF(P2:V2,Versiones!$G$5)>0, COUNTIF(P2:V2,Versiones!$H$5)>0), "Sprint 17",OR(COUNTIF(P2:V2,Versiones!$G$2)>0, COUNTIF(P2:V2,Versiones!$H$2)>0, COUNTIF(P2:V2,Versiones!$G$3)>0, COUNTIF(P2:V2,Versiones!$H$3)>0), "Sprint 16", OR(COUNTIF(P2:V2,Versiones!$G$2)>0, COUNTIF(P2:V2,Versiones!$H$2)>0, COUNTIF(P2:V2,Versiones!$G$3)>0, COUNTIF(P2:V2,Versiones!$H$3)>0), "Sprint 16",TRUE, "")} -> Sprint 16 | AF2: ="v"&MAX( IFERROR(VALUE(MID(Jira__32[[#This Row],[Versiones corregidas]],2,99)),0), IFERROR(VALUE(MID(Jira__32[[#This Row],[Versiones corregidas_13]],2,99)),0), IFERROR(VALUE(MID(Jira__32[[#This Row],[Versiones corregidas_14]],2,99)),0) ) -> v0.5 | AG2: {=_xlfn.IFS(Jira__32[[#This Row],[¿En qué versión fue corregido?]]="v0","N/A",Jira__32[[#This Row],[¿En qué versión fue corregido?]]="v0.4","Sprint 16", Jira__32[[#This Row],[¿En qué versión fue corregido?]]="v0.5","Sprint 17", Jira__32[[#This Row],[¿En qué versión fue corregido?]]="v0.6","Sprint 18", Jira__32[[#This Row],[¿En qué versión fue corregido?]]="v0.7","Sprint 19", Jira__32[[#This Row],[¿En qué versión fue corregido?]]="v0.8","Sprint 20",Jira__32[[#This Row],[¿En qué versión fue corregido?]]="v0.9","Sprint 21", TRUE,"Desconocido")} -> Sprint 17 | AH2: {=_xlfn.IFS(COUNTIF(P2:V2, Versiones!$A$13)>0, "Funcional", COUNTIF(P2:V2, Versiones!$A$14)>0, "Configuración", COUNTIF(P2:V2, Versiones!$A$15)>0, "Look&Feel", COUNTIF(P2:V2, Versiones!$A$16)>0, "Integración", COUNTIF(P2:V2, Versiones!$A$17)>0, "Contenido/Datos", COUNTIF(P2:V2, Versiones!$A$18)>0, "Eventos_Cosmos", COUNTIF(P2:V2, Versiones!$A$19)>0, "Eventos_iOT", COUNTIF(P2:V2, Versiones!$A$20)>0, "Eventos_Fabric", TRUE, "No encontrado")} -> Funcional
A3: Error | B3: T20-957 | C3: 83060 | D3: POS - Inicio de turno: corregir pantallas de monto de fondeo inicial | E3: 87100 | F3: T20-1091 | G3: 4.- QA | H3: Medio | I3: READY FOR UAT | J3: T20 Sprint 19 2025 | K3: Backlog BUGS | P3: doc_ludo | Q3: Look&Feel | R3: QA-SmokeV0.4 | S3: T3B20_POS | T3: Tienda2.0 | W3: Ludo | X3: 45873.219 | Y3: v0.7 | AB3: =IF(LEFT(Jira__32[[#This Row],[Resumen]],3)="POS","POS",IF(LEFT(Jira__32[[#This Row],[Resumen]],3)="BOT","BOT","")) -> POS | AC3: Ludovic Hern | AE3: {=_xlfn.IFS(OR(COUNTIF(P3:V3,Versiones!$G$9)>0, COUNTIF(P3:V3,Versiones!$H$8)>0), "Sprint 21",OR(COUNTIF(P3:V3,Versiones!$G$8)>0, COUNTIF(P3:V3,Versiones!$H$8)>0, COUNTIF(P3:V3,Versiones!$I$8)>0), "Sprint 20",OR(COUNTIF(P3:V3,Versiones!$G$7)>0, COUNTIF(P3:V3,Versiones!$H$7)>0, COUNTIF(P3:V3,Versiones!$I$7)>0), "Sprint 19",OR(COUNTIF(P3:V3,Versiones!$G$6)>0, COUNTIF(P3:V3,Versiones!$H$6)>0, COUNTIF(P3:V3,Versiones!$I$6)>0), "Sprint 18",OR(COUNTIF(P3:V3,Versiones!$G$4)>0, COUNTIF(P3:V3,Versiones!$H$4)>0, COUNTIF(P3:V3,Versiones!$G$5)>0, COUNTIF(P3:V3,Versiones!$H$5)>0), "Sprint 17",OR(COUNTIF(P3:V3,Versiones!$G$2)>0, COUNTIF(P3:V3,Versiones!$H$2)>0, COUNTIF(P3:V3,Versiones!$G$3)>0, COUNTIF(P3:V3,Versiones!$H$3)>0), "Sprint 16", OR(COUNTIF(P3:V3,Versiones!$G$2)>0, COUNTIF(P3:V3,Versiones!$H$2)>0, COUNTIF(P3:V3,Versiones!$G$3)>0, COUNTIF(P3:V3,Versiones!$H$3)>0), "Sprint 16",TRUE, "")} -> Sprint 16 | AF3: ="v"&MAX( IFERROR(VALUE(MID(Jira__32[[#This Row],[Versiones corregidas]],2,99)),0), IFERROR(VALUE(MID(Jira__32[[#This Row],[Versiones corregidas_13]],2,99)),0), IFERROR(VALUE(MID(Jira__32[[#This Row],[Versiones corregidas_14]],2,99)),0) ) -> v0.7 | AG3: {=_xlfn.IFS(Jira__32[[#This Row],[¿En qué versión fue corregido?]]="v0","N/A",Jira__32[[#This Row],[¿En qué versión fue corregido?]]="v0.4","Sprint 16", Jira__32[[#This Row],[¿En qué versión fue corregido?]]="v0.5","Sprint 17", Jira__32[[#This Row],[¿En qué versión fue corregido?]]="v0.6","Sprint 18", Jira__32[[#This Row],[¿En qué versión fue corregido?]]="v0.7","Sprint 19", Jira__32[[#This Row],[¿En qué versión fue corregido?]]="v0.8","Sprint 20",Jira__32[[#This Row],[¿En qué versión fue corregido?]]="v0.9","Sprint 21", TRUE,"Desconocido")} -> Sprint 19 | AH3: {=_xlfn.IFS(COUNTIF(P3:V3, Versiones!$A$13)>0, "Funcional", COUNTIF(P3:V3, Versiones!$A$14)>0, "Configuración", COUNTIF(P3:V3, Versiones!$A$15)>0, "Look&Feel", COUNTIF(P3:V3, Versiones!$A$16)>0, "Integración", COUNTIF(P3:V3, Versiones!$A$17)>0, "Contenido/Datos", COUNTIF(P3:V3, Versiones!$A$18)>0, "Eventos_Cosmos", COUNTIF(P3:V3, Versiones!$A$19)>0, "Eventos_iOT", COUNTIF(P3:V3, Versiones!$A$20)>0, "Eventos_Fabric", TRUE, "No encontrado")} -> Look&Feel
A4: Error | B4: T20-956 | C4: 83058 | D4: POS - Cierre de turno: permite ingresar monto para último alivio | E4: 87100 | F4: T20-1091 | G4: 4.- QA | H4: Medio | I4: Code Review | J4: Backlog BUGS | P4: doc_ludo | Q4: Funcional | R4: QA-SmokeV0.4 | S4: T3B20_POS | T4: Tienda2.0 | W4: Ludo | X4: 45873.197 | AB4: =IF(LEFT(Jira__32[[#This Row],[Resumen]],3)="POS","POS",IF(LEFT(Jira__32[[#This Row],[Resumen]],3)="BOT","BOT","")) -> POS | AC4: Ludovic Hern | AE4: {=_xlfn.IFS(OR(COUNTIF(P4:V4,Versiones!$G$9)>0, COUNTIF(P4:V4,Versiones!$H$8)>0), "Sprint 21",OR(COUNTIF(P4:V4,Versiones!$G$8)>0, COUNTIF(P4:V4,Versiones!$H$8)>0, COUNTIF(P4:V4,Versiones!$I$8)>0), "Sprint 20",OR(COUNTIF(P4:V4,Versiones!$G$7)>0, COUNTIF(P4:V4,Versiones!$H$7)>0, COUNTIF(P4:V4,Versiones!$I$7)>0), "Sprint 19",OR(COUNTIF(P4:V4,Versiones!$G$6)>0, COUNTIF(P4:V4,Versiones!$H$6)>0, COUNTIF(P4:V4,Versiones!$I$6)>0), "Sprint 18",OR(COUNTIF(P4:V4,Versiones!$G$4)>0, COUNTIF(P4:V4,Versiones!$H$4)>0, COUNTIF(P4:V4,Versiones!$G$5)>0, COUNTIF(P4:V4,Versiones!$H$5)>0), "Sprint 17",OR(COUNTIF(P4:V4,Versiones!$G$2)>0, COUNTIF(P4:V4,Versiones!$H$2)>0, COUNTIF(P4:V4,Versiones!$G$3)>0, COUNTIF(P4:V4,Versiones!$H$3)>0), "Sprint 16", OR(COUNTIF(P4:V4,Versiones!$G$2)>0, COUNTIF(P4:V4,Versiones!$H$2)>0, COUNTIF(P4:V4,Versiones!$G$3)>0, COUNTIF(P4:V4,Versiones!$H$3)>0), "Sprint 16",TRUE, "")} -> Sprint 16 | AF4: ="v"&MAX( IFERROR(VALUE(MID(Jira__32[[#This Row],[Versiones corregidas]],2,99)),0), IFERROR(VALUE(MID(Jira__32[[#This Row],[Versiones corregidas_13]],2,99)),0), IFERROR(VALUE(MID(Jira__32[[#This Row],[Versiones corregidas_14]],2,99)),0) ) -> v0 | AG4: {=_xlfn.IFS(Jira__32[[#This Row],[¿En qué versión fue corregido?]]="v0","N/A",Jira__32[[#This Row],[¿En qué versión fue corregido?]]="v0.4","Sprint 16", Jira__32[[#This Row],[¿En qué versión fue corregido?]]="v0.5","Sprint 17", Jira__32[[#This Row],[¿En qué versión fue corregido?]]="v0.6","Sprint 18", Jira__32[[#This Row],[¿En qué versión fue corregido?]]="v0.7","Sprint 19", Jira__32[[#This Row],[¿En qué versión fue corregido?]]="v0.8","Sprint 20",Jira__32[[#This Row],[¿En qué versión fue corregido?]]="v0.9","Sprint 21", TRUE,"Desconocido")} -> N/A | AH4: {=_xlfn.IFS(COUNTIF(P4:V4, Versiones!$A$13)>0, "Funcional", COUNTIF(P4:V4, Versiones!$A$14)>0, "Configuración", COUNTIF(P4:V4, Versiones!$A$15)>0, "Look&Feel", COUNTIF(P4:V4, Versiones!$A$16)>0, "Integración", COUNTIF(P4:V4, Versiones!$A$17)>0, "Contenido/Datos", COUNTIF(P4:V4, Versiones!$A$18)>0, "Eventos_Cosmos", COUNTIF(P4:V4, Versiones!$A$19)>0, "Eventos_iOT", COUNTIF(P4:V4, Versiones!$A$20)>0, "Eventos_Fabric", TRUE, "No encontrado")} -> Funcional
A5: Error | B5: T20-955 | C5: 83056 | D5: POS - Cierre de turno: autenticación del encargado de turno | E5: 87100 | F5: T20-1091 | G5: 4.- QA | H5: Medio | I5: Code Review | J5: Backlog BUGS | P5: doc_ludo | Q5: Funcional | R5: QA-SmokeV0.4 | S5: T3B20_POS | T5: Tienda2.0 | W5: Ludo | X5: 45873.194 | AB5: =IF(LEFT(Jira__32[[#This Row],[Resumen]],3)="POS","POS",IF(LEFT(Jira__32[[#This Row],[Resumen]],3)="BOT","BOT","")) -> POS | AC5: Ludovic Hern | AE5: {=_xlfn.IFS(OR(COUNTIF(P5:V5,Versiones!$G$9)>0, COUNTIF(P5:V5,Versiones!$H$8)>0), "Sprint 21",OR(COUNTIF(P5:V5,Versiones!$G$8)>0, COUNTIF(P5:V5,Versiones!$H$8)>0, COUNTIF(P5:V5,Versiones!$I$8)>0), "Sprint 20",OR(COUNTIF(P5:V5,Versiones!$G$7)>0, COUNTIF(P5:V5,Versiones!$H$7)>0, COUNTIF(P5:V5,Versiones!$I$7)>0), "Sprint 19",OR(COUNTIF(P5:V5,Versiones!$G$6)>0, COUNTIF(P5:V5,Versiones!$H$6)>0, COUNTIF(P5:V5,Versiones!$I$6)>0), "Sprint 18",OR(COUNTIF(P5:V5,Versiones!$G$4)>0, COUNTIF(P5:V5,Versiones!$H$4)>0, COUNTIF(P5:V5,Versiones!$G$5)>0, COUNTIF(P5:V5,Versiones!$H$5)>0), "Sprint 17",OR(COUNTIF(P5:V5,Versiones!$G$2)>0, COUNTIF(P5:V5,Versiones!$H$2)>0, COUNTIF(P5:V5,Versiones!$G$3)>0, COUNTIF(P5:V5,Versiones!$H$3)>0), "Sprint 16", OR(COUNTIF(P5:V5,Versiones!$G$2)>0, COUNTIF(P5:V5,Versiones!$H$2)>0, COUNTIF(P5:V5,Versiones!$G$3)>0, COUNTIF(P5:V5,Versiones!$H$3)>0), "Sprint 16",TRUE, "")} -> Sprint 16 | AF5: ="v"&MAX( IFERROR(VALUE(MID(Jira__32[[#This Row],[Versiones corregidas]],2,99)),0), IFERROR(VALUE(MID(Jira__32[[#This Row],[Versiones corregidas_13]],2,99)),0), IFERROR(VALUE(MID(Jira__32[[#This Row],[Versiones corregidas_14]],2,99)),0) ) -> v0 | AG5: {=_xlfn.IFS(Jira__32[[#This Row],[¿En qué versión fue corregido?]]="v0","N/A",Jira__32[[#This Row],[¿En qué versión fue corregido?]]="v0.4","Sprint 16", Jira__32[[#This Row],[¿En qué versión fue corregido?]]="v0.5","Sprint 17", Jira__32[[#This Row],[¿En qué versión fue corregido?]]="v0.6","Sprint 18", Jira__32[[#This Row],[¿En qué versión fue corregido?]]="v0.7","Sprint 19", Jira__32[[#This Row],[¿En qué versión fue corregido?]]="v0.8","Sprint 20",Jira__32[[#This Row],[¿En qué versión fue corregido?]]="v0.9","Sprint 21", TRUE,"Desconocido")} -> N/A | AH5: {=_xlfn.IFS(COUNTIF(P5:V5, Versiones!$A$13)>0, "Funcional", COUNTIF(P5:V5, Versiones!$A$14)>0, "Configuración", COUNTIF(P5:V5, Versiones!$A$15)>0, "Look&Feel", COUNTIF(P5:V5, Versiones!$A$16)>0, "Integración", COUNTIF(P5:V5, Versiones!$A$17)>0, "Contenido/Datos", COUNTIF(P5:V5, Versiones!$A$18)>0, "Eventos_Cosmos", COUNTIF(P5:V5, Versiones!$A$19)>0, "Eventos_iOT", COUNTIF(P5:V5, Versiones!$A$20)>0, "Eventos_Fabric", TRUE, "No encontrado")} -> Funcional
A6: Error | B6: T20-954 | C6: 83054 | D6: BOT - Modal de confirmación de cierre de día no aparece | E6: 87100 | F6: T20-1091 | G6: 4.- QA | H6: Alta | I6: Blocked | J6: T20 Sprint 17 2025 | K6: T20 Sprint 18 2025 | L6: T20 Sprint 21 2025 | P6: doc_ludo | Q6: Look&Feel | R6: QA | S6: QA-SmokeV0.4 | T6: T3B20_BOT | U6: Tienda2.0 | W6: Maria Pilar Albacete Occhi | X6: 45873.172 | Y6: v0.5 | Z6: v0.6 | AA6: v0.7 | AB6: =IF(LEFT(Jira__32[[#This Row],[Resumen]],3)="POS","POS",IF(LEFT(Jira__32[[#This Row],[Resumen]],3)="BOT","BOT","")) -> BOT | AC6: Ludovic Hern | AE6: {=_xlfn.IFS(OR(COUNTIF(P6:V6,Versiones!$G$9)>0, COUNTIF(P6:V6,Versiones!$H$8)>0), "Sprint 21",OR(COUNTIF(P6:V6,Versiones!$G$8)>0, COUNTIF(P6:V6,Versiones!$H$8)>0, COUNTIF(P6:V6,Versiones!$I$8)>0), "Sprint 20",OR(COUNTIF(P6:V6,Versiones!$G$7)>0, COUNTIF(P6:V6,Versiones!$H$7)>0, COUNTIF(P6:V6,Versiones!$I$7)>0), "Sprint 19",OR(COUNTIF(P6:V6,Versiones!$G$6)>0, COUNTIF(P6:V6,Versiones!$H$6)>0, COUNTIF(P6:V6,Versiones!$I$6)>0), "Sprint 18",OR(COUNTIF(P6:V6,Versiones!$G$4)>0, COUNTIF(P6:V6,Versiones!$H$4)>0, COUNTIF(P6:V6,Versiones!$G$5)>0, COUNTIF(P6:V6,Versiones!$H$5)>0), "Sprint 17",OR(COUNTIF(P6:V6,Versiones!$G$2)>0, COUNTIF(P6:V6,Versiones!$H$2)>0, COUNTIF(P6:V6,Versiones!$G$3)>0, COUNTIF(P6:V6,Versiones!$H$3)>0), "Sprint 16", OR(COUNTIF(P6:V6,Versiones!$G$2)>0, COUNTIF(P6:V6,Versiones!$H$2)>0, COUNTIF(P6:V6,Versiones!$G$3)>0, COUNTIF(P6:V6,Versiones!$H$3)>0), "Sprint 16",TRUE, "")} -> Sprint 16 | AF6: ="v"&MAX( IFERROR(VALUE(MID(Jira__32[[#This Row],[Versiones corregidas]],2,99)),0), IFERROR(VALUE(MID(Jira__32[[#This Row],[Versiones corregidas_13]],2,99)),0), IFERROR(VALUE(MID(Jira__32[[#This Row],[Versiones corregidas_14]],2,99)),0) ) -> v0.7 | AG6: {=_xlfn.IFS(Jira__32[[#This Row],[¿En qué versión fue corregido?]]="v0","N/A",Jira__32[[#This Row],[¿En qué versión fue corregido?]]="v0.4","Sprint 16", Jira__32[[#This Row],[¿En qué versión fue corregido?]]="v0.5","Sprint 17", Jira__32[[#This Row],[¿En qué versión fue corregido?]]="v0.6","Sprint 18", Jira__32[[#This Row],[¿En qué versión fue corregido?]]="v0.7","Sprint 19", Jira__32[[#This Row],[¿En qué versión fue corregido?]]="v0.8","Sprint 20",Jira__32[[#This Row],[¿En qué versión fue corregido?]]="v0.9","Sprint 21", TRUE,"Desconocido")} -> Sprint 19 | AH6: {=_xlfn.IFS(COUNTIF(P6:V6, Versiones!$A$13)>0, "Funcional", COUNTIF(P6:V6, Versiones!$A$14)>0, "Configuración", COUNTIF(P6:V6, Versiones!$A$15)>0, "Look&Feel", COUNTIF(P6:V6, Versiones!$A$16)>0, "Integración", COUNTIF(P6:V6, Versiones!$A$17)>0, "Contenido/Datos", COUNTIF(P6:V6, Versiones!$A$18)>0, "Eventos_Cosmos", COUNTIF(P6:V6, Versiones!$A$19)>0, "Eventos_iOT", COUNTIF(P6:V6, Versiones!$A$20)>0, "Eventos_Fabric", TRUE, "No encontrado")} -> Look&Feel
A7: Error | B7: T20-953 | C7: 83052 | D7: BOT - Inicio+Cierre de día: correcciones en el flujo | E7: 79941 | F7: T20-623 | G7: 3.-Desarrollo POS/BOT /CDM | H7: Medio | I7: Tareas por hacer | J7: T20 Sprint 16 2025 | K7: T20 Sprint 17 2025 | L7: T20 Sprint 18 2025 | M7: Backlog BUGS | P7: Funcional | Q7: QA | R7: QA-SmokeV0.4 | S7: T3B20_BOT | T7: Tienda2.0 | W7: Ludo | X7: 45873.169 | Y7: v0.6 | Z7: v0.7 | AB7: =IF(LEFT(Jira__32[[#This Row],[Resumen]],3)="POS","POS",IF(LEFT(Jira__32[[#This Row],[Resumen]],3)="BOT","BOT","")) -> BOT | AC7: Ludovic Hern | AE7: {=_xlfn.IFS(OR(COUNTIF(P7:V7,Versiones!$G$9)>0, COUNTIF(P7:V7,Versiones!$H$8)>0), "Sprint 21",OR(COUNTIF(P7:V7,Versiones!$G$8)>0, COUNTIF(P7:V7,Versiones!$H$8)>0, COUNTIF(P7:V7,Versiones!$I$8)>0), "Sprint 20",OR(COUNTIF(P7:V7,Versiones!$G$7)>0, COUNTIF(P7:V7,Versiones!$H$7)>0, COUNTIF(P7:V7,Versiones!$I$7)>0), "Sprint 19",OR(COUNTIF(P7:V7,Versiones!$G$6)>0, COUNTIF(P7:V7,Versiones!$H$6)>0, COUNTIF(P7:V7,Versiones!$I$6)>0), "Sprint 18",OR(COUNTIF(P7:V7,Versiones!$G$4)>0, COUNTIF(P7:V7,Versiones!$H$4)>0, COUNTIF(P7:V7,Versiones!$G$5)>0, COUNTIF(P7:V7,Versiones!$H$5)>0), "Sprint 17",OR(COUNTIF(P7:V7,Versiones!$G$2)>0, COUNTIF(P7:V7,Versiones!$H$2)>0, COUNTIF(P7:V7,Versiones!$G$3)>0, COUNTIF(P7:V7,Versiones!$H$3)>0), "Sprint 16", OR(COUNTIF(P7:V7,Versiones!$G$2)>0, COUNTIF(P7:V7,Versiones!$H$2)>0, COUNTIF(P7:V7,Versiones!$G$3)>0, COUNTIF(P7:V7,Versiones!$H$3)>0), "Sprint 16",TRUE, "")} -> Sprint 16 | AF7: ="v"&MAX( IFERROR(VALUE(MID(Jira__32[[#This Row],[Versiones corregidas]],2,99)),0), IFERROR(VALUE(MID(Jira__32[[#This Row],[Versiones corregidas_13]],2,99)),0), IFERROR(VALUE(MID(Jira__32[[#This Row],[Versiones corregidas_14]],2,99)),0) ) -> v0.7 | AG7: {=_xlfn.IFS(Jira__32[[#This Row],[¿En qué versión fue corregido?]]="v0","N/A",Jira__32[[#This Row],[¿En qué versión fue corregido?]]="v0.4","Sprint 16", Jira__32[[#This Row],[¿En qué versión fue corregido?]]="v0.5","Sprint 17", Jira__32[[#This Row],[¿En qué versión fue corregido?]]="v0.6","Sprint 18", Jira__32[[#This Row],[¿En qué versión fue corregido?]]="v0.7","Sprint 19", Jira__32[[#This Row],[¿En qué versión fue corregido?]]="v0.8","Sprint 20",Jira__32[[#This Row],[¿En qué versión fue corregido?]]="v0.9","Sprint 21", TRUE,"Desconocido")} -> Sprint 19 | AH7: {=_xlfn.IFS(COUNTIF(P7:V7, Versiones!$A$13)>0, "Funcional", COUNTIF(P7:V7, Versiones!$A$14)>0, "Configuración", COUNTIF(P7:V7, Versiones!$A$15)>0, "Look&Feel", COUNTIF(P7:V7, Versiones!$A$16)>0, "Integración", COUNTIF(P7:V7, Versiones!$A$17)>0, "Contenido/Datos", COUNTIF(P7:V7, Versiones!$A$18)>0, "Eventos_Cosmos", COUNTIF(P7:V7, Versiones!$A$19)>0, "Eventos_iOT", COUNTIF(P7:V7, Versiones!$A$20)>0, "Eventos_Fabric", TRUE, "No encontrado")} -> Funcional
A8: Error | B8: T20-951 | C8: 83049 | D8: POS - Generar evento de devolución (= ticket) (blocked) | E8: 87100 | F8: T20-1091 | G8: 4.- QA | H8: Medio | I8: READY FOR UAT | J8: T20 Sprint 18 2025 | K8: Backlog BUGS | P8: Eventos_iOT | Q8: Integración | R8: QA | S8: QA-SmokeV0.4 | T8: T3B20_POS | U8: Tienda2.0 | W8: Ludo | X8: 45873.149 | Y8: v0.7 | AB8: =IF(LEFT(Jira__32[[#This Row],[Resumen]],3)="POS","POS",IF(LEFT(Jira__32[[#This Row],[Resumen]],3)="BOT","BOT","")) -> POS | AC8: Juan Munoz | AE8: {=_xlfn.IFS(OR(COUNTIF(P8:V8,Versiones!$G$9)>0, COUNTIF(P8:V8,Versiones!$H$8)>0), "Sprint 21",OR(COUNTIF(P8:V8,Versiones!$G$8)>0, COUNTIF(P8:V8,Versiones!$H$8)>0, COUNTIF(P8:V8,Versiones!$I$8)>0), "Sprint 20",OR(COUNTIF(P8:V8,Versiones!$G$7)>0, COUNTIF(P8:V8,Versiones!$H$7)>0, COUNTIF(P8:V8,Versiones!$I$7)>0), "Sprint 19",OR(COUNTIF(P8:V8,Versiones!$G$6)>0, COUNTIF(P8:V8,Versiones!$H$6)>0, COUNTIF(P8:V8,Versiones!$I$6)>0), "Sprint 18",OR(COUNTIF(P8:V8,Versiones!$G$4)>0, COUNTIF(P8:V8,Versiones!$H$4)>0, COUNTIF(P8:V8,Versiones!$G$5)>0, COUNTIF(P8:V8,Versiones!$H$5)>0), "Sprint 17",OR(COUNTIF(P8:V8,Versiones!$G$2)>0, COUNTIF(P8:V8,Versiones!$H$2)>0, COUNTIF(P8:V8,Versiones!$G$3)>0, COUNTIF(P8:V8,Versiones!$H$3)>0), "Sprint 16", OR(COUNTIF(P8:V8,Versiones!$G$2)>0, COUNTIF(P8:V8,Versiones!$H$2)>0, COUNTIF(P8:V8,Versiones!$G$3)>0, COUNTIF(P8:V8,Versiones!$H$3)>0), "Sprint 16",TRUE, "")} -> Sprint 16 | AF8: ="v"&MAX( IFERROR(VALUE(MID(Jira__32[[#This Row],[Versiones corregidas]],2,99)),0), IFERROR(VALUE(MID(Jira__32[[#This Row],[Versiones corregidas_13]],2,99)),0), IFERROR(VALUE(MID(Jira__32[[#This Row],[Versiones corregidas_14]],2,99)),0) ) -> v0.7 | AG8: {=_xlfn.IFS(Jira__32[[#This Row],[¿En qué versión fue corregido?]]="v0","N/A",Jira__32[[#This Row],[¿En qué versión fue corregido?]]="v0.4","Sprint 16", Jira__32[[#This Row],[¿En qué versión fue corregido?]]="v0.5","Sprint 17", Jira__32[[#This Row],[¿En qué versión fue corregido?]]="v0.6","Sprint 18", Jira__32[[#This Row],[¿En qué versión fue corregido?]]="v0.7","Sprint 19", Jira__32[[#This Row],[¿En qué versión fue corregido?]]="v0.8","Sprint 20",Jira__32[[#This Row],[¿En qué versión fue corregido?]]="v0.9","Sprint 21", TRUE,"Desconocido")} -> Sprint 19 | AH8: {=_xlfn.IFS(COUNTIF(P8:V8, Versiones!$A$13)>0, "Funcional", COUNTIF(P8:V8, Versiones!$A$14)>0, "Configuración", COUNTIF(P8:V8, Versiones!$A$15)>0, "Look&Feel", COUNTIF(P8:V8, Versiones!$A$16)>0, "Integración", COUNTIF(P8:V8, Versiones!$A$17)>0, "Contenido/Datos", COUNTIF(P8:V8, Versiones!$A$18)>0, "Eventos_Cosmos", COUNTIF(P8:V8, Versiones!$A$19)>0, "Eventos_iOT", COUNTIF(P8:V8, Versiones!$A$20)>0, "Eventos_Fabric", TRUE, "No encontrado")} -> Integración
A9: Error | B9: T20-949 | C9: 83046 | D9: BOT - Validar una declaración de merma: guardar en DB + generar evento | E9: 87100 | F9: T20-1091 | G9: 4.- QA | H9: Medio | I9: Tareas por hacer | J9: Backlog BUGS | P9: doc_ludo | Q9: Integración | R9: QA-SmokeV0.4 | S9: T3B20_BOT | T9: Tienda2.0 | W9: Ludo | X9: 45873.131 | Y9: v0.5 | AB9: =IF(LEFT(Jira__32[[#This Row],[Resumen]],3)="POS","POS",IF(LEFT(Jira__32[[#This Row],[Resumen]],3)="BOT","BOT","")) -> BOT | AC9: PENDIENTES | AE9: {=_xlfn.IFS(OR(COUNTIF(P9:V9,Versiones!$G$9)>0, COUNTIF(P9:V9,Versiones!$H$8)>0), "Sprint 21",OR(COUNTIF(P9:V9,Versiones!$G$8)>0, COUNTIF(P9:V9,Versiones!$H$8)>0, COUNTIF(P9:V9,Versiones!$I$8)>0), "Sprint 20",OR(COUNTIF(P9:V9,Versiones!$G$7)>0, COUNTIF(P9:V9,Versiones!$H$7)>0, COUNTIF(P9:V9,Versiones!$I$7)>0), "Sprint 19",OR(COUNTIF(P9:V9,Versiones!$G$6)>0, COUNTIF(P9:V9,Versiones!$H$6)>0, COUNTIF(P9:V9,Versiones!$I$6)>0), "Sprint 18",OR(COUNTIF(P9:V9,Versiones!$G$4)>0, COUNTIF(P9:V9,Versiones!$H$4)>0, COUNTIF(P9:V9,Versiones!$G$5)>0, COUNTIF(P9:V9,Versiones!$H$5)>0), "Sprint 17",OR(COUNTIF(P9:V9,Versiones!$G$2)>0, COUNTIF(P9:V9,Versiones!$H$2)>0, COUNTIF(P9:V9,Versiones!$G$3)>0, COUNTIF(P9:V9,Versiones!$H$3)>0), "Sprint 16", OR(COUNTIF(P9:V9,Versiones!$G$2)>0, COUNTIF(P9:V9,Versiones!$H$2)>0, COUNTIF(P9:V9,Versiones!$G$3)>0, COUNTIF(P9:V9,Versiones!$H$3)>0), "Sprint 16",TRUE, "")} -> Sprint 16 | AF9: ="v"&MAX( IFERROR(VALUE(MID(Jira__32[[#This Row],[Versiones corregidas]],2,99)),0), IFERROR(VALUE(MID(Jira__32[[#This Row],[Versiones corregidas_13]],2,99)),0), IFERROR(VALUE(MID(Jira__32[[#This Row],[Versiones corregidas_14]],2,99)),0) ) -> v0.5 | AG9: {=_xlfn.IFS(Jira__32[[#This Row],[¿En qué versión fue corregido?]]="v0","N/A",Jira__32[[#This Row],[¿En qué versión fue corregido?]]="v0.4","Sprint 16", Jira__32[[#This Row],[¿En qué versión fue corregido?]]="v0.5","Sprint 17", Jira__32[[#This Row],[¿En qué versión fue corregido?]]="v0.6","Sprint 18", Jira__32[[#This Row],[¿En qué versión fue corregido?]]="v0.7","Sprint 19", Jira__32[[#This Row],[¿En qué versión fue corregido?]]="v0.8","Sprint 20",Jira__32[[#This Row],[¿En qué versión fue corregido?]]="v0.9","Sprint 21", TRUE,"Desconocido")} -> Sprint 17 | AH9: {=_xlfn.IFS(COUNTIF(P9:V9, Versiones!$A$13)>0, "Funcional", COUNTIF(P9:V9, Versiones!$A$14)>0, "Configuración", COUNTIF(P9:V9, Versiones!$A$15)>0, "Look&Feel", COUNTIF(P9:V9, Versiones!$A$16)>0, "Integración", COUNTIF(P9:V9, Versiones!$A$17)>0, "Contenido/Datos", COUNTIF(P9:V9, Versiones!$A$18)>0, "Eventos_Cosmos", COUNTIF(P9:V9, Versiones!$A$19)>0, "Eventos_iOT", COUNTIF(P9:V9, Versiones!$A$20)>0, "Eventos_Fabric", TRUE, "No encontrado")} -> Integración
A10: Error | B10: T20-948 | C10: 83044 | D10: BOT - Ingresar cantidad a mermar | E10: 87100 | F10: T20-1091 | G10: 4.- QA | H10: Medio | I10: READY FOR UAT | J10: Backlog BUGS | P10: doc_ludo | Q10: Funcional | R10: QA-SmokeV0.4 | S10: T3B20_BOT | T10: Tienda2.0 | W10: Ludo | X10: 45873.129 | Y10: v0.5 | AB10: =IF(LEFT(Jira__32[[#This Row],[Resumen]],3)="POS","POS",IF(LEFT(Jira__32[[#This Row],[Resumen]],3)="BOT","BOT","")) -> BOT | AC10: Juan Munoz | AE10: {=_xlfn.IFS(OR(COUNTIF(P10:V10,Versiones!$G$9)>0, COUNTIF(P10:V10,Versiones!$H$8)>0), "Sprint 21",OR(COUNTIF(P10:V10,Versiones!$G$8)>0, COUNTIF(P10:V10,Versiones!$H$8)>0, COUNTIF(P10:V10,Versiones!$I$8)>0), "Sprint 20",OR(COUNTIF(P10:V10,Versiones!$G$7)>0, COUNTIF(P10:V10,Versiones!$H$7)>0, COUNTIF(P10:V10,Versiones!$I$7)>0), "Sprint 19",OR(COUNTIF(P10:V10,Versiones!$G$6)>0, COUNTIF(P10:V10,Versiones!$H$6)>0, COUNTIF(P10:V10,Versiones!$I$6)>0), "Sprint 18",OR(COUNTIF(P10:V10,Versiones!$G$4)>0, COUNTIF(P10:V10,Versiones!$H$4)>0, COUNTIF(P10:V10,Versiones!$G$5)>0, COUNTIF(P10:V10,Versiones!$H$5)>0), "Sprint 17",OR(COUNTIF(P10:V10,Versiones!$G$2)>0, COUNTIF(P10:V10,Versiones!$H$2)>0, COUNTIF(P10:V10,Versiones!$G$3)>0, COUNTIF(P10:V10,Versiones!$H$3)>0), "Sprint 16", OR(COUNTIF(P10:V10,Versiones!$G$2)>0, COUNTIF(P10:V10,Versiones!$H$2)>0, COUNTIF(P10:V10,Versiones!$G$3)>0, COUNTIF(P10:V10,Versiones!$H$3)>0), "Sprint 16",TRUE, "")} -> Sprint 16 | AF10: ="v"&MAX( IFERROR(VALUE(MID(Jira__32[[#This Row],[Versiones corregidas]],2,99)),0), IFERROR(VALUE(MID(Jira__32[[#This Row],[Versiones corregidas_13]],2,99)),0), IFERROR(VALUE(MID(Jira__32[[#This Row],[Versiones corregidas_14]],2,99)),0) ) -> v0.5 | AG10: {=_xlfn.IFS(Jira__32[[#This Row],[¿En qué versión fue corregido?]]="v0","N/A",Jira__32[[#This Row],[¿En qué versión fue corregido?]]="v0.4","Sprint 16", Jira__32[[#This Row],[¿En qué versión fue corregido?]]="v0.5","Sprint 17", Jira__32[[#This Row],[¿En qué versión fue corregido?]]="v0.6","Sprint 18", Jira__32[[#This Row],[¿En qué versión fue corregido?]]="v0.7","Sprint 19", Jira__32[[#This Row],[¿En qué versión fue corregido?]]="v0.8","Sprint 20",Jira__32[[#This Row],[¿En qué versión fue corregido?]]="v0.9","Sprint 21", TRUE,"Desconocido")} -> Sprint 17 | AH10: {=_xlfn.IFS(COUNTIF(P10:V10, Versiones!$A$13)>0, "Funcional", COUNTIF(P10:V10, Versiones!$A$14)>0, "Configuración", COUNTIF(P10:V10, Versiones!$A$15)>0, "Look&Feel", COUNTIF(P10:V10, Versiones!$A$16)>0, "Integración", COUNTIF(P10:V10, Versiones!$A$17)>0, "Contenido/Datos", COUNTIF(P10:V10, Versiones!$A$18)>0, "Eventos_Cosmos", COUNTIF(P10:V10, Versiones!$A$19)>0, "Eventos_iOT", COUNTIF(P10:V10, Versiones!$A$20)>0, "Eventos_Fabric", TRUE, "No encontrado")} -> Funcional
A11: Error | B11: T20-947 | C11: 83042 | D11: BOT - Dropdown de motivo de merma | E11: 87100 | F11: T20-1091 | G11: 4.- QA | H11: Medio | I11: Tareas por hacer | J11: Backlog BUGS | P11: doc_ludo | Q11: Funcional | R11: QA-SmokeV0.4 | S11: T3B20_BOT | T11: Tienda2.0 | W11: Ludo | X11: 45873.128 | Y11: v0.5 | AB11: =IF(LEFT(Jira__32[[#This Row],[Resumen]],3)="POS","POS",IF(LEFT(Jira__32[[#This Row],[Resumen]],3)="BOT","BOT","")) -> BOT | AC11: PENDIENTES | AE11: {=_xlfn.IFS(OR(COUNTIF(P11:V11,Versiones!$G$9)>0, COUNTIF(P11:V11,Versiones!$H$8)>0), "Sprint 21",OR(COUNTIF(P11:V11,Versiones!$G$8)>0, COUNTIF(P11:V11,Versiones!$H$8)>0, COUNTIF(P11:V11,Versiones!$I$8)>0), "Sprint 20",OR(COUNTIF(P11:V11,Versiones!$G$7)>0, COUNTIF(P11:V11,Versiones!$H$7)>0, COUNTIF(P11:V11,Versiones!$I$7)>0), "Sprint 19",OR(COUNTIF(P11:V11,Versiones!$G$6)>0, COUNTIF(P11:V11,Versiones!$H$6)>0, COUNTIF(P11:V11,Versiones!$I$6)>0), "Sprint 18",OR(COUNTIF(P11:V11,Versiones!$G$4)>0, COUNTIF(P11:V11,Versiones!$H$4)>0, COUNTIF(P11:V11,Versiones!$G$5)>0, COUNTIF(P11:V11,Versiones!$H$5)>0), "Sprint 17",OR(COUNTIF(P11:V11,Versiones!$G$2)>0, COUNTIF(P11:V11,Versiones!$H$2)>0, COUNTIF(P11:V11,Versiones!$G$3)>0, COUNTIF(P11:V11,Versiones!$H$3)>0), "Sprint 16", OR(COUNTIF(P11:V11,Versiones!$G$2)>0, COUNTIF(P11:V11,Versiones!$H$2)>0, COUNTIF(P11:V11,Versiones!$G$3)>0, COUNTIF(P11:V11,Versiones!$H$3)>0), "Sprint 16",TRUE, "")} -> Sprint 16 | AF11: ="v"&MAX( IFERROR(VALUE(MID(Jira__32[[#This Row],[Versiones corregidas]],2,99)),0), IFERROR(VALUE(MID(Jira__32[[#This Row],[Versiones corregidas_13]],2,99)),0), IFERROR(VALUE(MID(Jira__32[[#This Row],[Versiones corregidas_14]],2,99)),0) ) -> v0.5 | AG11: {=_xlfn.IFS(Jira__32[[#This Row],[¿En qué versión fue corregido?]]="v0","N/A",Jira__32[[#This Row],[¿En qué versión fue corregido?]]="v0.4","Sprint 16", Jira__32[[#This Row],[¿En qué versión fue corregido?]]="v0.5","Sprint 17", Jira__32[[#This Row],[¿En qué versión fue corregido?]]="v0.6","Sprint 18", Jira__32[[#This Row],[¿En qué versión fue corregido?]]="v0.7","Sprint 19", Jira__32[[#This Row],[¿En qué versión fue corregido?]]="v0.8","Sprint 20",Jira__32[[#This Row],[¿En qué versión fue corregido?]]="v0.9","Sprint 21", TRUE,"Desconocido")} -> Sprint 17 | AH11: {=_xlfn.IFS(COUNTIF(P11:V11, Versiones!$A$13)>0, "Funcional", COUNTIF(P11:V11, Versiones!$A$14)>0, "Configuración", COUNTIF(P11:V11, Versiones!$A$15)>0, "Look&Feel", COUNTIF(P11:V11, Versiones!$A$16)>0, "Integración", COUNTIF(P11:V11, Versiones!$A$17)>0, "Contenido/Datos", COUNTIF(P11:V11, Versiones!$A$18)>0, "Eventos_Cosmos", COUNTIF(P11:V11, Versiones!$A$19)>0, "Eventos_iOT", COUNTIF(P11:V11, Versiones!$A$20)>0, "Eventos_Fabric", TRUE, "No encontrado")} -> Funcional
A12: Error | B12: T20-945 | C12: 83039 | D12: POS - Buscar y agregar producto | E12: 87100 | F12: T20-1091 | G12: 4.- QA | H12: Medio | I12: READY FOR UAT | P12: doc_ludo | Q12: Funcional | R12: QA-SmokeV0.4 | S12: T3B20_POS | T12: Tested_In_DEV | U12: Tienda2.0 | W12: Ludo | X12: 45873.107 | Y12: v0.5 | AB12: =IF(LEFT(Jira__32[[#This Row],[Resumen]],3)="POS","POS",IF(LEFT(Jira__32[[#This Row],[Resumen]],3)="BOT","BOT","")) -> POS | AC12: Juan Munoz | AE12: {=_xlfn.IFS(OR(COUNTIF(P12:V12,Versiones!$G$9)>0, COUNTIF(P12:V12,Versiones!$H$8)>0), "Sprint 21",OR(COUNTIF(P12:V12,Versiones!$G$8)>0, COUNTIF(P12:V12,Versiones!$H$8)>0, COUNTIF(P12:V12,Versiones!$I$8)>0), "Sprint 20",OR(COUNTIF(P12:V12,Versiones!$G$7)>0, COUNTIF(P12:V12,Versiones!$H$7)>0, COUNTIF(P12:V12,Versiones!$I$7)>0), "Sprint 19",OR(COUNTIF(P12:V12,Versiones!$G$6)>0, COUNTIF(P12:V12,Versiones!$H$6)>0, COUNTIF(P12:V12,Versiones!$I$6)>0), "Sprint 18",OR(COUNTIF(P12:V12,Versiones!$G$4)>0, COUNTIF(P12:V12,Versiones!$H$4)>0, COUNTIF(P12:V12,Versiones!$G$5)>0, COUNTIF(P12:V12,Versiones!$H$5)>0), "Sprint 17",OR(COUNTIF(P12:V12,Versiones!$G$2)>0, COUNTIF(P12:V12,Versiones!$H$2)>0, COUNTIF(P12:V12,Versiones!$G$3)>0, COUNTIF(P12:V12,Versiones!$H$3)>0), "Sprint 16", OR(COUNTIF(P12:V12,Versiones!$G$2)>0, COUNTIF(P12:V12,Versiones!$H$2)>0, COUNTIF(P12:V12,Versiones!$G$3)>0, COUNTIF(P12:V12,Versiones!$H$3)>0), "Sprint 16",TRUE, "")} -> Sprint 16 | AF12: ="v"&MAX( IFERROR(VALUE(MID(Jira__32[[#This Row],[Versiones corregidas]],2,99)),0), IFERROR(VALUE(MID(Jira__32[[#This Row],[Versiones corregidas_13]],2,99)),0), IFERROR(VALUE(MID(Jira__32[[#This Row],[Versiones corregidas_14]],2,99)),0) ) -> v0.5 | AG12: {=_xlfn.IFS(Jira__32[[#This Row],[¿En qué versión fue corregido?]]="v0","N/A",Jira__32[[#This Row],[¿En qué versión fue corregido?]]="v0.4","Sprint 16", Jira__32[[#This Row],[¿En qué versión fue corregido?]]="v0.5","Sprint 17", Jira__32[[#This Row],[¿En qué versión fue corregido?]]="v0.6","Sprint 18", Jira__32[[#This Row],[¿En qué versión fue corregido?]]="v0.7","Sprint 19", Jira__32[[#This Row],[¿En qué versión fue corregido?]]="v0.8","Sprint 20",Jira__32[[#This Row],[¿En qué versión fue corregido?]]="v0.9","Sprint 21", TRUE,"Desconocido")} -> Sprint 17 | AH12: {=_xlfn.IFS(COUNTIF(P12:V12, Versiones!$A$13)>0, "Funcional", COUNTIF(P12:V12, Versiones!$A$14)>0, "Configuración", COUNTIF(P12:V12, Versiones!$A$15)>0, "Look&Feel", COUNTIF(P12:V12, Versiones!$A$16)>0, "Integración", COUNTIF(P12:V12, Versiones!$A$17)>0, "Contenido/Datos", COUNTIF(P12:V12, Versiones!$A$18)>0, "Eventos_Cosmos", COUNTIF(P12:V12, Versiones!$A$19)>0, "Eventos_iOT", COUNTIF(P12:V12, Versiones!$A$20)>0, "Eventos_Fabric", TRUE, "No encontrado")} -> Funcional
A13: Error | B13: T20-943 | C13: 83035 | D13: POS - Eliminar articulo de venta: corrección del flujo | E13: 87100 | F13: T20-1091 | G13: 4.- QA | H13: Medio | I13: IN SIT | J13: Backlog BUGS | P13: doc_ludo | Q13: Funcional | R13: QA-SmokeV0.4 | S13: T3B20_POS | T13: Tested_In_DEV | U13: Tienda2.0 | W13: Ludo | X13: 45873.095 | Y13: v0.5 | AB13: =IF(LEFT(Jira__32[[#This Row],[Resumen]],3)="POS","POS",IF(LEFT(Jira__32[[#This Row],[Resumen]],3)="BOT","BOT","")) -> POS | AC13: Andres Vergara | AE13: {=_xlfn.IFS(OR(COUNTIF(P13:V13,Versiones!$G$9)>0, COUNTIF(P13:V13,Versiones!$H$8)>0), "Sprint 21",OR(COUNTIF(P13:V13,Versiones!$G$8)>0, COUNTIF(P13:V13,Versiones!$H$8)>0, COUNTIF(P13:V13,Versiones!$I$8)>0), "Sprint 20",OR(COUNTIF(P13:V13,Versiones!$G$7)>0, COUNTIF(P13:V13,Versiones!$H$7)>0, COUNTIF(P13:V13,Versiones!$I$7)>0), "Sprint 19",OR(COUNTIF(P13:V13,Versiones!$G$6)>0, COUNTIF(P13:V13,Versiones!$H$6)>0, COUNTIF(P13:V13,Versiones!$I$6)>0), "Sprint 18",OR(COUNTIF(P13:V13,Versiones!$G$4)>0, COUNTIF(P13:V13,Versiones!$H$4)>0, COUNTIF(P13:V13,Versiones!$G$5)>0, COUNTIF(P13:V13,Versiones!$H$5)>0), "Sprint 17",OR(COUNTIF(P13:V13,Versiones!$G$2)>0, COUNTIF(P13:V13,Versiones!$H$2)>0, COUNTIF(P13:V13,Versiones!$G$3)>0, COUNTIF(P13:V13,Versiones!$H$3)>0), "Sprint 16", OR(COUNTIF(P13:V13,Versiones!$G$2)>0, COUNTIF(P13:V13,Versiones!$H$2)>0, COUNTIF(P13:V13,Versiones!$G$3)>0, COUNTIF(P13:V13,Versiones!$H$3)>0), "Sprint 16",TRUE, "")} -> Sprint 16 | AF13: ="v"&MAX( IFERROR(VALUE(MID(Jira__32[[#This Row],[Versiones corregidas]],2,99)),0), IFERROR(VALUE(MID(Jira__32[[#This Row],[Versiones corregidas_13]],2,99)),0), IFERROR(VALUE(MID(Jira__32[[#This Row],[Versiones corregidas_14]],2,99)),0) ) -> v0.5 | AG13: {=_xlfn.IFS(Jira__32[[#This Row],[¿En qué versión fue corregido?]]="v0","N/A",Jira__32[[#This Row],[¿En qué versión fue corregido?]]="v0.4","Sprint 16", Jira__32[[#This Row],[¿En qué versión fue corregido?]]="v0.5","Sprint 17", Jira__32[[#This Row],[¿En qué versión fue corregido?]]="v0.6","Sprint 18", Jira__32[[#This Row],[¿En qué versión fue corregido?]]="v0.7","Sprint 19", Jira__32[[#This Row],[¿En qué versión fue corregido?]]="v0.8","Sprint 20",Jira__32[[#This Row],[¿En qué versión fue corregido?]]="v0.9","Sprint 21", TRUE,"Desconocido")} -> Sprint 17 | AH13: {=_xlfn.IFS(COUNTIF(P13:V13, Versiones!$A$13)>0, "Funcional", COUNTIF(P13:V13, Versiones!$A$14)>0, "Configuración", COUNTIF(P13:V13, Versiones!$A$15)>0, "Look&Feel", COUNTIF(P13:V13, Versiones!$A$16)>0, "Integración", COUNTIF(P13:V13, Versiones!$A$17)>0, "Contenido/Datos", COUNTIF(P13:V13, Versiones!$A$18)>0, "Eventos_Cosmos", COUNTIF(P13:V13, Versiones!$A$19)>0, "Eventos_iOT", COUNTIF(P13:V13, Versiones!$A$20)>0, "Eventos_Fabric", TRUE, "No encontrado")} -> Funcional
A14: Error | B14: T20-942 | C14: 83033 | D14: POS - Indicar el cambio a dar al cliente cuando paga con efectivo | E14: 87100 | F14: T20-1091 | G14: 4.- QA | H14: Medio | I14: READY FOR UAT | J14: T20 Sprint 18 2025 | K14: Backlog BUGS | P14: doc_ludo | Q14: Funcional | R14: QA-SmokeV0.4 | S14: T3B20_POS | T14: Tienda2.0 | W14: Ludo | X14: 45873.062 | Y14: v0.6 | AB14: =IF(LEFT(Jira__32[[#This Row],[Resumen]],3)="POS","POS",IF(LEFT(Jira__32[[#This Row],[Resumen]],3)="BOT","BOT","")) -> POS | AC14: Juan Munoz | AE14: {=_xlfn.IFS(OR(COUNTIF(P14:V14,Versiones!$G$9)>0, COUNTIF(P14:V14,Versiones!$H$8)>0), "Sprint 21",OR(COUNTIF(P14:V14,Versiones!$G$8)>0, COUNTIF(P14:V14,Versiones!$H$8)>0, COUNTIF(P14:V14,Versiones!$I$8)>0), "Sprint 20",OR(COUNTIF(P14:V14,Versiones!$G$7)>0, COUNTIF(P14:V14,Versiones!$H$7)>0, COUNTIF(P14:V14,Versiones!$I$7)>0), "Sprint 19",OR(COUNTIF(P14:V14,Versiones!$G$6)>0, COUNTIF(P14:V14,Versiones!$H$6)>0, COUNTIF(P14:V14,Versiones!$I$6)>0), "Sprint 18",OR(COUNTIF(P14:V14,Versiones!$G$4)>0, COUNTIF(P14:V14,Versiones!$H$4)>0, COUNTIF(P14:V14,Versiones!$G$5)>0, COUNTIF(P14:V14,Versiones!$H$5)>0), "Sprint 17",OR(COUNTIF(P14:V14,Versiones!$G$2)>0, COUNTIF(P14:V14,Versiones!$H$2)>0, COUNTIF(P14:V14,Versiones!$G$3)>0, COUNTIF(P14:V14,Versiones!$H$3)>0), "Sprint 16", OR(COUNTIF(P14:V14,Versiones!$G$2)>0, COUNTIF(P14:V14,Versiones!$H$2)>0, COUNTIF(P14:V14,Versiones!$G$3)>0, COUNTIF(P14:V14,Versiones!$H$3)>0), "Sprint 16",TRUE, "")} -> Sprint 16 | AF14: ="v"&MAX( IFERROR(VALUE(MID(Jira__32[[#This Row],[Versiones corregidas]],2,99)),0), IFERROR(VALUE(MID(Jira__32[[#This Row],[Versiones corregidas_13]],2,99)),0), IFERROR(VALUE(MID(Jira__32[[#This Row],[Versiones corregidas_14]],2,99)),0) ) -> v0.6 | AG14: {=_xlfn.IFS(Jira__32[[#This Row],[¿En qué versión fue corregido?]]="v0","N/A",Jira__32[[#This Row],[¿En qué versión fue corregido?]]="v0.4","Sprint 16", Jira__32[[#This Row],[¿En qué versión fue corregido?]]="v0.5","Sprint 17", Jira__32[[#This Row],[¿En qué versión fue corregido?]]="v0.6","Sprint 18", Jira__32[[#This Row],[¿En qué versión fue corregido?]]="v0.7","Sprint 19", Jira__32[[#This Row],[¿En qué versión fue corregido?]]="v0.8","Sprint 20",Jira__32[[#This Row],[¿En qué versión fue corregido?]]="v0.9","Sprint 21", TRUE,"Desconocido")} -> Sprint 18 | AH14: {=_xlfn.IFS(COUNTIF(P14:V14, Versiones!$A$13)>0, "Funcional", COUNTIF(P14:V14, Versiones!$A$14)>0, "Configuración", COUNTIF(P14:V14, Versiones!$A$15)>0, "Look&Feel", COUNTIF(P14:V14, Versiones!$A$16)>0, "Integración", COUNTIF(P14:V14, Versiones!$A$17)>0, "Contenido/Datos", COUNTIF(P14:V14, Versiones!$A$18)>0, "Eventos_Cosmos", COUNTIF(P14:V14, Versiones!$A$19)>0, "Eventos_iOT", COUNTIF(P14:V14, Versiones!$A$20)>0, "Eventos_Fabric", TRUE, "No encontrado")} -> Funcional
A15: Error | B15: T20-940 | C15: 83030 | D15: POS - Shortcuts ya no funcionan en flujo de pago | E15: 87100 | F15: T20-1091 | G15: 4.- QA | H15: Medio | I15: Tareas por hacer | J15: Backlog BUGS | P15: doc_ludo | Q15: Funcional | R15: QA-SmokeV0.4 | S15: T3B20_POS | T15: Tienda2.0 | W15: Ludo | X15: 45873.053 | Y15: v0.5 | AB15: =IF(LEFT(Jira__32[[#This Row],[Resumen]],3)="POS","POS",IF(LEFT(Jira__32[[#This Row],[Resumen]],3)="BOT","BOT","")) -> POS | AC15: PENDIENTES | AE15: {=_xlfn.IFS(OR(COUNTIF(P15:V15,Versiones!$G$9)>0, COUNTIF(P15:V15,Versiones!$H$8)>0), "Sprint 21",OR(COUNTIF(P15:V15,Versiones!$G$8)>0, COUNTIF(P15:V15,Versiones!$H$8)>0, COUNTIF(P15:V15,Versiones!$I$8)>0), "Sprint 20",OR(COUNTIF(P15:V15,Versiones!$G$7)>0, COUNTIF(P15:V15,Versiones!$H$7)>0, COUNTIF(P15:V15,Versiones!$I$7)>0), "Sprint 19",OR(COUNTIF(P15:V15,Versiones!$G$6)>0, COUNTIF(P15:V15,Versiones!$H$6)>0, COUNTIF(P15:V15,Versiones!$I$6)>0), "Sprint 18",OR(COUNTIF(P15:V15,Versiones!$G$4)>0, COUNTIF(P15:V15,Versiones!$H$4)>0, COUNTIF(P15:V15,Versiones!$G$5)>0, COUNTIF(P15:V15,Versiones!$H$5)>0), "Sprint 17",OR(COUNTIF(P15:V15,Versiones!$G$2)>0, COUNTIF(P15:V15,Versiones!$H$2)>0, COUNTIF(P15:V15,Versiones!$G$3)>0, COUNTIF(P15:V15,Versiones!$H$3)>0), "Sprint 16", OR(COUNTIF(P15:V15,Versiones!$G$2)>0, COUNTIF(P15:V15,Versiones!$H$2)>0, COUNTIF(P15:V15,Versiones!$G$3)>0, COUNTIF(P15:V15,Versiones!$H$3)>0), "Sprint 16",TRUE, "")} -> Sprint 16 | AF15: ="v"&MAX( IFERROR(VALUE(MID(Jira__32[[#This Row],[Versiones corregidas]],2,99)),0), IFERROR(VALUE(MID(Jira__32[[#This Row],[Versiones corregidas_13]],2,99)),0), IFERROR(VALUE(MID(Jira__32[[#This Row],[Versiones corregidas_14]],2,99)),0) ) -> v0.5 | AG15: {=_xlfn.IFS(Jira__32[[#This Row],[¿En qué versión fue corregido?]]="v0","N/A",Jira__32[[#This Row],[¿En qué versión fue corregido?]]="v0.4","Sprint 16", Jira__32[[#This Row],[¿En qué versión fue corregido?]]="v0.5","Sprint 17", Jira__32[[#This Row],[¿En qué versión fue corregido?]]="v0.6","Sprint 18", Jira__32[[#This Row],[¿En qué versión fue corregido?]]="v0.7","Sprint 19", Jira__32[[#This Row],[¿En qué versión fue corregido?]]="v0.8","Sprint 20",Jira__32[[#This Row],[¿En qué versión fue corregido?]]="v0.9","Sprint 21", TRUE,"Desconocido")} -> Sprint 17 | AH15: {=_xlfn.IFS(COUNTIF(P15:V15, Versiones!$A$13)>0, "Funcional", COUNTIF(P15:V15, Versiones!$A$14)>0, "Configuración", COUNTIF(P15:V15, Versiones!$A$15)>0, "Look&Feel", COUNTIF(P15:V15, Versiones!$A$16)>0, "Integración", COUNTIF(P15:V15, Versiones!$A$17)>0, "Contenido/Datos", COUNTIF(P15:V15, Versiones!$A$18)>0, "Eventos_Cosmos", COUNTIF(P15:V15, Versiones!$A$19)>0, "Eventos_iOT", COUNTIF(P15:V15, Versiones!$A$20)>0, "Eventos_Fabric", TRUE, "No encontrado")} -> Funcional
A16: Error | B16: T20-939 | C16: 83028 | D16: POS - Shortcuts invertidos para opciones de pago | E16: 87100 | F16: T20-1091 | G16: 4.- QA | H16: Medio | I16: READY FOR UAT | J16: Backlog BUGS | P16: doc_ludo | Q16: Funcional | R16: QA-SmokeV0.4 | S16: T3B20_POS | T16: Tested_In_DEV | U16: Tienda2.0 | W16: Ludo | X16: 45873.051 | Y16: v0.5 | AB16: =IF(LEFT(Jira__32[[#This Row],[Resumen]],3)="POS","POS",IF(LEFT(Jira__32[[#This Row],[Resumen]],3)="BOT","BOT","")) -> POS | AC16: Andres Vergara | AE16: {=_xlfn.IFS(OR(COUNTIF(P16:V16,Versiones!$G$9)>0, COUNTIF(P16:V16,Versiones!$H$8)>0), "Sprint 21",OR(COUNTIF(P16:V16,Versiones!$G$8)>0, COUNTIF(P16:V16,Versiones!$H$8)>0, COUNTIF(P16:V16,Versiones!$I$8)>0), "Sprint 20",OR(COUNTIF(P16:V16,Versiones!$G$7)>0, COUNTIF(P16:V16,Versiones!$H$7)>0, COUNTIF(P16:V16,Versiones!$I$7)>0), "Sprint 19",OR(COUNTIF(P16:V16,Versiones!$G$6)>0, COUNTIF(P16:V16,Versiones!$H$6)>0, COUNTIF(P16:V16,Versiones!$I$6)>0), "Sprint 18",OR(COUNTIF(P16:V16,Versiones!$G$4)>0, COUNTIF(P16:V16,Versiones!$H$4)>0, COUNTIF(P16:V16,Versiones!$G$5)>0, COUNTIF(P16:V16,Versiones!$H$5)>0), "Sprint 17",OR(COUNTIF(P16:V16,Versiones!$G$2)>0, COUNTIF(P16:V16,Versiones!$H$2)>0, COUNTIF(P16:V16,Versiones!$G$3)>0, COUNTIF(P16:V16,Versiones!$H$3)>0), "Sprint 16", OR(COUNTIF(P16:V16,Versiones!$G$2)>0, COUNTIF(P16:V16,Versiones!$H$2)>0, COUNTIF(P16:V16,Versiones!$G$3)>0, COUNTIF(P16:V16,Versiones!$H$3)>0), "Sprint 16",TRUE, "")} -> Sprint 16 | AF16: ="v"&MAX( IFERROR(VALUE(MID(Jira__32[[#This Row],[Versiones corregidas]],2,99)),0), IFERROR(VALUE(MID(Jira__32[[#This Row],[Versiones corregidas_13]],2,99)),0), IFERROR(VALUE(MID(Jira__32[[#This Row],[Versiones corregidas_14]],2,99)),0) ) -> v0.5 | AG16: {=_xlfn.IFS(Jira__32[[#This Row],[¿En qué versión fue corregido?]]="v0","N/A",Jira__32[[#This Row],[¿En qué versión fue corregido?]]="v0.4","Sprint 16", Jira__32[[#This Row],[¿En qué versión fue corregido?]]="v0.5","Sprint 17", Jira__32[[#This Row],[¿En qué versión fue corregido?]]="v0.6","Sprint 18", Jira__32[[#This Row],[¿En qué versión fue corregido?]]="v0.7","Sprint 19", Jira__32[[#This Row],[¿En qué versión fue corregido?]]="v0.8","Sprint 20",Jira__32[[#This Row],[¿En qué versión fue corregido?]]="v0.9","Sprint 21", TRUE,"Desconocido")} -> Sprint 17 | AH16: {=_xlfn.IFS(COUNTIF(P16:V16, Versiones!$A$13)>0, "Funcional", COUNTIF(P16:V16, Versiones!$A$14)>0, "Configuración", COUNTIF(P16:V16, Versiones!$A$15)>0, "Look&Feel", COUNTIF(P16:V16, Versiones!$A$16)>0, "Integración", COUNTIF(P16:V16, Versiones!$A$17)>0, "Contenido/Datos", COUNTIF(P16:V16, Versiones!$A$18)>0, "Eventos_Cosmos", COUNTIF(P16:V16, Versiones!$A$19)>0, "Eventos_iOT", COUNTIF(P16:V16, Versiones!$A$20)>0, "Eventos_Fabric", TRUE, "No encontrado")} -> Funcional
A17: Error | B17: T20-937 | C17: 83024 | D17: POS- Los modals de autenticación validan las credenciales | E17: 87100 | F17: T20-1091 | G17: 4.- QA | H17: Medio | I17: Cancelado | P17: doc_ludo | Q17: Funcional | R17: QA-SmokeV0.4 | S17: T3B20_BOT | T17: T3B20_POS | U17: Tested_In_DEV | V17: Tienda2.0 | W17: Ludo | X17: 45873.037 | Y17: v0.5 | AB17: =IF(LEFT(Jira__32[[#This Row],[Resumen]],3)="POS","POS",IF(LEFT(Jira__32[[#This Row],[Resumen]],3)="BOT","BOT","")) -> POS | AC17: CANCELADO | AE17: {=_xlfn.IFS(OR(COUNTIF(P17:V17,Versiones!$G$9)>0, COUNTIF(P17:V17,Versiones!$H$8)>0), "Sprint 21",OR(COUNTIF(P17:V17,Versiones!$G$8)>0, COUNTIF(P17:V17,Versiones!$H$8)>0, COUNTIF(P17:V17,Versiones!$I$8)>0), "Sprint 20",OR(COUNTIF(P17:V17,Versiones!$G$7)>0, COUNTIF(P17:V17,Versiones!$H$7)>0, COUNTIF(P17:V17,Versiones!$I$7)>0), "Sprint 19",OR(COUNTIF(P17:V17,Versiones!$G$6)>0, COUNTIF(P17:V17,Versiones!$H$6)>0, COUNTIF(P17:V17,Versiones!$I$6)>0), "Sprint 18",OR(COUNTIF(P17:V17,Versiones!$G$4)>0, COUNTIF(P17:V17,Versiones!$H$4)>0, COUNTIF(P17:V17,Versiones!$G$5)>0, COUNTIF(P17:V17,Versiones!$H$5)>0), "Sprint 17",OR(COUNTIF(P17:V17,Versiones!$G$2)>0, COUNTIF(P17:V17,Versiones!$H$2)>0, COUNTIF(P17:V17,Versiones!$G$3)>0, COUNTIF(P17:V17,Versiones!$H$3)>0), "Sprint 16", OR(COUNTIF(P17:V17,Versiones!$G$2)>0, COUNTIF(P17:V17,Versiones!$H$2)>0, COUNTIF(P17:V17,Versiones!$G$3)>0, COUNTIF(P17:V17,Versiones!$H$3)>0), "Sprint 16",TRUE, "")} -> Sprint 16 | AF17: ="v"&MAX( IFERROR(VALUE(MID(Jira__32[[#This Row],[Versiones corregidas]],2,99)),0), IFERROR(VALUE(MID(Jira__32[[#This Row],[Versiones corregidas_13]],2,99)),0), IFERROR(VALUE(MID(Jira__32[[#This Row],[Versiones corregidas_14]],2,99)),0) ) -> v0.5 | AG17: {=_xlfn.IFS(Jira__32[[#This Row],[¿En qué versión fue corregido?]]="v0","N/A",Jira__32[[#This Row],[¿En qué versión fue corregido?]]="v0.4","Sprint 16", Jira__32[[#This Row],[¿En qué versión fue corregido?]]="v0.5","Sprint 17", Jira__32[[#This Row],[¿En qué versión fue corregido?]]="v0.6","Sprint 18", Jira__32[[#This Row],[¿En qué versión fue corregido?]]="v0.7","Sprint 19", Jira__32[[#This Row],[¿En qué versión fue corregido?]]="v0.8","Sprint 20",Jira__32[[#This Row],[¿En qué versión fue corregido?]]="v0.9","Sprint 21", TRUE,"Desconocido")} -> Sprint 17 | AH17: {=_xlfn.IFS(COUNTIF(P17:V17, Versiones!$A$13)>0, "Funcional", COUNTIF(P17:V17, Versiones!$A$14)>0, "Configuración", COUNTIF(P17:V17, Versiones!$A$15)>0, "Look&Feel", COUNTIF(P17:V17, Versiones!$A$16)>0, "Integración", COUNTIF(P17:V17, Versiones!$A$17)>0, "Contenido/Datos", COUNTIF(P17:V17, Versiones!$A$18)>0, "Eventos_Cosmos", COUNTIF(P17:V17, Versiones!$A$19)>0, "Eventos_iOT", COUNTIF(P17:V17, Versiones!$A$20)>0, "Eventos_Fabric", TRUE, "No encontrado")} -> Funcional
A18: Error | B18: T20-936 | C18: 83022 | D18: POS - No se pueden realizar multiples devoluciones | E18: 87100 | F18: T20-1091 | G18: 4.- QA | H18: Alta | I18: Tareas por hacer | J18: T20 Sprint 21 2025 | P18: Funcional | Q18: QA-SmokeV0.4 | W18: Ludo | X18: 45873.034 | Y18: v0.5 | AB18: =IF(LEFT(Jira__32[[#This Row],[Resumen]],3)="POS","POS",IF(LEFT(Jira__32[[#This Row],[Resumen]],3)="BOT","BOT","")) -> POS | AC18: PENDIENTES | AE18: {=_xlfn.IFS(OR(COUNTIF(P18:V18,Versiones!$G$9)>0, COUNTIF(P18:V18,Versiones!$H$8)>0), "Sprint 21",OR(COUNTIF(P18:V18,Versiones!$G$8)>0, COUNTIF(P18:V18,Versiones!$H$8)>0, COUNTIF(P18:V18,Versiones!$I$8)>0), "Sprint 20",OR(COUNTIF(P18:V18,Versiones!$G$7)>0, COUNTIF(P18:V18,Versiones!$H$7)>0, COUNTIF(P18:V18,Versiones!$I$7)>0), "Sprint 19",OR(COUNTIF(P18:V18,Versiones!$G$6)>0, COUNTIF(P18:V18,Versiones!$H$6)>0, COUNTIF(P18:V18,Versiones!$I$6)>0), "Sprint 18",OR(COUNTIF(P18:V18,Versiones!$G$4)>0, COUNTIF(P18:V18,Versiones!$H$4)>0, COUNTIF(P18:V18,Versiones!$G$5)>0, COUNTIF(P18:V18,Versiones!$H$5)>0), "Sprint 17",OR(COUNTIF(P18:V18,Versiones!$G$2)>0, COUNTIF(P18:V18,Versiones!$H$2)>0, COUNTIF(P18:V18,Versiones!$G$3)>0, COUNTIF(P18:V18,Versiones!$H$3)>0), "Sprint 16", OR(COUNTIF(P18:V18,Versiones!$G$2)>0, COUNTIF(P18:V18,Versiones!$H$2)>0, COUNTIF(P18:V18,Versiones!$G$3)>0, COUNTIF(P18:V18,Versiones!$H$3)>0), "Sprint 16",TRUE, "")} -> Sprint 16 | AF18: ="v"&MAX( IFERROR(VALUE(MID(Jira__32[[#This Row],[Versiones corregidas]],2,99)),0), IFERROR(VALUE(MID(Jira__32[[#This Row],[Versiones corregidas_13]],2,99)),0), IFERROR(VALUE(MID(Jira__32[[#This Row],[Versiones corregidas_14]],2,99)),0) ) -> v0.5 | AG18: {=_xlfn.IFS(Jira__32[[#This Row],[¿En qué versión fue corregido?]]="v0","N/A",Jira__32[[#This Row],[¿En qué versión fue corregido?]]="v0.4","Sprint 16", Jira__32[[#This Row],[¿En qué versión fue corregido?]]="v0.5","Sprint 17", Jira__32[[#This Row],[¿En qué versión fue corregido?]]="v0.6","Sprint 18", Jira__32[[#This Row],[¿En qué versión fue corregido?]]="v0.7","Sprint 19", Jira__32[[#This Row],[¿En qué versión fue corregido?]]="v0.8","Sprint 20",Jira__32[[#This Row],[¿En qué versión fue corregido?]]="v0.9","Sprint 21", TRUE,"Desconocido")} -> Sprint 17 | AH18: {=_xlfn.IFS(COUNTIF(P18:V18, Versiones!$A$13)>0, "Funcional", COUNTIF(P18:V18, Versiones!$A$14)>0, "Configuración", COUNTIF(P18:V18, Versiones!$A$15)>0, "Look&Feel", COUNTIF(P18:V18, Versiones!$A$16)>0, "Integración", COUNTIF(P18:V18, Versiones!$A$17)>0, "Contenido/Datos", COUNTIF(P18:V18, Versiones!$A$18)>0, "Eventos_Cosmos", COUNTIF(P18:V18, Versiones!$A$19)>0, "Eventos_iOT", COUNTIF(P18:V18, Versiones!$A$20)>0, "Eventos_Fabric", TRUE, "No encontrado")} -> Funcional
A19: Error | B19: T20-935 | C19: 83020 | D19: POS - El shortcut F7 inicia el flujo de devoluciones | E19: 87100 | F19: T20-1091 | G19: 4.- QA | H19: Medio | I19: READY FOR UAT | J19: T20 Sprint 17 2025 | K19: T20 Sprint 18 2025 | L19: Backlog BUGS | P19: Funcional | Q19: QA-SmokeV0.4 | W19: Ludo | X19: 45873.033 | Y19: v0.5 | AB19: =IF(LEFT(Jira__32[[#This Row],[Resumen]],3)="POS","POS",IF(LEFT(Jira__32[[#This Row],[Resumen]],3)="BOT","BOT","")) -> POS | AC19: Ludovic Hern | AE19: {=_xlfn.IFS(OR(COUNTIF(P19:V19,Versiones!$G$9)>0, COUNTIF(P19:V19,Versiones!$H$8)>0), "Sprint 21",OR(COUNTIF(P19:V19,Versiones!$G$8)>0, COUNTIF(P19:V19,Versiones!$H$8)>0, COUNTIF(P19:V19,Versiones!$I$8)>0), "Sprint 20",OR(COUNTIF(P19:V19,Versiones!$G$7)>0, COUNTIF(P19:V19,Versiones!$H$7)>0, COUNTIF(P19:V19,Versiones!$I$7)>0), "Sprint 19",OR(COUNTIF(P19:V19,Versiones!$G$6)>0, COUNTIF(P19:V19,Versiones!$H$6)>0, COUNTIF(P19:V19,Versiones!$I$6)>0), "Sprint 18",OR(COUNTIF(P19:V19,Versiones!$G$4)>0, COUNTIF(P19:V19,Versiones!$H$4)>0, COUNTIF(P19:V19,Versiones!$G$5)>0, COUNTIF(P19:V19,Versiones!$H$5)>0), "Sprint 17",OR(COUNTIF(P19:V19,Versiones!$G$2)>0, COUNTIF(P19:V19,Versiones!$H$2)>0, COUNTIF(P19:V19,Versiones!$G$3)>0, COUNTIF(P19:V19,Versiones!$H$3)>0), "Sprint 16", OR(COUNTIF(P19:V19,Versiones!$G$2)>0, COUNTIF(P19:V19,Versiones!$H$2)>0, COUNTIF(P19:V19,Versiones!$G$3)>0, COUNTIF(P19:V19,Versiones!$H$3)>0), "Sprint 16",TRUE, "")} -> Sprint 16 | AF19: ="v"&MAX( IFERROR(VALUE(MID(Jira__32[[#This Row],[Versiones corregidas]],2,99)),0), IFERROR(VALUE(MID(Jira__32[[#This Row],[Versiones corregidas_13]],2,99)),0), IFERROR(VALUE(MID(Jira__32[[#This Row],[Versiones corregidas_14]],2,99)),0) ) -> v0.5 | AG19: {=_xlfn.IFS(Jira__32[[#This Row],[¿En qué versión fue corregido?]]="v0","N/A",Jira__32[[#This Row],[¿En qué versión fue corregido?]]="v0.4","Sprint 16", Jira__32[[#This Row],[¿En qué versión fue corregido?]]="v0.5","Sprint 17", Jira__32[[#This Row],[¿En qué versión fue corregido?]]="v0.6","Sprint 18", Jira__32[[#This Row],[¿En qué versión fue corregido?]]="v0.7","Sprint 19", Jira__32[[#This Row],[¿En qué versión fue corregido?]]="v0.8","Sprint 20",Jira__32[[#This Row],[¿En qué versión fue corregido?]]="v0.9","Sprint 21", TRUE,"Desconocido")} -> Sprint 17 | AH19: {=_xlfn.IFS(COUNTIF(P19:V19, Versiones!$A$13)>0, "Funcional", COUNTIF(P19:V19, Versiones!$A$14)>0, "Configuración", COUNTIF(P19:V19, Versiones!$A$15)>0, "Look&Feel", COUNTIF(P19:V19, Versiones!$A$16)>0, "Integración", COUNTIF(P19:V19, Versiones!$A$17)>0, "Contenido/Datos", COUNTIF(P19:V19, Versiones!$A$18)>0, "Eventos_Cosmos", COUNTIF(P19:V19, Versiones!$A$19)>0, "Eventos_iOT", COUNTIF(P19:V19, Versiones!$A$20)>0, "Eventos_Fabric", TRUE, "No encontrado")} -> Funcional
A20: Error | B20: T20-933 | C20: 83017 | D20: POS - Shortcut F9 inicia flujo de pago de servicio | E20: 87100 | F20: T20-1091 | G20: 4.- QA | H20: Medio | I20: READY FOR UAT | J20: T20 Sprint 19 2025 | K20: Backlog BUGS | P20: Funcional | Q20: QA-SmokeV0.4 | R20: T3B20_POS | S20: Tienda2.0 | W20: Ludo | X20: 45873.026 | Y20: v0.7 | AB20: =IF(LEFT(Jira__32[[#This Row],[Resumen]],3)="POS","POS",IF(LEFT(Jira__32[[#This Row],[Resumen]],3)="BOT","BOT","")) -> POS | AC20: PENDIENTES | AE20: {=_xlfn.IFS(OR(COUNTIF(P20:V20,Versiones!$G$9)>0, COUNTIF(P20:V20,Versiones!$H$8)>0), "Sprint 21",OR(COUNTIF(P20:V20,Versiones!$G$8)>0, COUNTIF(P20:V20,Versiones!$H$8)>0, COUNTIF(P20:V20,Versiones!$I$8)>0), "Sprint 20",OR(COUNTIF(P20:V20,Versiones!$G$7)>0, COUNTIF(P20:V20,Versiones!$H$7)>0, COUNTIF(P20:V20,Versiones!$I$7)>0), "Sprint 19",OR(COUNTIF(P20:V20,Versiones!$G$6)>0, COUNTIF(P20:V20,Versiones!$H$6)>0, COUNTIF(P20:V20,Versiones!$I$6)>0), "Sprint 18",OR(COUNTIF(P20:V20,Versiones!$G$4)>0, COUNTIF(P20:V20,Versiones!$H$4)>0, COUNTIF(P20:V20,Versiones!$G$5)>0, COUNTIF(P20:V20,Versiones!$H$5)>0), "Sprint 17",OR(COUNTIF(P20:V20,Versiones!$G$2)>0, COUNTIF(P20:V20,Versiones!$H$2)>0, COUNTIF(P20:V20,Versiones!$G$3)>0, COUNTIF(P20:V20,Versiones!$H$3)>0), "Sprint 16", OR(COUNTIF(P20:V20,Versiones!$G$2)>0, COUNTIF(P20:V20,Versiones!$H$2)>0, COUNTIF(P20:V20,Versiones!$G$3)>0, COUNTIF(P20:V20,Versiones!$H$3)>0), "Sprint 16",TRUE, "")} -> Sprint 16 | AF20: ="v"&MAX( IFERROR(VALUE(MID(Jira__32[[#This Row],[Versiones corregidas]],2,99)),0), IFERROR(VALUE(MID(Jira__32[[#This Row],[Versiones corregidas_13]],2,99)),0), IFERROR(VALUE(MID(Jira__32[[#This Row],[Versiones corregidas_14]],2,99)),0) ) -> v0.7 | AG20: {=_xlfn.IFS(Jira__32[[#This Row],[¿En qué versión fue corregido?]]="v0","N/A",Jira__32[[#This Row],[¿En qué versión fue corregido?]]="v0.4","Sprint 16", Jira__32[[#This Row],[¿En qué versión fue corregido?]]="v0.5","Sprint 17", Jira__32[[#This Row],[¿En qué versión fue corregido?]]="v0.6","Sprint 18", Jira__32[[#This Row],[¿En qué versión fue corregido?]]="v0.7","Sprint 19", Jira__32[[#This Row],[¿En qué versión fue corregido?]]="v0.8","Sprint 20",Jira__32[[#This Row],[¿En qué versión fue corregido?]]="v0.9","Sprint 21", TRUE,"Desconocido")} -> Sprint 19 | AH20: {=_xlfn.IFS(COUNTIF(P20:V20, Versiones!$A$13)>0, "Funcional", COUNTIF(P20:V20, Versiones!$A$14)>0, "Configuración", COUNTIF(P20:V20, Versiones!$A$15)>0, "Look&Feel", COUNTIF(P20:V20, Versiones!$A$16)>0, "Integración", COUNTIF(P20:V20, Versiones!$A$17)>0, "Contenido/Datos", COUNTIF(P20:V20, Versiones!$A$18)>0, "Eventos_Cosmos", COUNTIF(P20:V20, Versiones!$A$19)>0, "Eventos_iOT", COUNTIF(P20:V20, Versiones!$A$20)>0, "Eventos_Fabric", TRUE, "No encontrado")} -> Funcional
A21: Error | B21: T20-931 | C21: 83014 | D21: POS - Tamaño de los modals de autenticación | E21: 87100 | F21: T20-1091 | G21: 4.- QA | H21: Medio | I21: READY FOR UAT | J21: Backlog BUGS | P21: doc_ludo | Q21: Look&Feel | R21: QA-SmokeV0.4 | S21: T3B20_POS | T21: Tested_In_DEV | U21: Tienda2.0 | W21: Ludo | X21: 45873.017 | Y21: v0.5 | AB21: =IF(LEFT(Jira__32[[#This Row],[Resumen]],3)="POS","POS",IF(LEFT(Jira__32[[#This Row],[Resumen]],3)="BOT","BOT","")) -> POS | AC21: PENDIENTES | AE21: {=_xlfn.IFS(OR(COUNTIF(P21:V21,Versiones!$G$9)>0, COUNTIF(P21:V21,Versiones!$H$8)>0), "Sprint 21",OR(COUNTIF(P21:V21,Versiones!$G$8)>0, COUNTIF(P21:V21,Versiones!$H$8)>0, COUNTIF(P21:V21,Versiones!$I$8)>0), "Sprint 20",OR(COUNTIF(P21:V21,Versiones!$G$7)>0, COUNTIF(P21:V21,Versiones!$H$7)>0, COUNTIF(P21:V21,Versiones!$I$7)>0), "Sprint 19",OR(COUNTIF(P21:V21,Versiones!$G$6)>0, COUNTIF(P21:V21,Versiones!$H$6)>0, COUNTIF(P21:V21,Versiones!$I$6)>0), "Sprint 18",OR(COUNTIF(P21:V21,Versiones!$G$4)>0, COUNTIF(P21:V21,Versiones!$H$4)>0, COUNTIF(P21:V21,Versiones!$G$5)>0, COUNTIF(P21:V21,Versiones!$H$5)>0), "Sprint 17",OR(COUNTIF(P21:V21,Versiones!$G$2)>0, COUNTIF(P21:V21,Versiones!$H$2)>0, COUNTIF(P21:V21,Versiones!$G$3)>0, COUNTIF(P21:V21,Versiones!$H$3)>0), "Sprint 16", OR(COUNTIF(P21:V21,Versiones!$G$2)>0, COUNTIF(P21:V21,Versiones!$H$2)>0, COUNTIF(P21:V21,Versiones!$G$3)>0, COUNTIF(P21:V21,Versiones!$H$3)>0), "Sprint 16",TRUE, "")} -> Sprint 16 | AF21: ="v"&MAX( IFERROR(VALUE(MID(Jira__32[[#This Row],[Versiones corregidas]],2,99)),0), IFERROR(VALUE(MID(Jira__32[[#This Row],[Versiones corregidas_13]],2,99)),0), IFERROR(VALUE(MID(Jira__32[[#This Row],[Versiones corregidas_14]],2,99)),0) ) -> v0.5 | AG21: {=_xlfn.IFS(Jira__32[[#This Row],[¿En qué versión fue corregido?]]="v0","N/A",Jira__32[[#This Row],[¿En qué versión fue corregido?]]="v0.4","Sprint 16", Jira__32[[#This Row],[¿En qué versión fue corregido?]]="v0.5","Sprint 17", Jira__32[[#This Row],[¿En qué versión fue corregido?]]="v0.6","Sprint 18", Jira__32[[#This Row],[¿En qué versión fue corregido?]]="v0.7","Sprint 19", Jira__32[[#This Row],[¿En qué versión fue corregido?]]="v0.8","Sprint 20",Jira__32[[#This Row],[¿En qué versión fue corregido?]]="v0.9","Sprint 21", TRUE,"Desconocido")} -> Sprint 17 | AH21: {=_xlfn.IFS(COUNTIF(P21:V21, Versiones!$A$13)>0, "Funcional", COUNTIF(P21:V21, Versiones!$A$14)>0, "Configuración", COUNTIF(P21:V21, Versiones!$A$15)>0, "Look&Feel", COUNTIF(P21:V21, Versiones!$A$16)>0, "Integración", COUNTIF(P21:V21, Versiones!$A$17)>0, "Contenido/Datos", COUNTIF(P21:V21, Versiones!$A$18)>0, "Eventos_Cosmos", COUNTIF(P21:V21, Versiones!$A$19)>0, "Eventos_iOT", COUNTIF(P21:V21, Versiones!$A$20)>0, "Eventos_Fabric", TRUE, "No encontrado")} -> Look&Feel
A22: Error | B22: T20-930 | C22: 83012 | D22: POS - Cierre de turno: se cierra y se termina el cierre de turno al dar clic en el botón "Aceptar" | E22: 87100 | F22: T20-1091 | G22: 4.- QA | H22: Medio | I22: Code Review | J22: Backlog BUGS | P22: doc_ludo | Q22: Funcional | R22: QA-SmokeV0.4 | S22: T3B20_POS | T22: Tienda2.0 | W22: Ludo | X22: 45873.015 | AB22: =IF(LEFT(Jira__32[[#This Row],[Resumen]],3)="POS","POS",IF(LEFT(Jira__32[[#This Row],[Resumen]],3)="BOT","BOT","")) -> POS | AC22: PENDIENTES | AE22: {=_xlfn.IFS(OR(COUNTIF(P22:V22,Versiones!$G$9)>0, COUNTIF(P22:V22,Versiones!$H$8)>0), "Sprint 21",OR(COUNTIF(P22:V22,Versiones!$G$8)>0, COUNTIF(P22:V22,Versiones!$H$8)>0, COUNTIF(P22:V22,Versiones!$I$8)>0), "Sprint 20",OR(COUNTIF(P22:V22,Versiones!$G$7)>0, COUNTIF(P22:V22,Versiones!$H$7)>0, COUNTIF(P22:V22,Versiones!$I$7)>0), "Sprint 19",OR(COUNTIF(P22:V22,Versiones!$G$6)>0, COUNTIF(P22:V22,Versiones!$H$6)>0, COUNTIF(P22:V22,Versiones!$I$6)>0), "Sprint 18",OR(COUNTIF(P22:V22,Versiones!$G$4)>0, COUNTIF(P22:V22,Versiones!$H$4)>0, COUNTIF(P22:V22,Versiones!$G$5)>0, COUNTIF(P22:V22,Versiones!$H$5)>0), "Sprint 17",OR(COUNTIF(P22:V22,Versiones!$G$2)>0, COUNTIF(P22:V22,Versiones!$H$2)>0, COUNTIF(P22:V22,Versiones!$G$3)>0, COUNTIF(P22:V22,Versiones!$H$3)>0), "Sprint 16", OR(COUNTIF(P22:V22,Versiones!$G$2)>0, COUNTIF(P22:V22,Versiones!$H$2)>0, COUNTIF(P22:V22,Versiones!$G$3)>0, COUNTIF(P22:V22,Versiones!$H$3)>0), "Sprint 16",TRUE, "")} -> Sprint 16 | AF22: ="v"&MAX( IFERROR(VALUE(MID(Jira__32[[#This Row],[Versiones corregidas]],2,99)),0), IFERROR(VALUE(MID(Jira__32[[#This Row],[Versiones corregidas_13]],2,99)),0), IFERROR(VALUE(MID(Jira__32[[#This Row],[Versiones corregidas_14]],2,99)),0) ) -> v0 | AG22: {=_xlfn.IFS(Jira__32[[#This Row],[¿En qué versión fue corregido?]]="v0","N/A",Jira__32[[#This Row],[¿En qué versión fue corregido?]]="v0.4","Sprint 16", Jira__32[[#This Row],[¿En qué versión fue corregido?]]="v0.5","Sprint 17", Jira__32[[#This Row],[¿En qué versión fue corregido?]]="v0.6","Sprint 18", Jira__32[[#This Row],[¿En qué versión fue corregido?]]="v0.7","Sprint 19", Jira__32[[#This Row],[¿En qué versión fue corregido?]]="v0.8","Sprint 20",Jira__32[[#This Row],[¿En qué versión fue corregido?]]="v0.9","Sprint 21", TRUE,"Desconocido")} -> N/A | AH22: {=_xlfn.IFS(COUNTIF(P22:V22, Versiones!$A$13)>0, "Funcional", COUNTIF(P22:V22, Versiones!$A$14)>0, "Configuración", COUNTIF(P22:V22, Versiones!$A$15)>0, "Look&Feel", COUNTIF(P22:V22, Versiones!$A$16)>0, "Integración", COUNTIF(P22:V22, Versiones!$A$17)>0, "Contenido/Datos", COUNTIF(P22:V22, Versiones!$A$18)>0, "Eventos_Cosmos", COUNTIF(P22:V22, Versiones!$A$19)>0, "Eventos_iOT", COUNTIF(P22:V22, Versiones!$A$20)>0, "Eventos_Fabric", TRUE, "No encontrado")} -> Funcional
A23: Error | B23: T20-929 | C23: 83010 | D23: POS - Cierre de turno: con shortcut F11 | E23: 87100 | F23: T20-1091 | G23: 4.- QA | H23: Medio | I23: READY FOR UAT | J23: T20 Sprint 19 2025 | K23: Backlog BUGS | P23: doc_ludo | Q23: Funcional | R23: QA-SmokeV0.4 | S23: T3B20_POS | T23: Tienda2.0 | W23: Ludo | X23: 45873.012 | Y23: v0.7 | AB23: =IF(LEFT(Jira__32[[#This Row],[Resumen]],3)="POS","POS",IF(LEFT(Jira__32[[#This Row],[Resumen]],3)="BOT","BOT","")) -> POS | AC23: PENDIENTES | AE23: {=_xlfn.IFS(OR(COUNTIF(P23:V23,Versiones!$G$9)>0, COUNTIF(P23:V23,Versiones!$H$8)>0), "Sprint 21",OR(COUNTIF(P23:V23,Versiones!$G$8)>0, COUNTIF(P23:V23,Versiones!$H$8)>0, COUNTIF(P23:V23,Versiones!$I$8)>0), "Sprint 20",OR(COUNTIF(P23:V23,Versiones!$G$7)>0, COUNTIF(P23:V23,Versiones!$H$7)>0, COUNTIF(P23:V23,Versiones!$I$7)>0), "Sprint 19",OR(COUNTIF(P23:V23,Versiones!$G$6)>0, COUNTIF(P23:V23,Versiones!$H$6)>0, COUNTIF(P23:V23,Versiones!$I$6)>0), "Sprint 18",OR(COUNTIF(P23:V23,Versiones!$G$4)>0, COUNTIF(P23:V23,Versiones!$H$4)>0, COUNTIF(P23:V23,Versiones!$G$5)>0, COUNTIF(P23:V23,Versiones!$H$5)>0), "Sprint 17",OR(COUNTIF(P23:V23,Versiones!$G$2)>0, COUNTIF(P23:V23,Versiones!$H$2)>0, COUNTIF(P23:V23,Versiones!$G$3)>0, COUNTIF(P23:V23,Versiones!$H$3)>0), "Sprint 16", OR(COUNTIF(P23:V23,Versiones!$G$2)>0, COUNTIF(P23:V23,Versiones!$H$2)>0, COUNTIF(P23:V23,Versiones!$G$3)>0, COUNTIF(P23:V23,Versiones!$H$3)>0), "Sprint 16",TRUE, "")} -> Sprint 16 | AF23: ="v"&MAX( IFERROR(VALUE(MID(Jira__32[[#This Row],[Versiones corregidas]],2,99)),0), IFERROR(VALUE(MID(Jira__32[[#This Row],[Versiones corregidas_13]],2,99)),0), IFERROR(VALUE(MID(Jira__32[[#This Row],[Versiones corregidas_14]],2,99)),0) ) -> v0.7 | AG23: {=_xlfn.IFS(Jira__32[[#This Row],[¿En qué versión fue corregido?]]="v0","N/A",Jira__32[[#This Row],[¿En qué versión fue corregido?]]="v0.4","Sprint 16", Jira__32[[#This Row],[¿En qué versión fue corregido?]]="v0.5","Sprint 17", Jira__32[[#This Row],[¿En qué versión fue corregido?]]="v0.6","Sprint 18", Jira__32[[#This Row],[¿En qué versión fue corregido?]]="v0.7","Sprint 19", Jira__32[[#This Row],[¿En qué versión fue corregido?]]="v0.8","Sprint 20",Jira__32[[#This Row],[¿En qué versión fue corregido?]]="v0.9","Sprint 21", TRUE,"Desconocido")} -> Sprint 19 | AH23: {=_xlfn.IFS(COUNTIF(P23:V23, Versiones!$A$13)>0, "Funcional", COUNTIF(P23:V23, Versiones!$A$14)>0, "Configuración", COUNTIF(P23:V23, Versiones!$A$15)>0, "Look&Feel", COUNTIF(P23:V23, Versiones!$A$16)>0, "Integración", COUNTIF(P23:V23, Versiones!$A$17)>0, "Contenido/Datos", COUNTIF(P23:V23, Versiones!$A$18)>0, "Eventos_Cosmos", COUNTIF(P23:V23, Versiones!$A$19)>0, "Eventos_iOT", COUNTIF(P23:V23, Versiones!$A$20)>0, "Eventos_Fabric", TRUE, "No encontrado")} -> Funcional
A24: Error | B24: T20-927 | C24: 83006 | D24: POS - Inicio de turno con shortcut CTRL-A | E24: 87100 | F24: T20-1091 | G24: 4.- QA | H24: Medio | I24: READY FOR UAT | J24: T20 Sprint 17 2025 | K24: T20 Sprint 18 2025 | L24: Backlog BUGS | P24: doc_ludo | Q24: Funcional | R24: QA-SmokeV0.4 | S24: T3B20_POS | T24: Tienda2.0 | W24: Ludo | X24: 45872.992 | Y24: v0.6 | AB24: =IF(LEFT(Jira__32[[#This Row],[Resumen]],3)="POS","POS",IF(LEFT(Jira__32[[#This Row],[Resumen]],3)="BOT","BOT","")) -> POS | AC24: PENDIENTES | AE24: {=_xlfn.IFS(OR(COUNTIF(P24:V24,Versiones!$G$9)>0, COUNTIF(P24:V24,Versiones!$H$8)>0), "Sprint 21",OR(COUNTIF(P24:V24,Versiones!$G$8)>0, COUNTIF(P24:V24,Versiones!$H$8)>0, COUNTIF(P24:V24,Versiones!$I$8)>0), "Sprint 20",OR(COUNTIF(P24:V24,Versiones!$G$7)>0, COUNTIF(P24:V24,Versiones!$H$7)>0, COUNTIF(P24:V24,Versiones!$I$7)>0), "Sprint 19",OR(COUNTIF(P24:V24,Versiones!$G$6)>0, COUNTIF(P24:V24,Versiones!$H$6)>0, COUNTIF(P24:V24,Versiones!$I$6)>0), "Sprint 18",OR(COUNTIF(P24:V24,Versiones!$G$4)>0, COUNTIF(P24:V24,Versiones!$H$4)>0, COUNTIF(P24:V24,Versiones!$G$5)>0, COUNTIF(P24:V24,Versiones!$H$5)>0), "Sprint 17",OR(COUNTIF(P24:V24,Versiones!$G$2)>0, COUNTIF(P24:V24,Versiones!$H$2)>0, COUNTIF(P24:V24,Versiones!$G$3)>0, COUNTIF(P24:V24,Versiones!$H$3)>0), "Sprint 16", OR(COUNTIF(P24:V24,Versiones!$G$2)>0, COUNTIF(P24:V24,Versiones!$H$2)>0, COUNTIF(P24:V24,Versiones!$G$3)>0, COUNTIF(P24:V24,Versiones!$H$3)>0), "Sprint 16",TRUE, "")} -> Sprint 16 | AF24: ="v"&MAX( IFERROR(VALUE(MID(Jira__32[[#This Row],[Versiones corregidas]],2,99)),0), IFERROR(VALUE(MID(Jira__32[[#This Row],[Versiones corregidas_13]],2,99)),0), IFERROR(VALUE(MID(Jira__32[[#This Row],[Versiones corregidas_14]],2,99)),0) ) -> v0.6 | AG24: {=_xlfn.IFS(Jira__32[[#This Row],[¿En qué versión fue corregido?]]="v0","N/A",Jira__32[[#This Row],[¿En qué versión fue corregido?]]="v0.4","Sprint 16", Jira__32[[#This Row],[¿En qué versión fue corregido?]]="v0.5","Sprint 17", Jira__32[[#This Row],[¿En qué versión fue corregido?]]="v0.6","Sprint 18", Jira__32[[#This Row],[¿En qué versión fue corregido?]]="v0.7","Sprint 19", Jira__32[[#This Row],[¿En qué versión fue corregido?]]="v0.8","Sprint 20",Jira__32[[#This Row],[¿En qué versión fue corregido?]]="v0.9","Sprint 21", TRUE,"Desconocido")} -> Sprint 18 | AH24: {=_xlfn.IFS(COUNTIF(P24:V24, Versiones!$A$13)>0, "Funcional", COUNTIF(P24:V24, Versiones!$A$14)>0, "Configuración", COUNTIF(P24:V24, Versiones!$A$15)>0, "Look&Feel", COUNTIF(P24:V24, Versiones!$A$16)>0, "Integración", COUNTIF(P24:V24, Versiones!$A$17)>0, "Contenido/Datos", COUNTIF(P24:V24, Versiones!$A$18)>0, "Eventos_Cosmos", COUNTIF(P24:V24, Versiones!$A$19)>0, "Eventos_iOT", COUNTIF(P24:V24, Versiones!$A$20)>0, "Eventos_Fabric", TRUE, "No encontrado")} -> Funcional
A25: Error | B25: T20-926 | C25: 82992 | D25: POS - El formato de fecha en el header del POS es DD/MM/YYYY | E25: 87100 | F25: T20-1091 | G25: 4.- QA | H25: Medio | I25: READY FOR UAT | J25: Backlog BUGS | P25: doc_ludo | Q25: Look&Feel | R25: QA-SmokeV0.4 | S25: T3B20_POS | T25: Tienda2.0 | W25: Ludo | X25: 45872.974 | Y25: v0.5 | AB25: =IF(LEFT(Jira__32[[#This Row],[Resumen]],3)="POS","POS",IF(LEFT(Jira__32[[#This Row],[Resumen]],3)="BOT","BOT","")) -> POS | AC25: PENDIENTES | AE25: {=_xlfn.IFS(OR(COUNTIF(P25:V25,Versiones!$G$9)>0, COUNTIF(P25:V25,Versiones!$H$8)>0), "Sprint 21",OR(COUNTIF(P25:V25,Versiones!$G$8)>0, COUNTIF(P25:V25,Versiones!$H$8)>0, COUNTIF(P25:V25,Versiones!$I$8)>0), "Sprint 20",OR(COUNTIF(P25:V25,Versiones!$G$7)>0, COUNTIF(P25:V25,Versiones!$H$7)>0, COUNTIF(P25:V25,Versiones!$I$7)>0), "Sprint 19",OR(COUNTIF(P25:V25,Versiones!$G$6)>0, COUNTIF(P25:V25,Versiones!$H$6)>0, COUNTIF(P25:V25,Versiones!$I$6)>0), "Sprint 18",OR(COUNTIF(P25:V25,Versiones!$G$4)>0, COUNTIF(P25:V25,Versiones!$H$4)>0, COUNTIF(P25:V25,Versiones!$G$5)>0, COUNTIF(P25:V25,Versiones!$H$5)>0), "Sprint 17",OR(COUNTIF(P25:V25,Versiones!$G$2)>0, COUNTIF(P25:V25,Versiones!$H$2)>0, COUNTIF(P25:V25,Versiones!$G$3)>0, COUNTIF(P25:V25,Versiones!$H$3)>0), "Sprint 16", OR(COUNTIF(P25:V25,Versiones!$G$2)>0, COUNTIF(P25:V25,Versiones!$H$2)>0, COUNTIF(P25:V25,Versiones!$G$3)>0, COUNTIF(P25:V25,Versiones!$H$3)>0), "Sprint 16",TRUE, "")} -> Sprint 16 | AF25: ="v"&MAX( IFERROR(VALUE(MID(Jira__32[[#This Row],[Versiones corregidas]],2,99)),0), IFERROR(VALUE(MID(Jira__32[[#This Row],[Versiones corregidas_13]],2,99)),0), IFERROR(VALUE(MID(Jira__32[[#This Row],[Versiones corregidas_14]],2,99)),0) ) -> v0.5 | AG25: {=_xlfn.IFS(Jira__32[[#This Row],[¿En qué versión fue corregido?]]="v0","N/A",Jira__32[[#This Row],[¿En qué versión fue corregido?]]="v0.4","Sprint 16", Jira__32[[#This Row],[¿En qué versión fue corregido?]]="v0.5","Sprint 17", Jira__32[[#This Row],[¿En qué versión fue corregido?]]="v0.6","Sprint 18", Jira__32[[#This Row],[¿En qué versión fue corregido?]]="v0.7","Sprint 19", Jira__32[[#This Row],[¿En qué versión fue corregido?]]="v0.8","Sprint 20",Jira__32[[#This Row],[¿En qué versión fue corregido?]]="v0.9","Sprint 21", TRUE,"Desconocido")} -> Sprint 17 | AH25: {=_xlfn.IFS(COUNTIF(P25:V25, Versiones!$A$13)>0, "Funcional", COUNTIF(P25:V25, Versiones!$A$14)>0, "Configuración", COUNTIF(P25:V25, Versiones!$A$15)>0, "Look&Feel", COUNTIF(P25:V25, Versiones!$A$16)>0, "Integración", COUNTIF(P25:V25, Versiones!$A$17)>0, "Contenido/Datos", COUNTIF(P25:V25, Versiones!$A$18)>0, "Eventos_Cosmos", COUNTIF(P25:V25, Versiones!$A$19)>0, "Eventos_iOT", COUNTIF(P25:V25, Versiones!$A$20)>0, "Eventos_Fabric", TRUE, "No encontrado")} -> Look&Feel
A26: Error | B26: T20-924 | C26: 82987 | D26: POS - Inicio+Cierre de turno: correcciones en el flujo | E26: 87100 | F26: T20-1091 | G26: 4.- QA | H26: Medio | I26: READY FOR UAT | J26: T20 Sprint 16 2025 | K26: T20 Sprint 17 2025 | L26: T20 Sprint 18 2025 | M26: Backlog BUGS | P26: Funcional | Q26: QA | R26: QA-SmokeV0.4 | S26: T3B20_POS | T26: Tienda2.0 | W26: Ludo | X26: 45872.969 | Y26: v0.7 | AB26: =IF(LEFT(Jira__32[[#This Row],[Resumen]],3)="POS","POS",IF(LEFT(Jira__32[[#This Row],[Resumen]],3)="BOT","BOT","")) -> POS | AC26: PENDIENTES | AE26: {=_xlfn.IFS(OR(COUNTIF(P26:V26,Versiones!$G$9)>0, COUNTIF(P26:V26,Versiones!$H$8)>0), "Sprint 21",OR(COUNTIF(P26:V26,Versiones!$G$8)>0, COUNTIF(P26:V26,Versiones!$H$8)>0, COUNTIF(P26:V26,Versiones!$I$8)>0), "Sprint 20",OR(COUNTIF(P26:V26,Versiones!$G$7)>0, COUNTIF(P26:V26,Versiones!$H$7)>0, COUNTIF(P26:V26,Versiones!$I$7)>0), "Sprint 19",OR(COUNTIF(P26:V26,Versiones!$G$6)>0, COUNTIF(P26:V26,Versiones!$H$6)>0, COUNTIF(P26:V26,Versiones!$I$6)>0), "Sprint 18",OR(COUNTIF(P26:V26,Versiones!$G$4)>0, COUNTIF(P26:V26,Versiones!$H$4)>0, COUNTIF(P26:V26,Versiones!$G$5)>0, COUNTIF(P26:V26,Versiones!$H$5)>0), "Sprint 17",OR(COUNTIF(P26:V26,Versiones!$G$2)>0, COUNTIF(P26:V26,Versiones!$H$2)>0, COUNTIF(P26:V26,Versiones!$G$3)>0, COUNTIF(P26:V26,Versiones!$H$3)>0), "Sprint 16", OR(COUNTIF(P26:V26,Versiones!$G$2)>0, COUNTIF(P26:V26,Versiones!$H$2)>0, COUNTIF(P26:V26,Versiones!$G$3)>0, COUNTIF(P26:V26,Versiones!$H$3)>0), "Sprint 16",TRUE, "")} -> Sprint 16 | AF26: ="v"&MAX( IFERROR(VALUE(MID(Jira__32[[#This Row],[Versiones corregidas]],2,99)),0), IFERROR(VALUE(MID(Jira__32[[#This Row],[Versiones corregidas_13]],2,99)),0), IFERROR(VALUE(MID(Jira__32[[#This Row],[Versiones corregidas_14]],2,99)),0) ) -> v0.7 | AG26: {=_xlfn.IFS(Jira__32[[#This Row],[¿En qué versión fue corregido?]]="v0","N/A",Jira__32[[#This Row],[¿En qué versión fue corregido?]]="v0.4","Sprint 16", Jira__32[[#This Row],[¿En qué versión fue corregido?]]="v0.5","Sprint 17", Jira__32[[#This Row],[¿En qué versión fue corregido?]]="v0.6","Sprint 18", Jira__32[[#This Row],[¿En qué versión fue corregido?]]="v0.7","Sprint 19", Jira__32[[#This Row],[¿En qué versión fue corregido?]]="v0.8","Sprint 20",Jira__32[[#This Row],[¿En qué versión fue corregido?]]="v0.9","Sprint 21", TRUE,"Desconocido")} -> Sprint 19 | AH26: {=_xlfn.IFS(COUNTIF(P26:V26, Versiones!$A$13)>0, "Funcional", COUNTIF(P26:V26, Versiones!$A$14)>0, "Configuración", COUNTIF(P26:V26, Versiones!$A$15)>0, "Look&Feel", COUNTIF(P26:V26, Versiones!$A$16)>0, "Integración", COUNTIF(P26:V26, Versiones!$A$17)>0, "Contenido/Datos", COUNTIF(P26:V26, Versiones!$A$18)>0, "Eventos_Cosmos", COUNTIF(P26:V26, Versiones!$A$19)>0, "Eventos_iOT", COUNTIF(P26:V26, Versiones!$A$20)>0, "Eventos_Fabric", TRUE, "No encontrado")} -> Funcional
A27: Error | B27: T20-920 | C27: 82982 | D27: POS - Escanear producto | E27: 87100 | F27: T20-1091 | G27: 4.- QA | H27: Medio | I27: Cancelado | P27: doc_ludo | Q27: Funcional | R27: QA-SmokeV0.4 | S27: T3B20_POS | T27: Tienda2.0 | W27: Ludo | X27: 45872.952 | Y27: v0.6 | AB27: =IF(LEFT(Jira__32[[#This Row],[Resumen]],3)="POS","POS",IF(LEFT(Jira__32[[#This Row],[Resumen]],3)="BOT","BOT","")) -> POS | AC27: CANCELADO | AE27: {=_xlfn.IFS(OR(COUNTIF(P27:V27,Versiones!$G$9)>0, COUNTIF(P27:V27,Versiones!$H$8)>0), "Sprint 21",OR(COUNTIF(P27:V27,Versiones!$G$8)>0, COUNTIF(P27:V27,Versiones!$H$8)>0, COUNTIF(P27:V27,Versiones!$I$8)>0), "Sprint 20",OR(COUNTIF(P27:V27,Versiones!$G$7)>0, COUNTIF(P27:V27,Versiones!$H$7)>0, COUNTIF(P27:V27,Versiones!$I$7)>0), "Sprint 19",OR(COUNTIF(P27:V27,Versiones!$G$6)>0, COUNTIF(P27:V27,Versiones!$H$6)>0, COUNTIF(P27:V27,Versiones!$I$6)>0), "Sprint 18",OR(COUNTIF(P27:V27,Versiones!$G$4)>0, COUNTIF(P27:V27,Versiones!$H$4)>0, COUNTIF(P27:V27,Versiones!$G$5)>0, COUNTIF(P27:V27,Versiones!$H$5)>0), "Sprint 17",OR(COUNTIF(P27:V27,Versiones!$G$2)>0, COUNTIF(P27:V27,Versiones!$H$2)>0, COUNTIF(P27:V27,Versiones!$G$3)>0, COUNTIF(P27:V27,Versiones!$H$3)>0), "Sprint 16", OR(COUNTIF(P27:V27,Versiones!$G$2)>0, COUNTIF(P27:V27,Versiones!$H$2)>0, COUNTIF(P27:V27,Versiones!$G$3)>0, COUNTIF(P27:V27,Versiones!$H$3)>0), "Sprint 16",TRUE, "")} -> Sprint 16 | AF27: ="v"&MAX( IFERROR(VALUE(MID(Jira__32[[#This Row],[Versiones corregidas]],2,99)),0), IFERROR(VALUE(MID(Jira__32[[#This Row],[Versiones corregidas_13]],2,99)),0), IFERROR(VALUE(MID(Jira__32[[#This Row],[Versiones corregidas_14]],2,99)),0) ) -> v0.6 | AG27: {=_xlfn.IFS(Jira__32[[#This Row],[¿En qué versión fue corregido?]]="v0","N/A",Jira__32[[#This Row],[¿En qué versión fue corregido?]]="v0.4","Sprint 16", Jira__32[[#This Row],[¿En qué versión fue corregido?]]="v0.5","Sprint 17", Jira__32[[#This Row],[¿En qué versión fue corregido?]]="v0.6","Sprint 18", Jira__32[[#This Row],[¿En qué versión fue corregido?]]="v0.7","Sprint 19", Jira__32[[#This Row],[¿En qué versión fue corregido?]]="v0.8","Sprint 20",Jira__32[[#This Row],[¿En qué versión fue corregido?]]="v0.9","Sprint 21", TRUE,"Desconocido")} -> Sprint 18 | AH27: {=_xlfn.IFS(COUNTIF(P27:V27, Versiones!$A$13)>0, "Funcional", COUNTIF(P27:V27, Versiones!$A$14)>0, "Configuración", COUNTIF(P27:V27, Versiones!$A$15)>0, "Look&Feel", COUNTIF(P27:V27, Versiones!$A$16)>0, "Integración", COUNTIF(P27:V27, Versiones!$A$17)>0, "Contenido/Datos", COUNTIF(P27:V27, Versiones!$A$18)>0, "Eventos_Cosmos", COUNTIF(P27:V27, Versiones!$A$19)>0, "Eventos_iOT", COUNTIF(P27:V27, Versiones!$A$20)>0, "Eventos_Fabric", TRUE, "No encontrado")} -> Funcional
A28: Error | B28: T20-916 | C28: 82968 | D28: POS - Login BOT+POS: no se muestra el nombre del usuario conectado | E28: 87100 | F28: T20-1091 | G28: 4.- QA | H28: Medio | I28: Tareas por hacer | J28: Backlog BUGS | P28: doc_ludo | Q28: Look&Feel | R28: QA-SmokeV0.4 | S28: T3B20_BOT | T28: Tienda2.0 | W28: Ludo | X28: 45872.915 | Y28: v0.5 | AB28: =IF(LEFT(Jira__32[[#This Row],[Resumen]],3)="POS","POS",IF(LEFT(Jira__32[[#This Row],[Resumen]],3)="BOT","BOT","")) -> POS | AC28: Sergio Ordaz Romero | AE28: {=_xlfn.IFS(OR(COUNTIF(P28:V28,Versiones!$G$9)>0, COUNTIF(P28:V28,Versiones!$H$8)>0), "Sprint 21",OR(COUNTIF(P28:V28,Versiones!$G$8)>0, COUNTIF(P28:V28,Versiones!$H$8)>0, COUNTIF(P28:V28,Versiones!$I$8)>0), "Sprint 20",OR(COUNTIF(P28:V28,Versiones!$G$7)>0, COUNTIF(P28:V28,Versiones!$H$7)>0, COUNTIF(P28:V28,Versiones!$I$7)>0), "Sprint 19",OR(COUNTIF(P28:V28,Versiones!$G$6)>0, COUNTIF(P28:V28,Versiones!$H$6)>0, COUNTIF(P28:V28,Versiones!$I$6)>0), "Sprint 18",OR(COUNTIF(P28:V28,Versiones!$G$4)>0, COUNTIF(P28:V28,Versiones!$H$4)>0, COUNTIF(P28:V28,Versiones!$G$5)>0, COUNTIF(P28:V28,Versiones!$H$5)>0), "Sprint 17",OR(COUNTIF(P28:V28,Versiones!$G$2)>0, COUNTIF(P28:V28,Versiones!$H$2)>0, COUNTIF(P28:V28,Versiones!$G$3)>0, COUNTIF(P28:V28,Versiones!$H$3)>0), "Sprint 16", OR(COUNTIF(P28:V28,Versiones!$G$2)>0, COUNTIF(P28:V28,Versiones!$H$2)>0, COUNTIF(P28:V28,Versiones!$G$3)>0, COUNTIF(P28:V28,Versiones!$H$3)>0), "Sprint 16",TRUE, "")} -> Sprint 16 | AF28: ="v"&MAX( IFERROR(VALUE(MID(Jira__32[[#This Row],[Versiones corregidas]],2,99)),0), IFERROR(VALUE(MID(Jira__32[[#This Row],[Versiones corregidas_13]],2,99)),0), IFERROR(VALUE(MID(Jira__32[[#This Row],[Versiones corregidas_14]],2,99)),0) ) -> v0.5 | AG28: {=_xlfn.IFS(Jira__32[[#This Row],[¿En qué versión fue corregido?]]="v0","N/A",Jira__32[[#This Row],[¿En qué versión fue corregido?]]="v0.4","Sprint 16", Jira__32[[#This Row],[¿En qué versión fue corregido?]]="v0.5","Sprint 17", Jira__32[[#This Row],[¿En qué versión fue corregido?]]="v0.6","Sprint 18", Jira__32[[#This Row],[¿En qué versión fue corregido?]]="v0.7","Sprint 19", Jira__32[[#This Row],[¿En qué versión fue corregido?]]="v0.8","Sprint 20",Jira__32[[#This Row],[¿En qué versión fue corregido?]]="v0.9","Sprint 21", TRUE,"Desconocido")} -> Sprint 17 | AH28: {=_xlfn.IFS(COUNTIF(P28:V28, Versiones!$A$13)>0, "Funcional", COUNTIF(P28:V28, Versiones!$A$14)>0, "Configuración", COUNTIF(P28:V28, Versiones!$A$15)>0, "Look&Feel", COUNTIF(P28:V28, Versiones!$A$16)>0, "Integración", COUNTIF(P28:V28, Versiones!$A$17)>0, "Contenido/Datos", COUNTIF(P28:V28, Versiones!$A$18)>0, "Eventos_Cosmos", COUNTIF(P28:V28, Versiones!$A$19)>0, "Eventos_iOT", COUNTIF(P28:V28, Versiones!$A$20)>0, "Eventos_Fabric", TRUE, "No encontrado")} -> Look&Feel
A29: Error | B29: T20-882 | C29: 82878 | D29: BOT - [B+P] Navegación y menús: correcciones | E29: 87100 | F29: T20-1091 | G29: 4.- QA | H29: Medio | I29: READY FOR UAT | J29: T20 Sprint 16 2025 | K29: T20 Sprint 17 2025 | L29: T20 Sprint 18 2025 | M29: Backlog BUGS | P29: Funcional | Q29: QA-SmokeV0.4 | R29: T3B20_BOT | S29: Tested_In_DEV | T29: Tienda2.0 | W29: Ludo | X29: 45872.517 | Y29: v0.5 | Z29: v0.6 | AB29: =IF(LEFT(Jira__32[[#This Row],[Resumen]],3)="POS","POS",IF(LEFT(Jira__32[[#This Row],[Resumen]],3)="BOT","BOT","")) -> BOT | AC29: Juan Camilo Collantes Tovar | AE29: {=_xlfn.IFS(OR(COUNTIF(P29:V29,Versiones!$G$9)>0, COUNTIF(P29:V29,Versiones!$H$8)>0), "Sprint 21",OR(COUNTIF(P29:V29,Versiones!$G$8)>0, COUNTIF(P29:V29,Versiones!$H$8)>0, COUNTIF(P29:V29,Versiones!$I$8)>0), "Sprint 20",OR(COUNTIF(P29:V29,Versiones!$G$7)>0, COUNTIF(P29:V29,Versiones!$H$7)>0, COUNTIF(P29:V29,Versiones!$I$7)>0), "Sprint 19",OR(COUNTIF(P29:V29,Versiones!$G$6)>0, COUNTIF(P29:V29,Versiones!$H$6)>0, COUNTIF(P29:V29,Versiones!$I$6)>0), "Sprint 18",OR(COUNTIF(P29:V29,Versiones!$G$4)>0, COUNTIF(P29:V29,Versiones!$H$4)>0, COUNTIF(P29:V29,Versiones!$G$5)>0, COUNTIF(P29:V29,Versiones!$H$5)>0), "Sprint 17",OR(COUNTIF(P29:V29,Versiones!$G$2)>0, COUNTIF(P29:V29,Versiones!$H$2)>0, COUNTIF(P29:V29,Versiones!$G$3)>0, COUNTIF(P29:V29,Versiones!$H$3)>0), "Sprint 16", OR(COUNTIF(P29:V29,Versiones!$G$2)>0, COUNTIF(P29:V29,Versiones!$H$2)>0, COUNTIF(P29:V29,Versiones!$G$3)>0, COUNTIF(P29:V29,Versiones!$H$3)>0), "Sprint 16",TRUE, "")} -> Sprint 16 | AF29: ="v"&MAX( IFERROR(VALUE(MID(Jira__32[[#This Row],[Versiones corregidas]],2,99)),0), IFERROR(VALUE(MID(Jira__32[[#This Row],[Versiones corregidas_13]],2,99)),0), IFERROR(VALUE(MID(Jira__32[[#This Row],[Versiones corregidas_14]],2,99)),0) ) -> v0.6 | AG29: {=_xlfn.IFS(Jira__32[[#This Row],[¿En qué versión fue corregido?]]="v0","N/A",Jira__32[[#This Row],[¿En qué versión fue corregido?]]="v0.4","Sprint 16", Jira__32[[#This Row],[¿En qué versión fue corregido?]]="v0.5","Sprint 17", Jira__32[[#This Row],[¿En qué versión fue corregido?]]="v0.6","Sprint 18", Jira__32[[#This Row],[¿En qué versión fue corregido?]]="v0.7","Sprint 19", Jira__32[[#This Row],[¿En qué versión fue corregido?]]="v0.8","Sprint 20",Jira__32[[#This Row],[¿En qué versión fue corregido?]]="v0.9","Sprint 21", TRUE,"Desconocido")} -> Sprint 18 | AH29: {=_xlfn.IFS(COUNTIF(P29:V29, Versiones!$A$13)>0, "Funcional", COUNTIF(P29:V29, Versiones!$A$14)>0, "Configuración", COUNTIF(P29:V29, Versiones!$A$15)>0, "Look&Feel", COUNTIF(P29:V29, Versiones!$A$16)>0, "Integración", COUNTIF(P29:V29, Versiones!$A$17)>0, "Contenido/Datos", COUNTIF(P29:V29, Versiones!$A$18)>0, "Eventos_Cosmos", COUNTIF(P29:V29, Versiones!$A$19)>0, "Eventos_iOT", COUNTIF(P29:V29, Versiones!$A$20)>0, "Eventos_Fabric", TRUE, "No encontrado")} -> Funcional
A30: Error | B30: T20-879 | C30: 82873 | D30: BOT - Inicio de día: correcciones en el flujo | E30: 87100 | F30: T20-1091 | G30: 4.- QA | H30: Medio | I30: READY FOR UAT | J30: T20 Sprint 15 2025 | K30: T20 Sprint 16 2025 | L30: T20 Sprint 17 2025 | M30: T20 Sprint 18 2025 | N30: Backlog BUGS | P30: Funcional | Q30: QA-SmokeV0.4 | R30: T3B20_BOT | S30: Tienda2.0 | W30: Ludo | X30: 45872.511 | Y30: v0.5 | AB30: =IF(LEFT(Jira__32[[#This Row],[Resumen]],3)="POS","POS",IF(LEFT(Jira__32[[#This Row],[Resumen]],3)="BOT","BOT","")) -> BOT | AC30: Juan Camilo Collantes Tovar | AE30: {=_xlfn.IFS(OR(COUNTIF(P30:V30,Versiones!$G$9)>0, COUNTIF(P30:V30,Versiones!$H$8)>0), "Sprint 21",OR(COUNTIF(P30:V30,Versiones!$G$8)>0, COUNTIF(P30:V30,Versiones!$H$8)>0, COUNTIF(P30:V30,Versiones!$I$8)>0), "Sprint 20",OR(COUNTIF(P30:V30,Versiones!$G$7)>0, COUNTIF(P30:V30,Versiones!$H$7)>0, COUNTIF(P30:V30,Versiones!$I$7)>0), "Sprint 19",OR(COUNTIF(P30:V30,Versiones!$G$6)>0, COUNTIF(P30:V30,Versiones!$H$6)>0, COUNTIF(P30:V30,Versiones!$I$6)>0), "Sprint 18",OR(COUNTIF(P30:V30,Versiones!$G$4)>0, COUNTIF(P30:V30,Versiones!$H$4)>0, COUNTIF(P30:V30,Versiones!$G$5)>0, COUNTIF(P30:V30,Versiones!$H$5)>0), "Sprint 17",OR(COUNTIF(P30:V30,Versiones!$G$2)>0, COUNTIF(P30:V30,Versiones!$H$2)>0, COUNTIF(P30:V30,Versiones!$G$3)>0, COUNTIF(P30:V30,Versiones!$H$3)>0), "Sprint 16", OR(COUNTIF(P30:V30,Versiones!$G$2)>0, COUNTIF(P30:V30,Versiones!$H$2)>0, COUNTIF(P30:V30,Versiones!$G$3)>0, COUNTIF(P30:V30,Versiones!$H$3)>0), "Sprint 16",TRUE, "")} -> Sprint 16 | AF30: ="v"&MAX( IFERROR(VALUE(MID(Jira__32[[#This Row],[Versiones corregidas]],2,99)),0), IFERROR(VALUE(MID(Jira__32[[#This Row],[Versiones corregidas_13]],2,99)),0), IFERROR(VALUE(MID(Jira__32[[#This Row],[Versiones corregidas_14]],2,99)),0) ) -> v0.5 | AG30: {=_xlfn.IFS(Jira__32[[#This Row],[¿En qué versión fue corregido?]]="v0","N/A",Jira__32[[#This Row],[¿En qué versión fue corregido?]]="v0.4","Sprint 16", Jira__32[[#This Row],[¿En qué versión fue corregido?]]="v0.5","Sprint 17", Jira__32[[#This Row],[¿En qué versión fue corregido?]]="v0.6","Sprint 18", Jira__32[[#This Row],[¿En qué versión fue corregido?]]="v0.7","Sprint 19", Jira__32[[#This Row],[¿En qué versión fue corregido?]]="v0.8","Sprint 20",Jira__32[[#This Row],[¿En qué versión fue corregido?]]="v0.9","Sprint 21", TRUE,"Desconocido")} -> Sprint 17 | AH30: {=_xlfn.IFS(COUNTIF(P30:V30, Versiones!$A$13)>0, "Funcional", COUNTIF(P30:V30, Versiones!$A$14)>0, "Configuración", COUNTIF(P30:V30, Versiones!$A$15)>0, "Look&Feel", COUNTIF(P30:V30, Versiones!$A$16)>0, "Integración", COUNTIF(P30:V30, Versiones!$A$17)>0, "Contenido/Datos", COUNTIF(P30:V30, Versiones!$A$18)>0, "Eventos_Cosmos", COUNTIF(P30:V30, Versiones!$A$19)>0, "Eventos_iOT", COUNTIF(P30:V30, Versiones!$A$20)>0, "Eventos_Fabric", TRUE, "No encontrado")} -> Funcional
A31: Error | B31: T20-2094 | C31: 102710 | D31: Diferencias en tickets de venta - TC/Efectivo y Pago Mix | E31: 87100 | F31: T20-1091 | G31: 4.- QA | H31: Medio | I31: Tareas por hacer | J31: T20 Sprint 21 2025 | P31: Contenido/Datos | Q31: QA-IntegraciónV0.9 | W31: Carolina Rodríguez Soriano | X31: 45947.709 | AB31: =IF(LEFT(Jira__32[[#This Row],[Resumen]],3)="POS","POS",IF(LEFT(Jira__32[[#This Row],[Resumen]],3)="BOT","BOT","")) | AC31: Juan Munoz | AE31: {=_xlfn.IFS(OR(COUNTIF(P31:V31,Versiones!$G$9)>0, COUNTIF(P31:V31,Versiones!$H$8)>0), "Sprint 21",OR(COUNTIF(P31:V31,Versiones!$G$8)>0, COUNTIF(P31:V31,Versiones!$H$8)>0, COUNTIF(P31:V31,Versiones!$I$8)>0), "Sprint 20",OR(COUNTIF(P31:V31,Versiones!$G$7)>0, COUNTIF(P31:V31,Versiones!$H$7)>0, COUNTIF(P31:V31,Versiones!$I$7)>0), "Sprint 19",OR(COUNTIF(P31:V31,Versiones!$G$6)>0, COUNTIF(P31:V31,Versiones!$H$6)>0, COUNTIF(P31:V31,Versiones!$I$6)>0), "Sprint 18",OR(COUNTIF(P31:V31,Versiones!$G$4)>0, COUNTIF(P31:V31,Versiones!$H$4)>0, COUNTIF(P31:V31,Versiones!$G$5)>0, COUNTIF(P31:V31,Versiones!$H$5)>0), "Sprint 17",OR(COUNTIF(P31:V31,Versiones!$G$2)>0, COUNTIF(P31:V31,Versiones!$H$2)>0, COUNTIF(P31:V31,Versiones!$G$3)>0, COUNTIF(P31:V31,Versiones!$H$3)>0), "Sprint 16", OR(COUNTIF(P31:V31,Versiones!$G$2)>0, COUNTIF(P31:V31,Versiones!$H$2)>0, COUNTIF(P31:V31,Versiones!$G$3)>0, COUNTIF(P31:V31,Versiones!$H$3)>0), "Sprint 16",TRUE, "")} -> Sprint 21 | AF31: ="v"&MAX( IFERROR(VALUE(MID(Jira__32[[#This Row],[Versiones corregidas]],2,99)),0), IFERROR(VALUE(MID(Jira__32[[#This Row],[Versiones corregidas_13]],2,99)),0), IFERROR(VALUE(MID(Jira__32[[#This Row],[Versiones corregidas_14]],2,99)),0) ) -> v0 | AG31: {=_xlfn.IFS(Jira__32[[#This Row],[¿En qué versión fue corregido?]]="v0","N/A",Jira__32[[#This Row],[¿En qué versión fue corregido?]]="v0.4","Sprint 16", Jira__32[[#This Row],[¿En qué versión fue corregido?]]="v0.5","Sprint 17", Jira__32[[#This Row],[¿En qué versión fue corregido?]]="v0.6","Sprint 18", Jira__32[[#This Row],[¿En qué versión fue corregido?]]="v0.7","Sprint 19", Jira__32[[#This Row],[¿En qué versión fue corregido?]]="v0.8","Sprint 20",Jira__32[[#This Row],[¿En qué versión fue corregido?]]="v0.9","Sprint 21", TRUE,"Desconocido")} -> N/A | AH31: {=_xlfn.IFS(COUNTIF(P31:V31, Versiones!$A$13)>0, "Funcional", COUNTIF(P31:V31, Versiones!$A$14)>0, "Configuración", COUNTIF(P31:V31, Versiones!$A$15)>0, "Look&Feel", COUNTIF(P31:V31, Versiones!$A$16)>0, "Integración", COUNTIF(P31:V31, Versiones!$A$17)>0, "Contenido/Datos", COUNTIF(P31:V31, Versiones!$A$18)>0, "Eventos_Cosmos", COUNTIF(P31:V31, Versiones!$A$19)>0, "Eventos_iOT", COUNTIF(P31:V31, Versiones!$A$20)>0, "Eventos_Fabric", TRUE, "No encontrado")} -> Contenido/Datos
A32: Error | B32: T20-2093 | C32: 102674 | D32: BOT - Panel Productos no se actualiza | E32: 87100 | F32: T20-1091 | G32: 4.- QA | H32: Alta | I32: Tareas por hacer | J32: T20 Sprint 21 2025 | P32: Funcional | Q32: QA-IntegraciónV0.9 | W32: Daniela Soto | X32: 45947.628 | AB32: =IF(LEFT(Jira__32[[#This Row],[Resumen]],3)="POS","POS",IF(LEFT(Jira__32[[#This Row],[Resumen]],3)="BOT","BOT","")) -> BOT | AC32: Juan Munoz | AE32: {=_xlfn.IFS(OR(COUNTIF(P32:V32,Versiones!$G$9)>0, COUNTIF(P32:V32,Versiones!$H$8)>0), "Sprint 21",OR(COUNTIF(P32:V32,Versiones!$G$8)>0, COUNTIF(P32:V32,Versiones!$H$8)>0, COUNTIF(P32:V32,Versiones!$I$8)>0), "Sprint 20",OR(COUNTIF(P32:V32,Versiones!$G$7)>0, COUNTIF(P32:V32,Versiones!$H$7)>0, COUNTIF(P32:V32,Versiones!$I$7)>0), "Sprint 19",OR(COUNTIF(P32:V32,Versiones!$G$6)>0, COUNTIF(P32:V32,Versiones!$H$6)>0, COUNTIF(P32:V32,Versiones!$I$6)>0), "Sprint 18",OR(COUNTIF(P32:V32,Versiones!$G$4)>0, COUNTIF(P32:V32,Versiones!$H$4)>0, COUNTIF(P32:V32,Versiones!$G$5)>0, COUNTIF(P32:V32,Versiones!$H$5)>0), "Sprint 17",OR(COUNTIF(P32:V32,Versiones!$G$2)>0, COUNTIF(P32:V32,Versiones!$H$2)>0, COUNTIF(P32:V32,Versiones!$G$3)>0, COUNTIF(P32:V32,Versiones!$H$3)>0), "Sprint 16", OR(COUNTIF(P32:V32,Versiones!$G$2)>0, COUNTIF(P32:V32,Versiones!$H$2)>0, COUNTIF(P32:V32,Versiones!$G$3)>0, COUNTIF(P32:V32,Versiones!$H$3)>0), "Sprint 16",TRUE, "")} -> Sprint 21 | AF32: ="v"&MAX( IFERROR(VALUE(MID(Jira__32[[#This Row],[Versiones corregidas]],2,99)),0), IFERROR(VALUE(MID(Jira__32[[#This Row],[Versiones corregidas_13]],2,99)),0), IFERROR(VALUE(MID(Jira__32[[#This Row],[Versiones corregidas_14]],2,99)),0) ) -> v0 | AG32: {=_xlfn.IFS(Jira__32[[#This Row],[¿En qué versión fue corregido?]]="v0","N/A",Jira__32[[#This Row],[¿En qué versión fue corregido?]]="v0.4","Sprint 16", Jira__32[[#This Row],[¿En qué versión fue corregido?]]="v0.5","Sprint 17", Jira__32[[#This Row],[¿En qué versión fue corregido?]]="v0.6","Sprint 18", Jira__32[[#This Row],[¿En qué versión fue corregido?]]="v0.7","Sprint 19", Jira__32[[#This Row],[¿En qué versión fue corregido?]]="v0.8","Sprint 20",Jira__32[[#This Row],[¿En qué versión fue corregido?]]="v0.9","Sprint 21", TRUE,"Desconocido")} -> N/A | AH32: {=_xlfn.IFS(COUNTIF(P32:V32, Versiones!$A$13)>0, "Funcional", COUNTIF(P32:V32, Versiones!$A$14)>0, "Configuración", COUNTIF(P32:V32, Versiones!$A$15)>0, "Look&Feel", COUNTIF(P32:V32, Versiones!$A$16)>0, "Integración", COUNTIF(P32:V32, Versiones!$A$17)>0, "Contenido/Datos", COUNTIF(P32:V32, Versiones!$A$18)>0, "Eventos_Cosmos", COUNTIF(P32:V32, Versiones!$A$19)>0, "Eventos_iOT", COUNTIF(P32:V32, Versiones!$A$20)>0, "Eventos_Fabric", TRUE, "No encontrado")} -> Funcional
A33: Error | B33: T20-2089 | C33: 102586 | D33: POS - Pantalla principal - Info en inglés | E33: 87100 | F33: T20-1091 | G33: 4.- QA | H33: Medio | I33: Tareas por hacer | P33: Look&Feel | Q33: QA-IntegraciónV0.9 | W33: Daniela Soto | X33: 45947.399 | AB33: =IF(LEFT(Jira__32[[#This Row],[Resumen]],3)="POS","POS",IF(LEFT(Jira__32[[#This Row],[Resumen]],3)="BOT","BOT","")) -> POS | AC33: Juan Munoz | AE33: {=_xlfn.IFS(OR(COUNTIF(P33:V33,Versiones!$G$9)>0, COUNTIF(P33:V33,Versiones!$H$8)>0), "Sprint 21",OR(COUNTIF(P33:V33,Versiones!$G$8)>0, COUNTIF(P33:V33,Versiones!$H$8)>0, COUNTIF(P33:V33,Versiones!$I$8)>0), "Sprint 20",OR(COUNTIF(P33:V33,Versiones!$G$7)>0, COUNTIF(P33:V33,Versiones!$H$7)>0, COUNTIF(P33:V33,Versiones!$I$7)>0), "Sprint 19",OR(COUNTIF(P33:V33,Versiones!$G$6)>0, COUNTIF(P33:V33,Versiones!$H$6)>0, COUNTIF(P33:V33,Versiones!$I$6)>0), "Sprint 18",OR(COUNTIF(P33:V33,Versiones!$G$4)>0, COUNTIF(P33:V33,Versiones!$H$4)>0, COUNTIF(P33:V33,Versiones!$G$5)>0, COUNTIF(P33:V33,Versiones!$H$5)>0), "Sprint 17",OR(COUNTIF(P33:V33,Versiones!$G$2)>0, COUNTIF(P33:V33,Versiones!$H$2)>0, COUNTIF(P33:V33,Versiones!$G$3)>0, COUNTIF(P33:V33,Versiones!$H$3)>0), "Sprint 16", OR(COUNTIF(P33:V33,Versiones!$G$2)>0, COUNTIF(P33:V33,Versiones!$H$2)>0, COUNTIF(P33:V33,Versiones!$G$3)>0, COUNTIF(P33:V33,Versiones!$H$3)>0), "Sprint 16",TRUE, "")} -> Sprint 21 | AF33: ="v"&MAX( IFERROR(VALUE(MID(Jira__32[[#This Row],[Versiones corregidas]],2,99)),0), IFERROR(VALUE(MID(Jira__32[[#This Row],[Versiones corregidas_13]],2,99)),0), IFERROR(VALUE(MID(Jira__32[[#This Row],[Versiones corregidas_14]],2,99)),0) ) -> v0 | AG33: {=_xlfn.IFS(Jira__32[[#This Row],[¿En qué versión fue corregido?]]="v0","N/A",Jira__32[[#This Row],[¿En qué versión fue corregido?]]="v0.4","Sprint 16", Jira__32[[#This Row],[¿En qué versión fue corregido?]]="v0.5","Sprint 17", Jira__32[[#This Row],[¿En qué versión fue corregido?]]="v0.6","Sprint 18", Jira__32[[#This Row],[¿En qué versión fue corregido?]]="v0.7","Sprint 19", Jira__32[[#This Row],[¿En qué versión fue corregido?]]="v0.8","Sprint 20",Jira__32[[#This Row],[¿En qué versión fue corregido?]]="v0.9","Sprint 21", TRUE,"Desconocido")} -> N/A | AH33: {=_xlfn.IFS(COUNTIF(P33:V33, Versiones!$A$13)>0, "Funcional", COUNTIF(P33:V33, Versiones!$A$14)>0, "Configuración", COUNTIF(P33:V33, Versiones!$A$15)>0, "Look&Feel", COUNTIF(P33:V33, Versiones!$A$16)>0, "Integración", COUNTIF(P33:V33, Versiones!$A$17)>0, "Contenido/Datos", COUNTIF(P33:V33, Versiones!$A$18)>0, "Eventos_Cosmos", COUNTIF(P33:V33, Versiones!$A$19)>0, "Eventos_iOT", COUNTIF(P33:V33, Versiones!$A$20)>0, "Eventos_Fabric", TRUE, "No encontrado")} -> Look&Feel
A34: Error | B34: T20-2088 | C34: 102584 | D34: POS - Checar precio - Info en Inglés | E34: 87100 | F34: T20-1091 | G34: 4.- QA | H34: Medio | I34: Tareas por hacer | P34: Look&Feel | Q34: QA-IntegraciónV0.9 | W34: Daniela Soto | X34: 45947.383 | AB34: =IF(LEFT(Jira__32[[#This Row],[Resumen]],3)="POS","POS",IF(LEFT(Jira__32[[#This Row],[Resumen]],3)="BOT","BOT","")) -> POS | AC34: Andres Vergara | AE34: {=_xlfn.IFS(OR(COUNTIF(P34:V34,Versiones!$G$9)>0, COUNTIF(P34:V34,Versiones!$H$8)>0), "Sprint 21",OR(COUNTIF(P34:V34,Versiones!$G$8)>0, COUNTIF(P34:V34,Versiones!$H$8)>0, COUNTIF(P34:V34,Versiones!$I$8)>0), "Sprint 20",OR(COUNTIF(P34:V34,Versiones!$G$7)>0, COUNTIF(P34:V34,Versiones!$H$7)>0, COUNTIF(P34:V34,Versiones!$I$7)>0), "Sprint 19",OR(COUNTIF(P34:V34,Versiones!$G$6)>0, COUNTIF(P34:V34,Versiones!$H$6)>0, COUNTIF(P34:V34,Versiones!$I$6)>0), "Sprint 18",OR(COUNTIF(P34:V34,Versiones!$G$4)>0, COUNTIF(P34:V34,Versiones!$H$4)>0, COUNTIF(P34:V34,Versiones!$G$5)>0, COUNTIF(P34:V34,Versiones!$H$5)>0), "Sprint 17",OR(COUNTIF(P34:V34,Versiones!$G$2)>0, COUNTIF(P34:V34,Versiones!$H$2)>0, COUNTIF(P34:V34,Versiones!$G$3)>0, COUNTIF(P34:V34,Versiones!$H$3)>0), "Sprint 16", OR(COUNTIF(P34:V34,Versiones!$G$2)>0, COUNTIF(P34:V34,Versiones!$H$2)>0, COUNTIF(P34:V34,Versiones!$G$3)>0, COUNTIF(P34:V34,Versiones!$H$3)>0), "Sprint 16",TRUE, "")} -> Sprint 21 | AF34: ="v"&MAX( IFERROR(VALUE(MID(Jira__32[[#This Row],[Versiones corregidas]],2,99)),0), IFERROR(VALUE(MID(Jira__32[[#This Row],[Versiones corregidas_13]],2,99)),0), IFERROR(VALUE(MID(Jira__32[[#This Row],[Versiones corregidas_14]],2,99)),0) ) -> v0 | AG34: {=_xlfn.IFS(Jira__32[[#This Row],[¿En qué versión fue corregido?]]="v0","N/A",Jira__32[[#This Row],[¿En qué versión fue corregido?]]="v0.4","Sprint 16", Jira__32[[#This Row],[¿En qué versión fue corregido?]]="v0.5","Sprint 17", Jira__32[[#This Row],[¿En qué versión fue corregido?]]="v0.6","Sprint 18", Jira__32[[#This Row],[¿En qué versión fue corregido?]]="v0.7","Sprint 19", Jira__32[[#This Row],[¿En qué versión fue corregido?]]="v0.8","Sprint 20",Jira__32[[#This Row],[¿En qué versión fue corregido?]]="v0.9","Sprint 21", TRUE,"Desconocido")} -> N/A | AH34: {=_xlfn.IFS(COUNTIF(P34:V34, Versiones!$A$13)>0, "Funcional", COUNTIF(P34:V34, Versiones!$A$14)>0, "Configuración", COUNTIF(P34:V34, Versiones!$A$15)>0, "Look&Feel", COUNTIF(P34:V34, Versiones!$A$16)>0, "Integración", COUNTIF(P34:V34, Versiones!$A$17)>0, "Contenido/Datos", COUNTIF(P34:V34, Versiones!$A$18)>0, "Eventos_Cosmos", COUNTIF(P34:V34, Versiones!$A$19)>0, "Eventos_iOT", COUNTIF(P34:V34, Versiones!$A$20)>0, "Eventos_Fabric", TRUE, "No encontrado")} -> Look&Feel
A35: Error | B35: T20-2066 | C35: 102295 | D35: BOT - Modal pie de camión en inglés | E35: 87100 | F35: T20-1091 | G35: 4.- QA | H35: Medio | I35: Tareas por hacer | P35: Look&Feel | Q35: QA-IntegraciónV0.9 | W35: Daniela Soto | X35: 45946.557 | AB35: =IF(LEFT(Jira__32[[#This Row],[Resumen]],3)="POS","POS",IF(LEFT(Jira__32[[#This Row],[Resumen]],3)="BOT","BOT","")) -> BOT | AC35: Juan Munoz | AE35: {=_xlfn.IFS(OR(COUNTIF(P35:V35,Versiones!$G$9)>0, COUNTIF(P35:V35,Versiones!$H$8)>0), "Sprint 21",OR(COUNTIF(P35:V35,Versiones!$G$8)>0, COUNTIF(P35:V35,Versiones!$H$8)>0, COUNTIF(P35:V35,Versiones!$I$8)>0), "Sprint 20",OR(COUNTIF(P35:V35,Versiones!$G$7)>0, COUNTIF(P35:V35,Versiones!$H$7)>0, COUNTIF(P35:V35,Versiones!$I$7)>0), "Sprint 19",OR(COUNTIF(P35:V35,Versiones!$G$6)>0, COUNTIF(P35:V35,Versiones!$H$6)>0, COUNTIF(P35:V35,Versiones!$I$6)>0), "Sprint 18",OR(COUNTIF(P35:V35,Versiones!$G$4)>0, COUNTIF(P35:V35,Versiones!$H$4)>0, COUNTIF(P35:V35,Versiones!$G$5)>0, COUNTIF(P35:V35,Versiones!$H$5)>0), "Sprint 17",OR(COUNTIF(P35:V35,Versiones!$G$2)>0, COUNTIF(P35:V35,Versiones!$H$2)>0, COUNTIF(P35:V35,Versiones!$G$3)>0, COUNTIF(P35:V35,Versiones!$H$3)>0), "Sprint 16", OR(COUNTIF(P35:V35,Versiones!$G$2)>0, COUNTIF(P35:V35,Versiones!$H$2)>0, COUNTIF(P35:V35,Versiones!$G$3)>0, COUNTIF(P35:V35,Versiones!$H$3)>0), "Sprint 16",TRUE, "")} -> Sprint 21 | AF35: ="v"&MAX( IFERROR(VALUE(MID(Jira__32[[#This Row],[Versiones corregidas]],2,99)),0), IFERROR(VALUE(MID(Jira__32[[#This Row],[Versiones corregidas_13]],2,99)),0), IFERROR(VALUE(MID(Jira__32[[#This Row],[Versiones corregidas_14]],2,99)),0) ) -> v0 | AG35: {=_xlfn.IFS(Jira__32[[#This Row],[¿En qué versión fue corregido?]]="v0","N/A",Jira__32[[#This Row],[¿En qué versión fue corregido?]]="v0.4","Sprint 16", Jira__32[[#This Row],[¿En qué versión fue corregido?]]="v0.5","Sprint 17", Jira__32[[#This Row],[¿En qué versión fue corregido?]]="v0.6","Sprint 18", Jira__32[[#This Row],[¿En qué versión fue corregido?]]="v0.7","Sprint 19", Jira__32[[#This Row],[¿En qué versión fue corregido?]]="v0.8","Sprint 20",Jira__32[[#This Row],[¿En qué versión fue corregido?]]="v0.9","Sprint 21", TRUE,"Desconocido")} -> N/A | AH35: {=_xlfn.IFS(COUNTIF(P35:V35, Versiones!$A$13)>0, "Funcional", COUNTIF(P35:V35, Versiones!$A$14)>0, "Configuración", COUNTIF(P35:V35, Versiones!$A$15)>0, "Look&Feel", COUNTIF(P35:V35, Versiones!$A$16)>0, "Integración", COUNTIF(P35:V35, Versiones!$A$17)>0, "Contenido/Datos", COUNTIF(P35:V35, Versiones!$A$18)>0, "Eventos_Cosmos", COUNTIF(P35:V35, Versiones!$A$19)>0, "Eventos_iOT", COUNTIF(P35:V35, Versiones!$A$20)>0, "Eventos_Fabric", TRUE, "No encontrado")} -> Look&Feel
A36: Error | B36: T20-1994 | C36: 99976 | D36: BOT - Ctrl+N - No cierra sesión | E36: 87100 | F36: T20-1091 | G36: 4.- QA | H36: Medio | I36: Tareas por hacer | J36: Backlog BUGS | P36: Funcional | Q36: QA-IntegraciónV0.8 | W36: Daniela Soto | X36: 45937.669 | AB36: =IF(LEFT(Jira__32[[#This Row],[Resumen]],3)="POS","POS",IF(LEFT(Jira__32[[#This Row],[Resumen]],3)="BOT","BOT","")) -> BOT | AC36: Andres Vergara | AE36: {=_xlfn.IFS(OR(COUNTIF(P36:V36,Versiones!$G$9)>0, COUNTIF(P36:V36,Versiones!$H$8)>0), "Sprint 21",OR(COUNTIF(P36:V36,Versiones!$G$8)>0, COUNTIF(P36:V36,Versiones!$H$8)>0, COUNTIF(P36:V36,Versiones!$I$8)>0), "Sprint 20",OR(COUNTIF(P36:V36,Versiones!$G$7)>0, COUNTIF(P36:V36,Versiones!$H$7)>0, COUNTIF(P36:V36,Versiones!$I$7)>0), "Sprint 19",OR(COUNTIF(P36:V36,Versiones!$G$6)>0, COUNTIF(P36:V36,Versiones!$H$6)>0, COUNTIF(P36:V36,Versiones!$I$6)>0), "Sprint 18",OR(COUNTIF(P36:V36,Versiones!$G$4)>0, COUNTIF(P36:V36,Versiones!$H$4)>0, COUNTIF(P36:V36,Versiones!$G$5)>0, COUNTIF(P36:V36,Versiones!$H$5)>0), "Sprint 17",OR(COUNTIF(P36:V36,Versiones!$G$2)>0, COUNTIF(P36:V36,Versiones!$H$2)>0, COUNTIF(P36:V36,Versiones!$G$3)>0, COUNTIF(P36:V36,Versiones!$H$3)>0), "Sprint 16", OR(COUNTIF(P36:V36,Versiones!$G$2)>0, COUNTIF(P36:V36,Versiones!$H$2)>0, COUNTIF(P36:V36,Versiones!$G$3)>0, COUNTIF(P36:V36,Versiones!$H$3)>0), "Sprint 16",TRUE, "")} -> Sprint 20 | AF36: ="v"&MAX( IFERROR(VALUE(MID(Jira__32[[#This Row],[Versiones corregidas]],2,99)),0), IFERROR(VALUE(MID(Jira__32[[#This Row],[Versiones corregidas_13]],2,99)),0), IFERROR(VALUE(MID(Jira__32[[#This Row],[Versiones corregidas_14]],2,99)),0) ) -> v0 | AG36: {=_xlfn.IFS(Jira__32[[#This Row],[¿En qué versión fue corregido?]]="v0","N/A",Jira__32[[#This Row],[¿En qué versión fue corregido?]]="v0.4","Sprint 16", Jira__32[[#This Row],[¿En qué versión fue corregido?]]="v0.5","Sprint 17", Jira__32[[#This Row],[¿En qué versión fue corregido?]]="v0.6","Sprint 18", Jira__32[[#This Row],[¿En qué versión fue corregido?]]="v0.7","Sprint 19", Jira__32[[#This Row],[¿En qué versión fue corregido?]]="v0.8","Sprint 20",Jira__32[[#This Row],[¿En qué versión fue corregido?]]="v0.9","Sprint 21", TRUE,"Desconocido")} -> N/A | AH36: {=_xlfn.IFS(COUNTIF(P36:V36, Versiones!$A$13)>0, "Funcional", COUNTIF(P36:V36, Versiones!$A$14)>0, "Configuración", COUNTIF(P36:V36, Versiones!$A$15)>0, "Look&Feel", COUNTIF(P36:V36, Versiones!$A$16)>0, "Integración", COUNTIF(P36:V36, Versiones!$A$17)>0, "Contenido/Datos", COUNTIF(P36:V36, Versiones!$A$18)>0, "Eventos_Cosmos", COUNTIF(P36:V36, Versiones!$A$19)>0, "Eventos_iOT", COUNTIF(P36:V36, Versiones!$A$20)>0, "Eventos_Fabric", TRUE, "No encontrado")} -> Funcional
A37: Error | B37: T20-1993 | C37: 99972 | D37: POS_Evento POS_Pago con Tarjeta de débito llega a Iothub sin tipo de pago | E37: 87100 | F37: T20-1091 | G37: 4.- QA | H37: Alta | I37: Tareas por hacer | J37: T20 Sprint 21 2025 | P37: Eventos_iOT | Q37: Look&Feel | R37: QA-IntegraciónV0.8 | W37: Yubisleinys Mora Vega | X37: 45937.665 | Y37: v0.8 | AB37: =IF(LEFT(Jira__32[[#This Row],[Resumen]],3)="POS","POS",IF(LEFT(Jira__32[[#This Row],[Resumen]],3)="BOT","BOT","")) -> POS | AC37: Emiliano Fraile | AE37: {=_xlfn.IFS(OR(COUNTIF(P37:V37,Versiones!$G$9)>0, COUNTIF(P37:V37,Versiones!$H$8)>0), "Sprint 21",OR(COUNTIF(P37:V37,Versiones!$G$8)>0, COUNTIF(P37:V37,Versiones!$H$8)>0, COUNTIF(P37:V37,Versiones!$I$8)>0), "Sprint 20",OR(COUNTIF(P37:V37,Versiones!$G$7)>0, COUNTIF(P37:V37,Versiones!$H$7)>0, COUNTIF(P37:V37,Versiones!$I$7)>0), "Sprint 19",OR(COUNTIF(P37:V37,Versiones!$G$6)>0, COUNTIF(P37:V37,Versiones!$H$6)>0, COUNTIF(P37:V37,Versiones!$I$6)>0), "Sprint 18",OR(COUNTIF(P37:V37,Versiones!$G$4)>0, COUNTIF(P37:V37,Versiones!$H$4)>0, COUNTIF(P37:V37,Versiones!$G$5)>0, COUNTIF(P37:V37,Versiones!$H$5)>0), "Sprint 17",OR(COUNTIF(P37:V37,Versiones!$G$2)>0, COUNTIF(P37:V37,Versiones!$H$2)>0, COUNTIF(P37:V37,Versiones!$G$3)>0, COUNTIF(P37:V37,Versiones!$H$3)>0), "Sprint 16", OR(COUNTIF(P37:V37,Versiones!$G$2)>0, COUNTIF(P37:V37,Versiones!$H$2)>0, COUNTIF(P37:V37,Versiones!$G$3)>0, COUNTIF(P37:V37,Versiones!$H$3)>0), "Sprint 16",TRUE, "")} -> Sprint 20 | AF37: ="v"&MAX( IFERROR(VALUE(MID(Jira__32[[#This Row],[Versiones corregidas]],2,99)),0), IFERROR(VALUE(MID(Jira__32[[#This Row],[Versiones corregidas_13]],2,99)),0), IFERROR(VALUE(MID(Jira__32[[#This Row],[Versiones corregidas_14]],2,99)),0) ) -> v0.8 | AG37: {=_xlfn.IFS(Jira__32[[#This Row],[¿En qué versión fue corregido?]]="v0","N/A",Jira__32[[#This Row],[¿En qué versión fue corregido?]]="v0.4","Sprint 16", Jira__32[[#This Row],[¿En qué versión fue corregido?]]="v0.5","Sprint 17", Jira__32[[#This Row],[¿En qué versión fue corregido?]]="v0.6","Sprint 18", Jira__32[[#This Row],[¿En qué versión fue corregido?]]="v0.7","Sprint 19", Jira__32[[#This Row],[¿En qué versión fue corregido?]]="v0.8","Sprint 20",Jira__32[[#This Row],[¿En qué versión fue corregido?]]="v0.9","Sprint 21", TRUE,"Desconocido")} -> Sprint 20 | AH37: {=_xlfn.IFS(COUNTIF(P37:V37, Versiones!$A$13)>0, "Funcional", COUNTIF(P37:V37, Versiones!$A$14)>0, "Configuración", COUNTIF(P37:V37, Versiones!$A$15)>0, "Look&Feel", COUNTIF(P37:V37, Versiones!$A$16)>0, "Integración", COUNTIF(P37:V37, Versiones!$A$17)>0, "Contenido/Datos", COUNTIF(P37:V37, Versiones!$A$18)>0, "Eventos_Cosmos", COUNTIF(P37:V37, Versiones!$A$19)>0, "Eventos_iOT", COUNTIF(P37:V37, Versiones!$A$20)>0, "Eventos_Fabric", TRUE, "No encontrado")} -> Look&Feel
A38: Error | B38: T20-1992 | C38: 99963 | D38: POS_Evento POS_Pago con Efectivo llega a Iothub sin tipo de pago | E38: 87100 | F38: T20-1091 | G38: 4.- QA | H38: Alta | I38: Tareas por hacer | J38: T20 Sprint 21 2025 | P38: Eventos_iOT | Q38: Look&Feel | R38: QA-IntegraciónV0.8 | W38: Yubisleinys Mora Vega | X38: 45937.654 | Y38: v0.8 | AB38: =IF(LEFT(Jira__32[[#This Row],[Resumen]],3)="POS","POS",IF(LEFT(Jira__32[[#This Row],[Resumen]],3)="BOT","BOT","")) -> POS | AC38: Juan Munoz | AE38: {=_xlfn.IFS(OR(COUNTIF(P38:V38,Versiones!$G$9)>0, COUNTIF(P38:V38,Versiones!$H$8)>0), "Sprint 21",OR(COUNTIF(P38:V38,Versiones!$G$8)>0, COUNTIF(P38:V38,Versiones!$H$8)>0, COUNTIF(P38:V38,Versiones!$I$8)>0), "Sprint 20",OR(COUNTIF(P38:V38,Versiones!$G$7)>0, COUNTIF(P38:V38,Versiones!$H$7)>0, COUNTIF(P38:V38,Versiones!$I$7)>0), "Sprint 19",OR(COUNTIF(P38:V38,Versiones!$G$6)>0, COUNTIF(P38:V38,Versiones!$H$6)>0, COUNTIF(P38:V38,Versiones!$I$6)>0), "Sprint 18",OR(COUNTIF(P38:V38,Versiones!$G$4)>0, COUNTIF(P38:V38,Versiones!$H$4)>0, COUNTIF(P38:V38,Versiones!$G$5)>0, COUNTIF(P38:V38,Versiones!$H$5)>0), "Sprint 17",OR(COUNTIF(P38:V38,Versiones!$G$2)>0, COUNTIF(P38:V38,Versiones!$H$2)>0, COUNTIF(P38:V38,Versiones!$G$3)>0, COUNTIF(P38:V38,Versiones!$H$3)>0), "Sprint 16", OR(COUNTIF(P38:V38,Versiones!$G$2)>0, COUNTIF(P38:V38,Versiones!$H$2)>0, COUNTIF(P38:V38,Versiones!$G$3)>0, COUNTIF(P38:V38,Versiones!$H$3)>0), "Sprint 16",TRUE, "")} -> Sprint 20 | AF38: ="v"&MAX( IFERROR(VALUE(MID(Jira__32[[#This Row],[Versiones corregidas]],2,99)),0), IFERROR(VALUE(MID(Jira__32[[#This Row],[Versiones corregidas_13]],2,99)),0), IFERROR(VALUE(MID(Jira__32[[#This Row],[Versiones corregidas_14]],2,99)),0) ) -> v0.8 | AG38: {=_xlfn.IFS(Jira__32[[#This Row],[¿En qué versión fue corregido?]]="v0","N/A",Jira__32[[#This Row],[¿En qué versión fue corregido?]]="v0.4","Sprint 16", Jira__32[[#This Row],[¿En qué versión fue corregido?]]="v0.5","Sprint 17", Jira__32[[#This Row],[¿En qué versión fue corregido?]]="v0.6","Sprint 18", Jira__32[[#This Row],[¿En qué versión fue corregido?]]="v0.7","Sprint 19", Jira__32[[#This Row],[¿En qué versión fue corregido?]]="v0.8","Sprint 20",Jira__32[[#This Row],[¿En qué versión fue corregido?]]="v0.9","Sprint 21", TRUE,"Desconocido")} -> Sprint 20 | AH38: {=_xlfn.IFS(COUNTIF(P38:V38, Versiones!$A$13)>0, "Funcional", COUNTIF(P38:V38, Versiones!$A$14)>0, "Configuración", COUNTIF(P38:V38, Versiones!$A$15)>0, "Look&Feel", COUNTIF(P38:V38, Versiones!$A$16)>0, "Integración", COUNTIF(P38:V38, Versiones!$A$17)>0, "Contenido/Datos", COUNTIF(P38:V38, Versiones!$A$18)>0, "Eventos_Cosmos", COUNTIF(P38:V38, Versiones!$A$19)>0, "Eventos_iOT", COUNTIF(P38:V38, Versiones!$A$20)>0, "Eventos_Fabric", TRUE, "No encontrado")} -> Look&Feel
A39: Error | B39: T20-1981 | C39: 99800 | D39: BOT - Error en modal "Entrada a Pie de camión" | E39: 87100 | F39: T20-1091 | G39: 4.- QA | H39: Más alta | I39: Tareas por hacer | J39: T20 Sprint 21 2025 | P39: Funcional | Q39: QA-IntegraciónV0.8 | W39: Daniela Soto | X39: 45937.373 | AB39: =IF(LEFT(Jira__32[[#This Row],[Resumen]],3)="POS","POS",IF(LEFT(Jira__32[[#This Row],[Resumen]],3)="BOT","BOT","")) -> BOT | AC39: Sergio Ordaz Romero | AE39: {=_xlfn.IFS(OR(COUNTIF(P39:V39,Versiones!$G$9)>0, COUNTIF(P39:V39,Versiones!$H$8)>0), "Sprint 21",OR(COUNTIF(P39:V39,Versiones!$G$8)>0, COUNTIF(P39:V39,Versiones!$H$8)>0, COUNTIF(P39:V39,Versiones!$I$8)>0), "Sprint 20",OR(COUNTIF(P39:V39,Versiones!$G$7)>0, COUNTIF(P39:V39,Versiones!$H$7)>0, COUNTIF(P39:V39,Versiones!$I$7)>0), "Sprint 19",OR(COUNTIF(P39:V39,Versiones!$G$6)>0, COUNTIF(P39:V39,Versiones!$H$6)>0, COUNTIF(P39:V39,Versiones!$I$6)>0), "Sprint 18",OR(COUNTIF(P39:V39,Versiones!$G$4)>0, COUNTIF(P39:V39,Versiones!$H$4)>0, COUNTIF(P39:V39,Versiones!$G$5)>0, COUNTIF(P39:V39,Versiones!$H$5)>0), "Sprint 17",OR(COUNTIF(P39:V39,Versiones!$G$2)>0, COUNTIF(P39:V39,Versiones!$H$2)>0, COUNTIF(P39:V39,Versiones!$G$3)>0, COUNTIF(P39:V39,Versiones!$H$3)>0), "Sprint 16", OR(COUNTIF(P39:V39,Versiones!$G$2)>0, COUNTIF(P39:V39,Versiones!$H$2)>0, COUNTIF(P39:V39,Versiones!$G$3)>0, COUNTIF(P39:V39,Versiones!$H$3)>0), "Sprint 16",TRUE, "")} -> Sprint 20 | AF39: ="v"&MAX( IFERROR(VALUE(MID(Jira__32[[#This Row],[Versiones corregidas]],2,99)),0), IFERROR(VALUE(MID(Jira__32[[#This Row],[Versiones corregidas_13]],2,99)),0), IFERROR(VALUE(MID(Jira__32[[#This Row],[Versiones corregidas_14]],2,99)),0) ) -> v0 | AG39: {=_xlfn.IFS(Jira__32[[#This Row],[¿En qué versión fue corregido?]]="v0","N/A",Jira__32[[#This Row],[¿En qué versión fue corregido?]]="v0.4","Sprint 16", Jira__32[[#This Row],[¿En qué versión fue corregido?]]="v0.5","Sprint 17", Jira__32[[#This Row],[¿En qué versión fue corregido?]]="v0.6","Sprint 18", Jira__32[[#This Row],[¿En qué versión fue corregido?]]="v0.7","Sprint 19", Jira__32[[#This Row],[¿En qué versión fue corregido?]]="v0.8","Sprint 20",Jira__32[[#This Row],[¿En qué versión fue corregido?]]="v0.9","Sprint 21", TRUE,"Desconocido")} -> N/A | AH39: {=_xlfn.IFS(COUNTIF(P39:V39, Versiones!$A$13)>0, "Funcional", COUNTIF(P39:V39, Versiones!$A$14)>0, "Configuración", COUNTIF(P39:V39, Versiones!$A$15)>0, "Look&Feel", COUNTIF(P39:V39, Versiones!$A$16)>0, "Integración", COUNTIF(P39:V39, Versiones!$A$17)>0, "Contenido/Datos", COUNTIF(P39:V39, Versiones!$A$18)>0, "Eventos_Cosmos", COUNTIF(P39:V39, Versiones!$A$19)>0, "Eventos_iOT", COUNTIF(P39:V39, Versiones!$A$20)>0, "Eventos_Fabric", TRUE, "No encontrado")} -> Funcional
A40: Error | B40: T20-1976 | C40: 99744 | D40: BOT - Productos - Columnas sin filtros | E40: 87100 | F40: T20-1091 | G40: 4.- QA | H40: Alta | I40: Cancelado | J40: T20 Sprint 21 2025 | P40: Funcional | Q40: QA-IntegraciónV0.8 | W40: Daniela Soto | X40: 45936.699 | AB40: =IF(LEFT(Jira__32[[#This Row],[Resumen]],3)="POS","POS",IF(LEFT(Jira__32[[#This Row],[Resumen]],3)="BOT","BOT","")) -> BOT | AC40: Cancelado | AD40: Emiliano Fraile | AE40: {=_xlfn.IFS(OR(COUNTIF(P40:V40,Versiones!$G$9)>0, COUNTIF(P40:V40,Versiones!$H$8)>0), "Sprint 21",OR(COUNTIF(P40:V40,Versiones!$G$8)>0, COUNTIF(P40:V40,Versiones!$H$8)>0, COUNTIF(P40:V40,Versiones!$I$8)>0), "Sprint 20",OR(COUNTIF(P40:V40,Versiones!$G$7)>0, COUNTIF(P40:V40,Versiones!$H$7)>0, COUNTIF(P40:V40,Versiones!$I$7)>0), "Sprint 19",OR(COUNTIF(P40:V40,Versiones!$G$6)>0, COUNTIF(P40:V40,Versiones!$H$6)>0, COUNTIF(P40:V40,Versiones!$I$6)>0), "Sprint 18",OR(COUNTIF(P40:V40,Versiones!$G$4)>0, COUNTIF(P40:V40,Versiones!$H$4)>0, COUNTIF(P40:V40,Versiones!$G$5)>0, COUNTIF(P40:V40,Versiones!$H$5)>0), "Sprint 17",OR(COUNTIF(P40:V40,Versiones!$G$2)>0, COUNTIF(P40:V40,Versiones!$H$2)>0, COUNTIF(P40:V40,Versiones!$G$3)>0, COUNTIF(P40:V40,Versiones!$H$3)>0), "Sprint 16", OR(COUNTIF(P40:V40,Versiones!$G$2)>0, COUNTIF(P40:V40,Versiones!$H$2)>0, COUNTIF(P40:V40,Versiones!$G$3)>0, COUNTIF(P40:V40,Versiones!$H$3)>0), "Sprint 16",TRUE, "")} -> Sprint 20 | AF40: ="v"&MAX( IFERROR(VALUE(MID(Jira__32[[#This Row],[Versiones corregidas]],2,99)),0), IFERROR(VALUE(MID(Jira__32[[#This Row],[Versiones corregidas_13]],2,99)),0), IFERROR(VALUE(MID(Jira__32[[#This Row],[Versiones corregidas_14]],2,99)),0) ) -> v0 | AG40: {=_xlfn.IFS(Jira__32[[#This Row],[¿En qué versión fue corregido?]]="v0","N/A",Jira__32[[#This Row],[¿En qué versión fue corregido?]]="v0.4","Sprint 16", Jira__32[[#This Row],[¿En qué versión fue corregido?]]="v0.5","Sprint 17", Jira__32[[#This Row],[¿En qué versión fue corregido?]]="v0.6","Sprint 18", Jira__32[[#This Row],[¿En qué versión fue corregido?]]="v0.7","Sprint 19", Jira__32[[#This Row],[¿En qué versión fue corregido?]]="v0.8","Sprint 20",Jira__32[[#This Row],[¿En qué versión fue corregido?]]="v0.9","Sprint 21", TRUE,"Desconocido")} -> N/A | AH40: {=_xlfn.IFS(COUNTIF(P40:V40, Versiones!$A$13)>0, "Funcional", COUNTIF(P40:V40, Versiones!$A$14)>0, "Configuración", COUNTIF(P40:V40, Versiones!$A$15)>0, "Look&Feel", COUNTIF(P40:V40, Versiones!$A$16)>0, "Integración", COUNTIF(P40:V40, Versiones!$A$17)>0, "Contenido/Datos", COUNTIF(P40:V40, Versiones!$A$18)>0, "Eventos_Cosmos", COUNTIF(P40:V40, Versiones!$A$19)>0, "Eventos_iOT", COUNTIF(P40:V40, Versiones!$A$20)>0, "Eventos_Fabric", TRUE, "No encontrado")} -> Funcional
A41: Error | B41: T20-1973 | C41: 99727 | D41: BOT - Dashboard Efectivo - Error en Panel Movimientos | E41: 87100 | F41: T20-1091 | G41: 4.- QA | H41: Medio | I41: Tareas por hacer | J41: Backlog BUGS | P41: Look&Feel | Q41: QA-IntegraciónV0.8 | W41: Daniela Soto | X41: 45936.669 | AB41: =IF(LEFT(Jira__32[[#This Row],[Resumen]],3)="POS","POS",IF(LEFT(Jira__32[[#This Row],[Resumen]],3)="BOT","BOT","")) -> BOT | AC41: 915- Por definir | AE41: {=_xlfn.IFS(OR(COUNTIF(P41:V41,Versiones!$G$9)>0, COUNTIF(P41:V41,Versiones!$H$8)>0), "Sprint 21",OR(COUNTIF(P41:V41,Versiones!$G$8)>0, COUNTIF(P41:V41,Versiones!$H$8)>0, COUNTIF(P41:V41,Versiones!$I$8)>0), "Sprint 20",OR(COUNTIF(P41:V41,Versiones!$G$7)>0, COUNTIF(P41:V41,Versiones!$H$7)>0, COUNTIF(P41:V41,Versiones!$I$7)>0), "Sprint 19",OR(COUNTIF(P41:V41,Versiones!$G$6)>0, COUNTIF(P41:V41,Versiones!$H$6)>0, COUNTIF(P41:V41,Versiones!$I$6)>0), "Sprint 18",OR(COUNTIF(P41:V41,Versiones!$G$4)>0, COUNTIF(P41:V41,Versiones!$H$4)>0, COUNTIF(P41:V41,Versiones!$G$5)>0, COUNTIF(P41:V41,Versiones!$H$5)>0), "Sprint 17",OR(COUNTIF(P41:V41,Versiones!$G$2)>0, COUNTIF(P41:V41,Versiones!$H$2)>0, COUNTIF(P41:V41,Versiones!$G$3)>0, COUNTIF(P41:V41,Versiones!$H$3)>0), "Sprint 16", OR(COUNTIF(P41:V41,Versiones!$G$2)>0, COUNTIF(P41:V41,Versiones!$H$2)>0, COUNTIF(P41:V41,Versiones!$G$3)>0, COUNTIF(P41:V41,Versiones!$H$3)>0), "Sprint 16",TRUE, "")} -> Sprint 20 | AF41: ="v"&MAX( IFERROR(VALUE(MID(Jira__32[[#This Row],[Versiones corregidas]],2,99)),0), IFERROR(VALUE(MID(Jira__32[[#This Row],[Versiones corregidas_13]],2,99)),0), IFERROR(VALUE(MID(Jira__32[[#This Row],[Versiones corregidas_14]],2,99)),0) ) -> v0 | AG41: {=_xlfn.IFS(Jira__32[[#This Row],[¿En qué versión fue corregido?]]="v0","N/A",Jira__32[[#This Row],[¿En qué versión fue corregido?]]="v0.4","Sprint 16", Jira__32[[#This Row],[¿En qué versión fue corregido?]]="v0.5","Sprint 17", Jira__32[[#This Row],[¿En qué versión fue corregido?]]="v0.6","Sprint 18", Jira__32[[#This Row],[¿En qué versión fue corregido?]]="v0.7","Sprint 19", Jira__32[[#This Row],[¿En qué versión fue corregido?]]="v0.8","Sprint 20",Jira__32[[#This Row],[¿En qué versión fue corregido?]]="v0.9","Sprint 21", TRUE,"Desconocido")} -> N/A | AH41: {=_xlfn.IFS(COUNTIF(P41:V41, Versiones!$A$13)>0, "Funcional", COUNTIF(P41:V41, Versiones!$A$14)>0, "Configuración", COUNTIF(P41:V41, Versiones!$A$15)>0, "Look&Feel", COUNTIF(P41:V41, Versiones!$A$16)>0, "Integración", COUNTIF(P41:V41, Versiones!$A$17)>0, "Contenido/Datos", COUNTIF(P41:V41, Versiones!$A$18)>0, "Eventos_Cosmos", COUNTIF(P41:V41, Versiones!$A$19)>0, "Eventos_iOT", COUNTIF(P41:V41, Versiones!$A$20)>0, "Eventos_Fabric", TRUE, "No encontrado")} -> Look&Feel
A42: Error | B42: T20-1970 | C42: 99706 | D42: BOT_No se muestra el modal al seleccionar “Bloqueo de sesión” | E42: 87100 | F42: T20-1091 | G42: 4.- QA | H42: Alta | I42: Cancelado | J42: T20 Sprint 20 2025 | K42: T20 Sprint 21 2025 | P42: Funcional | Q42: QA-IntegraciónV0.8 | W42: Yubisleinys Mora Vega | X42: 45936.61 | AB42: =IF(LEFT(Jira__32[[#This Row],[Resumen]],3)="POS","POS",IF(LEFT(Jira__32[[#This Row],[Resumen]],3)="BOT","BOT","")) -> BOT | AC42: Andres Vergara | AE42: {=_xlfn.IFS(OR(COUNTIF(P42:V42,Versiones!$G$9)>0, COUNTIF(P42:V42,Versiones!$H$8)>0), "Sprint 21",OR(COUNTIF(P42:V42,Versiones!$G$8)>0, COUNTIF(P42:V42,Versiones!$H$8)>0, COUNTIF(P42:V42,Versiones!$I$8)>0), "Sprint 20",OR(COUNTIF(P42:V42,Versiones!$G$7)>0, COUNTIF(P42:V42,Versiones!$H$7)>0, COUNTIF(P42:V42,Versiones!$I$7)>0), "Sprint 19",OR(COUNTIF(P42:V42,Versiones!$G$6)>0, COUNTIF(P42:V42,Versiones!$H$6)>0, COUNTIF(P42:V42,Versiones!$I$6)>0), "Sprint 18",OR(COUNTIF(P42:V42,Versiones!$G$4)>0, COUNTIF(P42:V42,Versiones!$H$4)>0, COUNTIF(P42:V42,Versiones!$G$5)>0, COUNTIF(P42:V42,Versiones!$H$5)>0), "Sprint 17",OR(COUNTIF(P42:V42,Versiones!$G$2)>0, COUNTIF(P42:V42,Versiones!$H$2)>0, COUNTIF(P42:V42,Versiones!$G$3)>0, COUNTIF(P42:V42,Versiones!$H$3)>0), "Sprint 16", OR(COUNTIF(P42:V42,Versiones!$G$2)>0, COUNTIF(P42:V42,Versiones!$H$2)>0, COUNTIF(P42:V42,Versiones!$G$3)>0, COUNTIF(P42:V42,Versiones!$H$3)>0), "Sprint 16",TRUE, "")} -> Sprint 20 | AF42: ="v"&MAX( IFERROR(VALUE(MID(Jira__32[[#This Row],[Versiones corregidas]],2,99)),0), IFERROR(VALUE(MID(Jira__32[[#This Row],[Versiones corregidas_13]],2,99)),0), IFERROR(VALUE(MID(Jira__32[[#This Row],[Versiones corregidas_14]],2,99)),0) ) -> v0 | AG42: {=_xlfn.IFS(Jira__32[[#This Row],[¿En qué versión fue corregido?]]="v0","N/A",Jira__32[[#This Row],[¿En qué versión fue corregido?]]="v0.4","Sprint 16", Jira__32[[#This Row],[¿En qué versión fue corregido?]]="v0.5","Sprint 17", Jira__32[[#This Row],[¿En qué versión fue corregido?]]="v0.6","Sprint 18", Jira__32[[#This Row],[¿En qué versión fue corregido?]]="v0.7","Sprint 19", Jira__32[[#This Row],[¿En qué versión fue corregido?]]="v0.8","Sprint 20",Jira__32[[#This Row],[¿En qué versión fue corregido?]]="v0.9","Sprint 21", TRUE,"Desconocido")} -> N/A | AH42: {=_xlfn.IFS(COUNTIF(P42:V42, Versiones!$A$13)>0, "Funcional", COUNTIF(P42:V42, Versiones!$A$14)>0, "Configuración", COUNTIF(P42:V42, Versiones!$A$15)>0, "Look&Feel", COUNTIF(P42:V42, Versiones!$A$16)>0, "Integración", COUNTIF(P42:V42, Versiones!$A$17)>0, "Contenido/Datos", COUNTIF(P42:V42, Versiones!$A$18)>0, "Eventos_Cosmos", COUNTIF(P42:V42, Versiones!$A$19)>0, "Eventos_iOT", COUNTIF(P42:V42, Versiones!$A$20)>0, "Eventos_Fabric", TRUE, "No encontrado")} -> Funcional
A43: Error | B43: T20-1967 | C43: 99292 | D43: POS - Errores modal Tiempo Aire | E43: 87100 | F43: T20-1091 | G43: 4.- QA | H43: Alta | I43: Tareas por hacer | J43: T20 Sprint 21 2025 | P43: Funcional | Q43: QA-IntegraciónV0.8 | W43: Daniela Soto | X43: 45933.639 | AB43: =IF(LEFT(Jira__32[[#This Row],[Resumen]],3)="POS","POS",IF(LEFT(Jira__32[[#This Row],[Resumen]],3)="BOT","BOT","")) -> POS | AC43: Juan Munoz | AE43: {=_xlfn.IFS(OR(COUNTIF(P43:V43,Versiones!$G$9)>0, COUNTIF(P43:V43,Versiones!$H$8)>0), "Sprint 21",OR(COUNTIF(P43:V43,Versiones!$G$8)>0, COUNTIF(P43:V43,Versiones!$H$8)>0, COUNTIF(P43:V43,Versiones!$I$8)>0), "Sprint 20",OR(COUNTIF(P43:V43,Versiones!$G$7)>0, COUNTIF(P43:V43,Versiones!$H$7)>0, COUNTIF(P43:V43,Versiones!$I$7)>0), "Sprint 19",OR(COUNTIF(P43:V43,Versiones!$G$6)>0, COUNTIF(P43:V43,Versiones!$H$6)>0, COUNTIF(P43:V43,Versiones!$I$6)>0), "Sprint 18",OR(COUNTIF(P43:V43,Versiones!$G$4)>0, COUNTIF(P43:V43,Versiones!$H$4)>0, COUNTIF(P43:V43,Versiones!$G$5)>0, COUNTIF(P43:V43,Versiones!$H$5)>0), "Sprint 17",OR(COUNTIF(P43:V43,Versiones!$G$2)>0, COUNTIF(P43:V43,Versiones!$H$2)>0, COUNTIF(P43:V43,Versiones!$G$3)>0, COUNTIF(P43:V43,Versiones!$H$3)>0), "Sprint 16", OR(COUNTIF(P43:V43,Versiones!$G$2)>0, COUNTIF(P43:V43,Versiones!$H$2)>0, COUNTIF(P43:V43,Versiones!$G$3)>0, COUNTIF(P43:V43,Versiones!$H$3)>0), "Sprint 16",TRUE, "")} -> Sprint 20 | AF43: ="v"&MAX( IFERROR(VALUE(MID(Jira__32[[#This Row],[Versiones corregidas]],2,99)),0), IFERROR(VALUE(MID(Jira__32[[#This Row],[Versiones corregidas_13]],2,99)),0), IFERROR(VALUE(MID(Jira__32[[#This Row],[Versiones corregidas_14]],2,99)),0) ) -> v0 | AG43: {=_xlfn.IFS(Jira__32[[#This Row],[¿En qué versión fue corregido?]]="v0","N/A",Jira__32[[#This Row],[¿En qué versión fue corregido?]]="v0.4","Sprint 16", Jira__32[[#This Row],[¿En qué versión fue corregido?]]="v0.5","Sprint 17", Jira__32[[#This Row],[¿En qué versión fue corregido?]]="v0.6","Sprint 18", Jira__32[[#This Row],[¿En qué versión fue corregido?]]="v0.7","Sprint 19", Jira__32[[#This Row],[¿En qué versión fue corregido?]]="v0.8","Sprint 20",Jira__32[[#This Row],[¿En qué versión fue corregido?]]="v0.9","Sprint 21", TRUE,"Desconocido")} -> N/A | AH43: {=_xlfn.IFS(COUNTIF(P43:V43, Versiones!$A$13)>0, "Funcional", COUNTIF(P43:V43, Versiones!$A$14)>0, "Configuración", COUNTIF(P43:V43, Versiones!$A$15)>0, "Look&Feel", COUNTIF(P43:V43, Versiones!$A$16)>0, "Integración", COUNTIF(P43:V43, Versiones!$A$17)>0, "Contenido/Datos", COUNTIF(P43:V43, Versiones!$A$18)>0, "Eventos_Cosmos", COUNTIF(P43:V43, Versiones!$A$19)>0, "Eventos_iOT", COUNTIF(P43:V43, Versiones!$A$20)>0, "Eventos_Fabric", TRUE, "No encontrado")} -> Funcional
A44: Error | B44: T20-1966 | C44: 99290 | D44: POS - Shortcut F10 no funciona | E44: 87100 | F44: T20-1091 | G44: 4.- QA | H44: Medio | I44: Tareas por hacer | J44: Backlog BUGS | P44: Funcional | Q44: QA-IntegraciónV0.8 | W44: Daniela Soto | X44: 45933.63 | AB44: =IF(LEFT(Jira__32[[#This Row],[Resumen]],3)="POS","POS",IF(LEFT(Jira__32[[#This Row],[Resumen]],3)="BOT","BOT","")) -> POS | AC44: Emiliano Fraile | AE44: {=_xlfn.IFS(OR(COUNTIF(P44:V44,Versiones!$G$9)>0, COUNTIF(P44:V44,Versiones!$H$8)>0), "Sprint 21",OR(COUNTIF(P44:V44,Versiones!$G$8)>0, COUNTIF(P44:V44,Versiones!$H$8)>0, COUNTIF(P44:V44,Versiones!$I$8)>0), "Sprint 20",OR(COUNTIF(P44:V44,Versiones!$G$7)>0, COUNTIF(P44:V44,Versiones!$H$7)>0, COUNTIF(P44:V44,Versiones!$I$7)>0), "Sprint 19",OR(COUNTIF(P44:V44,Versiones!$G$6)>0, COUNTIF(P44:V44,Versiones!$H$6)>0, COUNTIF(P44:V44,Versiones!$I$6)>0), "Sprint 18",OR(COUNTIF(P44:V44,Versiones!$G$4)>0, COUNTIF(P44:V44,Versiones!$H$4)>0, COUNTIF(P44:V44,Versiones!$G$5)>0, COUNTIF(P44:V44,Versiones!$H$5)>0), "Sprint 17",OR(COUNTIF(P44:V44,Versiones!$G$2)>0, COUNTIF(P44:V44,Versiones!$H$2)>0, COUNTIF(P44:V44,Versiones!$G$3)>0, COUNTIF(P44:V44,Versiones!$H$3)>0), "Sprint 16", OR(COUNTIF(P44:V44,Versiones!$G$2)>0, COUNTIF(P44:V44,Versiones!$H$2)>0, COUNTIF(P44:V44,Versiones!$G$3)>0, COUNTIF(P44:V44,Versiones!$H$3)>0), "Sprint 16",TRUE, "")} -> Sprint 20 | AF44: ="v"&MAX( IFERROR(VALUE(MID(Jira__32[[#This Row],[Versiones corregidas]],2,99)),0), IFERROR(VALUE(MID(Jira__32[[#This Row],[Versiones corregidas_13]],2,99)),0), IFERROR(VALUE(MID(Jira__32[[#This Row],[Versiones corregidas_14]],2,99)),0) ) -> v0 | AG44: {=_xlfn.IFS(Jira__32[[#This Row],[¿En qué versión fue corregido?]]="v0","N/A",Jira__32[[#This Row],[¿En qué versión fue corregido?]]="v0.4","Sprint 16", Jira__32[[#This Row],[¿En qué versión fue corregido?]]="v0.5","Sprint 17", Jira__32[[#This Row],[¿En qué versión fue corregido?]]="v0.6","Sprint 18", Jira__32[[#This Row],[¿En qué versión fue corregido?]]="v0.7","Sprint 19", Jira__32[[#This Row],[¿En qué versión fue corregido?]]="v0.8","Sprint 20",Jira__32[[#This Row],[¿En qué versión fue corregido?]]="v0.9","Sprint 21", TRUE,"Desconocido")} -> N/A | AH44: {=_xlfn.IFS(COUNTIF(P44:V44, Versiones!$A$13)>0, "Funcional", COUNTIF(P44:V44, Versiones!$A$14)>0, "Configuración", COUNTIF(P44:V44, Versiones!$A$15)>0, "Look&Feel", COUNTIF(P44:V44, Versiones!$A$16)>0, "Integración", COUNTIF(P44:V44, Versiones!$A$17)>0, "Contenido/Datos", COUNTIF(P44:V44, Versiones!$A$18)>0, "Eventos_Cosmos", COUNTIF(P44:V44, Versiones!$A$19)>0, "Eventos_iOT", COUNTIF(P44:V44, Versiones!$A$20)>0, "Eventos_Fabric", TRUE, "No encontrado")} -> Funcional
A45: Error | B45: T20-1963 | C45: 99283 | D45: POS - Servicios - Error en modal Pago de Servicios | E45: 87100 | F45: T20-1091 | G45: 4.- QA | H45: Medio | I45: Tareas por hacer | J45: Backlog BUGS | P45: Look&Feel | Q45: QA-IntegraciónV0.8 | W45: Daniela Soto | X45: 45933.606 | AB45: =IF(LEFT(Jira__32[[#This Row],[Resumen]],3)="POS","POS",IF(LEFT(Jira__32[[#This Row],[Resumen]],3)="BOT","BOT","")) -> POS | AC45: Emiliano Fraile | AE45: {=_xlfn.IFS(OR(COUNTIF(P45:V45,Versiones!$G$9)>0, COUNTIF(P45:V45,Versiones!$H$8)>0), "Sprint 21",OR(COUNTIF(P45:V45,Versiones!$G$8)>0, COUNTIF(P45:V45,Versiones!$H$8)>0, COUNTIF(P45:V45,Versiones!$I$8)>0), "Sprint 20",OR(COUNTIF(P45:V45,Versiones!$G$7)>0, COUNTIF(P45:V45,Versiones!$H$7)>0, COUNTIF(P45:V45,Versiones!$I$7)>0), "Sprint 19",OR(COUNTIF(P45:V45,Versiones!$G$6)>0, COUNTIF(P45:V45,Versiones!$H$6)>0, COUNTIF(P45:V45,Versiones!$I$6)>0), "Sprint 18",OR(COUNTIF(P45:V45,Versiones!$G$4)>0, COUNTIF(P45:V45,Versiones!$H$4)>0, COUNTIF(P45:V45,Versiones!$G$5)>0, COUNTIF(P45:V45,Versiones!$H$5)>0), "Sprint 17",OR(COUNTIF(P45:V45,Versiones!$G$2)>0, COUNTIF(P45:V45,Versiones!$H$2)>0, COUNTIF(P45:V45,Versiones!$G$3)>0, COUNTIF(P45:V45,Versiones!$H$3)>0), "Sprint 16", OR(COUNTIF(P45:V45,Versiones!$G$2)>0, COUNTIF(P45:V45,Versiones!$H$2)>0, COUNTIF(P45:V45,Versiones!$G$3)>0, COUNTIF(P45:V45,Versiones!$H$3)>0), "Sprint 16",TRUE, "")} -> Sprint 20 | AF45: ="v"&MAX( IFERROR(VALUE(MID(Jira__32[[#This Row],[Versiones corregidas]],2,99)),0), IFERROR(VALUE(MID(Jira__32[[#This Row],[Versiones corregidas_13]],2,99)),0), IFERROR(VALUE(MID(Jira__32[[#This Row],[Versiones corregidas_14]],2,99)),0) ) -> v0 | AG45: {=_xlfn.IFS(Jira__32[[#This Row],[¿En qué versión fue corregido?]]="v0","N/A",Jira__32[[#This Row],[¿En qué versión fue corregido?]]="v0.4","Sprint 16", Jira__32[[#This Row],[¿En qué versión fue corregido?]]="v0.5","Sprint 17", Jira__32[[#This Row],[¿En qué versión fue corregido?]]="v0.6","Sprint 18", Jira__32[[#This Row],[¿En qué versión fue corregido?]]="v0.7","Sprint 19", Jira__32[[#This Row],[¿En qué versión fue corregido?]]="v0.8","Sprint 20",Jira__32[[#This Row],[¿En qué versión fue corregido?]]="v0.9","Sprint 21", TRUE,"Desconocido")} -> N/A | AH45: {=_xlfn.IFS(COUNTIF(P45:V45, Versiones!$A$13)>0, "Funcional", COUNTIF(P45:V45, Versiones!$A$14)>0, "Configuración", COUNTIF(P45:V45, Versiones!$A$15)>0, "Look&Feel", COUNTIF(P45:V45, Versiones!$A$16)>0, "Integración", COUNTIF(P45:V45, Versiones!$A$17)>0, "Contenido/Datos", COUNTIF(P45:V45, Versiones!$A$18)>0, "Eventos_Cosmos", COUNTIF(P45:V45, Versiones!$A$19)>0, "Eventos_iOT", COUNTIF(P45:V45, Versiones!$A$20)>0, "Eventos_Fabric", TRUE, "No encontrado")} -> Look&Feel
A46: Error | B46: T20-1950 | C46: 99159 | D46: BOT - Registrar merma - Errores en columnas | H46: Medio | I46: Tareas por hacer | J46: Backlog BUGS | P46: Look&Feel | Q46: QA-IntegraciónV0.8 | W46: Daniela Soto | X46: 45933.373 | AB46: =IF(LEFT(Jira__32[[#This Row],[Resumen]],3)="POS","POS",IF(LEFT(Jira__32[[#This Row],[Resumen]],3)="BOT","BOT","")) -> BOT | AC46: Emiliano Fraile | AE46: {=_xlfn.IFS(OR(COUNTIF(P46:V46,Versiones!$G$9)>0, COUNTIF(P46:V46,Versiones!$H$8)>0), "Sprint 21",OR(COUNTIF(P46:V46,Versiones!$G$8)>0, COUNTIF(P46:V46,Versiones!$H$8)>0, COUNTIF(P46:V46,Versiones!$I$8)>0), "Sprint 20",OR(COUNTIF(P46:V46,Versiones!$G$7)>0, COUNTIF(P46:V46,Versiones!$H$7)>0, COUNTIF(P46:V46,Versiones!$I$7)>0), "Sprint 19",OR(COUNTIF(P46:V46,Versiones!$G$6)>0, COUNTIF(P46:V46,Versiones!$H$6)>0, COUNTIF(P46:V46,Versiones!$I$6)>0), "Sprint 18",OR(COUNTIF(P46:V46,Versiones!$G$4)>0, COUNTIF(P46:V46,Versiones!$H$4)>0, COUNTIF(P46:V46,Versiones!$G$5)>0, COUNTIF(P46:V46,Versiones!$H$5)>0), "Sprint 17",OR(COUNTIF(P46:V46,Versiones!$G$2)>0, COUNTIF(P46:V46,Versiones!$H$2)>0, COUNTIF(P46:V46,Versiones!$G$3)>0, COUNTIF(P46:V46,Versiones!$H$3)>0), "Sprint 16", OR(COUNTIF(P46:V46,Versiones!$G$2)>0, COUNTIF(P46:V46,Versiones!$H$2)>0, COUNTIF(P46:V46,Versiones!$G$3)>0, COUNTIF(P46:V46,Versiones!$H$3)>0), "Sprint 16",TRUE, "")} -> Sprint 20 | AF46: ="v"&MAX( IFERROR(VALUE(MID(Jira__32[[#This Row],[Versiones corregidas]],2,99)),0), IFERROR(VALUE(MID(Jira__32[[#This Row],[Versiones corregidas_13]],2,99)),0), IFERROR(VALUE(MID(Jira__32[[#This Row],[Versiones corregidas_14]],2,99)),0) ) -> v0 | AG46: {=_xlfn.IFS(Jira__32[[#This Row],[¿En qué versión fue corregido?]]="v0","N/A",Jira__32[[#This Row],[¿En qué versión fue corregido?]]="v0.4","Sprint 16", Jira__32[[#This Row],[¿En qué versión fue corregido?]]="v0.5","Sprint 17", Jira__32[[#This Row],[¿En qué versión fue corregido?]]="v0.6","Sprint 18", Jira__32[[#This Row],[¿En qué versión fue corregido?]]="v0.7","Sprint 19", Jira__32[[#This Row],[¿En qué versión fue corregido?]]="v0.8","Sprint 20",Jira__32[[#This Row],[¿En qué versión fue corregido?]]="v0.9","Sprint 21", TRUE,"Desconocido")} -> N/A | AH46: {=_xlfn.IFS(COUNTIF(P46:V46, Versiones!$A$13)>0, "Funcional", COUNTIF(P46:V46, Versiones!$A$14)>0, "Configuración", COUNTIF(P46:V46, Versiones!$A$15)>0, "Look&Feel", COUNTIF(P46:V46, Versiones!$A$16)>0, "Integración", COUNTIF(P46:V46, Versiones!$A$17)>0, "Contenido/Datos", COUNTIF(P46:V46, Versiones!$A$18)>0, "Eventos_Cosmos", COUNTIF(P46:V46, Versiones!$A$19)>0, "Eventos_iOT", COUNTIF(P46:V46, Versiones!$A$20)>0, "Eventos_Fabric", TRUE, "No encontrado")} -> Look&Feel
A47: Error | B47: T20-1947 | C47: 99086 | D47: POS - BOT - Al seleccionar botones de la izquierda, se dehabilitan las funcionalidades seleccionadas y no se pueden volver a seleccionar. | H47: Alta | I47: En curso | J47: T20 Sprint 21 2025 | P47: Funcional | Q47: QA-IntegraciónV0.8 | W47: Daniela Soto | X47: 45932.694 | AB47: =IF(LEFT(Jira__32[[#This Row],[Resumen]],3)="POS","POS",IF(LEFT(Jira__32[[#This Row],[Resumen]],3)="BOT","BOT","")) -> POS | AC47: Emiliano Fraile | AE47: {=_xlfn.IFS(OR(COUNTIF(P47:V47,Versiones!$G$9)>0, COUNTIF(P47:V47,Versiones!$H$8)>0), "Sprint 21",OR(COUNTIF(P47:V47,Versiones!$G$8)>0, COUNTIF(P47:V47,Versiones!$H$8)>0, COUNTIF(P47:V47,Versiones!$I$8)>0), "Sprint 20",OR(COUNTIF(P47:V47,Versiones!$G$7)>0, COUNTIF(P47:V47,Versiones!$H$7)>0, COUNTIF(P47:V47,Versiones!$I$7)>0), "Sprint 19",OR(COUNTIF(P47:V47,Versiones!$G$6)>0, COUNTIF(P47:V47,Versiones!$H$6)>0, COUNTIF(P47:V47,Versiones!$I$6)>0), "Sprint 18",OR(COUNTIF(P47:V47,Versiones!$G$4)>0, COUNTIF(P47:V47,Versiones!$H$4)>0, COUNTIF(P47:V47,Versiones!$G$5)>0, COUNTIF(P47:V47,Versiones!$H$5)>0), "Sprint 17",OR(COUNTIF(P47:V47,Versiones!$G$2)>0, COUNTIF(P47:V47,Versiones!$H$2)>0, COUNTIF(P47:V47,Versiones!$G$3)>0, COUNTIF(P47:V47,Versiones!$H$3)>0), "Sprint 16", OR(COUNTIF(P47:V47,Versiones!$G$2)>0, COUNTIF(P47:V47,Versiones!$H$2)>0, COUNTIF(P47:V47,Versiones!$G$3)>0, COUNTIF(P47:V47,Versiones!$H$3)>0), "Sprint 16",TRUE, "")} -> Sprint 20 | AF47: ="v"&MAX( IFERROR(VALUE(MID(Jira__32[[#This Row],[Versiones corregidas]],2,99)),0), IFERROR(VALUE(MID(Jira__32[[#This Row],[Versiones corregidas_13]],2,99)),0), IFERROR(VALUE(MID(Jira__32[[#This Row],[Versiones corregidas_14]],2,99)),0) ) -> v0 | AG47: {=_xlfn.IFS(Jira__32[[#This Row],[¿En qué versión fue corregido?]]="v0","N/A",Jira__32[[#This Row],[¿En qué versión fue corregido?]]="v0.4","Sprint 16", Jira__32[[#This Row],[¿En qué versión fue corregido?]]="v0.5","Sprint 17", Jira__32[[#This Row],[¿En qué versión fue corregido?]]="v0.6","Sprint 18", Jira__32[[#This Row],[¿En qué versión fue corregido?]]="v0.7","Sprint 19", Jira__32[[#This Row],[¿En qué versión fue corregido?]]="v0.8","Sprint 20",Jira__32[[#This Row],[¿En qué versión fue corregido?]]="v0.9","Sprint 21", TRUE,"Desconocido")} -> N/A | AH47: {=_xlfn.IFS(COUNTIF(P47:V47, Versiones!$A$13)>0, "Funcional", COUNTIF(P47:V47, Versiones!$A$14)>0, "Configuración", COUNTIF(P47:V47, Versiones!$A$15)>0, "Look&Feel", COUNTIF(P47:V47, Versiones!$A$16)>0, "Integración", COUNTIF(P47:V47, Versiones!$A$17)>0, "Contenido/Datos", COUNTIF(P47:V47, Versiones!$A$18)>0, "Eventos_Cosmos", COUNTIF(P47:V47, Versiones!$A$19)>0, "Eventos_iOT", COUNTIF(P47:V47, Versiones!$A$20)>0, "Eventos_Fabric", TRUE, "No encontrado")} -> Funcional
A48: Error | B48: T20-1946 | C48: 99070 | D48: POS - Errores en módulo "Devolución" | H48: Alta | I48: Tareas por hacer | J48: T20 Sprint 21 2025 | P48: Funcional | Q48: QA-IntegraciónV0.8 | W48: Daniela Soto | X48: 45932.672 | AB48: =IF(LEFT(Jira__32[[#This Row],[Resumen]],3)="POS","POS",IF(LEFT(Jira__32[[#This Row],[Resumen]],3)="BOT","BOT","")) -> POS | AC48: Andres Vergara | AE48: {=_xlfn.IFS(OR(COUNTIF(P48:V48,Versiones!$G$9)>0, COUNTIF(P48:V48,Versiones!$H$8)>0), "Sprint 21",OR(COUNTIF(P48:V48,Versiones!$G$8)>0, COUNTIF(P48:V48,Versiones!$H$8)>0, COUNTIF(P48:V48,Versiones!$I$8)>0), "Sprint 20",OR(COUNTIF(P48:V48,Versiones!$G$7)>0, COUNTIF(P48:V48,Versiones!$H$7)>0, COUNTIF(P48:V48,Versiones!$I$7)>0), "Sprint 19",OR(COUNTIF(P48:V48,Versiones!$G$6)>0, COUNTIF(P48:V48,Versiones!$H$6)>0, COUNTIF(P48:V48,Versiones!$I$6)>0), "Sprint 18",OR(COUNTIF(P48:V48,Versiones!$G$4)>0, COUNTIF(P48:V48,Versiones!$H$4)>0, COUNTIF(P48:V48,Versiones!$G$5)>0, COUNTIF(P48:V48,Versiones!$H$5)>0), "Sprint 17",OR(COUNTIF(P48:V48,Versiones!$G$2)>0, COUNTIF(P48:V48,Versiones!$H$2)>0, COUNTIF(P48:V48,Versiones!$G$3)>0, COUNTIF(P48:V48,Versiones!$H$3)>0), "Sprint 16", OR(COUNTIF(P48:V48,Versiones!$G$2)>0, COUNTIF(P48:V48,Versiones!$H$2)>0, COUNTIF(P48:V48,Versiones!$G$3)>0, COUNTIF(P48:V48,Versiones!$H$3)>0), "Sprint 16",TRUE, "")} -> Sprint 20 | AF48: ="v"&MAX( IFERROR(VALUE(MID(Jira__32[[#This Row],[Versiones corregidas]],2,99)),0), IFERROR(VALUE(MID(Jira__32[[#This Row],[Versiones corregidas_13]],2,99)),0), IFERROR(VALUE(MID(Jira__32[[#This Row],[Versiones corregidas_14]],2,99)),0) ) -> v0 | AG48: {=_xlfn.IFS(Jira__32[[#This Row],[¿En qué versión fue corregido?]]="v0","N/A",Jira__32[[#This Row],[¿En qué versión fue corregido?]]="v0.4","Sprint 16", Jira__32[[#This Row],[¿En qué versión fue corregido?]]="v0.5","Sprint 17", Jira__32[[#This Row],[¿En qué versión fue corregido?]]="v0.6","Sprint 18", Jira__32[[#This Row],[¿En qué versión fue corregido?]]="v0.7","Sprint 19", Jira__32[[#This Row],[¿En qué versión fue corregido?]]="v0.8","Sprint 20",Jira__32[[#This Row],[¿En qué versión fue corregido?]]="v0.9","Sprint 21", TRUE,"Desconocido")} -> N/A | AH48: {=_xlfn.IFS(COUNTIF(P48:V48, Versiones!$A$13)>0, "Funcional", COUNTIF(P48:V48, Versiones!$A$14)>0, "Configuración", COUNTIF(P48:V48, Versiones!$A$15)>0, "Look&Feel", COUNTIF(P48:V48, Versiones!$A$16)>0, "Integración", COUNTIF(P48:V48, Versiones!$A$17)>0, "Contenido/Datos", COUNTIF(P48:V48, Versiones!$A$18)>0, "Eventos_Cosmos", COUNTIF(P48:V48, Versiones!$A$19)>0, "Eventos_iOT", COUNTIF(P48:V48, Versiones!$A$20)>0, "Eventos_Fabric", TRUE, "No encontrado")} -> Funcional
A49: Error | B49: T20-1944 | C49: 99024 | D49: POS - Menú BBB con opciones erradas | H49: Alta | I49: Tareas por hacer | J49: T20 Sprint 21 2025 | P49: Funcional | Q49: QA-IntegraciónV0.8 | W49: Daniela Soto | X49: 45932.606 | AB49: =IF(LEFT(Jira__32[[#This Row],[Resumen]],3)="POS","POS",IF(LEFT(Jira__32[[#This Row],[Resumen]],3)="BOT","BOT","")) -> POS | AC49: Emiliano Fraile | AE49: {=_xlfn.IFS(OR(COUNTIF(P49:V49,Versiones!$G$9)>0, COUNTIF(P49:V49,Versiones!$H$8)>0), "Sprint 21",OR(COUNTIF(P49:V49,Versiones!$G$8)>0, COUNTIF(P49:V49,Versiones!$H$8)>0, COUNTIF(P49:V49,Versiones!$I$8)>0), "Sprint 20",OR(COUNTIF(P49:V49,Versiones!$G$7)>0, COUNTIF(P49:V49,Versiones!$H$7)>0, COUNTIF(P49:V49,Versiones!$I$7)>0), "Sprint 19",OR(COUNTIF(P49:V49,Versiones!$G$6)>0, COUNTIF(P49:V49,Versiones!$H$6)>0, COUNTIF(P49:V49,Versiones!$I$6)>0), "Sprint 18",OR(COUNTIF(P49:V49,Versiones!$G$4)>0, COUNTIF(P49:V49,Versiones!$H$4)>0, COUNTIF(P49:V49,Versiones!$G$5)>0, COUNTIF(P49:V49,Versiones!$H$5)>0), "Sprint 17",OR(COUNTIF(P49:V49,Versiones!$G$2)>0, COUNTIF(P49:V49,Versiones!$H$2)>0, COUNTIF(P49:V49,Versiones!$G$3)>0, COUNTIF(P49:V49,Versiones!$H$3)>0), "Sprint 16", OR(COUNTIF(P49:V49,Versiones!$G$2)>0, COUNTIF(P49:V49,Versiones!$H$2)>0, COUNTIF(P49:V49,Versiones!$G$3)>0, COUNTIF(P49:V49,Versiones!$H$3)>0), "Sprint 16",TRUE, "")} -> Sprint 20 | AF49: ="v"&MAX( IFERROR(VALUE(MID(Jira__32[[#This Row],[Versiones corregidas]],2,99)),0), IFERROR(VALUE(MID(Jira__32[[#This Row],[Versiones corregidas_13]],2,99)),0), IFERROR(VALUE(MID(Jira__32[[#This Row],[Versiones corregidas_14]],2,99)),0) ) -> v0 | AG49: {=_xlfn.IFS(Jira__32[[#This Row],[¿En qué versión fue corregido?]]="v0","N/A",Jira__32[[#This Row],[¿En qué versión fue corregido?]]="v0.4","Sprint 16", Jira__32[[#This Row],[¿En qué versión fue corregido?]]="v0.5","Sprint 17", Jira__32[[#This Row],[¿En qué versión fue corregido?]]="v0.6","Sprint 18", Jira__32[[#This Row],[¿En qué versión fue corregido?]]="v0.7","Sprint 19", Jira__32[[#This Row],[¿En qué versión fue corregido?]]="v0.8","Sprint 20",Jira__32[[#This Row],[¿En qué versión fue corregido?]]="v0.9","Sprint 21", TRUE,"Desconocido")} -> N/A | AH49: {=_xlfn.IFS(COUNTIF(P49:V49, Versiones!$A$13)>0, "Funcional", COUNTIF(P49:V49, Versiones!$A$14)>0, "Configuración", COUNTIF(P49:V49, Versiones!$A$15)>0, "Look&Feel", COUNTIF(P49:V49, Versiones!$A$16)>0, "Integración", COUNTIF(P49:V49, Versiones!$A$17)>0, "Contenido/Datos", COUNTIF(P49:V49, Versiones!$A$18)>0, "Eventos_Cosmos", COUNTIF(P49:V49, Versiones!$A$19)>0, "Eventos_iOT", COUNTIF(P49:V49, Versiones!$A$20)>0, "Eventos_Fabric", TRUE, "No encontrado")} -> Funcional
A50: Error | B50: T20-1943 | C50: 99022 | D50: POS - No figura opción "Cerrar Turno y Cerrar Sesión" | H50: Más alta | I50: Code Review | J50: T20 Sprint 21 2025 | P50: Funcional | Q50: QA-IntegraciónV0.8 | W50: Daniela Soto | X50: 45932.595 | AB50: =IF(LEFT(Jira__32[[#This Row],[Resumen]],3)="POS","POS",IF(LEFT(Jira__32[[#This Row],[Resumen]],3)="BOT","BOT","")) -> POS | AC50: Andres Vergara | AE50: {=_xlfn.IFS(OR(COUNTIF(P50:V50,Versiones!$G$9)>0, COUNTIF(P50:V50,Versiones!$H$8)>0), "Sprint 21",OR(COUNTIF(P50:V50,Versiones!$G$8)>0, COUNTIF(P50:V50,Versiones!$H$8)>0, COUNTIF(P50:V50,Versiones!$I$8)>0), "Sprint 20",OR(COUNTIF(P50:V50,Versiones!$G$7)>0, COUNTIF(P50:V50,Versiones!$H$7)>0, COUNTIF(P50:V50,Versiones!$I$7)>0), "Sprint 19",OR(COUNTIF(P50:V50,Versiones!$G$6)>0, COUNTIF(P50:V50,Versiones!$H$6)>0, COUNTIF(P50:V50,Versiones!$I$6)>0), "Sprint 18",OR(COUNTIF(P50:V50,Versiones!$G$4)>0, COUNTIF(P50:V50,Versiones!$H$4)>0, COUNTIF(P50:V50,Versiones!$G$5)>0, COUNTIF(P50:V50,Versiones!$H$5)>0), "Sprint 17",OR(COUNTIF(P50:V50,Versiones!$G$2)>0, COUNTIF(P50:V50,Versiones!$H$2)>0, COUNTIF(P50:V50,Versiones!$G$3)>0, COUNTIF(P50:V50,Versiones!$H$3)>0), "Sprint 16", OR(COUNTIF(P50:V50,Versiones!$G$2)>0, COUNTIF(P50:V50,Versiones!$H$2)>0, COUNTIF(P50:V50,Versiones!$G$3)>0, COUNTIF(P50:V50,Versiones!$H$3)>0), "Sprint 16",TRUE, "")} -> Sprint 20 | AF50: ="v"&MAX( IFERROR(VALUE(MID(Jira__32[[#This Row],[Versiones corregidas]],2,99)),0), IFERROR(VALUE(MID(Jira__32[[#This Row],[Versiones corregidas_13]],2,99)),0), IFERROR(VALUE(MID(Jira__32[[#This Row],[Versiones corregidas_14]],2,99)),0) ) -> v0 | AG50: {=_xlfn.IFS(Jira__32[[#This Row],[¿En qué versión fue corregido?]]="v0","N/A",Jira__32[[#This Row],[¿En qué versión fue corregido?]]="v0.4","Sprint 16", Jira__32[[#This Row],[¿En qué versión fue corregido?]]="v0.5","Sprint 17", Jira__32[[#This Row],[¿En qué versión fue corregido?]]="v0.6","Sprint 18", Jira__32[[#This Row],[¿En qué versión fue corregido?]]="v0.7","Sprint 19", Jira__32[[#This Row],[¿En qué versión fue corregido?]]="v0.8","Sprint 20",Jira__32[[#This Row],[¿En qué versión fue corregido?]]="v0.9","Sprint 21", TRUE,"Desconocido")} -> N/A | AH50: {=_xlfn.IFS(COUNTIF(P50:V50, Versiones!$A$13)>0, "Funcional", COUNTIF(P50:V50, Versiones!$A$14)>0, "Configuración", COUNTIF(P50:V50, Versiones!$A$15)>0, "Look&Feel", COUNTIF(P50:V50, Versiones!$A$16)>0, "Integración", COUNTIF(P50:V50, Versiones!$A$17)>0, "Contenido/Datos", COUNTIF(P50:V50, Versiones!$A$18)>0, "Eventos_Cosmos", COUNTIF(P50:V50, Versiones!$A$19)>0, "Eventos_iOT", COUNTIF(P50:V50, Versiones!$A$20)>0, "Eventos_Fabric", TRUE, "No encontrado")} -> Funcional
A51: Error | B51: T20-1930 | C51: 98875 | D51: POS - Login con usuario inválido no permite corregir. | H51: Alta | I51: Cancelado | J51: T20 Sprint 20 2025 | K51: T20 Sprint 21 2025 | P51: Funcional | Q51: QA-IntegraciónV0.8 | W51: Daniela Soto | X51: 45932.39 | AB51: =IF(LEFT(Jira__32[[#This Row],[Resumen]],3)="POS","POS",IF(LEFT(Jira__32[[#This Row],[Resumen]],3)="BOT","BOT","")) -> POS | AC51: Nicolas Dubiansky | AE51: {=_xlfn.IFS(OR(COUNTIF(P51:V51,Versiones!$G$9)>0, COUNTIF(P51:V51,Versiones!$H$8)>0), "Sprint 21",OR(COUNTIF(P51:V51,Versiones!$G$8)>0, COUNTIF(P51:V51,Versiones!$H$8)>0, COUNTIF(P51:V51,Versiones!$I$8)>0), "Sprint 20",OR(COUNTIF(P51:V51,Versiones!$G$7)>0, COUNTIF(P51:V51,Versiones!$H$7)>0, COUNTIF(P51:V51,Versiones!$I$7)>0), "Sprint 19",OR(COUNTIF(P51:V51,Versiones!$G$6)>0, COUNTIF(P51:V51,Versiones!$H$6)>0, COUNTIF(P51:V51,Versiones!$I$6)>0), "Sprint 18",OR(COUNTIF(P51:V51,Versiones!$G$4)>0, COUNTIF(P51:V51,Versiones!$H$4)>0, COUNTIF(P51:V51,Versiones!$G$5)>0, COUNTIF(P51:V51,Versiones!$H$5)>0), "Sprint 17",OR(COUNTIF(P51:V51,Versiones!$G$2)>0, COUNTIF(P51:V51,Versiones!$H$2)>0, COUNTIF(P51:V51,Versiones!$G$3)>0, COUNTIF(P51:V51,Versiones!$H$3)>0), "Sprint 16", OR(COUNTIF(P51:V51,Versiones!$G$2)>0, COUNTIF(P51:V51,Versiones!$H$2)>0, COUNTIF(P51:V51,Versiones!$G$3)>0, COUNTIF(P51:V51,Versiones!$H$3)>0), "Sprint 16",TRUE, "")} -> Sprint 20 | AF51: ="v"&MAX( IFERROR(VALUE(MID(Jira__32[[#This Row],[Versiones corregidas]],2,99)),0), IFERROR(VALUE(MID(Jira__32[[#This Row],[Versiones corregidas_13]],2,99)),0), IFERROR(VALUE(MID(Jira__32[[#This Row],[Versiones corregidas_14]],2,99)),0) ) -> v0 | AG51: {=_xlfn.IFS(Jira__32[[#This Row],[¿En qué versión fue corregido?]]="v0","N/A",Jira__32[[#This Row],[¿En qué versión fue corregido?]]="v0.4","Sprint 16", Jira__32[[#This Row],[¿En qué versión fue corregido?]]="v0.5","Sprint 17", Jira__32[[#This Row],[¿En qué versión fue corregido?]]="v0.6","Sprint 18", Jira__32[[#This Row],[¿En qué versión fue corregido?]]="v0.7","Sprint 19", Jira__32[[#This Row],[¿En qué versión fue corregido?]]="v0.8","Sprint 20",Jira__32[[#This Row],[¿En qué versión fue corregido?]]="v0.9","Sprint 21", TRUE,"Desconocido")} -> N/A | AH51: {=_xlfn.IFS(COUNTIF(P51:V51, Versiones!$A$13)>0, "Funcional", COUNTIF(P51:V51, Versiones!$A$14)>0, "Configuración", COUNTIF(P51:V51, Versiones!$A$15)>0, "Look&Feel", COUNTIF(P51:V51, Versiones!$A$16)>0, "Integración", COUNTIF(P51:V51, Versiones!$A$17)>0, "Contenido/Datos", COUNTIF(P51:V51, Versiones!$A$18)>0, "Eventos_Cosmos", COUNTIF(P51:V51, Versiones!$A$19)>0, "Eventos_iOT", COUNTIF(P51:V51, Versiones!$A$20)>0, "Eventos_Fabric", TRUE, "No encontrado")} -> Funcional
A52: Error | B52: T20-1927 | C52: 98650 | D52: BOT - Modal inventario no se visualiza | H52: Más alta | I52: Cancelado | J52: T20 Sprint 20 2025 | K52: T20 Sprint 21 2025 | P52: Funcional | Q52: QA-IntegraciónV0.8 | W52: Yubisleinys Mora Vega | X52: 45931.628 | AB52: =IF(LEFT(Jira__32[[#This Row],[Resumen]],3)="POS","POS",IF(LEFT(Jira__32[[#This Row],[Resumen]],3)="BOT","BOT","")) -> BOT | AC52: Nicolas Dubiansky | AE52: {=_xlfn.IFS(OR(COUNTIF(P52:V52,Versiones!$G$9)>0, COUNTIF(P52:V52,Versiones!$H$8)>0), "Sprint 21",OR(COUNTIF(P52:V52,Versiones!$G$8)>0, COUNTIF(P52:V52,Versiones!$H$8)>0, COUNTIF(P52:V52,Versiones!$I$8)>0), "Sprint 20",OR(COUNTIF(P52:V52,Versiones!$G$7)>0, COUNTIF(P52:V52,Versiones!$H$7)>0, COUNTIF(P52:V52,Versiones!$I$7)>0), "Sprint 19",OR(COUNTIF(P52:V52,Versiones!$G$6)>0, COUNTIF(P52:V52,Versiones!$H$6)>0, COUNTIF(P52:V52,Versiones!$I$6)>0), "Sprint 18",OR(COUNTIF(P52:V52,Versiones!$G$4)>0, COUNTIF(P52:V52,Versiones!$H$4)>0, COUNTIF(P52:V52,Versiones!$G$5)>0, COUNTIF(P52:V52,Versiones!$H$5)>0), "Sprint 17",OR(COUNTIF(P52:V52,Versiones!$G$2)>0, COUNTIF(P52:V52,Versiones!$H$2)>0, COUNTIF(P52:V52,Versiones!$G$3)>0, COUNTIF(P52:V52,Versiones!$H$3)>0), "Sprint 16", OR(COUNTIF(P52:V52,Versiones!$G$2)>0, COUNTIF(P52:V52,Versiones!$H$2)>0, COUNTIF(P52:V52,Versiones!$G$3)>0, COUNTIF(P52:V52,Versiones!$H$3)>0), "Sprint 16",TRUE, "")} -> Sprint 20 | AF52: ="v"&MAX( IFERROR(VALUE(MID(Jira__32[[#This Row],[Versiones corregidas]],2,99)),0), IFERROR(VALUE(MID(Jira__32[[#This Row],[Versiones corregidas_13]],2,99)),0), IFERROR(VALUE(MID(Jira__32[[#This Row],[Versiones corregidas_14]],2,99)),0) ) -> v0 | AG52: {=_xlfn.IFS(Jira__32[[#This Row],[¿En qué versión fue corregido?]]="v0","N/A",Jira__32[[#This Row],[¿En qué versión fue corregido?]]="v0.4","Sprint 16", Jira__32[[#This Row],[¿En qué versión fue corregido?]]="v0.5","Sprint 17", Jira__32[[#This Row],[¿En qué versión fue corregido?]]="v0.6","Sprint 18", Jira__32[[#This Row],[¿En qué versión fue corregido?]]="v0.7","Sprint 19", Jira__32[[#This Row],[¿En qué versión fue corregido?]]="v0.8","Sprint 20",Jira__32[[#This Row],[¿En qué versión fue corregido?]]="v0.9","Sprint 21", TRUE,"Desconocido")} -> N/A | AH52: {=_xlfn.IFS(COUNTIF(P52:V52, Versiones!$A$13)>0, "Funcional", COUNTIF(P52:V52, Versiones!$A$14)>0, "Configuración", COUNTIF(P52:V52, Versiones!$A$15)>0, "Look&Feel", COUNTIF(P52:V52, Versiones!$A$16)>0, "Integración", COUNTIF(P52:V52, Versiones!$A$17)>0, "Contenido/Datos", COUNTIF(P52:V52, Versiones!$A$18)>0, "Eventos_Cosmos", COUNTIF(P52:V52, Versiones!$A$19)>0, "Eventos_iOT", COUNTIF(P52:V52, Versiones!$A$20)>0, "Eventos_Fabric", TRUE, "No encontrado")} -> Funcional
A53: Error | B53: T20-1924 | C53: 98563 | D53: BOT_Evento BOT_Logout llega a Iothub con datos incorrectos | H53: Alta | I53: TO BE DEPLOYED-SIT | J53: T20 Sprint 21 2025 | P53: Eventos_iOT | Q53: QA-IntegraciónV0.8 | W53: Yubisleinys Mora Vega | X53: 45931.461 | Y53: v0.8 | AB53: =IF(LEFT(Jira__32[[#This Row],[Resumen]],3)="POS","POS",IF(LEFT(Jira__32[[#This Row],[Resumen]],3)="BOT","BOT","")) -> BOT | AC53: Andres Vergara | AE53: {=_xlfn.IFS(OR(COUNTIF(P53:V53,Versiones!$G$9)>0, COUNTIF(P53:V53,Versiones!$H$8)>0), "Sprint 21",OR(COUNTIF(P53:V53,Versiones!$G$8)>0, COUNTIF(P53:V53,Versiones!$H$8)>0, COUNTIF(P53:V53,Versiones!$I$8)>0), "Sprint 20",OR(COUNTIF(P53:V53,Versiones!$G$7)>0, COUNTIF(P53:V53,Versiones!$H$7)>0, COUNTIF(P53:V53,Versiones!$I$7)>0), "Sprint 19",OR(COUNTIF(P53:V53,Versiones!$G$6)>0, COUNTIF(P53:V53,Versiones!$H$6)>0, COUNTIF(P53:V53,Versiones!$I$6)>0), "Sprint 18",OR(COUNTIF(P53:V53,Versiones!$G$4)>0, COUNTIF(P53:V53,Versiones!$H$4)>0, COUNTIF(P53:V53,Versiones!$G$5)>0, COUNTIF(P53:V53,Versiones!$H$5)>0), "Sprint 17",OR(COUNTIF(P53:V53,Versiones!$G$2)>0, COUNTIF(P53:V53,Versiones!$H$2)>0, COUNTIF(P53:V53,Versiones!$G$3)>0, COUNTIF(P53:V53,Versiones!$H$3)>0), "Sprint 16", OR(COUNTIF(P53:V53,Versiones!$G$2)>0, COUNTIF(P53:V53,Versiones!$H$2)>0, COUNTIF(P53:V53,Versiones!$G$3)>0, COUNTIF(P53:V53,Versiones!$H$3)>0), "Sprint 16",TRUE, "")} -> Sprint 20 | AF53: ="v"&MAX( IFERROR(VALUE(MID(Jira__32[[#This Row],[Versiones corregidas]],2,99)),0), IFERROR(VALUE(MID(Jira__32[[#This Row],[Versiones corregidas_13]],2,99)),0), IFERROR(VALUE(MID(Jira__32[[#This Row],[Versiones corregidas_14]],2,99)),0) ) -> v0.8 | AG53: {=_xlfn.IFS(Jira__32[[#This Row],[¿En qué versión fue corregido?]]="v0","N/A",Jira__32[[#This Row],[¿En qué versión fue corregido?]]="v0.4","Sprint 16", Jira__32[[#This Row],[¿En qué versión fue corregido?]]="v0.5","Sprint 17", Jira__32[[#This Row],[¿En qué versión fue corregido?]]="v0.6","Sprint 18", Jira__32[[#This Row],[¿En qué versión fue corregido?]]="v0.7","Sprint 19", Jira__32[[#This Row],[¿En qué versión fue corregido?]]="v0.8","Sprint 20",Jira__32[[#This Row],[¿En qué versión fue corregido?]]="v0.9","Sprint 21", TRUE,"Desconocido")} -> Sprint 20 | AH53: {=_xlfn.IFS(COUNTIF(P53:V53, Versiones!$A$13)>0, "Funcional", COUNTIF(P53:V53, Versiones!$A$14)>0, "Configuración", COUNTIF(P53:V53, Versiones!$A$15)>0, "Look&Feel", COUNTIF(P53:V53, Versiones!$A$16)>0, "Integración", COUNTIF(P53:V53, Versiones!$A$17)>0, "Contenido/Datos", COUNTIF(P53:V53, Versiones!$A$18)>0, "Eventos_Cosmos", COUNTIF(P53:V53, Versiones!$A$19)>0, "Eventos_iOT", COUNTIF(P53:V53, Versiones!$A$20)>0, "Eventos_Fabric", TRUE, "No encontrado")} -> Eventos_iOT
A54: Error | B54: T20-1915 | C54: 98503 | D54: BOT - Aceptar mensaje entrante falla, se debe de forzar el cierre. | H54: Alta | I54: Blocked | J54: T20 Sprint 21 2025 | P54: Funcional | Q54: QA-IntegraciónV0.8 | W54: Daniela Soto | X54: 45931.367 | AB54: =IF(LEFT(Jira__32[[#This Row],[Resumen]],3)="POS","POS",IF(LEFT(Jira__32[[#This Row],[Resumen]],3)="BOT","BOT","")) -> BOT | AC54: Andres Vergara | AE54: {=_xlfn.IFS(OR(COUNTIF(P54:V54,Versiones!$G$9)>0, COUNTIF(P54:V54,Versiones!$H$8)>0), "Sprint 21",OR(COUNTIF(P54:V54,Versiones!$G$8)>0, COUNTIF(P54:V54,Versiones!$H$8)>0, COUNTIF(P54:V54,Versiones!$I$8)>0), "Sprint 20",OR(COUNTIF(P54:V54,Versiones!$G$7)>0, COUNTIF(P54:V54,Versiones!$H$7)>0, COUNTIF(P54:V54,Versiones!$I$7)>0), "Sprint 19",OR(COUNTIF(P54:V54,Versiones!$G$6)>0, COUNTIF(P54:V54,Versiones!$H$6)>0, COUNTIF(P54:V54,Versiones!$I$6)>0), "Sprint 18",OR(COUNTIF(P54:V54,Versiones!$G$4)>0, COUNTIF(P54:V54,Versiones!$H$4)>0, COUNTIF(P54:V54,Versiones!$G$5)>0, COUNTIF(P54:V54,Versiones!$H$5)>0), "Sprint 17",OR(COUNTIF(P54:V54,Versiones!$G$2)>0, COUNTIF(P54:V54,Versiones!$H$2)>0, COUNTIF(P54:V54,Versiones!$G$3)>0, COUNTIF(P54:V54,Versiones!$H$3)>0), "Sprint 16", OR(COUNTIF(P54:V54,Versiones!$G$2)>0, COUNTIF(P54:V54,Versiones!$H$2)>0, COUNTIF(P54:V54,Versiones!$G$3)>0, COUNTIF(P54:V54,Versiones!$H$3)>0), "Sprint 16",TRUE, "")} -> Sprint 20 | AF54: ="v"&MAX( IFERROR(VALUE(MID(Jira__32[[#This Row],[Versiones corregidas]],2,99)),0), IFERROR(VALUE(MID(Jira__32[[#This Row],[Versiones corregidas_13]],2,99)),0), IFERROR(VALUE(MID(Jira__32[[#This Row],[Versiones corregidas_14]],2,99)),0) ) -> v0 | AG54: {=_xlfn.IFS(Jira__32[[#This Row],[¿En qué versión fue corregido?]]="v0","N/A",Jira__32[[#This Row],[¿En qué versión fue corregido?]]="v0.4","Sprint 16", Jira__32[[#This Row],[¿En qué versión fue corregido?]]="v0.5","Sprint 17", Jira__32[[#This Row],[¿En qué versión fue corregido?]]="v0.6","Sprint 18", Jira__32[[#This Row],[¿En qué versión fue corregido?]]="v0.7","Sprint 19", Jira__32[[#This Row],[¿En qué versión fue corregido?]]="v0.8","Sprint 20",Jira__32[[#This Row],[¿En qué versión fue corregido?]]="v0.9","Sprint 21", TRUE,"Desconocido")} -> N/A | AH54: {=_xlfn.IFS(COUNTIF(P54:V54, Versiones!$A$13)>0, "Funcional", COUNTIF(P54:V54, Versiones!$A$14)>0, "Configuración", COUNTIF(P54:V54, Versiones!$A$15)>0, "Look&Feel", COUNTIF(P54:V54, Versiones!$A$16)>0, "Integración", COUNTIF(P54:V54, Versiones!$A$17)>0, "Contenido/Datos", COUNTIF(P54:V54, Versiones!$A$18)>0, "Eventos_Cosmos", COUNTIF(P54:V54, Versiones!$A$19)>0, "Eventos_iOT", COUNTIF(P54:V54, Versiones!$A$20)>0, "Eventos_Fabric", TRUE, "No encontrado")} -> Funcional
A55: Error | B55: T20-1800 | C55: 97844 | D55: BOT - Toast de "trasnsferencia de productos" reaparece al seleccionar otros productos | H55: Alta | I55: TO BE DEPLOYED-SIT | J55: T20 Sprint 21 2025 | P55: Look&Feel | Q55: QA-IntegraciónV0.7 | W55: Daniela Soto | X55: 45929.381 | AB55: =IF(LEFT(Jira__32[[#This Row],[Resumen]],3)="POS","POS",IF(LEFT(Jira__32[[#This Row],[Resumen]],3)="BOT","BOT","")) -> BOT | AC55: Andres Vergara | AE55: {=_xlfn.IFS(OR(COUNTIF(P55:V55,Versiones!$G$9)>0, COUNTIF(P55:V55,Versiones!$H$8)>0), "Sprint 21",OR(COUNTIF(P55:V55,Versiones!$G$8)>0, COUNTIF(P55:V55,Versiones!$H$8)>0, COUNTIF(P55:V55,Versiones!$I$8)>0), "Sprint 20",OR(COUNTIF(P55:V55,Versiones!$G$7)>0, COUNTIF(P55:V55,Versiones!$H$7)>0, COUNTIF(P55:V55,Versiones!$I$7)>0), "Sprint 19",OR(COUNTIF(P55:V55,Versiones!$G$6)>0, COUNTIF(P55:V55,Versiones!$H$6)>0, COUNTIF(P55:V55,Versiones!$I$6)>0), "Sprint 18",OR(COUNTIF(P55:V55,Versiones!$G$4)>0, COUNTIF(P55:V55,Versiones!$H$4)>0, COUNTIF(P55:V55,Versiones!$G$5)>0, COUNTIF(P55:V55,Versiones!$H$5)>0), "Sprint 17",OR(COUNTIF(P55:V55,Versiones!$G$2)>0, COUNTIF(P55:V55,Versiones!$H$2)>0, COUNTIF(P55:V55,Versiones!$G$3)>0, COUNTIF(P55:V55,Versiones!$H$3)>0), "Sprint 16", OR(COUNTIF(P55:V55,Versiones!$G$2)>0, COUNTIF(P55:V55,Versiones!$H$2)>0, COUNTIF(P55:V55,Versiones!$G$3)>0, COUNTIF(P55:V55,Versiones!$H$3)>0), "Sprint 16",TRUE, "")} -> Sprint 19 | AF55: ="v"&MAX( IFERROR(VALUE(MID(Jira__32[[#This Row],[Versiones corregidas]],2,99)),0), IFERROR(VALUE(MID(Jira__32[[#This Row],[Versiones corregidas_13]],2,99)),0), IFERROR(VALUE(MID(Jira__32[[#This Row],[Versiones corregidas_14]],2,99)),0) ) -> v0 | AG55: {=_xlfn.IFS(Jira__32[[#This Row],[¿En qué versión fue corregido?]]="v0","N/A",Jira__32[[#This Row],[¿En qué versión fue corregido?]]="v0.4","Sprint 16", Jira__32[[#This Row],[¿En qué versión fue corregido?]]="v0.5","Sprint 17", Jira__32[[#This Row],[¿En qué versión fue corregido?]]="v0.6","Sprint 18", Jira__32[[#This Row],[¿En qué versión fue corregido?]]="v0.7","Sprint 19", Jira__32[[#This Row],[¿En qué versión fue corregido?]]="v0.8","Sprint 20",Jira__32[[#This Row],[¿En qué versión fue corregido?]]="v0.9","Sprint 21", TRUE,"Desconocido")} -> N/A | AH55: {=_xlfn.IFS(COUNTIF(P55:V55, Versiones!$A$13)>0, "Funcional", COUNTIF(P55:V55, Versiones!$A$14)>0, "Configuración", COUNTIF(P55:V55, Versiones!$A$15)>0, "Look&Feel", COUNTIF(P55:V55, Versiones!$A$16)>0, "Integración", COUNTIF(P55:V55, Versiones!$A$17)>0, "Contenido/Datos", COUNTIF(P55:V55, Versiones!$A$18)>0, "Eventos_Cosmos", COUNTIF(P55:V55, Versiones!$A$19)>0, "Eventos_iOT", COUNTIF(P55:V55, Versiones!$A$20)>0, "Eventos_Fabric", TRUE, "No encontrado")} -> Look&Feel
A56: Error | B56: T20-1797 | C56: 97661 | D56: POS - opción "Realizar alivio" abre modal de "Cerrar Turno" | H56: Alta | I56: Tareas por hacer | J56: T20 Sprint 19 2025 | K56: T20 Sprint 21 2025 | P56: Funcional | Q56: QA-IntegraciónV0.7 | W56: Daniela Soto | X56: 45926.625 | AB56: =IF(LEFT(Jira__32[[#This Row],[Resumen]],3)="POS","POS",IF(LEFT(Jira__32[[#This Row],[Resumen]],3)="BOT","BOT","")) -> POS | AC56: Sergio Ordaz Romero | AE56: {=_xlfn.IFS(OR(COUNTIF(P56:V56,Versiones!$G$9)>0, COUNTIF(P56:V56,Versiones!$H$8)>0), "Sprint 21",OR(COUNTIF(P56:V56,Versiones!$G$8)>0, COUNTIF(P56:V56,Versiones!$H$8)>0, COUNTIF(P56:V56,Versiones!$I$8)>0), "Sprint 20",OR(COUNTIF(P56:V56,Versiones!$G$7)>0, COUNTIF(P56:V56,Versiones!$H$7)>0, COUNTIF(P56:V56,Versiones!$I$7)>0), "Sprint 19",OR(COUNTIF(P56:V56,Versiones!$G$6)>0, COUNTIF(P56:V56,Versiones!$H$6)>0, COUNTIF(P56:V56,Versiones!$I$6)>0), "Sprint 18",OR(COUNTIF(P56:V56,Versiones!$G$4)>0, COUNTIF(P56:V56,Versiones!$H$4)>0, COUNTIF(P56:V56,Versiones!$G$5)>0, COUNTIF(P56:V56,Versiones!$H$5)>0), "Sprint 17",OR(COUNTIF(P56:V56,Versiones!$G$2)>0, COUNTIF(P56:V56,Versiones!$H$2)>0, COUNTIF(P56:V56,Versiones!$G$3)>0, COUNTIF(P56:V56,Versiones!$H$3)>0), "Sprint 16", OR(COUNTIF(P56:V56,Versiones!$G$2)>0, COUNTIF(P56:V56,Versiones!$H$2)>0, COUNTIF(P56:V56,Versiones!$G$3)>0, COUNTIF(P56:V56,Versiones!$H$3)>0), "Sprint 16",TRUE, "")} -> Sprint 19 | AF56: ="v"&MAX( IFERROR(VALUE(MID(Jira__32[[#This Row],[Versiones corregidas]],2,99)),0), IFERROR(VALUE(MID(Jira__32[[#This Row],[Versiones corregidas_13]],2,99)),0), IFERROR(VALUE(MID(Jira__32[[#This Row],[Versiones corregidas_14]],2,99)),0) ) -> v0 | AG56: {=_xlfn.IFS(Jira__32[[#This Row],[¿En qué versión fue corregido?]]="v0","N/A",Jira__32[[#This Row],[¿En qué versión fue corregido?]]="v0.4","Sprint 16", Jira__32[[#This Row],[¿En qué versión fue corregido?]]="v0.5","Sprint 17", Jira__32[[#This Row],[¿En qué versión fue corregido?]]="v0.6","Sprint 18", Jira__32[[#This Row],[¿En qué versión fue corregido?]]="v0.7","Sprint 19", Jira__32[[#This Row],[¿En qué versión fue corregido?]]="v0.8","Sprint 20",Jira__32[[#This Row],[¿En qué versión fue corregido?]]="v0.9","Sprint 21", TRUE,"Desconocido")} -> N/A | AH56: {=_xlfn.IFS(COUNTIF(P56:V56, Versiones!$A$13)>0, "Funcional", COUNTIF(P56:V56, Versiones!$A$14)>0, "Configuración", COUNTIF(P56:V56, Versiones!$A$15)>0, "Look&Feel", COUNTIF(P56:V56, Versiones!$A$16)>0, "Integración", COUNTIF(P56:V56, Versiones!$A$17)>0, "Contenido/Datos", COUNTIF(P56:V56, Versiones!$A$18)>0, "Eventos_Cosmos", COUNTIF(P56:V56, Versiones!$A$19)>0, "Eventos_iOT", COUNTIF(P56:V56, Versiones!$A$20)>0, "Eventos_Fabric", TRUE, "No encontrado")} -> Funcional
A57: Error | B57: T20-1794 | C57: 97648 | D57: POS - Confirmar Realizar alivio falla | E57: 79941 | F57: T20-623 | G57: 3.-Desarrollo POS/BOT /CDM | H57: Alta | I57: Tareas por hacer | J57: T20 Sprint 19 2025 | K57: T20 Sprint 21 2025 | P57: Funcional | Q57: QA-IntegraciónV0.7 | W57: Daniela Soto | X57: 45926.607 | AB57: =IF(LEFT(Jira__32[[#This Row],[Resumen]],3)="POS","POS",IF(LEFT(Jira__32[[#This Row],[Resumen]],3)="BOT","BOT","")) -> POS | AC57: Sergio Ordaz Romero | AE57: {=_xlfn.IFS(OR(COUNTIF(P57:V57,Versiones!$G$9)>0, COUNTIF(P57:V57,Versiones!$H$8)>0), "Sprint 21",OR(COUNTIF(P57:V57,Versiones!$G$8)>0, COUNTIF(P57:V57,Versiones!$H$8)>0, COUNTIF(P57:V57,Versiones!$I$8)>0), "Sprint 20",OR(COUNTIF(P57:V57,Versiones!$G$7)>0, COUNTIF(P57:V57,Versiones!$H$7)>0, COUNTIF(P57:V57,Versiones!$I$7)>0), "Sprint 19",OR(COUNTIF(P57:V57,Versiones!$G$6)>0, COUNTIF(P57:V57,Versiones!$H$6)>0, COUNTIF(P57:V57,Versiones!$I$6)>0), "Sprint 18",OR(COUNTIF(P57:V57,Versiones!$G$4)>0, COUNTIF(P57:V57,Versiones!$H$4)>0, COUNTIF(P57:V57,Versiones!$G$5)>0, COUNTIF(P57:V57,Versiones!$H$5)>0), "Sprint 17",OR(COUNTIF(P57:V57,Versiones!$G$2)>0, COUNTIF(P57:V57,Versiones!$H$2)>0, COUNTIF(P57:V57,Versiones!$G$3)>0, COUNTIF(P57:V57,Versiones!$H$3)>0), "Sprint 16", OR(COUNTIF(P57:V57,Versiones!$G$2)>0, COUNTIF(P57:V57,Versiones!$H$2)>0, COUNTIF(P57:V57,Versiones!$G$3)>0, COUNTIF(P57:V57,Versiones!$H$3)>0), "Sprint 16",TRUE, "")} -> Sprint 19 | AF57: ="v"&MAX( IFERROR(VALUE(MID(Jira__32[[#This Row],[Versiones corregidas]],2,99)),0), IFERROR(VALUE(MID(Jira__32[[#This Row],[Versiones corregidas_13]],2,99)),0), IFERROR(VALUE(MID(Jira__32[[#This Row],[Versiones corregidas_14]],2,99)),0) ) -> v0 | AG57: {=_xlfn.IFS(Jira__32[[#This Row],[¿En qué versión fue corregido?]]="v0","N/A",Jira__32[[#This Row],[¿En qué versión fue corregido?]]="v0.4","Sprint 16", Jira__32[[#This Row],[¿En qué versión fue corregido?]]="v0.5","Sprint 17", Jira__32[[#This Row],[¿En qué versión fue corregido?]]="v0.6","Sprint 18", Jira__32[[#This Row],[¿En qué versión fue corregido?]]="v0.7","Sprint 19", Jira__32[[#This Row],[¿En qué versión fue corregido?]]="v0.8","Sprint 20",Jira__32[[#This Row],[¿En qué versión fue corregido?]]="v0.9","Sprint 21", TRUE,"Desconocido")} -> N/A | AH57: {=_xlfn.IFS(COUNTIF(P57:V57, Versiones!$A$13)>0, "Funcional", COUNTIF(P57:V57, Versiones!$A$14)>0, "Configuración", COUNTIF(P57:V57, Versiones!$A$15)>0, "Look&Feel", COUNTIF(P57:V57, Versiones!$A$16)>0, "Integración", COUNTIF(P57:V57, Versiones!$A$17)>0, "Contenido/Datos", COUNTIF(P57:V57, Versiones!$A$18)>0, "Eventos_Cosmos", COUNTIF(P57:V57, Versiones!$A$19)>0, "Eventos_iOT", COUNTIF(P57:V57, Versiones!$A$20)>0, "Eventos_Fabric", TRUE, "No encontrado")} -> Funcional
A58: Error | B58: T20-1791 | C58: 97611 | D58: POS - No coincide el boton "Aceptar" versión de la aplicación VS Figma | E58: 87100 | F58: T20-1091 | G58: 4.- QA | H58: Medio | I58: Cancelado | J58: Backlog BUGS | P58: Contenido/Datos | Q58: QA-EquipoMV0.7 | W58: Josue Jesus Espindola Velasco | X58: 45926.549 | Y58: v0.7 | AB58: =IF(LEFT(Jira__32[[#This Row],[Resumen]],3)="POS","POS",IF(LEFT(Jira__32[[#This Row],[Resumen]],3)="BOT","BOT","")) -> POS | AC58: Sergio Ordaz Romero | AE58: {=_xlfn.IFS(OR(COUNTIF(P58:V58,Versiones!$G$9)>0, COUNTIF(P58:V58,Versiones!$H$8)>0), "Sprint 21",OR(COUNTIF(P58:V58,Versiones!$G$8)>0, COUNTIF(P58:V58,Versiones!$H$8)>0, COUNTIF(P58:V58,Versiones!$I$8)>0), "Sprint 20",OR(COUNTIF(P58:V58,Versiones!$G$7)>0, COUNTIF(P58:V58,Versiones!$H$7)>0, COUNTIF(P58:V58,Versiones!$I$7)>0), "Sprint 19",OR(COUNTIF(P58:V58,Versiones!$G$6)>0, COUNTIF(P58:V58,Versiones!$H$6)>0, COUNTIF(P58:V58,Versiones!$I$6)>0), "Sprint 18",OR(COUNTIF(P58:V58,Versiones!$G$4)>0, COUNTIF(P58:V58,Versiones!$H$4)>0, COUNTIF(P58:V58,Versiones!$G$5)>0, COUNTIF(P58:V58,Versiones!$H$5)>0), "Sprint 17",OR(COUNTIF(P58:V58,Versiones!$G$2)>0, COUNTIF(P58:V58,Versiones!$H$2)>0, COUNTIF(P58:V58,Versiones!$G$3)>0, COUNTIF(P58:V58,Versiones!$H$3)>0), "Sprint 16", OR(COUNTIF(P58:V58,Versiones!$G$2)>0, COUNTIF(P58:V58,Versiones!$H$2)>0, COUNTIF(P58:V58,Versiones!$G$3)>0, COUNTIF(P58:V58,Versiones!$H$3)>0), "Sprint 16",TRUE, "")} -> Sprint 19 | AF58: ="v"&MAX( IFERROR(VALUE(MID(Jira__32[[#This Row],[Versiones corregidas]],2,99)),0), IFERROR(VALUE(MID(Jira__32[[#This Row],[Versiones corregidas_13]],2,99)),0), IFERROR(VALUE(MID(Jira__32[[#This Row],[Versiones corregidas_14]],2,99)),0) ) -> v0.7 | AG58: {=_xlfn.IFS(Jira__32[[#This Row],[¿En qué versión fue corregido?]]="v0","N/A",Jira__32[[#This Row],[¿En qué versión fue corregido?]]="v0.4","Sprint 16", Jira__32[[#This Row],[¿En qué versión fue corregido?]]="v0.5","Sprint 17", Jira__32[[#This Row],[¿En qué versión fue corregido?]]="v0.6","Sprint 18", Jira__32[[#This Row],[¿En qué versión fue corregido?]]="v0.7","Sprint 19", Jira__32[[#This Row],[¿En qué versión fue corregido?]]="v0.8","Sprint 20",Jira__32[[#This Row],[¿En qué versión fue corregido?]]="v0.9","Sprint 21", TRUE,"Desconocido")} -> Sprint 19 | AH58: {=_xlfn.IFS(COUNTIF(P58:V58, Versiones!$A$13)>0, "Funcional", COUNTIF(P58:V58, Versiones!$A$14)>0, "Configuración", COUNTIF(P58:V58, Versiones!$A$15)>0, "Look&Feel", COUNTIF(P58:V58, Versiones!$A$16)>0, "Integración", COUNTIF(P58:V58, Versiones!$A$17)>0, "Contenido/Datos", COUNTIF(P58:V58, Versiones!$A$18)>0, "Eventos_Cosmos", COUNTIF(P58:V58, Versiones!$A$19)>0, "Eventos_iOT", COUNTIF(P58:V58, Versiones!$A$20)>0, "Eventos_Fabric", TRUE, "No encontrado")} -> Contenido/Datos
A59: Error | B59: T20-1755 | C59: 97011 | D59: POS_Solicitud fondeo adicional - No se visualiza evento | E59: 87100 | F59: T20-1091 | G59: 4.- QA | H59: Alta | I59: Tareas por hacer | J59: T20 Sprint 19 2025 | K59: T20 Sprint 21 2025 | P59: Eventos_iOT | Q59: QA-IntegraciónV0.7 | W59: Yubisleinys Mora Vega | X59: 45924.77 | Y59: v0.7 | AB59: =IF(LEFT(Jira__32[[#This Row],[Resumen]],3)="POS","POS",IF(LEFT(Jira__32[[#This Row],[Resumen]],3)="BOT","BOT","")) -> POS | AC59: Sergio Ordaz Romero | AE59: {=_xlfn.IFS(OR(COUNTIF(P59:V59,Versiones!$G$9)>0, COUNTIF(P59:V59,Versiones!$H$8)>0), "Sprint 21",OR(COUNTIF(P59:V59,Versiones!$G$8)>0, COUNTIF(P59:V59,Versiones!$H$8)>0, COUNTIF(P59:V59,Versiones!$I$8)>0), "Sprint 20",OR(COUNTIF(P59:V59,Versiones!$G$7)>0, COUNTIF(P59:V59,Versiones!$H$7)>0, COUNTIF(P59:V59,Versiones!$I$7)>0), "Sprint 19",OR(COUNTIF(P59:V59,Versiones!$G$6)>0, COUNTIF(P59:V59,Versiones!$H$6)>0, COUNTIF(P59:V59,Versiones!$I$6)>0), "Sprint 18",OR(COUNTIF(P59:V59,Versiones!$G$4)>0, COUNTIF(P59:V59,Versiones!$H$4)>0, COUNTIF(P59:V59,Versiones!$G$5)>0, COUNTIF(P59:V59,Versiones!$H$5)>0), "Sprint 17",OR(COUNTIF(P59:V59,Versiones!$G$2)>0, COUNTIF(P59:V59,Versiones!$H$2)>0, COUNTIF(P59:V59,Versiones!$G$3)>0, COUNTIF(P59:V59,Versiones!$H$3)>0), "Sprint 16", OR(COUNTIF(P59:V59,Versiones!$G$2)>0, COUNTIF(P59:V59,Versiones!$H$2)>0, COUNTIF(P59:V59,Versiones!$G$3)>0, COUNTIF(P59:V59,Versiones!$H$3)>0), "Sprint 16",TRUE, "")} -> Sprint 19 | AF59: ="v"&MAX( IFERROR(VALUE(MID(Jira__32[[#This Row],[Versiones corregidas]],2,99)),0), IFERROR(VALUE(MID(Jira__32[[#This Row],[Versiones corregidas_13]],2,99)),0), IFERROR(VALUE(MID(Jira__32[[#This Row],[Versiones corregidas_14]],2,99)),0) ) -> v0.7 | AG59: {=_xlfn.IFS(Jira__32[[#This Row],[¿En qué versión fue corregido?]]="v0","N/A",Jira__32[[#This Row],[¿En qué versión fue corregido?]]="v0.4","Sprint 16", Jira__32[[#This Row],[¿En qué versión fue corregido?]]="v0.5","Sprint 17", Jira__32[[#This Row],[¿En qué versión fue corregido?]]="v0.6","Sprint 18", Jira__32[[#This Row],[¿En qué versión fue corregido?]]="v0.7","Sprint 19", Jira__32[[#This Row],[¿En qué versión fue corregido?]]="v0.8","Sprint 20",Jira__32[[#This Row],[¿En qué versión fue corregido?]]="v0.9","Sprint 21", TRUE,"Desconocido")} -> Sprint 19 | AH59: {=_xlfn.IFS(COUNTIF(P59:V59, Versiones!$A$13)>0, "Funcional", COUNTIF(P59:V59, Versiones!$A$14)>0, "Configuración", COUNTIF(P59:V59, Versiones!$A$15)>0, "Look&Feel", COUNTIF(P59:V59, Versiones!$A$16)>0, "Integración", COUNTIF(P59:V59, Versiones!$A$17)>0, "Contenido/Datos", COUNTIF(P59:V59, Versiones!$A$18)>0, "Eventos_Cosmos", COUNTIF(P59:V59, Versiones!$A$19)>0, "Eventos_iOT", COUNTIF(P59:V59, Versiones!$A$20)>0, "Eventos_Fabric", TRUE, "No encontrado")} -> Eventos_iOT
A60: Error | B60: T20-1754 | C60: 96997 | D60: POS_Realizar alivio - No se visualiza evento | E60: 87100 | F60: T20-1091 | G60: 4.- QA | H60: Medio | I60: Tareas por hacer | J60: T20 Sprint 19 2025 | K60: Backlog BUGS | P60: Eventos_iOT | Q60: QA-IntegraciónV0.7 | W60: Yubisleinys Mora Vega | X60: 45924.737 | Y60: v0.7 | AB60: =IF(LEFT(Jira__32[[#This Row],[Resumen]],3)="POS","POS",IF(LEFT(Jira__32[[#This Row],[Resumen]],3)="BOT","BOT","")) -> POS | AC60: Sergio Ordaz Romero | AE60: {=_xlfn.IFS(OR(COUNTIF(P60:V60,Versiones!$G$9)>0, COUNTIF(P60:V60,Versiones!$H$8)>0), "Sprint 21",OR(COUNTIF(P60:V60,Versiones!$G$8)>0, COUNTIF(P60:V60,Versiones!$H$8)>0, COUNTIF(P60:V60,Versiones!$I$8)>0), "Sprint 20",OR(COUNTIF(P60:V60,Versiones!$G$7)>0, COUNTIF(P60:V60,Versiones!$H$7)>0, COUNTIF(P60:V60,Versiones!$I$7)>0), "Sprint 19",OR(COUNTIF(P60:V60,Versiones!$G$6)>0, COUNTIF(P60:V60,Versiones!$H$6)>0, COUNTIF(P60:V60,Versiones!$I$6)>0), "Sprint 18",OR(COUNTIF(P60:V60,Versiones!$G$4)>0, COUNTIF(P60:V60,Versiones!$H$4)>0, COUNTIF(P60:V60,Versiones!$G$5)>0, COUNTIF(P60:V60,Versiones!$H$5)>0), "Sprint 17",OR(COUNTIF(P60:V60,Versiones!$G$2)>0, COUNTIF(P60:V60,Versiones!$H$2)>0, COUNTIF(P60:V60,Versiones!$G$3)>0, COUNTIF(P60:V60,Versiones!$H$3)>0), "Sprint 16", OR(COUNTIF(P60:V60,Versiones!$G$2)>0, COUNTIF(P60:V60,Versiones!$H$2)>0, COUNTIF(P60:V60,Versiones!$G$3)>0, COUNTIF(P60:V60,Versiones!$H$3)>0), "Sprint 16",TRUE, "")} -> Sprint 19 | AF60: ="v"&MAX( IFERROR(VALUE(MID(Jira__32[[#This Row],[Versiones corregidas]],2,99)),0), IFERROR(VALUE(MID(Jira__32[[#This Row],[Versiones corregidas_13]],2,99)),0), IFERROR(VALUE(MID(Jira__32[[#This Row],[Versiones corregidas_14]],2,99)),0) ) -> v0.7 | AG60: {=_xlfn.IFS(Jira__32[[#This Row],[¿En qué versión fue corregido?]]="v0","N/A",Jira__32[[#This Row],[¿En qué versión fue corregido?]]="v0.4","Sprint 16", Jira__32[[#This Row],[¿En qué versión fue corregido?]]="v0.5","Sprint 17", Jira__32[[#This Row],[¿En qué versión fue corregido?]]="v0.6","Sprint 18", Jira__32[[#This Row],[¿En qué versión fue corregido?]]="v0.7","Sprint 19", Jira__32[[#This Row],[¿En qué versión fue corregido?]]="v0.8","Sprint 20",Jira__32[[#This Row],[¿En qué versión fue corregido?]]="v0.9","Sprint 21", TRUE,"Desconocido")} -> Sprint 19 | AH60: {=_xlfn.IFS(COUNTIF(P60:V60, Versiones!$A$13)>0, "Funcional", COUNTIF(P60:V60, Versiones!$A$14)>0, "Configuración", COUNTIF(P60:V60, Versiones!$A$15)>0, "Look&Feel", COUNTIF(P60:V60, Versiones!$A$16)>0, "Integración", COUNTIF(P60:V60, Versiones!$A$17)>0, "Contenido/Datos", COUNTIF(P60:V60, Versiones!$A$18)>0, "Eventos_Cosmos", COUNTIF(P60:V60, Versiones!$A$19)>0, "Eventos_iOT", COUNTIF(P60:V60, Versiones!$A$20)>0, "Eventos_Fabric", TRUE, "No encontrado")} -> Eventos_iOT
A61: Error | B61: T20-1753 | C61: 96996 | D61: BOT - No apareció el botón de Inicio de Día después de hacer log in | E61: 87100 | F61: T20-1091 | G61: 4.- QA | H61: Alta | I61: READY FOR UAT | J61: T20 Sprint 19 2025 | K61: Backlog BUGS | P61: Funcional | Q61: QA-EquipoMV0.7 | R61: T3B20_BOT | S61: Tienda2.0 | W61: Daniela Rodríguez | X61: 45924.735 | Y61: v0.8 | AB61: =IF(LEFT(Jira__32[[#This Row],[Resumen]],3)="POS","POS",IF(LEFT(Jira__32[[#This Row],[Resumen]],3)="BOT","BOT","")) -> BOT | AC61: Sergio Ordaz Romero | AE61: {=_xlfn.IFS(OR(COUNTIF(P61:V61,Versiones!$G$9)>0, COUNTIF(P61:V61,Versiones!$H$8)>0), "Sprint 21",OR(COUNTIF(P61:V61,Versiones!$G$8)>0, COUNTIF(P61:V61,Versiones!$H$8)>0, COUNTIF(P61:V61,Versiones!$I$8)>0), "Sprint 20",OR(COUNTIF(P61:V61,Versiones!$G$7)>0, COUNTIF(P61:V61,Versiones!$H$7)>0, COUNTIF(P61:V61,Versiones!$I$7)>0), "Sprint 19",OR(COUNTIF(P61:V61,Versiones!$G$6)>0, COUNTIF(P61:V61,Versiones!$H$6)>0, COUNTIF(P61:V61,Versiones!$I$6)>0), "Sprint 18",OR(COUNTIF(P61:V61,Versiones!$G$4)>0, COUNTIF(P61:V61,Versiones!$H$4)>0, COUNTIF(P61:V61,Versiones!$G$5)>0, COUNTIF(P61:V61,Versiones!$H$5)>0), "Sprint 17",OR(COUNTIF(P61:V61,Versiones!$G$2)>0, COUNTIF(P61:V61,Versiones!$H$2)>0, COUNTIF(P61:V61,Versiones!$G$3)>0, COUNTIF(P61:V61,Versiones!$H$3)>0), "Sprint 16", OR(COUNTIF(P61:V61,Versiones!$G$2)>0, COUNTIF(P61:V61,Versiones!$H$2)>0, COUNTIF(P61:V61,Versiones!$G$3)>0, COUNTIF(P61:V61,Versiones!$H$3)>0), "Sprint 16",TRUE, "")} -> Sprint 19 | AF61: ="v"&MAX( IFERROR(VALUE(MID(Jira__32[[#This Row],[Versiones corregidas]],2,99)),0), IFERROR(VALUE(MID(Jira__32[[#This Row],[Versiones corregidas_13]],2,99)),0), IFERROR(VALUE(MID(Jira__32[[#This Row],[Versiones corregidas_14]],2,99)),0) ) -> v0.8 | AG61: {=_xlfn.IFS(Jira__32[[#This Row],[¿En qué versión fue corregido?]]="v0","N/A",Jira__32[[#This Row],[¿En qué versión fue corregido?]]="v0.4","Sprint 16", Jira__32[[#This Row],[¿En qué versión fue corregido?]]="v0.5","Sprint 17", Jira__32[[#This Row],[¿En qué versión fue corregido?]]="v0.6","Sprint 18", Jira__32[[#This Row],[¿En qué versión fue corregido?]]="v0.7","Sprint 19", Jira__32[[#This Row],[¿En qué versión fue corregido?]]="v0.8","Sprint 20",Jira__32[[#This Row],[¿En qué versión fue corregido?]]="v0.9","Sprint 21", TRUE,"Desconocido")} -> Sprint 20 | AH61: {=_xlfn.IFS(COUNTIF(P61:V61, Versiones!$A$13)>0, "Funcional", COUNTIF(P61:V61, Versiones!$A$14)>0, "Configuración", COUNTIF(P61:V61, Versiones!$A$15)>0, "Look&Feel", COUNTIF(P61:V61, Versiones!$A$16)>0, "Integración", COUNTIF(P61:V61, Versiones!$A$17)>0, "Contenido/Datos", COUNTIF(P61:V61, Versiones!$A$18)>0, "Eventos_Cosmos", COUNTIF(P61:V61, Versiones!$A$19)>0, "Eventos_iOT", COUNTIF(P61:V61, Versiones!$A$20)>0, "Eventos_Fabric", TRUE, "No encontrado")} -> Funcional
A62: Error | B62: T20-1752 | C62: 96993 | D62: BOT – Confirmar fondeo adicional - No se visualiza evento | E62: 87100 | F62: T20-1091 | G62: 4.- QA | H62: Medio | I62: Tareas por hacer | J62: T20 Sprint 19 2025 | K62: Backlog BUGS | P62: Eventos_iOT | Q62: QA-IntegraciónV0.7 | W62: Yubisleinys Mora Vega | X62: 45924.728 | Y62: v0.7 | AB62: =IF(LEFT(Jira__32[[#This Row],[Resumen]],3)="POS","POS",IF(LEFT(Jira__32[[#This Row],[Resumen]],3)="BOT","BOT","")) -> BOT | AC62: Sergio Ordaz Romero | AE62: {=_xlfn.IFS(OR(COUNTIF(P62:V62,Versiones!$G$9)>0, COUNTIF(P62:V62,Versiones!$H$8)>0), "Sprint 21",OR(COUNTIF(P62:V62,Versiones!$G$8)>0, COUNTIF(P62:V62,Versiones!$H$8)>0, COUNTIF(P62:V62,Versiones!$I$8)>0), "Sprint 20",OR(COUNTIF(P62:V62,Versiones!$G$7)>0, COUNTIF(P62:V62,Versiones!$H$7)>0, COUNTIF(P62:V62,Versiones!$I$7)>0), "Sprint 19",OR(COUNTIF(P62:V62,Versiones!$G$6)>0, COUNTIF(P62:V62,Versiones!$H$6)>0, COUNTIF(P62:V62,Versiones!$I$6)>0), "Sprint 18",OR(COUNTIF(P62:V62,Versiones!$G$4)>0, COUNTIF(P62:V62,Versiones!$H$4)>0, COUNTIF(P62:V62,Versiones!$G$5)>0, COUNTIF(P62:V62,Versiones!$H$5)>0), "Sprint 17",OR(COUNTIF(P62:V62,Versiones!$G$2)>0, COUNTIF(P62:V62,Versiones!$H$2)>0, COUNTIF(P62:V62,Versiones!$G$3)>0, COUNTIF(P62:V62,Versiones!$H$3)>0), "Sprint 16", OR(COUNTIF(P62:V62,Versiones!$G$2)>0, COUNTIF(P62:V62,Versiones!$H$2)>0, COUNTIF(P62:V62,Versiones!$G$3)>0, COUNTIF(P62:V62,Versiones!$H$3)>0), "Sprint 16",TRUE, "")} -> Sprint 19 | AF62: ="v"&MAX( IFERROR(VALUE(MID(Jira__32[[#This Row],[Versiones corregidas]],2,99)),0), IFERROR(VALUE(MID(Jira__32[[#This Row],[Versiones corregidas_13]],2,99)),0), IFERROR(VALUE(MID(Jira__32[[#This Row],[Versiones corregidas_14]],2,99)),0) ) -> v0.7 | AG62: {=_xlfn.IFS(Jira__32[[#This Row],[¿En qué versión fue corregido?]]="v0","N/A",Jira__32[[#This Row],[¿En qué versión fue corregido?]]="v0.4","Sprint 16", Jira__32[[#This Row],[¿En qué versión fue corregido?]]="v0.5","Sprint 17", Jira__32[[#This Row],[¿En qué versión fue corregido?]]="v0.6","Sprint 18", Jira__32[[#This Row],[¿En qué versión fue corregido?]]="v0.7","Sprint 19", Jira__32[[#This Row],[¿En qué versión fue corregido?]]="v0.8","Sprint 20",Jira__32[[#This Row],[¿En qué versión fue corregido?]]="v0.9","Sprint 21", TRUE,"Desconocido")} -> Sprint 19 | AH62: {=_xlfn.IFS(COUNTIF(P62:V62, Versiones!$A$13)>0, "Funcional", COUNTIF(P62:V62, Versiones!$A$14)>0, "Configuración", COUNTIF(P62:V62, Versiones!$A$15)>0, "Look&Feel", COUNTIF(P62:V62, Versiones!$A$16)>0, "Integración", COUNTIF(P62:V62, Versiones!$A$17)>0, "Contenido/Datos", COUNTIF(P62:V62, Versiones!$A$18)>0, "Eventos_Cosmos", COUNTIF(P62:V62, Versiones!$A$19)>0, "Eventos_iOT", COUNTIF(P62:V62, Versiones!$A$20)>0, "Eventos_Fabric", TRUE, "No encontrado")} -> Eventos_iOT
A63: Error | B63: T20-1751 | C63: 96991 | D63: BOT - Imagen de Inicio de sesión no concuerda para BOT | E63: 87100 | F63: T20-1091 | G63: 4.- QA | H63: Baja | I63: Tareas por hacer | J63: Backlog BUGS | P63: Look&Feel | Q63: QA-EquipoMV0.7 | W63: Daniela Rodríguez | X63: 45924.728 | AB63: =IF(LEFT(Jira__32[[#This Row],[Resumen]],3)="POS","POS",IF(LEFT(Jira__32[[#This Row],[Resumen]],3)="BOT","BOT","")) -> BOT | AC63: Sergio Ordaz Romero | AE63: {=_xlfn.IFS(OR(COUNTIF(P63:V63,Versiones!$G$9)>0, COUNTIF(P63:V63,Versiones!$H$8)>0), "Sprint 21",OR(COUNTIF(P63:V63,Versiones!$G$8)>0, COUNTIF(P63:V63,Versiones!$H$8)>0, COUNTIF(P63:V63,Versiones!$I$8)>0), "Sprint 20",OR(COUNTIF(P63:V63,Versiones!$G$7)>0, COUNTIF(P63:V63,Versiones!$H$7)>0, COUNTIF(P63:V63,Versiones!$I$7)>0), "Sprint 19",OR(COUNTIF(P63:V63,Versiones!$G$6)>0, COUNTIF(P63:V63,Versiones!$H$6)>0, COUNTIF(P63:V63,Versiones!$I$6)>0), "Sprint 18",OR(COUNTIF(P63:V63,Versiones!$G$4)>0, COUNTIF(P63:V63,Versiones!$H$4)>0, COUNTIF(P63:V63,Versiones!$G$5)>0, COUNTIF(P63:V63,Versiones!$H$5)>0), "Sprint 17",OR(COUNTIF(P63:V63,Versiones!$G$2)>0, COUNTIF(P63:V63,Versiones!$H$2)>0, COUNTIF(P63:V63,Versiones!$G$3)>0, COUNTIF(P63:V63,Versiones!$H$3)>0), "Sprint 16", OR(COUNTIF(P63:V63,Versiones!$G$2)>0, COUNTIF(P63:V63,Versiones!$H$2)>0, COUNTIF(P63:V63,Versiones!$G$3)>0, COUNTIF(P63:V63,Versiones!$H$3)>0), "Sprint 16",TRUE, "")} -> Sprint 19 | AF63: ="v"&MAX( IFERROR(VALUE(MID(Jira__32[[#This Row],[Versiones corregidas]],2,99)),0), IFERROR(VALUE(MID(Jira__32[[#This Row],[Versiones corregidas_13]],2,99)),0), IFERROR(VALUE(MID(Jira__32[[#This Row],[Versiones corregidas_14]],2,99)),0) ) -> v0 | AG63: {=_xlfn.IFS(Jira__32[[#This Row],[¿En qué versión fue corregido?]]="v0","N/A",Jira__32[[#This Row],[¿En qué versión fue corregido?]]="v0.4","Sprint 16", Jira__32[[#This Row],[¿En qué versión fue corregido?]]="v0.5","Sprint 17", Jira__32[[#This Row],[¿En qué versión fue corregido?]]="v0.6","Sprint 18", Jira__32[[#This Row],[¿En qué versión fue corregido?]]="v0.7","Sprint 19", Jira__32[[#This Row],[¿En qué versión fue corregido?]]="v0.8","Sprint 20",Jira__32[[#This Row],[¿En qué versión fue corregido?]]="v0.9","Sprint 21", TRUE,"Desconocido")} -> N/A | AH63: {=_xlfn.IFS(COUNTIF(P63:V63, Versiones!$A$13)>0, "Funcional", COUNTIF(P63:V63, Versiones!$A$14)>0, "Configuración", COUNTIF(P63:V63, Versiones!$A$15)>0, "Look&Feel", COUNTIF(P63:V63, Versiones!$A$16)>0, "Integración", COUNTIF(P63:V63, Versiones!$A$17)>0, "Contenido/Datos", COUNTIF(P63:V63, Versiones!$A$18)>0, "Eventos_Cosmos", COUNTIF(P63:V63, Versiones!$A$19)>0, "Eventos_iOT", COUNTIF(P63:V63, Versiones!$A$20)>0, "Eventos_Fabric", TRUE, "No encontrado")} -> Look&Feel
A64: Error | B64: T20-1750 | C64: 96982 | D64: BOT - Inputs de log in no muestran el label de Usuario y contraseña | E64: 87100 | F64: T20-1091 | G64: 4.- QA | H64: Medio | I64: Tareas por hacer | J64: T20 Sprint 19 2025 | K64: Backlog BUGS | P64: Bug_Devuelto_v0.8 | Q64: Look&Feel | R64: QA-EquipoMV0.7 | S64: T3B20_BOT | T64: Tienda2.0 | W64: Daniela Rodríguez | X64: 45924.713 | Y64: v0.8 | AB64: =IF(LEFT(Jira__32[[#This Row],[Resumen]],3)="POS","POS",IF(LEFT(Jira__32[[#This Row],[Resumen]],3)="BOT","BOT","")) -> BOT | AC64: Juan Camilo Collantes Tovar | AE64: {=_xlfn.IFS(OR(COUNTIF(P64:V64,Versiones!$G$9)>0, COUNTIF(P64:V64,Versiones!$H$8)>0), "Sprint 21",OR(COUNTIF(P64:V64,Versiones!$G$8)>0, COUNTIF(P64:V64,Versiones!$H$8)>0, COUNTIF(P64:V64,Versiones!$I$8)>0), "Sprint 20",OR(COUNTIF(P64:V64,Versiones!$G$7)>0, COUNTIF(P64:V64,Versiones!$H$7)>0, COUNTIF(P64:V64,Versiones!$I$7)>0), "Sprint 19",OR(COUNTIF(P64:V64,Versiones!$G$6)>0, COUNTIF(P64:V64,Versiones!$H$6)>0, COUNTIF(P64:V64,Versiones!$I$6)>0), "Sprint 18",OR(COUNTIF(P64:V64,Versiones!$G$4)>0, COUNTIF(P64:V64,Versiones!$H$4)>0, COUNTIF(P64:V64,Versiones!$G$5)>0, COUNTIF(P64:V64,Versiones!$H$5)>0), "Sprint 17",OR(COUNTIF(P64:V64,Versiones!$G$2)>0, COUNTIF(P64:V64,Versiones!$H$2)>0, COUNTIF(P64:V64,Versiones!$G$3)>0, COUNTIF(P64:V64,Versiones!$H$3)>0), "Sprint 16", OR(COUNTIF(P64:V64,Versiones!$G$2)>0, COUNTIF(P64:V64,Versiones!$H$2)>0, COUNTIF(P64:V64,Versiones!$G$3)>0, COUNTIF(P64:V64,Versiones!$H$3)>0), "Sprint 16",TRUE, "")} -> Sprint 19 | AF64: ="v"&MAX( IFERROR(VALUE(MID(Jira__32[[#This Row],[Versiones corregidas]],2,99)),0), IFERROR(VALUE(MID(Jira__32[[#This Row],[Versiones corregidas_13]],2,99)),0), IFERROR(VALUE(MID(Jira__32[[#This Row],[Versiones corregidas_14]],2,99)),0) ) -> v0.8 | AG64: {=_xlfn.IFS(Jira__32[[#This Row],[¿En qué versión fue corregido?]]="v0","N/A",Jira__32[[#This Row],[¿En qué versión fue corregido?]]="v0.4","Sprint 16", Jira__32[[#This Row],[¿En qué versión fue corregido?]]="v0.5","Sprint 17", Jira__32[[#This Row],[¿En qué versión fue corregido?]]="v0.6","Sprint 18", Jira__32[[#This Row],[¿En qué versión fue corregido?]]="v0.7","Sprint 19", Jira__32[[#This Row],[¿En qué versión fue corregido?]]="v0.8","Sprint 20",Jira__32[[#This Row],[¿En qué versión fue corregido?]]="v0.9","Sprint 21", TRUE,"Desconocido")} -> Sprint 20 | AH64: {=_xlfn.IFS(COUNTIF(P64:V64, Versiones!$A$13)>0, "Funcional", COUNTIF(P64:V64, Versiones!$A$14)>0, "Configuración", COUNTIF(P64:V64, Versiones!$A$15)>0, "Look&Feel", COUNTIF(P64:V64, Versiones!$A$16)>0, "Integración", COUNTIF(P64:V64, Versiones!$A$17)>0, "Contenido/Datos", COUNTIF(P64:V64, Versiones!$A$18)>0, "Eventos_Cosmos", COUNTIF(P64:V64, Versiones!$A$19)>0, "Eventos_iOT", COUNTIF(P64:V64, Versiones!$A$20)>0, "Eventos_Fabric", TRUE, "No encontrado")} -> Look&Feel
A65: Error | B65: T20-1749 | C65: 96978 | D65: POS - El campo buscador y botón cancelar no coincide con el FIGMA | E65: 87100 | F65: T20-1091 | G65: 4.- QA | H65: Medio | I65: Tareas por hacer | J65: Backlog BUGS | P65: Look&Feel | Q65: QA-EquipoMV0.7 | W65: Josue Jesus Espindola Velasco | X65: 45924.706 | AB65: =IF(LEFT(Jira__32[[#This Row],[Resumen]],3)="POS","POS",IF(LEFT(Jira__32[[#This Row],[Resumen]],3)="BOT","BOT","")) -> POS | AC65: Juan Camilo Collantes Tovar | AE65: {=_xlfn.IFS(OR(COUNTIF(P65:V65,Versiones!$G$9)>0, COUNTIF(P65:V65,Versiones!$H$8)>0), "Sprint 21",OR(COUNTIF(P65:V65,Versiones!$G$8)>0, COUNTIF(P65:V65,Versiones!$H$8)>0, COUNTIF(P65:V65,Versiones!$I$8)>0), "Sprint 20",OR(COUNTIF(P65:V65,Versiones!$G$7)>0, COUNTIF(P65:V65,Versiones!$H$7)>0, COUNTIF(P65:V65,Versiones!$I$7)>0), "Sprint 19",OR(COUNTIF(P65:V65,Versiones!$G$6)>0, COUNTIF(P65:V65,Versiones!$H$6)>0, COUNTIF(P65:V65,Versiones!$I$6)>0), "Sprint 18",OR(COUNTIF(P65:V65,Versiones!$G$4)>0, COUNTIF(P65:V65,Versiones!$H$4)>0, COUNTIF(P65:V65,Versiones!$G$5)>0, COUNTIF(P65:V65,Versiones!$H$5)>0), "Sprint 17",OR(COUNTIF(P65:V65,Versiones!$G$2)>0, COUNTIF(P65:V65,Versiones!$H$2)>0, COUNTIF(P65:V65,Versiones!$G$3)>0, COUNTIF(P65:V65,Versiones!$H$3)>0), "Sprint 16", OR(COUNTIF(P65:V65,Versiones!$G$2)>0, COUNTIF(P65:V65,Versiones!$H$2)>0, COUNTIF(P65:V65,Versiones!$G$3)>0, COUNTIF(P65:V65,Versiones!$H$3)>0), "Sprint 16",TRUE, "")} -> Sprint 19 | AF65: ="v"&MAX( IFERROR(VALUE(MID(Jira__32[[#This Row],[Versiones corregidas]],2,99)),0), IFERROR(VALUE(MID(Jira__32[[#This Row],[Versiones corregidas_13]],2,99)),0), IFERROR(VALUE(MID(Jira__32[[#This Row],[Versiones corregidas_14]],2,99)),0) ) -> v0 | AG65: {=_xlfn.IFS(Jira__32[[#This Row],[¿En qué versión fue corregido?]]="v0","N/A",Jira__32[[#This Row],[¿En qué versión fue corregido?]]="v0.4","Sprint 16", Jira__32[[#This Row],[¿En qué versión fue corregido?]]="v0.5","Sprint 17", Jira__32[[#This Row],[¿En qué versión fue corregido?]]="v0.6","Sprint 18", Jira__32[[#This Row],[¿En qué versión fue corregido?]]="v0.7","Sprint 19", Jira__32[[#This Row],[¿En qué versión fue corregido?]]="v0.8","Sprint 20",Jira__32[[#This Row],[¿En qué versión fue corregido?]]="v0.9","Sprint 21", TRUE,"Desconocido")} -> N/A | AH65: {=_xlfn.IFS(COUNTIF(P65:V65, Versiones!$A$13)>0, "Funcional", COUNTIF(P65:V65, Versiones!$A$14)>0, "Configuración", COUNTIF(P65:V65, Versiones!$A$15)>0, "Look&Feel", COUNTIF(P65:V65, Versiones!$A$16)>0, "Integración", COUNTIF(P65:V65, Versiones!$A$17)>0, "Contenido/Datos", COUNTIF(P65:V65, Versiones!$A$18)>0, "Eventos_Cosmos", COUNTIF(P65:V65, Versiones!$A$19)>0, "Eventos_iOT", COUNTIF(P65:V65, Versiones!$A$20)>0, "Eventos_Fabric", TRUE, "No encontrado")} -> Look&Feel
A66: Error | B66: T20-1722 | C66: 96732 | D66: POS - Texto de Botón incorrecto | E66: 87100 | F66: T20-1091 | G66: 4.- QA | H66: Baja | I66: Cancelado | J66: Backlog BUGS | P66: Contenido/Datos | Q66: QA-EquipoMV0.7 | W66: Rocio Gallegos | X66: 45923.729 | AB66: =IF(LEFT(Jira__32[[#This Row],[Resumen]],3)="POS","POS",IF(LEFT(Jira__32[[#This Row],[Resumen]],3)="BOT","BOT","")) -> POS | AC66: Cancelado | AE66: {=_xlfn.IFS(OR(COUNTIF(P66:V66,Versiones!$G$9)>0, COUNTIF(P66:V66,Versiones!$H$8)>0), "Sprint 21",OR(COUNTIF(P66:V66,Versiones!$G$8)>0, COUNTIF(P66:V66,Versiones!$H$8)>0, COUNTIF(P66:V66,Versiones!$I$8)>0), "Sprint 20",OR(COUNTIF(P66:V66,Versiones!$G$7)>0, COUNTIF(P66:V66,Versiones!$H$7)>0, COUNTIF(P66:V66,Versiones!$I$7)>0), "Sprint 19",OR(COUNTIF(P66:V66,Versiones!$G$6)>0, COUNTIF(P66:V66,Versiones!$H$6)>0, COUNTIF(P66:V66,Versiones!$I$6)>0), "Sprint 18",OR(COUNTIF(P66:V66,Versiones!$G$4)>0, COUNTIF(P66:V66,Versiones!$H$4)>0, COUNTIF(P66:V66,Versiones!$G$5)>0, COUNTIF(P66:V66,Versiones!$H$5)>0), "Sprint 17",OR(COUNTIF(P66:V66,Versiones!$G$2)>0, COUNTIF(P66:V66,Versiones!$H$2)>0, COUNTIF(P66:V66,Versiones!$G$3)>0, COUNTIF(P66:V66,Versiones!$H$3)>0), "Sprint 16", OR(COUNTIF(P66:V66,Versiones!$G$2)>0, COUNTIF(P66:V66,Versiones!$H$2)>0, COUNTIF(P66:V66,Versiones!$G$3)>0, COUNTIF(P66:V66,Versiones!$H$3)>0), "Sprint 16",TRUE, "")} -> Sprint 19 | AF66: ="v"&MAX( IFERROR(VALUE(MID(Jira__32[[#This Row],[Versiones corregidas]],2,99)),0), IFERROR(VALUE(MID(Jira__32[[#This Row],[Versiones corregidas_13]],2,99)),0), IFERROR(VALUE(MID(Jira__32[[#This Row],[Versiones corregidas_14]],2,99)),0) ) -> v0 | AG66: {=_xlfn.IFS(Jira__32[[#This Row],[¿En qué versión fue corregido?]]="v0","N/A",Jira__32[[#This Row],[¿En qué versión fue corregido?]]="v0.4","Sprint 16", Jira__32[[#This Row],[¿En qué versión fue corregido?]]="v0.5","Sprint 17", Jira__32[[#This Row],[¿En qué versión fue corregido?]]="v0.6","Sprint 18", Jira__32[[#This Row],[¿En qué versión fue corregido?]]="v0.7","Sprint 19", Jira__32[[#This Row],[¿En qué versión fue corregido?]]="v0.8","Sprint 20",Jira__32[[#This Row],[¿En qué versión fue corregido?]]="v0.9","Sprint 21", TRUE,"Desconocido")} -> N/A | AH66: {=_xlfn.IFS(COUNTIF(P66:V66, Versiones!$A$13)>0, "Funcional", COUNTIF(P66:V66, Versiones!$A$14)>0, "Configuración", COUNTIF(P66:V66, Versiones!$A$15)>0, "Look&Feel", COUNTIF(P66:V66, Versiones!$A$16)>0, "Integración", COUNTIF(P66:V66, Versiones!$A$17)>0, "Contenido/Datos", COUNTIF(P66:V66, Versiones!$A$18)>0, "Eventos_Cosmos", COUNTIF(P66:V66, Versiones!$A$19)>0, "Eventos_iOT", COUNTIF(P66:V66, Versiones!$A$20)>0, "Eventos_Fabric", TRUE, "No encontrado")} -> Contenido/Datos
A67: Error | B67: T20-1721 | C67: 96711 | D67: POS - Las credenciales aparecen pre-cargadas | E67: 87100 | F67: T20-1091 | G67: 4.- QA | H67: Baja | I67: Tareas por hacer | J67: Backlog BUGS | P67: Configuración | Q67: QA-EquipoMV0.7 | W67: Rocio Gallegos | X67: 45923.706 | AB67: =IF(LEFT(Jira__32[[#This Row],[Resumen]],3)="POS","POS",IF(LEFT(Jira__32[[#This Row],[Resumen]],3)="BOT","BOT","")) -> POS | AC67: Juan Camilo Collantes Tovar | AE67: {=_xlfn.IFS(OR(COUNTIF(P67:V67,Versiones!$G$9)>0, COUNTIF(P67:V67,Versiones!$H$8)>0), "Sprint 21",OR(COUNTIF(P67:V67,Versiones!$G$8)>0, COUNTIF(P67:V67,Versiones!$H$8)>0, COUNTIF(P67:V67,Versiones!$I$8)>0), "Sprint 20",OR(COUNTIF(P67:V67,Versiones!$G$7)>0, COUNTIF(P67:V67,Versiones!$H$7)>0, COUNTIF(P67:V67,Versiones!$I$7)>0), "Sprint 19",OR(COUNTIF(P67:V67,Versiones!$G$6)>0, COUNTIF(P67:V67,Versiones!$H$6)>0, COUNTIF(P67:V67,Versiones!$I$6)>0), "Sprint 18",OR(COUNTIF(P67:V67,Versiones!$G$4)>0, COUNTIF(P67:V67,Versiones!$H$4)>0, COUNTIF(P67:V67,Versiones!$G$5)>0, COUNTIF(P67:V67,Versiones!$H$5)>0), "Sprint 17",OR(COUNTIF(P67:V67,Versiones!$G$2)>0, COUNTIF(P67:V67,Versiones!$H$2)>0, COUNTIF(P67:V67,Versiones!$G$3)>0, COUNTIF(P67:V67,Versiones!$H$3)>0), "Sprint 16", OR(COUNTIF(P67:V67,Versiones!$G$2)>0, COUNTIF(P67:V67,Versiones!$H$2)>0, COUNTIF(P67:V67,Versiones!$G$3)>0, COUNTIF(P67:V67,Versiones!$H$3)>0), "Sprint 16",TRUE, "")} -> Sprint 19 | AF67: ="v"&MAX( IFERROR(VALUE(MID(Jira__32[[#This Row],[Versiones corregidas]],2,99)),0), IFERROR(VALUE(MID(Jira__32[[#This Row],[Versiones corregidas_13]],2,99)),0), IFERROR(VALUE(MID(Jira__32[[#This Row],[Versiones corregidas_14]],2,99)),0) ) -> v0 | AG67: {=_xlfn.IFS(Jira__32[[#This Row],[¿En qué versión fue corregido?]]="v0","N/A",Jira__32[[#This Row],[¿En qué versión fue corregido?]]="v0.4","Sprint 16", Jira__32[[#This Row],[¿En qué versión fue corregido?]]="v0.5","Sprint 17", Jira__32[[#This Row],[¿En qué versión fue corregido?]]="v0.6","Sprint 18", Jira__32[[#This Row],[¿En qué versión fue corregido?]]="v0.7","Sprint 19", Jira__32[[#This Row],[¿En qué versión fue corregido?]]="v0.8","Sprint 20",Jira__32[[#This Row],[¿En qué versión fue corregido?]]="v0.9","Sprint 21", TRUE,"Desconocido")} -> N/A | AH67: {=_xlfn.IFS(COUNTIF(P67:V67, Versiones!$A$13)>0, "Funcional", COUNTIF(P67:V67, Versiones!$A$14)>0, "Configuración", COUNTIF(P67:V67, Versiones!$A$15)>0, "Look&Feel", COUNTIF(P67:V67, Versiones!$A$16)>0, "Integración", COUNTIF(P67:V67, Versiones!$A$17)>0, "Contenido/Datos", COUNTIF(P67:V67, Versiones!$A$18)>0, "Eventos_Cosmos", COUNTIF(P67:V67, Versiones!$A$19)>0, "Eventos_iOT", COUNTIF(P67:V67, Versiones!$A$20)>0, "Eventos_Fabric", TRUE, "No encontrado")} -> Configuración
A68: Error | B68: T20-1685 | C68: 96292 | D68: POS - Nombre incorrecto de modal | E68: 87100 | F68: T20-1091 | G68: 4.- QA | H68: Baja | I68: Tareas por hacer | J68: Backlog BUGS | P68: Look&Feel | Q68: QA-EquipoMV0.7 | W68: Roberto Gomez Hernandez | X68: 45922.543 | AB68: =IF(LEFT(Jira__32[[#This Row],[Resumen]],3)="POS","POS",IF(LEFT(Jira__32[[#This Row],[Resumen]],3)="BOT","BOT","")) -> POS | AC68: Juan Camilo Collantes Tovar | AE68: {=_xlfn.IFS(OR(COUNTIF(P68:V68,Versiones!$G$9)>0, COUNTIF(P68:V68,Versiones!$H$8)>0), "Sprint 21",OR(COUNTIF(P68:V68,Versiones!$G$8)>0, COUNTIF(P68:V68,Versiones!$H$8)>0, COUNTIF(P68:V68,Versiones!$I$8)>0), "Sprint 20",OR(COUNTIF(P68:V68,Versiones!$G$7)>0, COUNTIF(P68:V68,Versiones!$H$7)>0, COUNTIF(P68:V68,Versiones!$I$7)>0), "Sprint 19",OR(COUNTIF(P68:V68,Versiones!$G$6)>0, COUNTIF(P68:V68,Versiones!$H$6)>0, COUNTIF(P68:V68,Versiones!$I$6)>0), "Sprint 18",OR(COUNTIF(P68:V68,Versiones!$G$4)>0, COUNTIF(P68:V68,Versiones!$H$4)>0, COUNTIF(P68:V68,Versiones!$G$5)>0, COUNTIF(P68:V68,Versiones!$H$5)>0), "Sprint 17",OR(COUNTIF(P68:V68,Versiones!$G$2)>0, COUNTIF(P68:V68,Versiones!$H$2)>0, COUNTIF(P68:V68,Versiones!$G$3)>0, COUNTIF(P68:V68,Versiones!$H$3)>0), "Sprint 16", OR(COUNTIF(P68:V68,Versiones!$G$2)>0, COUNTIF(P68:V68,Versiones!$H$2)>0, COUNTIF(P68:V68,Versiones!$G$3)>0, COUNTIF(P68:V68,Versiones!$H$3)>0), "Sprint 16",TRUE, "")} -> Sprint 19 | AF68: ="v"&MAX( IFERROR(VALUE(MID(Jira__32[[#This Row],[Versiones corregidas]],2,99)),0), IFERROR(VALUE(MID(Jira__32[[#This Row],[Versiones corregidas_13]],2,99)),0), IFERROR(VALUE(MID(Jira__32[[#This Row],[Versiones corregidas_14]],2,99)),0) ) -> v0 | AG68: {=_xlfn.IFS(Jira__32[[#This Row],[¿En qué versión fue corregido?]]="v0","N/A",Jira__32[[#This Row],[¿En qué versión fue corregido?]]="v0.4","Sprint 16", Jira__32[[#This Row],[¿En qué versión fue corregido?]]="v0.5","Sprint 17", Jira__32[[#This Row],[¿En qué versión fue corregido?]]="v0.6","Sprint 18", Jira__32[[#This Row],[¿En qué versión fue corregido?]]="v0.7","Sprint 19", Jira__32[[#This Row],[¿En qué versión fue corregido?]]="v0.8","Sprint 20",Jira__32[[#This Row],[¿En qué versión fue corregido?]]="v0.9","Sprint 21", TRUE,"Desconocido")} -> N/A | AH68: {=_xlfn.IFS(COUNTIF(P68:V68, Versiones!$A$13)>0, "Funcional", COUNTIF(P68:V68, Versiones!$A$14)>0, "Configuración", COUNTIF(P68:V68, Versiones!$A$15)>0, "Look&Feel", COUNTIF(P68:V68, Versiones!$A$16)>0, "Integración", COUNTIF(P68:V68, Versiones!$A$17)>0, "Contenido/Datos", COUNTIF(P68:V68, Versiones!$A$18)>0, "Eventos_Cosmos", COUNTIF(P68:V68, Versiones!$A$19)>0, "Eventos_iOT", COUNTIF(P68:V68, Versiones!$A$20)>0, "Eventos_Fabric", TRUE, "No encontrado")} -> Look&Feel
A69: Error | B69: T20-1684 | C69: 96268 | D69: BOT_Registro de gasto - No se visualiza evento en Iothub | E69: 87100 | F69: T20-1091 | G69: 4.- QA | H69: Alta | I69: TO BE DEPLOYED-SIT | J69: T20 Sprint 19 2025 | K69: T20 Sprint 21 2025 | P69: Eventos_iOT | Q69: QA-IntegraciónV0.7 | R69: T3B20_BOT | S69: Tienda2.0 | W69: Yubisleinys Mora Vega | X69: 45922.513 | Y69: v0.10 | AB69: =IF(LEFT(Jira__32[[#This Row],[Resumen]],3)="POS","POS",IF(LEFT(Jira__32[[#This Row],[Resumen]],3)="BOT","BOT","")) -> BOT | AC69: Juan Camilo Collantes Tovar | AE69: {=_xlfn.IFS(OR(COUNTIF(P69:V69,Versiones!$G$9)>0, COUNTIF(P69:V69,Versiones!$H$8)>0), "Sprint 21",OR(COUNTIF(P69:V69,Versiones!$G$8)>0, COUNTIF(P69:V69,Versiones!$H$8)>0, COUNTIF(P69:V69,Versiones!$I$8)>0), "Sprint 20",OR(COUNTIF(P69:V69,Versiones!$G$7)>0, COUNTIF(P69:V69,Versiones!$H$7)>0, COUNTIF(P69:V69,Versiones!$I$7)>0), "Sprint 19",OR(COUNTIF(P69:V69,Versiones!$G$6)>0, COUNTIF(P69:V69,Versiones!$H$6)>0, COUNTIF(P69:V69,Versiones!$I$6)>0), "Sprint 18",OR(COUNTIF(P69:V69,Versiones!$G$4)>0, COUNTIF(P69:V69,Versiones!$H$4)>0, COUNTIF(P69:V69,Versiones!$G$5)>0, COUNTIF(P69:V69,Versiones!$H$5)>0), "Sprint 17",OR(COUNTIF(P69:V69,Versiones!$G$2)>0, COUNTIF(P69:V69,Versiones!$H$2)>0, COUNTIF(P69:V69,Versiones!$G$3)>0, COUNTIF(P69:V69,Versiones!$H$3)>0), "Sprint 16", OR(COUNTIF(P69:V69,Versiones!$G$2)>0, COUNTIF(P69:V69,Versiones!$H$2)>0, COUNTIF(P69:V69,Versiones!$G$3)>0, COUNTIF(P69:V69,Versiones!$H$3)>0), "Sprint 16",TRUE, "")} -> Sprint 19 | AF69: v0.10 | AG69: N/A | AH69: {=_xlfn.IFS(COUNTIF(P69:V69, Versiones!$A$13)>0, "Funcional", COUNTIF(P69:V69, Versiones!$A$14)>0, "Configuración", COUNTIF(P69:V69, Versiones!$A$15)>0, "Look&Feel", COUNTIF(P69:V69, Versiones!$A$16)>0, "Integración", COUNTIF(P69:V69, Versiones!$A$17)>0, "Contenido/Datos", COUNTIF(P69:V69, Versiones!$A$18)>0, "Eventos_Cosmos", COUNTIF(P69:V69, Versiones!$A$19)>0, "Eventos_iOT", COUNTIF(P69:V69, Versiones!$A$20)>0, "Eventos_Fabric", TRUE, "No encontrado")} -> Eventos_iOT
A70: Error | B70: T20-1675 | C70: 95951 | D70: BOT - Toast de Transferencia de productos reaparece al seleccionar otros productos | E70: 87100 | F70: T20-1091 | G70: 4.- QA | H70: Medio | I70: Tareas por hacer | J70: Backlog BUGS | P70: Funcional | Q70: QA-IntegraciónV0.7 | W70: Daniela Soto | X70: 45919.646 | AB70: =IF(LEFT(Jira__32[[#This Row],[Resumen]],3)="POS","POS",IF(LEFT(Jira__32[[#This Row],[Resumen]],3)="BOT","BOT","")) -> BOT | AC70: Juan Camilo Collantes Tovar | AE70: {=_xlfn.IFS(OR(COUNTIF(P70:V70,Versiones!$G$9)>0, COUNTIF(P70:V70,Versiones!$H$8)>0), "Sprint 21",OR(COUNTIF(P70:V70,Versiones!$G$8)>0, COUNTIF(P70:V70,Versiones!$H$8)>0, COUNTIF(P70:V70,Versiones!$I$8)>0), "Sprint 20",OR(COUNTIF(P70:V70,Versiones!$G$7)>0, COUNTIF(P70:V70,Versiones!$H$7)>0, COUNTIF(P70:V70,Versiones!$I$7)>0), "Sprint 19",OR(COUNTIF(P70:V70,Versiones!$G$6)>0, COUNTIF(P70:V70,Versiones!$H$6)>0, COUNTIF(P70:V70,Versiones!$I$6)>0), "Sprint 18",OR(COUNTIF(P70:V70,Versiones!$G$4)>0, COUNTIF(P70:V70,Versiones!$H$4)>0, COUNTIF(P70:V70,Versiones!$G$5)>0, COUNTIF(P70:V70,Versiones!$H$5)>0), "Sprint 17",OR(COUNTIF(P70:V70,Versiones!$G$2)>0, COUNTIF(P70:V70,Versiones!$H$2)>0, COUNTIF(P70:V70,Versiones!$G$3)>0, COUNTIF(P70:V70,Versiones!$H$3)>0), "Sprint 16", OR(COUNTIF(P70:V70,Versiones!$G$2)>0, COUNTIF(P70:V70,Versiones!$H$2)>0, COUNTIF(P70:V70,Versiones!$G$3)>0, COUNTIF(P70:V70,Versiones!$H$3)>0), "Sprint 16",TRUE, "")} -> Sprint 19 | AF70: ="v"&MAX( IFERROR(VALUE(MID(Jira__32[[#This Row],[Versiones corregidas]],2,99)),0), IFERROR(VALUE(MID(Jira__32[[#This Row],[Versiones corregidas_13]],2,99)),0), IFERROR(VALUE(MID(Jira__32[[#This Row],[Versiones corregidas_14]],2,99)),0) ) -> v0 | AG70: {=_xlfn.IFS(Jira__32[[#This Row],[¿En qué versión fue corregido?]]="v0","N/A",Jira__32[[#This Row],[¿En qué versión fue corregido?]]="v0.4","Sprint 16", Jira__32[[#This Row],[¿En qué versión fue corregido?]]="v0.5","Sprint 17", Jira__32[[#This Row],[¿En qué versión fue corregido?]]="v0.6","Sprint 18", Jira__32[[#This Row],[¿En qué versión fue corregido?]]="v0.7","Sprint 19", Jira__32[[#This Row],[¿En qué versión fue corregido?]]="v0.8","Sprint 20",Jira__32[[#This Row],[¿En qué versión fue corregido?]]="v0.9","Sprint 21", TRUE,"Desconocido")} -> N/A | AH70: {=_xlfn.IFS(COUNTIF(P70:V70, Versiones!$A$13)>0, "Funcional", COUNTIF(P70:V70, Versiones!$A$14)>0, "Configuración", COUNTIF(P70:V70, Versiones!$A$15)>0, "Look&Feel", COUNTIF(P70:V70, Versiones!$A$16)>0, "Integración", COUNTIF(P70:V70, Versiones!$A$17)>0, "Contenido/Datos", COUNTIF(P70:V70, Versiones!$A$18)>0, "Eventos_Cosmos", COUNTIF(P70:V70, Versiones!$A$19)>0, "Eventos_iOT", COUNTIF(P70:V70, Versiones!$A$20)>0, "Eventos_Fabric", TRUE, "No encontrado")} -> Funcional
A71: Error | B71: T20-1599 | C71: 95629 | D71: BOT - Tipo de gasto no se despliega correctamente ni coincide | E71: 87100 | F71: T20-1091 | G71: 4.- QA | H71: Alta | I71: TO BE DEPLOYED-SIT | J71: T20 Sprint 21 2025 | P71: Funcional | Q71: QA-IntegraciónV0.7 | W71: Daniela Soto | X71: 45918.651 | AB71: =IF(LEFT(Jira__32[[#This Row],[Resumen]],3)="POS","POS",IF(LEFT(Jira__32[[#This Row],[Resumen]],3)="BOT","BOT","")) -> BOT | AC71: Juan Camilo Collantes Tovar | AE71: {=_xlfn.IFS(OR(COUNTIF(P71:V71,Versiones!$G$9)>0, COUNTIF(P71:V71,Versiones!$H$8)>0), "Sprint 21",OR(COUNTIF(P71:V71,Versiones!$G$8)>0, COUNTIF(P71:V71,Versiones!$H$8)>0, COUNTIF(P71:V71,Versiones!$I$8)>0), "Sprint 20",OR(COUNTIF(P71:V71,Versiones!$G$7)>0, COUNTIF(P71:V71,Versiones!$H$7)>0, COUNTIF(P71:V71,Versiones!$I$7)>0), "Sprint 19",OR(COUNTIF(P71:V71,Versiones!$G$6)>0, COUNTIF(P71:V71,Versiones!$H$6)>0, COUNTIF(P71:V71,Versiones!$I$6)>0), "Sprint 18",OR(COUNTIF(P71:V71,Versiones!$G$4)>0, COUNTIF(P71:V71,Versiones!$H$4)>0, COUNTIF(P71:V71,Versiones!$G$5)>0, COUNTIF(P71:V71,Versiones!$H$5)>0), "Sprint 17",OR(COUNTIF(P71:V71,Versiones!$G$2)>0, COUNTIF(P71:V71,Versiones!$H$2)>0, COUNTIF(P71:V71,Versiones!$G$3)>0, COUNTIF(P71:V71,Versiones!$H$3)>0), "Sprint 16", OR(COUNTIF(P71:V71,Versiones!$G$2)>0, COUNTIF(P71:V71,Versiones!$H$2)>0, COUNTIF(P71:V71,Versiones!$G$3)>0, COUNTIF(P71:V71,Versiones!$H$3)>0), "Sprint 16",TRUE, "")} -> Sprint 19 | AF71: ="v"&MAX( IFERROR(VALUE(MID(Jira__32[[#This Row],[Versiones corregidas]],2,99)),0), IFERROR(VALUE(MID(Jira__32[[#This Row],[Versiones corregidas_13]],2,99)),0), IFERROR(VALUE(MID(Jira__32[[#This Row],[Versiones corregidas_14]],2,99)),0) ) -> v0 | AG71: {=_xlfn.IFS(Jira__32[[#This Row],[¿En qué versión fue corregido?]]="v0","N/A",Jira__32[[#This Row],[¿En qué versión fue corregido?]]="v0.4","Sprint 16", Jira__32[[#This Row],[¿En qué versión fue corregido?]]="v0.5","Sprint 17", Jira__32[[#This Row],[¿En qué versión fue corregido?]]="v0.6","Sprint 18", Jira__32[[#This Row],[¿En qué versión fue corregido?]]="v0.7","Sprint 19", Jira__32[[#This Row],[¿En qué versión fue corregido?]]="v0.8","Sprint 20",Jira__32[[#This Row],[¿En qué versión fue corregido?]]="v0.9","Sprint 21", TRUE,"Desconocido")} -> N/A | AH71: {=_xlfn.IFS(COUNTIF(P71:V71, Versiones!$A$13)>0, "Funcional", COUNTIF(P71:V71, Versiones!$A$14)>0, "Configuración", COUNTIF(P71:V71, Versiones!$A$15)>0, "Look&Feel", COUNTIF(P71:V71, Versiones!$A$16)>0, "Integración", COUNTIF(P71:V71, Versiones!$A$17)>0, "Contenido/Datos", COUNTIF(P71:V71, Versiones!$A$18)>0, "Eventos_Cosmos", COUNTIF(P71:V71, Versiones!$A$19)>0, "Eventos_iOT", COUNTIF(P71:V71, Versiones!$A$20)>0, "Eventos_Fabric", TRUE, "No encontrado")} -> Funcional
A72: Error | B72: T20-1598 | C72: 95626 | D72: BOT - Registrar gastos no registra el valor ingresado | E72: 87100 | F72: T20-1091 | G72: 4.- QA | H72: Alta | I72: TO BE DEPLOYED-SIT | J72: T20 Sprint 19 2025 | K72: T20 Sprint 21 2025 | P72: Funcional | Q72: QA-IntegraciónV0.7 | R72: T3B20_BOT | S72: Tienda2.0 | W72: Daniela Soto | X72: 45918.644 | Y72: v0.10 | AB72: =IF(LEFT(Jira__32[[#This Row],[Resumen]],3)="POS","POS",IF(LEFT(Jira__32[[#This Row],[Resumen]],3)="BOT","BOT","")) -> BOT | AC72: Juan Camilo Collantes Tovar | AE72: {=_xlfn.IFS(OR(COUNTIF(P72:V72,Versiones!$G$9)>0, COUNTIF(P72:V72,Versiones!$H$8)>0), "Sprint 21",OR(COUNTIF(P72:V72,Versiones!$G$8)>0, COUNTIF(P72:V72,Versiones!$H$8)>0, COUNTIF(P72:V72,Versiones!$I$8)>0), "Sprint 20",OR(COUNTIF(P72:V72,Versiones!$G$7)>0, COUNTIF(P72:V72,Versiones!$H$7)>0, COUNTIF(P72:V72,Versiones!$I$7)>0), "Sprint 19",OR(COUNTIF(P72:V72,Versiones!$G$6)>0, COUNTIF(P72:V72,Versiones!$H$6)>0, COUNTIF(P72:V72,Versiones!$I$6)>0), "Sprint 18",OR(COUNTIF(P72:V72,Versiones!$G$4)>0, COUNTIF(P72:V72,Versiones!$H$4)>0, COUNTIF(P72:V72,Versiones!$G$5)>0, COUNTIF(P72:V72,Versiones!$H$5)>0), "Sprint 17",OR(COUNTIF(P72:V72,Versiones!$G$2)>0, COUNTIF(P72:V72,Versiones!$H$2)>0, COUNTIF(P72:V72,Versiones!$G$3)>0, COUNTIF(P72:V72,Versiones!$H$3)>0), "Sprint 16", OR(COUNTIF(P72:V72,Versiones!$G$2)>0, COUNTIF(P72:V72,Versiones!$H$2)>0, COUNTIF(P72:V72,Versiones!$G$3)>0, COUNTIF(P72:V72,Versiones!$H$3)>0), "Sprint 16",TRUE, "")} -> Sprint 19 | AF72: v0.10 | AG72: N/A | AH72: {=_xlfn.IFS(COUNTIF(P72:V72, Versiones!$A$13)>0, "Funcional", COUNTIF(P72:V72, Versiones!$A$14)>0, "Configuración", COUNTIF(P72:V72, Versiones!$A$15)>0, "Look&Feel", COUNTIF(P72:V72, Versiones!$A$16)>0, "Integración", COUNTIF(P72:V72, Versiones!$A$17)>0, "Contenido/Datos", COUNTIF(P72:V72, Versiones!$A$18)>0, "Eventos_Cosmos", COUNTIF(P72:V72, Versiones!$A$19)>0, "Eventos_iOT", COUNTIF(P72:V72, Versiones!$A$20)>0, "Eventos_Fabric", TRUE, "No encontrado")} -> Funcional
